Workbook

Sheet industry_fields
A1: company_cd | B1: field_code | C1: field_name | D1: org_desc | E1: facility_desc | F1: sort_order | G1: is_use | H1: created_at | I1: updated_at | J1: created_by | K1: updated_by
A2: TESTCOMP | B2: AICC | C2: AICC | D2: 콜센터 연계 | E2: 금융, 공공, 교통, 일반 Enterp. 등 | F2: 11 | G2: Y | H2: 46056.917 | I2: 46060.35
A3: TESTCOMP | B3: 공공 | C3: 공공 | D3: 중앙·지방 행정기관 | E3: 관공서, 주민센터, 복지관, 체육 시설, 행정센터 | F3: 2 | G3: Y | H3: 46056.917 | I3: 46060.35
A4: TESTCOMP | B4: 교육 | C4: 교육 | D4: 초중등·고등·기타교육 | E4: 도서관, 학교, 학원, 직업훈련기관 | F4: 3 | G4: Y | H4: 46056.917 | I4: 46060.35
A5: TESTCOMP | B5: 교통 | C5: 교통 | D5: 육상·철도·항공·해운 | E5: 버스, 지하철, 공항, 물류센터, 주유소 | F5: 5 | G5: Y | H5: 46056.917 | I5: 46060.35
A6: TESTCOMP | B6: 금융 | C6: 금융 | D6: 은행·보험·증권 | E6: 지점·콜센터·모바일 | F6: 4 | G6: Y | H6: 46056.917 | I6: 46060.35
A7: TESTCOMP | B7: 문화 | C7: 문화 | D7: 공연·전시·스포츠, 오락,서비스 | E7: 극장, 박물관, 테마파크 | F7: 6 | G7: Y | H7: 46056.917 | I7: 46060.35
A8: TESTCOMP | B8: 방송 | C8: 방송 | D8: 방송업 | E8: 지상파·케이블·OTT | F8: 9 | G8: Y | H8: 46056.917 | I8: 46060.35
A9: TESTCOMP | B9: 법률 | C9: 법률 | D9: 법무관련 서비스 | E9: 변호사사무소, 법무법인 | F9: 10 | G9: Y | H9: 46056.917 | I9: 46060.35
A10: TESTCOMP | B10: 숙박 | C10: 숙박 | D10: 호텔·리조트.숙박 | E10: 호텔, 리조트, 콘도 | F10: 7 | G10: Y | H10: 46056.917 | I10: 46060.35
A11: TESTCOMP | B11: 의료 | C11: 의료 | D11: 병원·의원·복지시설 | E11: 종합병원, 지방 의료원, 보건소, 요양병원 | F11: 1 | G11: Y | H11: 46056.917 | I11: 46060.35
A12: TESTCOMP | B12: 제조 | C12: 제조 | D12: 제조 | E12: 전기, 전자, 기계 | F12: 8 | G12: Y | H12: 46056.917 | I12: 46060.35

Sheet service_codes
A1: company_cd | B1: service_code | C1: parent_code | D1: service_name | E1: display_name | F1: sort_order | G1: is_use | H1: created_at | I1: updated_at | J1: created_by | K1: updated_by
A2: TESTCOMP | B2: AI서비스 | D2: AI서비스 | E2: AI서비스 | F2: 1 | G2: Y | H2: 46056.917 | I2: 46060.351
A3: TESTCOMP | B3: AI서비스-IPCC | C3: AI서비스 | D3: IPCC | E3: AI서비스-IPCC | F3: 2 | G3: Y | H3: 46056.917 | I3: 46060.351
A4: TESTCOMP | B4: AI서비스-SI부문 | C4: AI서비스 | D4: SI부문 | E4: AI서비스-SI부문 | F4: 1 | G4: Y | H4: 46056.917 | I4: 46060.351
A5: TESTCOMP | B5: AI서비스-시스템 | C5: AI서비스 | D5: 시스템 | E5: AI서비스-시스템 | F5: 3 | G5: Y | H5: 46056.917 | I5: 46060.351
A6: TESTCOMP | B6: AI서비스-패키지 | C6: AI서비스 | D6: 패키지 | E6: AI서비스-패키지 | F6: 4 | G6: Y | H6: 46056.917 | I6: 46060.351
A7: TESTCOMP | B7: AI수어 | D7: AI수어 | E7: AI수어 | F7: 2 | G7: Y | H7: 46056.917 | I7: 46060.351
A8: TESTCOMP | B8: AI수어-과제형 | C8: AI수어 | D8: 과제형 | E8: AI수어-과제형 | F8: 7 | G8: Y | H8: 46056.917 | I8: 46060.351
A9: TESTCOMP | B9: AI수어-구독형 | C9: AI수어 | D9: 구독형 | E9: AI수어-구독형 | F9: 6 | G9: Y | H9: 46056.917 | I9: 46060.351
A10: TESTCOMP | B10: AI수어-구축형 | C10: AI수어 | D10: 구축형 | E10: AI수어-구축형 | F10: 5 | G10: Y | H10: 46056.917 | I10: 46060.351
A11: TESTCOMP | B11: AI수어-대외매출 | C11: AI수어 | D11: 대외매출 | E11: AI수어-대외매출 | F11: 8 | G11: Y | H11: 46056.917 | I11: 46060.351
A12: TESTCOMP | B12: 기타 | D12: 기타 | E12: 기타 | F12: 3 | G12: Y | H12: 46056.917 | I12: 46060.351
A13: TESTCOMP | B13: 기타-유지보수(MA) | C13: 기타 | D13: 유지보수(MA) | E13: 기타-유지보수(MA) | F13: 10 | G13: Y | H13: 46056.917 | I13: 46060.351
A14: TESTCOMP | B14: 기타-유지보수(SM) | C14: 기타 | D14: 유지보수(SM) | E14: 기타-유지보수(SM) | F14: 9 | G14: Y | H14: 46056.917 | I14: 46060.351

Sheet org_units
A1: company_cd | B1: org_id | C1: org_name | D1: parent_id | E1: org_type | F1: sort_order | G1: is_use | H1: created_at | I1: updated_at | J1: created_by | K1: updated_by
A2: TESTCOMP | B2: 1 | C2: AX기술영업팀 | E2: TEAM | F2: 0 | G2: Y | H2: 46056.917 | I2: 46060.351
A3: TESTCOMP | B3: 2 | C3: AX프로젝트팀 | E3: TEAM | F3: 0 | G3: Y | H3: 46056.917 | I3: 46060.351
A4: TESTCOMP | B4: 3 | C4: AX기술수행팀 | E4: TEAM | F4: 0 | G4: Y | H4: 46056.917 | I4: 46060.351

Sheet comm_code
A1: company_cd | B1: group_code | C1: group_name | D1: code | E1: code_name | F1: sort_order | G1: is_use | H1: created_at | I1: updated_at | J1: created_by | K1: updated_by
A2: TESTCOMP | B2: ACTIVITY_TYPE | C2: 활동유형 | D2: CONTRACT | E2: 계약 | F2: 3 | G2: Y | H2: 46061.749 | I2: 46061.749 | J2: system | K2: system
A3: TESTCOMP | B3: ACTIVITY_TYPE | C3: 활동유형 | D3: ETC | E3: 기타 | F3: 6 | G3: Y | H3: 46061.749 | I3: 46061.749 | J3: system | K3: system
A4: TESTCOMP | B4: ACTIVITY_TYPE | C4: 활동유형 | D4: FOLLOWUP | E4: 후속 | F4: 4 | G4: Y | H4: 46061.749 | I4: 46061.749 | J4: system | K4: system
A5: TESTCOMP | B5: ACTIVITY_TYPE | C5: 활동유형 | D5: MEETING | E5: 미팅 | F5: 1 | G5: Y | H5: 46061.749 | I5: 46061.749 | J5: system | K5: system
A6: TESTCOMP | B6: ACTIVITY_TYPE | C6: 활동유형 | D6: PROPOSAL | E6: 제안 | F6: 2 | G6: Y | H6: 46061.749 | I6: 46061.749 | J6: system | K6: system
A7: TESTCOMP | B7: ACTIVITY_TYPE | C7: 활동유형 | D7: SUPPORT | E7: 지원 | F7: 5 | G7: Y | H7: 46061.749 | I7: 46061.749 | J7: system | K7: system
A8: TESTCOMP | B8: GROUP_CODE | C8: 그룹코드 | D8: NOTICE_CATEGORY | E8: 게시판구분 | F8: 2 | G8: Y | H8: 46056.642 | I8: 46060.351
A9: TESTCOMP | B9: GROUP_CODE | C9: 그룹코드 | D9: PROJECT_ATTRIBUTE | E9: 사업속성 | F9: 3 | G9: Y | H9: 46056.642 | I9: 46060.351
A10: TESTCOMP | B10: GROUP_CODE | C10: 그룹코드 | D10: ROLE | E10: 역할 | F10: 4 | G10: Y | H10: 46056.642 | I10: 46060.351
A11: TESTCOMP | B11: GROUP_CODE | C11: 그룹코드 | D11: STAGE | E11: 진행단계 | F11: 5 | G11: Y | H11: 46056.642 | I11: 46060.351
A12: TESTCOMP | B12: NOTICE_CATEGORY | C12: 게시판구분 | D12: DEV | E12: DEV | F12: 4 | G12: Y | H12: 46039.934 | I12: 46060.351 | J12: admin
A13: TESTCOMP | B13: NOTICE_CATEGORY | C13: 게시판구분 | D13: GENERAL | E13: GENERAL | F13: 2 | G13: Y | H13: 46039.934 | I13: 46060.351 | J13: admin
A14: TESTCOMP | B14: NOTICE_CATEGORY | C14: 게시판구분 | D14: HR | E14: HR | F14: 6 | G14: Y | H14: 46039.934 | I14: 46060.351 | J14: admin
A15: TESTCOMP | B15: NOTICE_CATEGORY | C15: 게시판구분 | D15: SALES | E15: SALES | F15: 1 | G15: Y | H15: 46039.934 | I15: 46060.351 | J15: admin
A16: TESTCOMP | B16: NOTICE_CATEGORY | C16: 게시판구분 | D16: SYSTEM | E16: SYSTEM | F16: 5 | G16: Y | H16: 46039.934 | I16: 46060.351 | J16: admin
A17: TESTCOMP | B17: NOTICE_CATEGORY | C17: 게시판구분 | D17: WELFARE | E17: WELFARE | F17: 3 | G17: Y | H17: 46039.934 | I17: 46060.351 | J17: admin
A18: TESTCOMP | B18: PROJECT_ATTRIBUTE | C18: 사업속성 | D18: ATTR_BIZ_STR | E18: 사업구도 | F18: 4 | G18: Y | H18: 46030.63 | I18: 46060.351
A19: TESTCOMP | B19: PROJECT_ATTRIBUTE | C19: 사업속성 | D19: ATTR_CHANGE | E19: 변동여부 | F19: 5 | G19: Y | H19: 46030.63 | I19: 46060.351
A20: TESTCOMP | B20: PROJECT_ATTRIBUTE | C20: 사업속성 | D20: ATTR_CON_TIME | E20: 계약시기 | F20: 2 | G20: Y | H20: 46030.63 | I20: 46060.351
A21: TESTCOMP | B21: PROJECT_ATTRIBUTE | C21: 사업속성 | D21: ATTR_CONFIRM | E21: 확정여부 | F21: 6 | G21: Y | H21: 46035.839 | I21: 46060.351 | J21: 양승구
A22: TESTCOMP | B22: PROJECT_ATTRIBUTE | C22: 사업속성 | D22: ATTR_ORD_TIME | E22: 발주시기 | F22: 1 | G22: Y | H22: 46030.63 | I22: 46060.351
A23: TESTCOMP | B23: PROJECT_ATTRIBUTE | C23: 사업속성 | D23: ATTR_SALES | E23: 매출정보 | F23: 3 | G23: Y | H23: 46030.63 | I23: 46060.351
A24: TESTCOMP | B24: ROLE | C24: 역할 | D24: Admin | E24: 어드민 | F24: 1 | G24: Y | H24: 46033.669 | I24: 46060.351
A25: TESTCOMP | B25: ROLE | C25: 역할 | D25: User | E25: 사용자 | F25: 2 | G25: Y | H25: 46033.669 | I25: 46060.351
A26: TESTCOMP | B26: ROLE | C26: 역할 | D26: Viewer | E26: 조회 | F26: 3 | G26: Y | H26: 46033.669 | I26: 46060.351
A27: TESTCOMP | B27: STAGE | C27: 진행단계 | D27: S01 | E27: 1 영업중 | F27: 1 | G27: Y | H27: 46030.63 | I27: 46060.351
A28: TESTCOMP | B28: STAGE | C28: 진행단계 | D28: S02 | E28: 2 견적제출 | F28: 2 | G28: Y | H28: 46030.63 | I28: 46060.351
A29: TESTCOMP | B29: STAGE | C29: 진행단계 | D29: S03 | E29: 3 제안중 | F29: 3 | G29: Y | H29: 46030.63 | I29: 46060.351
A30: TESTCOMP | B30: STAGE | C30: 진행단계 | D30: S04 | E30: 4 입찰중 | F30: 4 | G30: Y | H30: 46030.63 | I30: 46060.351
A31: TESTCOMP | B31: STAGE | C31: 진행단계 | D31: S05 | E31: 5 DROP | F31: 5 | G31: Y | H31: 46030.63 | I31: 46060.351
A32: TESTCOMP | B32: STAGE | C32: 진행단계 | D32: S06 | E32: 6 실주 | F32: 6 | G32: Y | H32: 46030.63 | I32: 46060.351
A33: TESTCOMP | B33: STAGE | C33: 진행단계 | D33: S07 | E33: 7 수주완료 | F33: 7 | G33: Y | H33: 46030.63 | I33: 46060.351
... A35: TESTCOMP | B35: STAGE | C35: 진행단계 | D35: S09 | E35: 9 유지보수 | F35: 9 | G35: Y | H35: 46030.63 | I35: 46060.351

Sheet psms_schema
A1: table_name | B1: column_name | C1: col_pos | D1: is_pk | E1: data_type | F1: data_length | G1: comments
A2: auth_forms | B2: company_cd | C2: 1 | D2: Y | E2: varchar | F2: 20 | G2: 회사 코드
A3: auth_forms | B3: form_id | C3: 2 | D3: Y | E3: varchar | F3: 50 | G3: VBA UserForm 객체 이름
A4: auth_forms | B4: form_name | C4: 3 | D4: N | E4: varchar | F4: 100 | G4: 화면 한글명
A5: auth_forms | B5: created_at | C5: 4 | D5: N | E5: timestamp | G5: 최초 생성일시
A6: auth_forms | B6: updated_at | C6: 5 | D6: N | E6: timestamp | G6: 최종 수정일시
A7: auth_forms | B7: created_by | C7: 6 | D7: N | E7: varchar | F7: 50 | G7: 생성자 ID
A8: auth_forms | B8: updated_by | C8: 7 | D8: N | E8: varchar | F8: 50 | G8: 수정자 ID
A9: auth_role_permissions | B9: company_cd | C9: 1 | D9: Y | E9: varchar | F9: 20 | G9: 회사 코드
A10: auth_role_permissions | B10: role | C10: 2 | D10: Y | E10: varchar | F10: 20 | G10: 역할
A11: auth_role_permissions | B11: form_id | C11: 3 | D11: Y | E11: varchar | F11: 50 | G11: 화면 ID
A12: auth_role_permissions | B12: can_view | C12: 4 | D12: N | E12: char | F12: 1 | G12: 조회 권한
A13: auth_role_permissions | B13: can_create | C13: 5 | D13: N | E13: char | F13: 1 | G13: 등록 권한
A14: auth_role_permissions | B14: can_update | C14: 6 | D14: N | E14: char | F14: 1 | G14: 수정 권한
A15: auth_role_permissions | B15: can_delete | C15: 7 | D15: N | E15: char | F15: 1 | G15: 삭제 권한
A16: auth_role_permissions | B16: created_at | C16: 8 | D16: N | E16: timestamp | G16: 최초 생성일시
A17: auth_role_permissions | B17: updated_at | C17: 9 | D17: N | E17: timestamp | G17: 최종 수정일시
A18: auth_role_permissions | B18: created_by | C18: 10 | D18: N | E18: varchar | F18: 50 | G18: 생성자 ID
A19: auth_role_permissions | B19: updated_by | C19: 11 | D19: N | E19: varchar | F19: 50 | G19: 수정자 ID
A20: auth_user_permissions | B20: company_cd | C20: 1 | D20: Y | E20: varchar | F20: 20 | G20: 회사 코드
A21: auth_user_permissions | B21: login_id | C21: 2 | D21: Y | E21: varchar | F21: 50 | G21: 로그인 ID
A22: auth_user_permissions | B22: form_id | C22: 3 | D22: Y | E22: varchar | F22: 50 | G22: 화면 ID
A23: auth_user_permissions | B23: can_view | C23: 4 | D23: N | E23: char | F23: 1 | G23: 조회 권한
A24: auth_user_permissions | B24: can_create | C24: 5 | D24: N | E24: char | F24: 1 | G24: 등록 권한
A25: auth_user_permissions | B25: can_update | C25: 6 | D25: N | E25: char | F25: 1 | G25: 수정 권한
A26: auth_user_permissions | B26: can_delete | C26: 7 | D26: N | E26: char | F26: 1 | G26: 삭제 권한
A27: auth_user_permissions | B27: created_at | C27: 8 | D27: N | E27: timestamp | G27: 최초 생성일시
A28: auth_user_permissions | B28: updated_at | C28: 9 | D28: N | E28: timestamp | G28: 최종 수정일시
A29: auth_user_permissions | B29: created_by | C29: 10 | D29: N | E29: varchar | F29: 50 | G29: 생성자 ID
A30: auth_user_permissions | B30: updated_by | C30: 11 | D30: N | E30: varchar | F30: 50 | G30: 수정자 ID
A31: board_notice_files | B31: company_cd | C31: 1 | D31: Y | E31: varchar | F31: 20 | G31: 회사 코드
A32: board_notice_files | B32: map_id | C32: 2 | D32: Y | E32: int | F32: 10 | G32: 매핑 ID
A33: board_notice_files | B33: notice_id | C33: 3 | D33: N | E33: int | F33: 10 | G33: 공지 ID
A34: board_notice_files | B34: reply_id | C34: 4 | D34: N | E34: int | F34: 10 | G34: 답글 ID
A35: board_notice_files | B35: file_id | C35: 5 | D35: N | E35: int | F35: 10 | G35: 파일 ID
A36: board_notice_files | B36: created_at | C36: 6 | D36: N | E36: timestamp | G36: 생성 일시
A37: board_notice_files | B37: created_by | C37: 7 | D37: N | E37: varchar | F37: 50 | G37: 생성자 ID
A38: board_notice_reactions | B38: company_cd | C38: 1 | D38: Y | E38: varchar | F38: 20 | G38: 회사 코드
A39: board_notice_reactions | B39: notice_id | C39: 2 | D39: Y | E39: int | F39: 10 | G39: 공지 ID
A40: board_notice_reactions | B40: user_id | C40: 3 | D40: Y | E40: varchar | F40: 50 | G40: 사용자 ID
A41: board_notice_reactions | B41: reaction | C41: 4 | D41: Y | E41: varchar | F41: 20 | G41: 반응 유형(LIKE/CHECK)
A42: board_notice_reactions | B42: created_at | C42: 5 | D42: N | E42: timestamp | G42: 반응 일시
A43: board_notice_reads | B43: company_cd | C43: 1 | D43: Y | E43: varchar | F43: 20 | G43: 회사 코드
A44: board_notice_reads | B44: notice_id | C44: 2 | D44: Y | E44: int | F44: 10 | G44: 공지 ID
A45: board_notice_reads | B45: reader_id | C45: 3 | D45: Y | E45: varchar | F45: 50 | G45: 읽은 사용자 ID
A46: board_notice_reads | B46: created_at | C46: 4 | D46: N | E46: timestamp | G46: 읽음 일시
A47: board_notice_replies | B47: company_cd | C47: 1 | D47: Y | E47: varchar | F47: 20 | G47: 회사 코드
A48: board_notice_replies | B48: reply_id | C48: 2 | D48: Y | E48: int | F48: 10 | G48: 답글 ID
A49: board_notice_replies | B49: notice_id | C49: 3 | D49: N | E49: int | F49: 10 | G49: 공지 ID
A50: board_notice_replies | B50: author_id | C50: 4 | D50: N | E50: varchar | F50: 50 | G50: 작성자 ID
A51: board_notice_replies | B51: content | C51: 5 | D51: N | E51: text | F51: 65535 | G51: 답글 내용
A52: board_notice_replies | B52: created_at | C52: 6 | D52: N | E52: timestamp | G52: 작성 일시
A53: board_notice_replies | B53: updated_at | C53: 7 | D53: N | E53: timestamp | G53: 수정 일시
A54: board_notice_replies | B54: created_by | C54: 8 | D54: N | E54: varchar | F54: 50 | G54: 생성자 ID
A55: board_notice_replies | B55: updated_by | C55: 9 | D55: N | E55: varchar | F55: 50 | G55: 수정자 ID
A56: board_notice_replies | B56: parent_reply_id | C56: 10 | D56: N | E56: int | F56: 10 | G56: 대댓글 대상 답글 ID
A57: board_notice_tags | B57: company_cd | C57: 1 | D57: Y | E57: varchar | F57: 20 | G57: 회사 코드
A58: board_notice_tags | B58: notice_id | C58: 2 | D58: Y | E58: int | F58: 10 | G58: 공지 ID
A59: board_notice_tags | B59: tag | C59: 3 | D59: Y | E59: varchar | F59: 50 | G59: 해시태그
A60: board_notice_tags | B60: created_at | C60: 4 | D60: N | E60: timestamp | G60: 생성 일시
A61: board_notices | B61: company_cd | C61: 1 | D61: Y | E61: varchar | F61: 20 | G61: 회사 코드
A62: board_notices | B62: notice_id | C62: 2 | D62: Y | E62: int | F62: 10 | G62: 공지사항 일련번호
A63: board_notices | B63: title | C63: 3 | D63: N | E63: varchar | F63: 255 | G63: 공지 제목
A64: board_notices | B64: content | C64: 4 | D64: N | E64: text | F64: 65535 | G64: 공지 내용(상세)
A65: board_notices | B65: is_fixed | C65: 5 | D65: N | E65: char | F65: 1 | G65: 상단 고정 여부 (Y/N)
A66: board_notices | B66: category | C66: 6 | D66: N | E66: varchar | F66: 50 | G66: 공지 분류 (시스템, 영업기획, 긴급 등)
A67: board_notices | B67: author_id | C67: 7 | D67: N | E67: varchar | F67: 50 | G67: 작성자 ID
A68: board_notices | B68: view_count | C68: 8 | D68: N | E68: int | F68: 10 | G68: 조회수
A69: board_notices | B69: start_date | C69: 9 | D69: N | E69: date | G69: 게시 시작일
A70: board_notices | B70: end_date | C70: 10 | D70: N | E70: date | G70: 게시 종료일
A71: board_notices | B71: created_at | C71: 11 | D71: N | E71: timestamp | G71: 생성 일시
A72: board_notices | B72: updated_at | C72: 12 | D72: N | E72: timestamp | G72: 수정 일시
A73: board_notices | B73: created_by | C73: 13 | D73: N | E73: varchar | F73: 50 | G73: 생성자 ID
A74: board_notices | B74: updated_by | C74: 14 | D74: N | E74: varchar | F74: 50 | G74: 수정자 ID
A75: board_notices | B75: status | C75: 15 | D75: N | E75: varchar | F75: 20 | G75: 상태 (NORMAL/IN_PROGRESS/DONE/HOLD)
A76: board_notices | B76: hashtags | C76: 16 | D76: N | E76: varchar | F76: 500 | G76: 해시태그(#tag #tag2)
A77: clients | B77: company_cd | C77: 1 | D77: Y | E77: varchar | F77: 20 | G77: 회사 코드
A78: clients | B78: client_id | C78: 2 | D78: Y | E78: int | F78: 10 | G78: 거래처 일련번호(PK)
A79: clients | B79: client_name | C79: 3 | D79: N | E79: varchar | F79: 100 | G79: 거래처명
A80: clients | B80: business_number | C80: 4 | D80: N | E80: varchar | F80: 20 | G80: 사업자등록번호
A81: clients | B81: ceo_name | C81: 5 | D81: N | E81: varchar | F81: 50 | G81: 대표자명
A82: clients | B82: address | C82: 6 | D82: N | E82: varchar | F82: 200 | G82: 주소
A83: clients | B83: phone | C83: 7 | D83: N | E83: varchar | F83: 20 | G83: 전화번호
A84: clients | B84: email | C84: 8 | D84: N | E84: varchar | F84: 100 | G84: 이메일
... A88: clients | B88: employee_count | C88: 12 | D88: N | E88: int | F88: 10 | G88: 직원 수
A89: clients | B89: established_date | C89: 13 | D89: N | E89: date | G89: 설립일자
A90: clients | B90: is_active | C90: 14 | D90: N | E90: tinyint | F90: 3 | G90: 활성 상태 (TRUE: 활성, FALSE: 비활성)
A91: clients | B91: remarks | C91: 15 | D91: N | E91: text | F91: 65535 | G91: 비고
A92: clients | B92: created_at | C92: 16 | D92: N | E92: timestamp | G92: 생성일시
A93: clients | B93: updated_at | C93: 17 | D93: N | E93: timestamp | G93: 수정일시
A94: clients | B94: created_by | C94: 18 | D94: N | E94: varchar | F94: 50 | G94: 생성자ID
A95: clients | B95: updated_by | C95: 19 | D95: N | E95: varchar | F95: 50 | G95: 수정자ID
A96: comm_code | B96: company_cd | C96: 1 | D96: Y | E96: varchar | F96: 20 | G96: 회사 코드
A97: comm_code | B97: group_code | C97: 2 | D97: Y | E97: varchar | F97: 20 | G97: 그룹 코드
A98: comm_code | B98: group_name | C98: 3 | D98: N | E98: varchar | F98: 100 | G98: 그룹명
A99: comm_code | B99: code | C99: 4 | D99: Y | E99: varchar | F99: 20 | G99: 코드
A100: comm_code | B100: code_name | C100: 5 | D100: N | E100: varchar | F100: 100 | G100: 코드명
A101: comm_code | B101: sort_order | C101: 6 | D101: N | E101: int | F101: 10 | G101: 정렬순서
A102: comm_code | B102: is_use | C102: 7 | D102: N | E102: char | F102: 1 | G102: 사용 여부
A103: comm_code | B103: created_at | C103: 8 | D103: N | E103: timestamp | G103: 생성일시
...

Sheet Mig_규칙
A1: Source Sheet Name | B1: Title행 | C1: Source Sheet Column ( :source_value ) | D1: Mig 대상여부 | E1: Mapping Rule | F1: Target Table | G1: Target Column | I1: projects | J1: company_cd | L1: project_history | M1: company_cd | O1: clients | P1: company_cd
A2: 2026년 주요추진사업 | B2: 3 | C2: 주차 | D2: N | I2: projects | J2: pipeline_id | L2: project_history | M2: history_id | O2: clients | P2: client_id
A3: 2026년 주요추진사업 | B3: 3 | C3: 파이프라인 ID | D3: Y | E3: :source_value | F3: projects | G3: pipeline_id | I3: projects | J3: project_name | L3: project_history | M3: pipeline_id | O3: clients | P3: client_name
A4: 2026년 주요추진사업 | B4: 3 | C4: 분야 | D4: N | E4: NULL | F4: projects | G4: field_code | I4: projects | J4: field_code | L4: project_history | M4: base_date | O4: clients | P4: business_number
A5: 2026년 주요추진사업 | B5: 3 | C5: 고객사 | D5: Y | E5: select c.client_id from clients c where c.client_name = :source_value [Not Fount] insert into clients (clint_name) value (:source_value) insert 후 자동채번된 client_id Set | F5: projects | G5: clients | I5: projects | J5: service_code | L5: project_history | M5: record_date | O5: clients | P5: ceo_name
A6: 2026년 주요추진사업 | B6: 3 | C6: 발주처 | D6: Y | E6: select c.client_id from clients c where c.client_name = :source_value [Not Fount] insert into clients (clint_name) value (:source_value) insert 후 자동채번된 client_id Set | F6: projects | G6: clients | I6: projects | J6: manager_id | L6: project_history | M6: progress_stage | O6: clients | P6: address
A7: 2026년 주요추진사업 | B7: 3 | C7: 사업명 | D7: Y | E7: :source_value | F7: projects | G7: project_name | I7: projects | J7: org_id | L7: project_history | M7: activity_type | O7: clients | P7: phone
A8: 2026년 주요추진사업 | B8: 3 | C8: 담당자 | D8: Y | E8: select u.login_id from users u where u.user_name=:source_value | F8: projects | G8: manager_id | I8: projects | J8: customer_id | L8: project_history | M8: strategy_content | O8: clients | P8: email
A9: 2026년 주요추진사업 | B9: 3 | C9: 진행단계 | D9: Y | E9: select cc.code from comm_code cc where cc.group_code='STAGE' and cc.code_name = :source_value | F9: projects | G9: current_stage | I9: projects | J9: ordering_party_id | L9: project_history | M9: creator_id | O9: clients | P9: fax
A10: 2026년 주요추진사업 | B10: 3 | C10: 업무 기준일 | D10: Y | E10: :source_value | F10: project_history | G10: base_date | I10: projects | J10: current_stage | L10: project_history | M10: created_at | O10: clients | P10: homepage
A11: 2026년 주요추진사업 | B11: 3 | C11: 진행상황 및 영업전략 | D11: Y | E11: :source_value | F11: project_history | G11: strategy_content | I11: projects | J11: quoted_amount | L11: project_history | M11: updated_at | O11: clients | P11: industry_type
A12: 2026년 주요추진사업 | B12: 3 | C12: 견적금액 단위 원. VAT제외 | D12: Y | E12: :source_value | F12: projects | G12: quoted_amount | I12: projects | J12: win_probability | L12: project_history | M12: created_by | O12: clients | P12: employee_count
A13: 2026년 주요추진사업 | B13: 3 | C13: 발주시기(예상) | D13: Y | E13: :source_value | F13: project_attributes | G13: attr_code='ATTR_ORD_TIME' attr_value=:source_value | I13: projects | J13: notes | L13: project_history | M13: updated_by | O13: clients | P13: established_date
A14: 2026년 주요추진사업 | B14: 3 | C14: 계약시기(예상) | D14: Y | E14: :source_value | F14: project_attributes | G14: attr_code='ATTR_CON_TIME' attr_value=:source_value | I14: projects | J14: status | O14: clients | P14: is_active
A15: 2026년 주요추진사업 | B15: 3 | C15: 계약일자 | D15: Y | E15: :source_value | F15: project_contracts | G15: contract_date | O15: clients | P15: remarks
A16: 2026년 주요추진사업 | B16: 3 | C16: 프로젝트기간(시작) | D16: Y | E16: :source_value | F16: project_contracts | G16: start_date | O16: clients | P16: created_at
A17: 2026년 주요추진사업 | B17: 3 | C17: 프로젝트기간(종료) | D17: Y | E17: :source_value | F17: project_contracts | G17: end_date | I17: project_attributes | J17: company_cd | L17: project_contracts | M17: company_cd | O17: clients | P17: updated_at
A18: 2026년 주요추진사업 | B18: 3 | C18: 계약(수주금액) 단위 원. VAT제외 | D18: Y | E18: :source_value | F18: project_contracts | G18: order_amount | I18: project_attributes | J18: pipeline_id | L18: project_contracts | M18: pipeline_id | O18: clients | P18: created_by
A19: 2026년 주요추진사업 | B19: 3 | C19: 계약(계약금액) 단위 원. VAT제외 | D19: Y | E19: :source_value | F19: project_contracts | G19: contract_amount | I19: project_attributes | J19: attr_code | L19: project_contracts | M19: contract_date | O19: clients | P19: updated_by
A20: 2026년 주요추진사업 | B20: 3 | C20: 매출 | D20: N | I20: project_attributes | J20: attr_value | L20: project_contracts | M20: start_date
A21: 2026년 주요추진사업 | B21: 3 | C21: 사업구도 ex) 마도 : OOO | D21: Y | E21: :source_value | F21: project_attributes | G21: attr_code='ATTR_BIZ_STR' attr_value=:source_value | I21: project_attributes | J21: updated_at | L21: project_contracts | M21: end_date
A22: 2026년 주요추진사업 | B22: 3 | C22: 이전 파이프라인 | D22: N | I22: project_attributes | J22: created_at | L22: project_contracts | M22: order_amount
A23: 2026년 주요추진사업 | B23: 3 | C23: 비고 | D23: Y | E23: :source_value | F23: projects | G23: notes | I23: project_attributes | J23: created_by | L23: project_contracts | M23: contract_amount
A24: 2025년 주요추진사업(NEW) | B24: 3 | C24: 파이프라인 ID | D24: Y | E24: :source_value | F24: projects | G24: pipeline_id | I24: project_attributes | J24: updated_by | L24: project_contracts | M24: remarks
A25: 2025년 주요추진사업(NEW) | B25: 3 | C25: 분야 | D25: N | E25: NULL | F25: projects | G25: field_code | L25: project_contracts | M25: updated_at
A26: 2025년 주요추진사업(NEW) | B26: 3 | C26: 고객사 | D26: Y | E26: select c.client_id from clients c where c.client_name = :source_value [Not Fount] insert into clients (clint_name) value (:source_value) insert 후 자동채번된 client_id Set | F26: projects | G26: clients | L26: project_contracts | M26: created_at
A27: 2025년 주요추진사업(NEW) | B27: 3 | C27: 발주처 | D27: Y | E27: select c.client_id from clients c where c.client_name = :source_value [Not Fount] insert into clients (clint_name) value (:source_value) insert 후 자동채번된 client_id Set | F27: projects | G27: clients | I27: org_units | J27: company_cd | L27: project_contracts | M27: created_by
A28: 2025년 주요추진사업(NEW) | B28: 3 | C28: 사업명 | D28: Y | E28: :source_value | F28: projects | G28: project_name | I28: org_units | J28: org_id | L28: project_contracts | M28: updated_by
A29: 2025년 주요추진사업(NEW) | B29: 3 | C29: 담당자 | D29: Y | E29: select u.login_id from users u where u.user_name=:source_value | F29: projects | G29: manager_id | I29: org_units | J29: org_name
A30: 2025년 주요추진사업(NEW) | B30: 3 | C30: 진행단계 | D30: Y | E30: select cc.code from comm_code cc where cc.group_code='STAGE' and cc.code_name = :source_value | F30: projects | G30: current_stage | I30: org_units | J30: parent_id | L30: users | M30: company_cd
A31: 2025년 주요추진사업(NEW) | B31: 3 | C31: 발주시기 | D31: Y | E31: :source_value | F31: project_attributes | G31: attr_code='ATTR_ORD_TIME' attr_value=:source_value | I31: org_units | J31: org_type | L31: users | M31: user_no
A32: 2025년 주요추진사업(NEW) | B32: 3 | C32: 계약시기 | D32: Y | E32: :source_value | F32: project_attributes | G32: attr_code='ATTR_CON_TIME' attr_value=:source_value | I32: org_units | J32: sort_order | L32: users | M32: login_id
A33: 2025년 주요추진사업(NEW) | B33: 3 | C33: 매출 | D33: N | I33: org_units | J33: is_use | L33: users | M33: password
A34: 2025년 주요추진사업(NEW) | B34: 3 | C34: 사업구도 ex) 마도 : OOO | D34: Y | E34: :source_value | F34: project_attributes | G34: attr_code='ATTR_BIZ_STR' attr_value=:source_value | I34: org_units | J34: created_at | L34: users | M34: user_name
A35: 2025년 주요추진사업(NEW) | B35: 3 | C35: 변동여부 | D35: Y | E35: :source_value | F35: project_attributes | G35: attr_code='ATTR_CHANGE' attr_value=:source_value | I35: org_units | J35: updated_at | L35: users | M35: role
A36: 2025년 주요추진사업(NEW) | B36: 3 | C36: - | D36: N | E36: :source_value | F36: project_history | G36: :source_value 내용을 파싱해서 라인의 시작부분에 일자가 형식이 있는 경우 해당일자를 base_date 일자 이후 라인의 내용을 strategy_content 에 insert ※기록된 일자 형익이 다양해서 인텔리전트하게 판단 필요 | I36: org_units | J36: created_by | L36: users | M36: is_sales_rep
A37: 2025년 주요추진사업(NEW) | B37: 3 | C37: 견적가(vat제외) | D37: Y | E37: :source_value | F37: projects | G37: quoted_amount | I37: org_units | J37: updated_by | L37: users | M37: email
A38: 2025년 주요추진사업(NEW) | B38: 3 | C38: 비고 | D38: Y | E38: :source_value | F38: projects | G38: notes | L38: users | M38: phone
A39: 2025년 주요추진사업(NEW) | B39: 3 | C39: 진행상황 및 영업전략(1) | D39: Y | E39: :source_value | F39: project_history | G39: :source_value 내용을 파싱해서 라인의 시작부분에 일자 형식이 있는 경우 해당일자를 base_date에 insert. 일자 이후 라인의 내용을 strategy_content 에 insert ※기록된 일자 형익이 다양해서 인텔리전트하게 판단 필요 | L39: users | M39: headquarters
A40: 2025년 주요추진사업(NEW) | B40: 3 | C40: 진행상황 및 영업전략(2) | D40: Y | E40: :source_value | F40: project_history | G40: :source_value 내용을 파싱해서 라인의 시작부분에 일자 형식이 있는 경우 해당일자를 base_date에 insert. 일자 이후 라인의 내용을 strategy_content 에 insert ※기록된 일자 형익이 다양해서 인텔리전트하게 판단 필요 | L40: users | M40: department
A41: 2025년 주요추진사업(NEW) | B41: 3 | C41: 진행상황 및 영업전략(3) | D41: Y | E41: :source_value | F41: project_history | G41: :source_value 내용을 파싱해서 라인의 시작부분에 일자 형식이 있는 경우 해당일자를 base_date에 insert. 일자 이후 라인의 내용을 strategy_content 에 insert ※기록된 일자 형익이 다양해서 인텔리전트하게 판단 필요 | L41: users | M41: team
A42: 2025년 주요추진사업(NEW) | B42: 3 | C42: 진행상황 및 영업전략(4) | D42: Y | E42: :source_value | F42: project_history | G42: :source_value 내용을 파싱해서 라인의 시작부분에 일자 형식이 있는 경우 해당일자를 base_date에 insert. 일자 이후 라인의 내용을 strategy_content 에 insert ※기록된 일자 형익이 다양해서 인텔리전트하게 판단 필요 | L42: users | M42: org_id
L43: users | M43: start_date
L44: users | M44: end_date
L45: users | M45: status
L46: users | M46: created_at
L47: users | M47: updated_at
L48: users | M48: created_by
L49: users | M49: updated_by

Sheet 26년 매출운영 현황
B2: ■ 2026년도 영업진행 및 계약 현황
B3: ※ 계약 고객사 파이프라인 ID 만 기입하세요(복사-붙여넣기) | O3: ※ 금액 단위 원. VAT별도
B4: 파이프라인 ID | C4: 분야 | D4: 고객사 | E4: 발주처 | F4: 사업명 | G4: 담당 | H4: 진행단계 | I4: 계약일자 | J4: 프로젝트 기간 | L4: 계약 | N4: 견적 제공 금액 | O4: 비고
J5: 시작 | K5: 종료 | L5: 수주금액 | M5: 계약금액
C6: =IF(ISERROR(VLOOKUP(B6,'2026년 주요추진사업'!C:W,2,FALSE)),"",VLOOKUP(B6,'2026년 주요추진사업'!C:W,2,FALSE)) | D6: =IF(ISERROR(VLOOKUP(B6,'2026년 주요추진사업'!C:W,3,FALSE)),"",VLOOKUP(B6,'2026년 주요추진사업'!C:W,3,FALSE)) | E6: =IF(ISERROR(VLOOKUP(B6,'2026년 주요추진사업'!C:W,4,FALSE)),"",VLOOKUP(B6,'2026년 주요추진사업'!C:W,4,FALSE)) | F6: =IF(ISERROR(VLOOKUP(B6,'2026년 주요추진사업'!C:W,5,FALSE)),"",VLOOKUP(B6,'2026년 주요추진사업'!C:W,5,FALSE)) | G6: =IF(ISERROR(VLOOKUP(B6,'2026년 주요추진사업'!C:W,6,FALSE)),"",VLOOKUP(B6,'2026년 주요추진사업'!C:W,6,FALSE)) | H6: =IF(ISERROR(VLOOKUP(B6,'2026년 주요추진사업'!C:W,7,FALSE)),"",VLOOKUP(B6,'2026년 주요추진사업'!C:W,7,FALSE)) | I6: =IF(ISERROR(VLOOKUP(B6,'2026년 주요추진사업'!C:W,13,FALSE)),"",VLOOKUP(B6,'2026년 주요추진사업'!C:W,13,FALSE)) | J6: =IF(ISERROR(VLOOKUP(B6,'2026년 주요추진사업'!C:W,14,FALSE)),"",VLOOKUP(B6,'2026년 주요추진사업'!C:W,14,FALSE)) | K6: =IF(ISERROR(VLOOKUP(B6,'2026년 주요추진사업'!C:W,15,FALSE)),"",VLOOKUP(B6,'2026년 주요추진사업'!C:W,15,FALSE)) | L6: =IF(ISERROR(VLOOKUP(B6,'2026년 주요추진사업'!C:W,16,FALSE)),"",VLOOKUP(B6,'2026년 주요추진사업'!C:W,16,FALSE)) | M6: =IF(ISERROR(VLOOKUP(B6,'2026년 주요추진사업'!C:W,17,FALSE)),"",VLOOKUP(B6,'2026년 주요추진사업'!C:W,17,FALSE)) | N6: =IF(ISERROR(VLOOKUP(B6,'2026년 주요추진사업'!C:W,10,FALSE)),"",VLOOKUP(B6,'2026년 주요추진사업'!C:W,10,FALSE))
C7: =IF(ISERROR(VLOOKUP(B7,'2026년 주요추진사업'!C:W,2,FALSE)),"",VLOOKUP(B7,'2026년 주요추진사업'!C:W,2,FALSE)) | D7: =IF(ISERROR(VLOOKUP(B7,'2026년 주요추진사업'!C:W,3,FALSE)),"",VLOOKUP(B7,'2026년 주요추진사업'!C:W,3,FALSE)) | E7: =IF(ISERROR(VLOOKUP(B7,'2026년 주요추진사업'!C:W,4,FALSE)),"",VLOOKUP(B7,'2026년 주요추진사업'!C:W,4,FALSE)) | F7: =IF(ISERROR(VLOOKUP(B7,'2026년 주요추진사업'!C:W,5,FALSE)),"",VLOOKUP(B7,'2026년 주요추진사업'!C:W,5,FALSE)) | G7: =IF(ISERROR(VLOOKUP(B7,'2026년 주요추진사업'!C:W,6,FALSE)),"",VLOOKUP(B7,'2026년 주요추진사업'!C:W,6,FALSE)) | H7: =IF(ISERROR(VLOOKUP(B7,'2026년 주요추진사업'!C:W,7,FALSE)),"",VLOOKUP(B7,'2026년 주요추진사업'!C:W,7,FALSE)) | I7: =IF(ISERROR(VLOOKUP(B7,'2026년 주요추진사업'!C:W,13,FALSE)),"",VLOOKUP(B7,'2026년 주요추진사업'!C:W,13,FALSE)) | J7: =IF(ISERROR(VLOOKUP(B7,'2026년 주요추진사업'!C:W,14,FALSE)),"",VLOOKUP(B7,'2026년 주요추진사업'!C:W,14,FALSE)) | K7: =IF(ISERROR(VLOOKUP(B7,'2026년 주요추진사업'!C:W,15,FALSE)),"",VLOOKUP(B7,'2026년 주요추진사업'!C:W,15,FALSE)) | L7: =IF(ISERROR(VLOOKUP(B7,'2026년 주요추진사업'!C:W,16,FALSE)),"",VLOOKUP(B7,'2026년 주요추진사업'!C:W,16,FALSE)) | M7: =IF(ISERROR(VLOOKUP(B7,'2026년 주요추진사업'!C:W,17,FALSE)),"",VLOOKUP(B7,'2026년 주요추진사업'!C:W,17,FALSE)) | N7: =IF(ISERROR(VLOOKUP(B7,'2026년 주요추진사업'!C:W,10,FALSE)),"",VLOOKUP(B7,'2026년 주요추진사업'!C:W,10,FALSE))
C8: =IF(ISERROR(VLOOKUP(B8,'2026년 주요추진사업'!C:W,2,FALSE)),"",VLOOKUP(B8,'2026년 주요추진사업'!C:W,2,FALSE)) | D8: =IF(ISERROR(VLOOKUP(B8,'2026년 주요추진사업'!C:W,3,FALSE)),"",VLOOKUP(B8,'2026년 주요추진사업'!C:W,3,FALSE)) | E8: =IF(ISERROR(VLOOKUP(B8,'2026년 주요추진사업'!C:W,4,FALSE)),"",VLOOKUP(B8,'2026년 주요추진사업'!C:W,4,FALSE)) | F8: =IF(ISERROR(VLOOKUP(B8,'2026년 주요추진사업'!C:W,5,FALSE)),"",VLOOKUP(B8,'2026년 주요추진사업'!C:W,5,FALSE)) | G8: =IF(ISERROR(VLOOKUP(B8,'2026년 주요추진사업'!C:W,6,FALSE)),"",VLOOKUP(B8,'2026년 주요추진사업'!C:W,6,FALSE)) | H8: =IF(ISERROR(VLOOKUP(B8,'2026년 주요추진사업'!C:W,7,FALSE)),"",VLOOKUP(B8,'2026년 주요추진사업'!C:W,7,FALSE)) | I8: =IF(ISERROR(VLOOKUP(B8,'2026년 주요추진사업'!C:W,13,FALSE)),"",VLOOKUP(B8,'2026년 주요추진사업'!C:W,13,FALSE)) | J8: =IF(ISERROR(VLOOKUP(B8,'2026년 주요추진사업'!C:W,14,FALSE)),"",VLOOKUP(B8,'2026년 주요추진사업'!C:W,14,FALSE)) | K8: =IF(ISERROR(VLOOKUP(B8,'2026년 주요추진사업'!C:W,15,FALSE)),"",VLOOKUP(B8,'2026년 주요추진사업'!C:W,15,FALSE)) | L8: =IF(ISERROR(VLOOKUP(B8,'2026년 주요추진사업'!C:W,16,FALSE)),"",VLOOKUP(B8,'2026년 주요추진사업'!C:W,16,FALSE)) | M8: =IF(ISERROR(VLOOKUP(B8,'2026년 주요추진사업'!C:W,17,FALSE)),"",VLOOKUP(B8,'2026년 주요추진사업'!C:W,17,FALSE)) | N8: =IF(ISERROR(VLOOKUP(B8,'2026년 주요추진사업'!C:W,10,FALSE)),"",VLOOKUP(B8,'2026년 주요추진사업'!C:W,10,FALSE))
C9: =IF(ISERROR(VLOOKUP(B9,'2026년 주요추진사업'!C:W,2,FALSE)),"",VLOOKUP(B9,'2026년 주요추진사업'!C:W,2,FALSE)) | D9: =IF(ISERROR(VLOOKUP(B9,'2026년 주요추진사업'!C:W,3,FALSE)),"",VLOOKUP(B9,'2026년 주요추진사업'!C:W,3,FALSE)) | E9: =IF(ISERROR(VLOOKUP(B9,'2026년 주요추진사업'!C:W,4,FALSE)),"",VLOOKUP(B9,'2026년 주요추진사업'!C:W,4,FALSE)) | F9: =IF(ISERROR(VLOOKUP(B9,'2026년 주요추진사업'!C:W,5,FALSE)),"",VLOOKUP(B9,'2026년 주요추진사업'!C:W,5,FALSE)) | G9: =IF(ISERROR(VLOOKUP(B9,'2026년 주요추진사업'!C:W,6,FALSE)),"",VLOOKUP(B9,'2026년 주요추진사업'!C:W,6,FALSE)) | H9: =IF(ISERROR(VLOOKUP(B9,'2026년 주요추진사업'!C:W,7,FALSE)),"",VLOOKUP(B9,'2026년 주요추진사업'!C:W,7,FALSE)) | I9: =IF(ISERROR(VLOOKUP(B9,'2026년 주요추진사업'!C:W,13,FALSE)),"",VLOOKUP(B9,'2026년 주요추진사업'!C:W,13,FALSE)) | J9: =IF(ISERROR(VLOOKUP(B9,'2026년 주요추진사업'!C:W,14,FALSE)),"",VLOOKUP(B9,'2026년 주요추진사업'!C:W,14,FALSE)) | K9: =IF(ISERROR(VLOOKUP(B9,'2026년 주요추진사업'!C:W,15,FALSE)),"",VLOOKUP(B9,'2026년 주요추진사업'!C:W,15,FALSE)) | L9: =IF(ISERROR(VLOOKUP(B9,'2026년 주요추진사업'!C:W,16,FALSE)),"",VLOOKUP(B9,'2026년 주요추진사업'!C:W,16,FALSE)) | M9: =IF(ISERROR(VLOOKUP(B9,'2026년 주요추진사업'!C:W,17,FALSE)),"",VLOOKUP(B9,'2026년 주요추진사업'!C:W,17,FALSE)) | N9: =IF(ISERROR(VLOOKUP(B9,'2026년 주요추진사업'!C:W,10,FALSE)),"",VLOOKUP(B9,'2026년 주요추진사업'!C:W,10,FALSE))
C10: =IF(ISERROR(VLOOKUP(B10,'2026년 주요추진사업'!C:W,2,FALSE)),"",VLOOKUP(B10,'2026년 주요추진사업'!C:W,2,FALSE)) | D10: =IF(ISERROR(VLOOKUP(B10,'2026년 주요추진사업'!C:W,3,FALSE)),"",VLOOKUP(B10,'2026년 주요추진사업'!C:W,3,FALSE)) | E10: =IF(ISERROR(VLOOKUP(B10,'2026년 주요추진사업'!C:W,4,FALSE)),"",VLOOKUP(B10,'2026년 주요추진사업'!C:W,4,FALSE)) | F10: =IF(ISERROR(VLOOKUP(B10,'2026년 주요추진사업'!C:W,5,FALSE)),"",VLOOKUP(B10,'2026년 주요추진사업'!C:W,5,FALSE)) | G10: =IF(ISERROR(VLOOKUP(B10,'2026년 주요추진사업'!C:W,6,FALSE)),"",VLOOKUP(B10,'2026년 주요추진사업'!C:W,6,FALSE)) | H10: =IF(ISERROR(VLOOKUP(B10,'2026년 주요추진사업'!C:W,7,FALSE)),"",VLOOKUP(B10,'2026년 주요추진사업'!C:W,7,FALSE)) | I10: =IF(ISERROR(VLOOKUP(B10,'2026년 주요추진사업'!C:W,13,FALSE)),"",VLOOKUP(B10,'2026년 주요추진사업'!C:W,13,FALSE)) | J10: =IF(ISERROR(VLOOKUP(B10,'2026년 주요추진사업'!C:W,14,FALSE)),"",VLOOKUP(B10,'2026년 주요추진사업'!C:W,14,FALSE)) | K10: =IF(ISERROR(VLOOKUP(B10,'2026년 주요추진사업'!C:W,15,FALSE)),"",VLOOKUP(B10,'2026년 주요추진사업'!C:W,15,FALSE)) | L10: =IF(ISERROR(VLOOKUP(B10,'2026년 주요추진사업'!C:W,16,FALSE)),"",VLOOKUP(B10,'2026년 주요추진사업'!C:W,16,FALSE)) | M10: =IF(ISERROR(VLOOKUP(B10,'2026년 주요추진사업'!C:W,17,FALSE)),"",VLOOKUP(B10,'2026년 주요추진사업'!C:W,17,FALSE)) | N10: =IF(ISERROR(VLOOKUP(B10,'2026년 주요추진사업'!C:W,10,FALSE)),"",VLOOKUP(B10,'2026년 주요추진사업'!C:W,10,FALSE))
C11: =IF(ISERROR(VLOOKUP(B11,'2026년 주요추진사업'!C:W,2,FALSE)),"",VLOOKUP(B11,'2026년 주요추진사업'!C:W,2,FALSE)) | D11: =IF(ISERROR(VLOOKUP(B11,'2026년 주요추진사업'!C:W,3,FALSE)),"",VLOOKUP(B11,'2026년 주요추진사업'!C:W,3,FALSE)) | E11: =IF(ISERROR(VLOOKUP(B11,'2026년 주요추진사업'!C:W,4,FALSE)),"",VLOOKUP(B11,'2026년 주요추진사업'!C:W,4,FALSE)) | F11: =IF(ISERROR(VLOOKUP(B11,'2026년 주요추진사업'!C:W,5,FALSE)),"",VLOOKUP(B11,'2026년 주요추진사업'!C:W,5,FALSE)) | G11: =IF(ISERROR(VLOOKUP(B11,'2026년 주요추진사업'!C:W,6,FALSE)),"",VLOOKUP(B11,'2026년 주요추진사업'!C:W,6,FALSE)) | H11: =IF(ISERROR(VLOOKUP(B11,'2026년 주요추진사업'!C:W,7,FALSE)),"",VLOOKUP(B11,'2026년 주요추진사업'!C:W,7,FALSE)) | I11: =IF(ISERROR(VLOOKUP(B11,'2026년 주요추진사업'!C:W,13,FALSE)),"",VLOOKUP(B11,'2026년 주요추진사업'!C:W,13,FALSE)) | J11: =IF(ISERROR(VLOOKUP(B11,'2026년 주요추진사업'!C:W,14,FALSE)),"",VLOOKUP(B11,'2026년 주요추진사업'!C:W,14,FALSE)) | K11: =IF(ISERROR(VLOOKUP(B11,'2026년 주요추진사업'!C:W,15,FALSE)),"",VLOOKUP(B11,'2026년 주요추진사업'!C:W,15,FALSE)) | L11: =IF(ISERROR(VLOOKUP(B11,'2026년 주요추진사업'!C:W,16,FALSE)),"",VLOOKUP(B11,'2026년 주요추진사업'!C:W,16,FALSE)) | M11: =IF(ISERROR(VLOOKUP(B11,'2026년 주요추진사업'!C:W,17,FALSE)),"",VLOOKUP(B11,'2026년 주요추진사업'!C:W,17,FALSE)) | N11: =IF(ISERROR(VLOOKUP(B11,'2026년 주요추진사업'!C:W,10,FALSE)),"",VLOOKUP(B11,'2026년 주요추진사업'!C:W,10,FALSE))
C12: =IF(ISERROR(VLOOKUP(B12,'2026년 주요추진사업'!C:W,2,FALSE)),"",VLOOKUP(B12,'2026년 주요추진사업'!C:W,2,FALSE)) | D12: =IF(ISERROR(VLOOKUP(B12,'2026년 주요추진사업'!C:W,3,FALSE)),"",VLOOKUP(B12,'2026년 주요추진사업'!C:W,3,FALSE)) | E12: =IF(ISERROR(VLOOKUP(B12,'2026년 주요추진사업'!C:W,4,FALSE)),"",VLOOKUP(B12,'2026년 주요추진사업'!C:W,4,FALSE)) | F12: =IF(ISERROR(VLOOKUP(B12,'2026년 주요추진사업'!C:W,5,FALSE)),"",VLOOKUP(B12,'2026년 주요추진사업'!C:W,5,FALSE)) | G12: =IF(ISERROR(VLOOKUP(B12,'2026년 주요추진사업'!C:W,6,FALSE)),"",VLOOKUP(B12,'2026년 주요추진사업'!C:W,6,FALSE)) | H12: =IF(ISERROR(VLOOKUP(B12,'2026년 주요추진사업'!C:W,7,FALSE)),"",VLOOKUP(B12,'2026년 주요추진사업'!C:W,7,FALSE)) | I12: =IF(ISERROR(VLOOKUP(B12,'2026년 주요추진사업'!C:W,13,FALSE)),"",VLOOKUP(B12,'2026년 주요추진사업'!C:W,13,FALSE)) | J12: =IF(ISERROR(VLOOKUP(B12,'2026년 주요추진사업'!C:W,14,FALSE)),"",VLOOKUP(B12,'2026년 주요추진사업'!C:W,14,FALSE)) | K12: =IF(ISERROR(VLOOKUP(B12,'2026년 주요추진사업'!C:W,15,FALSE)),"",VLOOKUP(B12,'2026년 주요추진사업'!C:W,15,FALSE)) | L12: =IF(ISERROR(VLOOKUP(B12,'2026년 주요추진사업'!C:W,16,FALSE)),"",VLOOKUP(B12,'2026년 주요추진사업'!C:W,16,FALSE)) | M12: =IF(ISERROR(VLOOKUP(B12,'2026년 주요추진사업'!C:W,17,FALSE)),"",VLOOKUP(B12,'2026년 주요추진사업'!C:W,17,FALSE)) | N12: =IF(ISERROR(VLOOKUP(B12,'2026년 주요추진사업'!C:W,10,FALSE)),"",VLOOKUP(B12,'2026년 주요추진사업'!C:W,10,FALSE))
C13: =IF(ISERROR(VLOOKUP(B13,'2026년 주요추진사업'!C:W,2,FALSE)),"",VLOOKUP(B13,'2026년 주요추진사업'!C:W,2,FALSE)) | D13: =IF(ISERROR(VLOOKUP(B13,'2026년 주요추진사업'!C:W,3,FALSE)),"",VLOOKUP(B13,'2026년 주요추진사업'!C:W,3,FALSE)) | E13: =IF(ISERROR(VLOOKUP(B13,'2026년 주요추진사업'!C:W,4,FALSE)),"",VLOOKUP(B13,'2026년 주요추진사업'!C:W,4,FALSE)) | F13: =IF(ISERROR(VLOOKUP(B13,'2026년 주요추진사업'!C:W,5,FALSE)),"",VLOOKUP(B13,'2026년 주요추진사업'!C:W,5,FALSE)) | G13: =IF(ISERROR(VLOOKUP(B13,'2026년 주요추진사업'!C:W,6,FALSE)),"",VLOOKUP(B13,'2026년 주요추진사업'!C:W,6,FALSE)) | H13: =IF(ISERROR(VLOOKUP(B13,'2026년 주요추진사업'!C:W,7,FALSE)),"",VLOOKUP(B13,'2026년 주요추진사업'!C:W,7,FALSE)) | I13: =IF(ISERROR(VLOOKUP(B13,'2026년 주요추진사업'!C:W,13,FALSE)),"",VLOOKUP(B13,'2026년 주요추진사업'!C:W,13,FALSE)) | J13: =IF(ISERROR(VLOOKUP(B13,'2026년 주요추진사업'!C:W,14,FALSE)),"",VLOOKUP(B13,'2026년 주요추진사업'!C:W,14,FALSE)) | K13: =IF(ISERROR(VLOOKUP(B13,'2026년 주요추진사업'!C:W,15,FALSE)),"",VLOOKUP(B13,'2026년 주요추진사업'!C:W,15,FALSE)) | L13: =IF(ISERROR(VLOOKUP(B13,'2026년 주요추진사업'!C:W,16,FALSE)),"",VLOOKUP(B13,'2026년 주요추진사업'!C:W,16,FALSE)) | M13: =IF(ISERROR(VLOOKUP(B13,'2026년 주요추진사업'!C:W,17,FALSE)),"",VLOOKUP(B13,'2026년 주요추진사업'!C:W,17,FALSE)) | N13: =IF(ISERROR(VLOOKUP(B13,'2026년 주요추진사업'!C:W,10,FALSE)),"",VLOOKUP(B13,'2026년 주요추진사업'!C:W,10,FALSE))
C14: =IF(ISERROR(VLOOKUP(B14,'2026년 주요추진사업'!C:W,2,FALSE)),"",VLOOKUP(B14,'2026년 주요추진사업'!C:W,2,FALSE)) | D14: =IF(ISERROR(VLOOKUP(B14,'2026년 주요추진사업'!C:W,3,FALSE)),"",VLOOKUP(B14,'2026년 주요추진사업'!C:W,3,FALSE)) | E14: =IF(ISERROR(VLOOKUP(B14,'2026년 주요추진사업'!C:W,4,FALSE)),"",VLOOKUP(B14,'2026년 주요추진사업'!C:W,4,FALSE)) | F14: =IF(ISERROR(VLOOKUP(B14,'2026년 주요추진사업'!C:W,5,FALSE)),"",VLOOKUP(B14,'2026년 주요추진사업'!C:W,5,FALSE)) | G14: =IF(ISERROR(VLOOKUP(B14,'2026년 주요추진사업'!C:W,6,FALSE)),"",VLOOKUP(B14,'2026년 주요추진사업'!C:W,6,FALSE)) | H14: =IF(ISERROR(VLOOKUP(B14,'2026년 주요추진사업'!C:W,7,FALSE)),"",VLOOKUP(B14,'2026년 주요추진사업'!C:W,7,FALSE)) | I14: =IF(ISERROR(VLOOKUP(B14,'2026년 주요추진사업'!C:W,13,FALSE)),"",VLOOKUP(B14,'2026년 주요추진사업'!C:W,13,FALSE)) | J14: =IF(ISERROR(VLOOKUP(B14,'2026년 주요추진사업'!C:W,14,FALSE)),"",VLOOKUP(B14,'2026년 주요추진사업'!C:W,14,FALSE)) | K14: =IF(ISERROR(VLOOKUP(B14,'2026년 주요추진사업'!C:W,15,FALSE)),"",VLOOKUP(B14,'2026년 주요추진사업'!C:W,15,FALSE)) | L14: =IF(ISERROR(VLOOKUP(B14,'2026년 주요추진사업'!C:W,16,FALSE)),"",VLOOKUP(B14,'2026년 주요추진사업'!C:W,16,FALSE)) | M14: =IF(ISERROR(VLOOKUP(B14,'2026년 주요추진사업'!C:W,17,FALSE)),"",VLOOKUP(B14,'2026년 주요추진사업'!C:W,17,FALSE)) | N14: =IF(ISERROR(VLOOKUP(B14,'2026년 주요추진사업'!C:W,10,FALSE)),"",VLOOKUP(B14,'2026년 주요추진사업'!C:W,10,FALSE))
C15: =IF(ISERROR(VLOOKUP(B15,'2026년 주요추진사업'!C:W,2,FALSE)),"",VLOOKUP(B15,'2026년 주요추진사업'!C:W,2,FALSE)) | D15: =IF(ISERROR(VLOOKUP(B15,'2026년 주요추진사업'!C:W,3,FALSE)),"",VLOOKUP(B15,'2026년 주요추진사업'!C:W,3,FALSE)) | E15: =IF(ISERROR(VLOOKUP(B15,'2026년 주요추진사업'!C:W,4,FALSE)),"",VLOOKUP(B15,'2026년 주요추진사업'!C:W,4,FALSE)) | F15: =IF(ISERROR(VLOOKUP(B15,'2026년 주요추진사업'!C:W,5,FALSE)),"",VLOOKUP(B15,'2026년 주요추진사업'!C:W,5,FALSE)) | G15: =IF(ISERROR(VLOOKUP(B15,'2026년 주요추진사업'!C:W,6,FALSE)),"",VLOOKUP(B15,'2026년 주요추진사업'!C:W,6,FALSE)) | H15: =IF(ISERROR(VLOOKUP(B15,'2026년 주요추진사업'!C:W,7,FALSE)),"",VLOOKUP(B15,'2026년 주요추진사업'!C:W,7,FALSE)) | I15: =IF(ISERROR(VLOOKUP(B15,'2026년 주요추진사업'!C:W,13,FALSE)),"",VLOOKUP(B15,'2026년 주요추진사업'!C:W,13,FALSE)) | J15: =IF(ISERROR(VLOOKUP(B15,'2026년 주요추진사업'!C:W,14,FALSE)),"",VLOOKUP(B15,'2026년 주요추진사업'!C:W,14,FALSE)) | K15: =IF(ISERROR(VLOOKUP(B15,'2026년 주요추진사업'!C:W,15,FALSE)),"",VLOOKUP(B15,'2026년 주요추진사업'!C:W,15,FALSE)) | L15: =IF(ISERROR(VLOOKUP(B15,'2026년 주요추진사업'!C:W,16,FALSE)),"",VLOOKUP(B15,'2026년 주요추진사업'!C:W,16,FALSE)) | M15: =IF(ISERROR(VLOOKUP(B15,'2026년 주요추진사업'!C:W,17,FALSE)),"",VLOOKUP(B15,'2026년 주요추진사업'!C:W,17,FALSE)) | N15: =IF(ISERROR(VLOOKUP(B15,'2026년 주요추진사업'!C:W,10,FALSE)),"",VLOOKUP(B15,'2026년 주요추진사업'!C:W,10,FALSE))
C16: =IF(ISERROR(VLOOKUP(B16,'2026년 주요추진사업'!C:W,2,FALSE)),"",VLOOKUP(B16,'2026년 주요추진사업'!C:W,2,FALSE)) | D16: =IF(ISERROR(VLOOKUP(B16,'2026년 주요추진사업'!C:W,3,FALSE)),"",VLOOKUP(B16,'2026년 주요추진사업'!C:W,3,FALSE)) | E16: =IF(ISERROR(VLOOKUP(B16,'2026년 주요추진사업'!C:W,4,FALSE)),"",VLOOKUP(B16,'2026년 주요추진사업'!C:W,4,FALSE)) | F16: =IF(ISERROR(VLOOKUP(B16,'2026년 주요추진사업'!C:W,5,FALSE)),"",VLOOKUP(B16,'2026년 주요추진사업'!C:W,5,FALSE)) | G16: =IF(ISERROR(VLOOKUP(B16,'2026년 주요추진사업'!C:W,6,FALSE)),"",VLOOKUP(B16,'2026년 주요추진사업'!C:W,6,FALSE)) | H16: =IF(ISERROR(VLOOKUP(B16,'2026년 주요추진사업'!C:W,7,FALSE)),"",VLOOKUP(B16,'2026년 주요추진사업'!C:W,7,FALSE)) | I16: =IF(ISERROR(VLOOKUP(B16,'2026년 주요추진사업'!C:W,13,FALSE)),"",VLOOKUP(B16,'2026년 주요추진사업'!C:W,13,FALSE)) | J16: =IF(ISERROR(VLOOKUP(B16,'2026년 주요추진사업'!C:W,14,FALSE)),"",VLOOKUP(B16,'2026년 주요추진사업'!C:W,14,FALSE)) | K16: =IF(ISERROR(VLOOKUP(B16,'2026년 주요추진사업'!C:W,15,FALSE)),"",VLOOKUP(B16,'2026년 주요추진사업'!C:W,15,FALSE)) | L16: =IF(ISERROR(VLOOKUP(B16,'2026년 주요추진사업'!C:W,16,FALSE)),"",VLOOKUP(B16,'2026년 주요추진사업'!C:W,16,FALSE)) | M16: =IF(ISERROR(VLOOKUP(B16,'2026년 주요추진사업'!C:W,17,FALSE)),"",VLOOKUP(B16,'2026년 주요추진사업'!C:W,17,FALSE)) | N16: =IF(ISERROR(VLOOKUP(B16,'2026년 주요추진사업'!C:W,10,FALSE)),"",VLOOKUP(B16,'2026년 주요추진사업'!C:W,10,FALSE))
C17: =IF(ISERROR(VLOOKUP(B17,'2026년 주요추진사업'!C:W,2,FALSE)),"",VLOOKUP(B17,'2026년 주요추진사업'!C:W,2,FALSE)) | D17: =IF(ISERROR(VLOOKUP(B17,'2026년 주요추진사업'!C:W,3,FALSE)),"",VLOOKUP(B17,'2026년 주요추진사업'!C:W,3,FALSE)) | E17: =IF(ISERROR(VLOOKUP(B17,'2026년 주요추진사업'!C:W,4,FALSE)),"",VLOOKUP(B17,'2026년 주요추진사업'!C:W,4,FALSE)) | F17: =IF(ISERROR(VLOOKUP(B17,'2026년 주요추진사업'!C:W,5,FALSE)),"",VLOOKUP(B17,'2026년 주요추진사업'!C:W,5,FALSE)) | G17: =IF(ISERROR(VLOOKUP(B17,'2026년 주요추진사업'!C:W,6,FALSE)),"",VLOOKUP(B17,'2026년 주요추진사업'!C:W,6,FALSE)) | H17: =IF(ISERROR(VLOOKUP(B17,'2026년 주요추진사업'!C:W,7,FALSE)),"",VLOOKUP(B17,'2026년 주요추진사업'!C:W,7,FALSE)) | I17: =IF(ISERROR(VLOOKUP(B17,'2026년 주요추진사업'!C:W,13,FALSE)),"",VLOOKUP(B17,'2026년 주요추진사업'!C:W,13,FALSE)) | J17: =IF(ISERROR(VLOOKUP(B17,'2026년 주요추진사업'!C:W,14,FALSE)),"",VLOOKUP(B17,'2026년 주요추진사업'!C:W,14,FALSE)) | K17: =IF(ISERROR(VLOOKUP(B17,'2026년 주요추진사업'!C:W,15,FALSE)),"",VLOOKUP(B17,'2026년 주요추진사업'!C:W,15,FALSE)) | L17: =IF(ISERROR(VLOOKUP(B17,'2026년 주요추진사업'!C:W,16,FALSE)),"",VLOOKUP(B17,'2026년 주요추진사업'!C:W,16,FALSE)) | M17: =IF(ISERROR(VLOOKUP(B17,'2026년 주요추진사업'!C:W,17,FALSE)),"",VLOOKUP(B17,'2026년 주요추진사업'!C:W,17,FALSE)) | N17: =IF(ISERROR(VLOOKUP(B17,'2026년 주요추진사업'!C:W,10,FALSE)),"",VLOOKUP(B17,'2026년 주요추진사업'!C:W,10,FALSE))
... C119: =IF(ISERROR(VLOOKUP(B119,'2026년 주요추진사업'!C:W,2,FALSE)),"",VLOOKUP(B119,'2026년 주요추진사업'!C:W,2,FALSE)) | D119: =IF(ISERROR(VLOOKUP(B119,'2026년 주요추진사업'!C:W,3,FALSE)),"",VLOOKUP(B119,'2026년 주요추진사업'!C:W,3,FALSE)) | E119: =IF(ISERROR(VLOOKUP(B119,'2026년 주요추진사업'!C:W,4,FALSE)),"",VLOOKUP(B119,'2026년 주요추진사업'!C:W,4,FALSE)) | F119: =IF(ISERROR(VLOOKUP(B119,'2026년 주요추진사업'!C:W,5,FALSE)),"",VLOOKUP(B119,'2026년 주요추진사업'!C:W,5,FALSE)) | G119: =IF(ISERROR(VLOOKUP(B119,'2026년 주요추진사업'!C:W,6,FALSE)),"",VLOOKUP(B119,'2026년 주요추진사업'!C:W,6,FALSE)) | H119: =IF(ISERROR(VLOOKUP(B119,'2026년 주요추진사업'!C:W,7,FALSE)),"",VLOOKUP(B119,'2026년 주요추진사업'!C:W,7,FALSE)) | I119: =IF(ISERROR(VLOOKUP(B119,'2026년 주요추진사업'!C:W,13,FALSE)),"",VLOOKUP(B119,'2026년 주요추진사업'!C:W,13,FALSE)) | J119: =IF(ISERROR(VLOOKUP(B119,'2026년 주요추진사업'!C:W,14,FALSE)),"",VLOOKUP(B119,'2026년 주요추진사업'!C:W,14,FALSE)) | K119: =IF(ISERROR(VLOOKUP(B119,'2026년 주요추진사업'!C:W,15,FALSE)),"",VLOOKUP(B119,'2026년 주요추진사업'!C:W,15,FALSE)) | L119: =IF(ISERROR(VLOOKUP(B119,'2026년 주요추진사업'!C:W,16,FALSE)),"",VLOOKUP(B119,'2026년 주요추진사업'!C:W,16,FALSE)) | M119: =IF(ISERROR(VLOOKUP(B119,'2026년 주요추진사업'!C:W,17,FALSE)),"",VLOOKUP(B119,'2026년 주요추진사업'!C:W,17,FALSE)) | N119: =IF(ISERROR(VLOOKUP(B119,'2026년 주요추진사업'!C:W,10,FALSE)),"",VLOOKUP(B119,'2026년 주요추진사업'!C:W,10,FALSE))
H121: 합계 | L121: =SUM(L6:L119) -> 0 | M121: =SUM(M6:M119) -> 0

Sheet 2026년 주요추진사업
B1: 2026년도 신사업개발/엔터프라이즈컨설팅팀 주요사업 추진 내역
B2: ※ 작성법: 담당 고객사 위에 행 삽입 후 복사-붙여넣기. 업무기준일~진행상황 및 영업전략 작성.
B3: 주차 | C3: 파이프라인 ID | D3: 분야 | E3: 고객사 | F3: 발주처 | G3: 사업명 | H3: 담당자 | I3: 진행단계 | J3: 업무 기준일 | K3: 진행상황 및 영업전략 | L3: 견적금액 단위 원. VAT제외 | M3: 발주시기(예상) | N3: 계약시기(예상) | O3: 계약일자 | P3: 프로젝트기간(시작) | Q3: 프로젝트기간(종료) | R3: 계약(수주금액) 단위 원. VAT제외 | S3: 계약(계약금액) 단위 원. VAT제외 | T3: 매출 | U3: 사업구도 ex) 마도 : OOO | V3: 이전 파이프라인 | W3: 비고
B4: =IF(ISERROR(VLOOKUP(J4,'==='!B:E,4,FALSE)),"",VLOOKUP(J4,'==='!B:E,4,FALSE)) -> 1월 2주 | C4: 2026-014 | D4: AICC | E4: 경찰청 | F4: 펜타시스템 | G4: 경찰청 경찰견문관리시스템 고도화 사업(STT) | H4: 오민규 | I4: 7 수주완료 | J4: 46036 | K4: - PJT 시작일정: 5~6월 예상 (※ 발주 3~4월) . STT 솔루션 타사 견적 확인중(사운드마인드) | V4: 2025-065
B5: =IF(ISERROR(VLOOKUP(J5,'==='!B:E,4,FALSE)),"",VLOOKUP(J5,'==='!B:E,4,FALSE)) -> 1월 2주 | C5: 2026-016 | D5: 수어 | E5: 국립인천해양박물관 | F5: 국립인천해양박물관 | G5: 국립인천해양박물관 안내 및 전시정보 영상 제작 | H5: 양승구 | I5: 2 견적제출 | J5: 46036 | K5: 국립인천해양박물관 - 박물관 안내 및 전시정보스포츠안전관련 홍보팀 업무 담당 - 디지털미디어부 학예연구사 님과 협의 후 견적서 제출 (27년도 예산 산출) - 표준 견적서 제출 후 문구 확정하면 최종 견적서 제공 - 수어 인식율에 대한 문의 (현재 미약함 - 60%정도, 현재 연구 중이며, 개선 진행 중) | L5: 132000 | M5: 12월 | U5: 단독
B6: =IF(ISERROR(VLOOKUP(J6,'==='!B:E,4,FALSE)),"",VLOOKUP(J6,'==='!B:E,4,FALSE)) -> 2월 1주 | C6: 2026-015 | D6: 수어 | E6: 국민체육진흥공단 | F6: 국민체육진흥공단 | G6: 국민체육진흥공단 체육시설 안전 홍보 안내 AI수어 아바타 영상 제작 | H6: 임철현 | I6: 1 영업중 | J6: 46056 | K6: 국민체육진흥공단 스포츠시설안전실 안전교육팀 김수빈대리 통화 - 타업무로 인하여 내부 스포츠안전 영상관련 우선순위 선정 및 관련농인 인터뷰 업무 지연, 차주 진행사항 체크 예정
B7: =IF(ISERROR(VLOOKUP(J7,'==='!B:E,4,FALSE)),"",VLOOKUP(J7,'==='!B:E,4,FALSE)) -> 1월 3주 | C7: 2026-015 | D7: 수어 | E7: 국민체육진흥공단 | F7: 국민체육진흥공단 | G7: 국민체육진흥공단 체육시설 안전 홍보 안내 AI수어 아바타 영상 제작 | H7: 임철현 | I7: 1 영업중 | J7: 46043 | K7: 국민체육진흥공단 스포츠시설안전실 안전교육팀 김수빈대리 통화 - 스포츠안전관련 내부 보고관련 기획안 제공 - 내부 스포츠안전 영상관련 우선순위 선정 및 관련농인 인터뷰등 진행예정, 2월초 진행사항관련 재협의 하기로 함
B8: =IF(ISERROR(VLOOKUP(J8,'==='!B:E,4,FALSE)),"",VLOOKUP(J8,'==='!B:E,4,FALSE)) -> 1월 2주 | C8: 2026-015 | D8: 수어 | E8: 국민체육진흥공단 | F8: 국민체육진흥공단 | G8: 국민체육진흥공단 체육시설 안전 홍보 안내 AI수어 아바타 영상 제작 | H8: 임철현 | I8: 1 영업중 | J8: 46036 | K8: 국민체육진흥공단 스포츠시설안전실 안전교육팀 김수빈대리 미팅 - 스포츠안전관련 홍보팀 업무 담당 - 공단내 스포츠안전관련 홍보영상 다수 보유 중이며 국정과제 기반 기 홍보중인 영상에 Ai수어아바타 서비스를 적용하는 시범서비스 계획중 - 홍보예산 1.4억 중 일부(2~3천만원)를 명확하게 금액을 얘기 하진 않음, 기보유 홍보영상 3~5개에 수어아바타 시범 적용을 계획 L 차주 월요일까지 내부 보고관련 기획안 제공을 제안드림
B9: =IF(ISERROR(VLOOKUP(J9,'==='!B:E,4,FALSE)),"",VLOOKUP(J9,'==='!B:E,4,FALSE)) -> 1월 2주 | C9: 2026-018 | D9: 수어 | E9: 남양주수어통역센터 | F9: 남양주수어통역센터 | G9: 남양주수어통역센터 당사 핸드사인톡톡 입정 협의 | H9: 양승구 | I9: 3 제안중 | J9: 46036 | K9: 남양주시수어통역센터 "당사 핸드사인툭툭 입정"에 따른 공문 발송 - 담당자 공분 수보 완료, 내부 검토 후 진행에 대한 협의예정 (1.16일 전화 연럭 후 확인)
C10: 2026-018 | D10: 수어 | E10: 남양주수어통역센터 | F10: 남양주수어통역센터 | G10: 남양주수어통역센터 당사 핸드사인톡톡 입정 협의 | H10: 양승구 | I10: 3 제안중 | J10: 46043 | K10: 남양주시수어통역센터 담당자님 이직에 따른 남양주시 시각장애인협회 센터장님 미팅 - 당사 소개 및 추후 시각장애인을 위한 사업 진행시 조언 요청 (적극 지원 하겠음 - 당사 서울 120다산콜재단 사업 진행시 조언 요청 하겠음)
B11: =IF(ISERROR(VLOOKUP(J11,'==='!B:E,4,FALSE)),"",VLOOKUP(J11,'==='!B:E,4,FALSE)) -> 1월 2주 | C11: 2026-016 | D11: 수어 | E11: 남양주시청 | F11: 남양주시청 홍보과 | G11: 남양주시청 시장님 신년인사에 AI수어 구축 | H11: 양승구 | I11: 6 실주 | J11: 46036 | K11: AI 수어를 일반 수어통역사를 통해서 사업을 진행하는 것으로 변경 - 16어절 당사 300만원, 일반 수어통역사 비용 - 30만원 사유로 일반통역사의 촬영으로 사업 변경하여 진향
B12: =IF(ISERROR(VLOOKUP(J12,'==='!B:E,4,FALSE)),"",VLOOKUP(J12,'==='!B:E,4,FALSE)) -> 1월 2주 | C12: 2026-001 | D12: AICC | E12: 모던텍 | F12: 모던텍 | G12: 모던텍 음성봇(SaaS) 도입 및 고객센터 운영 | H12: 오민규 | I12: 3 제안중 | J12: 46031 | K12: - 담당자 미팅 : 1/8 조원부장 . 전체적인 비용효과가 크지 않아 추진 부정적(5개년 52백만원 ↓) . 현 상담센터 최저가 운영중. 최근 충전기 고장/오류 통합관리시스템 오픈으로 운영 애로사항 많이 개선됨 . 초기 검토시 퀄리티&비용효율화 도모하였으나, 비용 최우선으로 검토중 . 결제, 고장신고 등의 클레임성 고객 전화로 AI보다는 상담사 직접 대응이 효율적으로 판단됨 | V12: 2025-104
B13: =IF(ISERROR(VLOOKUP(J13,'==='!B:E,4,FALSE)),"",VLOOKUP(J13,'==='!B:E,4,FALSE)) -> 1월 2주 | C13: 2026-019 | D13: 수어 | E13: 법원행정처 | F13: 법원행정처 | G13: 법원행정처 교육자료 AI 수어영상 제작 | H13: 양승구 | I13: 1 영업중 | J13: 46037 | K13: 기 구축한 "법정수어통역 표준 교육자료 발간을 위한 수어영상 제작" 사용에 대한 문의 - 당사 AI 수어서비스의 제안 및 수어용어집 진행 가능성에 댜헌 협의
B14: =IF(ISERROR(VLOOKUP(J14,'==='!B:E,4,FALSE)),"",VLOOKUP(J14,'==='!B:E,4,FALSE)) -> 2월 1주 | C14: 2026-005 | D14: 수어 | E14: 식품안전정보원 | F14: 식품안전정보원 | G14: 식품안전정보원 실시간 식품정보 수어 영상 제공 프로그램 개발 용역 | H14: 임철현 | I14: 4 입찰중 | J14: 46055 | K14: - 기술협상대상자 선정 확인 - 02.05. 14:00 기술협상 진행예정 | L14: =49950000/1.1 -> 45409091 | M14: 1월 | N14: 1월 말 또는 2월 초 | P14: 계약일 | Q14: 46203 | U14: 주관사 | V14: 2025-117
B15: =IF(ISERROR(VLOOKUP(J15,'==='!B:E,4,FALSE)),"",VLOOKUP(J15,'==='!B:E,4,FALSE)) -> 1월 4주 | C15: 2026-005 | D15: 수어 | E15: 식품안전정보원 | F15: 식품안전정보원 | G15: 식품안전정보원 실시간 식품정보 수어 영상 제공 프로그램 개발 용역 | H15: 임철현 | I15: 3 제안중 | J15: 46051 | K15: - 01/29 제안발표관련 (발표자: 허길량부장, 동석자: 이하형팀장,임철현) L 14:50분부터 발표 L 3개사 참여 확인, 당사 발표 - 01/28 제안발표관련 최종 리뷰(허길량대표, 이하형팀장) | M15: 1월 | N15: 1월 말 또는 2월 초 | P15: 계약일 | Q15: 46203 | U15: 주관사 | V15: 2025-117
B16: =IF(ISERROR(VLOOKUP(J16,'==='!B:E,4,FALSE)),"",VLOOKUP(J16,'==='!B:E,4,FALSE)) -> 1월 3주 | C16: 2026-005 | D16: 수어 | E16: 식품안전정보원 | F16: 식품안전정보원 | G16: 식품안전정보원 실시간 식품정보 수어 영상 제공 프로그램 개발 용역 | H16: 임철현 | I16: 3 제안중 | J16: 46043 | K16: - 01/21 제안발표관련 1차 리뷰(허길량대표, 이하형팀장) L 발표자료관련 당사 강점 설명 및 발표시 전략등 협의 L 차주 월요일 또는 화요일 2차 리뷰 진행 협의 L 제안발표장 참석자(안): 허길양(PM), 이하형팀장, 임철현 | M16: 1월 | N16: 1월 말 또는 2월 초 | P16: 계약일 | Q16: 46203 | U16: 주관사 | V16: 2025-117
B17: =IF(ISERROR(VLOOKUP(J17,'==='!B:E,4,FALSE)),"",VLOOKUP(J17,'==='!B:E,4,FALSE)) -> 1월 2주 | C17: 2026-005 | D17: 수어 | E17: 식품안전정보원 | F17: 식품안전정보원 | G17: 식품안전정보원 실시간 식품정보 수어 영상 제공 프로그램 개발 용역 | H17: 임철현 | I17: 3 제안중 | J17: 46037 | K17: - 01-14 제안서 작성관련 제안팀 및 협력사(허시정보) 미팅 진행/ 참석자: 김태형, 고윤창, 김해밝음, 백승준, 임철현, 허시정보(허길양대표) L 제안서 기술파트 및 발표자료 허시정보 작성, 그외 파트 사업제안팀 작성, 1차 완료 16일까지 진행 - 01-15 고객사(임현수 선임연구원) 미팅 w 허길양 L RFP관련 문의 및 정보 취득, 고객사 금번 사업외 향후 사업 발전방안(식품표시정보 수정영상등 활용)에 대해서도 제안 요청 접수 L 경쟁사(멀틱스)관련 정보 취득, 제안서 작성관련 문의 있었다고 함. | M17: 1월 | N17: 1월 말 또는 2월 초 | P17: 계약일 | Q17: 46203 | U17: 주관사 | V17: 2025-117
B18: =IF(ISERROR(VLOOKUP(J18,'==='!B:E,4,FALSE)),"",VLOOKUP(J18,'==='!B:E,4,FALSE)) -> 1월 2주 | C18: 2026-005 | D18: 수어 | E18: 식품안전정보원 | F18: 식품안전정보원 | G18: 식품안전정보원 실시간 식품정보 수어 영상 제공 프로그램 개발 용역 | H18: 임철현 | I18: 3 제안중 | J18: 46035 | K18: - 입찰공고: 01/06 공동수급(마감): 01/19 18:00까지 제안마감: 01/20 10:00 -> 단독 제안 및 제안전략관련 고객사 미팅 | M18: 1월 | N18: 1월 말 또는 2월 초 | P18: 계약일 | Q18: 46203 | U18: 주관사 | V18: 2025-117
B19: =IF(ISERROR(VLOOKUP(J19,'==='!B:E,4,FALSE)),"",VLOOKUP(J19,'==='!B:E,4,FALSE)) -> 1월 2주 | C19: 2026-004 | D19: AICC | E19: 티플리스 | F19: - | G19: 티플리스 공공기관, 지자체 AICC. MOU | H19: 오민규 | I19: 1 영업중 | J19: 46037 | K19: - 차주 미팅 예정(김동훈그룹장 외. 일정 미정) | V19: -
B20: =IF(ISERROR(VLOOKUP(J20,'==='!B:E,4,FALSE)),"",VLOOKUP(J20,'==='!B:E,4,FALSE)) -> 2월 1주 | C20: 2026-013 | D20: 수어 | E20: 현성컨버전스 | F20: 현성컨버전스 | G20: 현성컨버전스 엘리베이터 비상통화장치 수어서비스 | H20: 임철현 | I20: 1 영업중 | J20: 46056 | K20: 현성컨버전스 김정록팀장, 김용호연구소장 미팅 L 비상통화장치기기내 카메라로 수어인식 문제점 설명 및 당사 롤기반 수어봇 기술 제안 협의 L 개발팀 경유 당사 수어봇 HW적정스펙 공유 예정 L 승강기공단(김희석과장) 현재상황관련 설명 및 기술자료 제공, 내부 검토후 이견있을경우 재통화 하기로 함
B21: =IF(ISERROR(VLOOKUP(J21,'==='!B:E,4,FALSE)),"",VLOOKUP(J21,'==='!B:E,4,FALSE)) -> 1월 4주 | C21: 2026-013 | D21: 수어 | E21: 현성컨버전스 | F21: 현성컨버전스 | G21: 현성컨버전스 엘리베이터 비상통화장치 수어서비스 | H21: 임철현 | I21: 1 영업중 | J21: 46051 | K21: 전략기획실 미팅(김민선, 안혜신, 임철현) L 현성컨버전스 및 승강기안전공단 제안 기술(비상통화장치기기내 카메라로 수어인식)에 대한 문제점 자료 준비 및 당사 롤기반 수어봇 기술 제안 협의 L 개발팀 기술자료 준비시 차주 화, 수중 현성컨버전스 영업과 협의 진행 예정
B22: =IF(ISERROR(VLOOKUP(J22,'==='!B:E,4,FALSE)),"",VLOOKUP(J22,'==='!B:E,4,FALSE)) -> 1월 2주 | C22: 2026-013 | D22: 수어 | E22: 현성컨버전스 | F22: 현성컨버전스 | G22: 현성컨버전스 엘리베이터 비상통화장치 수어서비스 | H22: 임철현 | I22: 1 영업중 | J22: 46035 | K22: 현성컨버전스 대표이사, 연구소장, 영업팀장 미팅 - 현성컨버전스에서 엘리베이터 비상통화장치 KC 안전 인증 취득(25.07.07) - 자체 비상통화장치에 시청각 장애인을 위한 수어 및 음성서비스 고려 중 L 현황: 엘리베이터에 설치된 비상통화장치에 있는 카메라(화소: 2M픽셀)를 통해 수어 인식-> 음성으로 전환하여 상황실 화상전화기로 전달 되는 방식을 구상 중임 -> 당사 룰베이스 기반 수어봇으로 서비스 전환을 제안 및 비상상황에 대한 질의응답 사례 수집 요청 함/ 당사 제안에 대해 내부 검토 하기로 함. 당사 기술팀에서도 카메라를 통한 실시간 수어인식 및 상황실로 음성전달 가능 여부 확인 하기로 함 이슈사항: 현성의 비상통화서비스는 Server-Client 구성으로 제안중에 있으며 1Server에 100 ~ 1,000대의 비상통화장치 연결이 가능 하다고 함 비상통화장치 시장은 대당 3만원 대로 공급되고 있으나, 현성은 조금더 고가로 시장인식 있다고 함. 이에 대해 비상통화장치외 서버비용을 임대형식으로 제안공급 중 임 당사 수어서비스 적용시 원가 상승에 대한 고민 있으나 당사와의 협업을 하고자 함
B23: =IF(ISERROR(VLOOKUP(J23,'==='!B:E,4,FALSE)),"",VLOOKUP(J23,'==='!B:E,4,FALSE)) -> 1월 2주 | C23: 2026-010 | D23: 수어 | E23: KB국민은행 | F23: KB국민은행 | G23: KB국민은행 AI 수어 상담에 대한 챗봇 연계 구축 | H23: 양승구 | I23: 3 제안중 | J23: 46037 | K23: 본 프로젝트 담당자 소개 및 사업의 진행 방향 협의 - 사업의 진행이 느리지만 시작 예정(1월초 --> 설 이후) , 지속적인 협의 진행 | V23: 2025-084
B24: =IF(ISERROR(VLOOKUP(J24,'==='!B:E,4,FALSE)),"",VLOOKUP(J24,'==='!B:E,4,FALSE)) -> 1월 1주 | C24: 2026-002 | D24: 수어 | E24: (주)서원 | F24: (주)서원 | G24: (주)서원 고속도록 휴게소 배리어프리 무인발권기 도입사업 | H24: 오민규 | I24: 1 영업중 | J24: 46028 | K24: - 담당자 연락 : 임재현팀장(퇴사함) . 2025년 7월 선산휴게소 사업 제안시 당사 수어 제안하였으나 실주함 . 신규 서원 담당자 연락처 요청하며 명함 전달함 | V24: 2025-056
B25: =IF(ISERROR(VLOOKUP(J25,'==='!B:E,4,FALSE)),"",VLOOKUP(J25,'==='!B:E,4,FALSE)) -> 1월 3주 | C25: 2026-010 | D25: 수어 | E25: KB국민은행 | F25: KB국민은행 | G25: KB국민은행 AI 수어 상담에 대한 챗봇 연계 구축 | H25: 양승구 | I25: 3 제안중 | J25: 46042 | K25: 프로젝트 담당자 변경에 따른 지속적인 관계 개선 작업 진행 | V25: 2025-084
B26: =IF(ISERROR(VLOOKUP(J26,'==='!B:E,4,FALSE)),"",VLOOKUP(J26,'==='!B:E,4,FALSE)) -> 1월 4주 | C26: 2026-010 | D26: 수어 | E26: KB국민은행 | F26: KB국민은행 | G26: KB국민은행 AI 수어 상담에 대한 챗봇 연계 구축 | H26: 양승구 | I26: 3 제안중 | J26: 46050 | K26: 디지털데스크의 화상 시스템 Upgrade 구축시 당사의 수어 솔루션 추가에 따른 협의 미팅 - PC,모바일, DD에서 수어 서비스 시스템이 구축 될 수 있는 방안 협의, 시스템 구서으, 서비스 방아느 구축 일정, M/M 등에 대한 제안 요청 받음 - 견적서 차주 제공 요청 - 진행일정 : 2~3월 RFP 발송, 4중 프로젝트 시작 예정으로 KB데이타시스템 단독 제안으로 구축 * 양방향의 소통과 수어 운영 데이타의 관리 방안에 대한 구축적인 일정 요청 --> 1.30일 정리하여 메일 전송 | V26: 2025-084
B27: =IF(ISERROR(VLOOKUP(J27,'==='!B:E,4,FALSE)),"",VLOOKUP(J27,'==='!B:E,4,FALSE)) -> 2월 1주 | C27: 2026-010 | D27: 수어 | E27: KB국민은행 | F27: KB국민은행 | G27: KB국민은행 AI 수어 상담에 대한 챗봇 연계 구축 | H27: 양승구 | I27: 3 제안중 | J27: 46056 | K27: 견적서 자료 제출 : 3.5억 (300문장 기준), 현재 KB테이타시스템 및 페르미 견적서 통합하여 진행 예정 - 진행일정 : 2~3월 RFP 발송, 4중 프로젝트 시작 예정으로 KB데이타시스템 단독 제안으로 구축 * 양방향의 소통과 수어 운영 데이타의 관리 방안에 대한 구축적인 일정 요청 --> 1.30일 정리하여 메일 전송 완료 | V27: 2025-084
B28: =IF(ISERROR(VLOOKUP(J28,'==='!B:E,4,FALSE)),"",VLOOKUP(J28,'==='!B:E,4,FALSE)) -> 1월 1주 | C28: 2026-009 | D28: 수어 | E28: 120다산콜재단 | F28: 120다산콜재단 | G28: 120다산콜재단 AI수어 시스템 구축 | H28: 양승구 | I28: 3 제안중 | J28: 46027 | K28: 120다산콜센터와 KL큐브 업무 협약식 진행 - 2026.1.5 11:00 120다산콜재단 이사장실, 이사장님 및 관계자 참여하여 업무협약식 진행 - AI수어시스템의 구축, 서비스 고도화 와 수어 상담에 대한 공동 연구 진행 - 우선 사업 진행 사항 : 행정용어 수어 사전 제작을 최우선으로 진행 : 26년 2월가지 서비스 방안 확정, 3월부터 구축하는 방안으로 추진 - 다산콜센터는 홈페이지 및 챗봇 구축 방안으로 협의 진행(스마트 전산부장 업무 미팅 추진) | V28: -
B29: =IF(ISERROR(VLOOKUP(J29,'==='!B:E,4,FALSE)),"",VLOOKUP(J29,'==='!B:E,4,FALSE)) -> 1월 3주 | C29: 2026-009 | D29: 수어 | E29: 120다산콜재단 | F29: 120다산콜재단 | G29: 120다산콜재단 AI수어 시스템 구축 | H29: 양승구 | I29: 3 제안중 | J29: 46041 | K29: 120다산콜센터의 콜 업무 분석을 위한 인력 파견 - 다산콜재단의 수어 상담의 현황 및 업무 분석 후 개선 방안 수립 - 기간 : 1.20 ~ 30일까지 오민규부장 파견하여 업무 분석 진행 후 Report 작성 제안 예정 - 서울시 행정용어집 구축을 위한 사전 자료 분석 : 제안을 위한 제언서 2차 준비 완료 | V29: -
B30: =IF(ISERROR(VLOOKUP(J30,'==='!B:E,4,FALSE)),"",VLOOKUP(J30,'==='!B:E,4,FALSE)) -> 2월 1주 | C30: 2026-009 | D30: 수어 | E30: 120다산콜재단 | F30: 120다산콜재단 | G30: 120다산콜재단 AI수어 시스템 구축 | H30: 양승구 | I30: 3 제안중 | J30: 46057 | K30: 120다산콜센터의 상담콜의 업무 분석 완료(1.30일, 2월 3일 보고서 작성 완료) - 다산콜재단 수어상담 현황 분석자료 완료(보고서 작성) - 다산콜재단은 행정용어집 구축 방향으로 제안 (용어의 선정 - 행정업무 위주로 선정, 홈페이지와 연계 Page로 구성) - 2월 계약, 3월 개발, 4월 오픈 일정으로 진행 예정, 구축 예산 범위로 업무 개발 진행(비용은 차주 확정) | V30: -
B31: =IF(ISERROR(VLOOKUP(J31,'==='!B:E,4,FALSE)),"",VLOOKUP(J31,'==='!B:E,4,FALSE)) -> 1월 1주 | C31: 2026-011 | D31: 수어 | E31: 건양대학교 | F31: 건양대학교 | G31: 건양대학교 간호대학 AI 수어 시스템 구축 | H31: 양승구 | I31: 3 제안중 | J31: 46028 | K31: 당사의 핸드사인 톡톡에 대한솔루션 셜명 - 당사의 제안 솔루션에 대한 호의적인 반응, 현재 당사만 솔루션 검토 진행 중이며, 당사 핸드사인툭톡에서 설문지의 기능을 추가 요청 (개발 가능함) - AI 수어 플랫폼의 핸드사인 버스의 구독형 서비스로 제안, 수어 영상에 관심을 가지고 있으며, 기존에 간호학과에서 청각 장애인을 위한 연구가 많이 이루어 졌음 - "인공지능 수어 통역 건강코칭을 활요한 청각장애인의 고협압 자기관리 중애 개발 및 효과 평가" 3개년 연구 과재로 진행, 개인 연구 과ㅈ제, 비용은 4억 예산 - 진행일정 : 1월 검토 완료, 2월 확정, 3월 계약, 4월 부터 연구과제 진행 의 일정으로 수행 - 지속적인 영업관리로 진행 | V31: -
B32: =IF(ISERROR(VLOOKUP(J32,'==='!B:E,4,FALSE)),"",VLOOKUP(J32,'==='!B:E,4,FALSE)) -> 1월 1주 | C32: 2026-001 | D32: AICC | E32: 모던텍 | F32: 모던텍 | G32: 모던텍 음성봇(SaaS) 도입 및 고객센터 운영 | H32: 오민규 | I32: 3 제안중 | J32: 46028 | K32: - 담당자 미팅 예정 : 1/8 조원부장 | V32: 2025-104
B33: =IF(ISERROR(VLOOKUP(J33,'==='!B:E,4,FALSE)),"",VLOOKUP(J33,'==='!B:E,4,FALSE)) -> 1월 4주 | C33: 2026-007 | D33: 수어 | E33: 문화체육관광부 국립국어원 | F33: 문화체육관광부 국립국어원 | G33: 국립국어원 2026년 한국수어-한국어 사전 자료 집필 | H33: 임철현 | I33: 8 계약완료 | J33: 46050 | K33: - 선급금(70%, 562,990,910원VAT별도) 나라장터 경유 청구완료 L 차주 초 대금수금 예정 | P33: 46020 | Q33: 46371 | R33: =884700000/1.1 -> 8.0427273e+08 | S33: =884700000/1.1 -> 8.0427273e+08 | U33: 단독 | V33: 2025-090
B34: =IF(ISERROR(VLOOKUP(J34,'==='!B:E,4,FALSE)),"",VLOOKUP(J34,'==='!B:E,4,FALSE)) -> 1월 3주 | C34: 2026-007 | D34: 수어 | E34: 문화체육관광부 국립국어원 | F34: 문화체육관광부 국립국어원 | G34: 국립국어원 2026년 한국수어-한국어 사전 자료 집필 | H34: 임철현 | I34: 8 계약완료 | J34: 46041 | K34: - 선급금(70%) 신청관련 당사 실적증명서 발행 및 장철성부장전달 L 조달청 경유 선급금 신청시 영업팀에서 지원하기로 협의 함 | P34: 46020 | Q34: 46371 | R34: =884700000/1.1 -> 8.0427273e+08 | S34: =884700000/1.1 -> 8.0427273e+08 | U34: 단독 | V34: 2025-090
B35: =IF(ISERROR(VLOOKUP(J35,'==='!B:E,4,FALSE)),"",VLOOKUP(J35,'==='!B:E,4,FALSE)) -> 1월 1주 | C35: 2026-007 | D35: 수어 | E35: 문화체육관광부 국립국어원 | F35: 문화체육관광부 국립국어원 | G35: 국립국어원 2026년 한국수어-한국어 사전 자료 집필 | H35: 임철현 | I35: 8 계약완료 | J35: 46030 | K35: - '26년 착수보고회 진행 일시: 01/09 10:00 | P35: 46020 | Q35: 46371 | R35: =884700000/1.1 -> 8.0427273e+08 | S35: =884700000/1.1 -> 8.0427273e+08 | U35: 단독 | V35: 2025-090
B36: =IF(ISERROR(VLOOKUP(J36,'==='!B:E,4,FALSE)),"",VLOOKUP(J36,'==='!B:E,4,FALSE)) -> 2월 1주 | C36: 2026-008 | D36: 수어 | E36: 서울의료원 | F36: 서울경제진흥원 | G36: 2025년 테스트베드 서울 실증 지원사업(서울의료원) | H36: 임철현 | I36: 8 계약완료 | J36: 46055 | K36: 서울의료원 미팅 - 키오스크(안내형1, 발급기3) 확정, 설치 위치 실사 및 시공관련(통신 3곳 및 전원1곳)시공필요 견적의뢰(C&S에너지) - 시공비용관련 정상욱부장 경유 SBA에 문의 진행시 수행계획에 대한 변경보고 또는 자부담 처리 가능함 - 키오스크 구매비용에 시공비 포함하여 처리하는 방식으로 진행코자 한 | O36: 45924 | P36: 45915 | Q36: 2026-0914 | R36: =200000000/1.1 -> 1.8181818e+08 | S36: =200000000/1.1 -> 1.8181818e+08 | U36: 단독 | V36: 2025-045
B37: =IF(ISERROR(VLOOKUP(J37,'==='!B:E,4,FALSE)),"",VLOOKUP(J37,'==='!B:E,4,FALSE)) -> 1월 4주 | C37: 2026-008 | D37: 수어 | E37: 서울의료원 | F37: 서울경제진흥원 | G37: 2025년 테스트베드 서울 실증 지원사업(서울의료원) | H37: 임철현 | I37: 8 계약완료 | J37: 46048 | K37: 과제관련 키오스크(배리어프리 안내형 1식, 발급기 3식)관련 발주 및 키오스크업체와 납품 협의 - 포씨게이트 '서울의료원 발급시스템' 원 소스 공유 요청 - 차주 서울의료원 미팅시 키오스크 설치위치 및 시공관련 실사 진행예정, 서울의료원 전산팀 일정 확인 중 | O37: 45924 | P37: 45915 | Q37: 2026-0914 | R37: =200000000/1.1 -> 1.8181818e+08 | S37: =200000000/1.1 -> 1.8181818e+08 | U37: 단독 | V37: 2025-045
B38: =IF(ISERROR(VLOOKUP(J38,'==='!B:E,4,FALSE)),"",VLOOKUP(J38,'==='!B:E,4,FALSE)) -> 1월 3주 | C38: 2026-008 | D38: 수어 | E38: 서울의료원 | F38: 서울경제진흥원 | G38: 2025년 테스트베드 서울 실증 지원사업(서울의료원) | H38: 임철현 | I38: 8 계약완료 | J38: 46043 | K38: 과제관련 키오스크(배리어프리 안내형 1식, 발급기 3식)관련 발주서 내용관련 키오스크업체와 협의 - 납품은 2월 중 진행, 무상유지보수 기간은 실증기관 종료 이후인 '26.09.15일부터 2년간 협의 - 대금지급은 납품 후 30일 이내 현금 지급 협의 * 서울의료원 2월 행사관련 안내형키오스크 대여관련 엘토브와 협의 진행(대여기간 확인 후 재협의 예정) | O38: 45924 | P38: 45915 | Q38: 2026-0914 | R38: =200000000/1.1 -> 1.8181818e+08 | S38: =200000000/1.1 -> 1.8181818e+08 | U38: 단독 | V38: 2025-045
B39: =IF(ISERROR(VLOOKUP(J39,'==='!B:E,4,FALSE)),"",VLOOKUP(J39,'==='!B:E,4,FALSE)) -> 1월 1주 | C39: 2026-008 | D39: 수어 | E39: 서울의료원 | F39: 서울경제진흥원 | G39: 2025년 테스트베드 서울 실증 지원사업(서울의료원) | H39: 임철현 | I39: 8 계약완료 | J39: 46029 | K39: 과제관련 키오스크(배리어프리 안내형 1식, 발급기 3식)관련 내부 사전 품의 완료 - 배리어프리 안내형 1식 키오스크 -> 엘토브 43인치 스탠드형 BF인증 키오스크 선정 - 발급기 3식 키오스그 -> 포시케이트 21.5인치 발급기 3식 선정, 발급시스템 연동관련 금액 조정 협의 중 | O39: 45924 | P39: 45915 | Q39: 2026-0914 | R39: =200000000/1.1 -> 1.8181818e+08 | S39: =200000000/1.1 -> 1.8181818e+08 | U39: 단독 | V39: 2025-045
B40: =IF(ISERROR(VLOOKUP(J40,'==='!B:E,4,FALSE)),"",VLOOKUP(J40,'==='!B:E,4,FALSE)) -> 1월 1주 | C40: 2026-008 | D40: 수어 | E40: 서울의료원 | F40: 서울경제진흥원원 | G40: 2025년 테스트베드 서울 실증 지원사업(서울의료원) | H40: 임철현 | I40: 8 계약완료 | J40: 46024 | K40: 과제관련 당사 핸드사인톡톡 조달청'혁신제품' 선정 및 유지보수 금액관련 협의, 의료원 내부 보고관련 사전 협의 및 관련 견적서(비교) 2부 제공 완료 | O40: 45924 | P40: 45915 | Q40: 2026-0914 | R40: =200000000/1.1 -> 1.8181818e+08 | S40: =200000000/1.1 -> 1.8181818e+08 | U40: 단독 | V40: 2025-045
B41: =IF(ISERROR(VLOOKUP(J41,'==='!B:E,4,FALSE)),"",VLOOKUP(J41,'==='!B:E,4,FALSE)) -> 1월 1주 | C41: 2026-005 | D41: 수어 | E41: 식품안전정보원 | F41: 식품안전정보원 | G41: 식품안전정보원 실시간 식품정보 수어 영상 제공 프로그램 개발 용역 | H41: 임철현 | I41: 3 제안중 | J41: 46030 | K41: - 입찰공고: 01/06 공동수급(마감): 01/19 18:00까지 제안마감: 01/20 10:00 -> 단독 제안 및 제안전략관련 고객사 미팅 | M41: 1월 | N41: 1월 말 또는 2월 초 | P41: 계약일 | Q41: 46203 | U41: 주관사 | V41: 2025-117
B42: =IF(ISERROR(VLOOKUP(J42,'==='!B:E,4,FALSE)),"",VLOOKUP(J42,'==='!B:E,4,FALSE)) -> 1월 1주 | C42: 2026-003 | D42: 수어 | E42: 에니텍시스 | F42: 에니텍시스 | G42: 에니텍시스 무인민원발급기 수어 서비스 제안 | H42: 오민규 | I42: 1 영업중 | J42: 46028 | K42: - 차주 담당자 미팅 예정 (w. 양승구상무) | V42: 2025-116
B43: =IF(ISERROR(VLOOKUP(J43,'==='!B:E,4,FALSE)),"",VLOOKUP(J43,'==='!B:E,4,FALSE)) -> 1월 1주 | C43: 2026-004 | D43: AICC | E43: 티플리스 | F43: - | G43: 티플리스 공공기관, 지자체 AICC. MOU | H43: 오민규 | I43: 1 영업중 | J43: 46028 | K43: - 담당자 연락: 김동훈그룹장 . 1월 내 미팅 예정. 차주 재 연락 예정 | V43: -
B44: =IF(ISERROR(VLOOKUP(J44,'==='!B:E,4,FALSE)),"",VLOOKUP(J44,'==='!B:E,4,FALSE)) -> 2월 1주 | C44: 2026-006 | D44: 수어 | E44: 한국승강기안전공단 | F44: 한국승강기안전공단 | G44: 한국승강기안전공단 승강기 비상상황시 시청각장애인 안내시스템 | H44: 임철현 | I44: 1 영업중 | J44: 46057 | K44: - 현성컨버전스(2026-013)로 통합 보고 진행하고자 함 | L44: 70000000 | M44: 3월 | U44: 미정 | V44: 2025-112
B45: =IF(ISERROR(VLOOKUP(J45,'==='!B:E,4,FALSE)),"",VLOOKUP(J45,'==='!B:E,4,FALSE)) -> 1월 1주 | C45: 2026-006 | D45: 수어 | E45: 한국승강기안전공단 | F45: 한국승강기안전공단 | G45: 한국승강기안전공단 승강기 비상상황시 시청각장애인 안내시스템 | H45: 임철현 | I45: 1 영업중 | J45: 46030 | K45: - 현성컨버전스 미팅건관련 기술연구소장(입원)으로 인하여 미팅일정 1월 13일(화)로 조정 진행 | L45: 70000000 | M45: 3월 | U45: 미정 | V45: 2025-112
B46: =IF(ISERROR(VLOOKUP(J46,'==='!B:E,4,FALSE)),"",VLOOKUP(J46,'==='!B:E,4,FALSE)) -> 1월 1주 | C46: 2026-010 | D46: 수어 | E46: KB국민은행 | F46: KB국민은행 | G46: KB국민은행 AI 수어 상담에 대한 챗봇 연계 구축 | H46: 양승구 | I46: 3 제안중 | J46: 46027 | K46: 해당 솔루션 담당 부장님 퇴직 예정(1.19일)으로 프로젝트는 지연 예상(담당본부장님 --> 부행장님으로 승진) - 시급 사업의 필요성에 대한 인식 부족으로 지연 예상 됨 - AI수어 담당팀작에 대한 소개 와 지주에 해당 업무 담당자의 소개 받음 KB국민은행(고덕지점장님 미팅) - 당사의 수어 솔루션 설명(카카오뱅크 적용 완료, 국민은행 스타뱅킹에 적용하는 것이 우선적으로 보임 - 1.9일 인사발령의 스타뱅킹 담당자 확인 후 소개하겠음. | V46: 2025-084
B47: =IF(ISERROR(VLOOKUP(J47,'==='!B:E,4,FALSE)),"",VLOOKUP(J47,'==='!B:E,4,FALSE)) -> 1월 1주 | C47: 2026-012 | D47: 수어 | E47: MG새마을 금고 | F47: 포시에스 | G47: MG새마을금고 디지털창구 고도화 | H47: 양승구 | I47: 7 수주완료 | J47: 46029 | K47: 구축 운영 PM 미팅 - MG새마을 금고 조직 및 담당자의 변경으로 기술 협상이 지연되고 있음 - 전체적인 비용이 10%정도는 금액의 DC가 진행 될 것으로 파악 됨으로 고통 분담 요청 --> 최대한 대응, 빠른 진행 요청 | V47: 2025-109
B48: =IF(ISERROR(VLOOKUP(J48,'==='!B:E,4,FALSE)),"",VLOOKUP(J48,'==='!B:E,4,FALSE)) -> 1월 4주 | C48: 2026-012 | D48: 수어 | E48: MG새마을 금고 | F48: 포시에스 | G48: MG새마을금고 디지털창구 고도화 | H48: 양승구 | I48: 7 수주완료 | J48: 46050 | K48: 지술 협상 진행 완료 - 1.29일, 차주부터 가격 협상 진행 예정 - 당사 솔루션 기술 협상에서 추가 진행 확정 - 구매팀에서 금액에 대한 조정 있을 수 있음(고통 분담차원에서 추후 진행 요청 하겠음) | V48: 2025-109
B49: =IF(ISERROR(VLOOKUP(J49,'==='!B:E,4,FALSE)),"",VLOOKUP(J49,'==='!B:E,4,FALSE)) -> 2월 1주 | C49: 2026-012 | D49: 수어 | E49: MG새마을 금고 | F49: 포시에스 | G49: MG새마을금고 디지털창구 고도화 | H49: 양승구 | I49: 7 수주완료 | J49: 46057 | K49: 기격협상 완료 - 최종 견적서 제출, 250ch, 100문장으로 제안 - 진행일정 : 2월 계약, 3월 개발 시작, 6 ~7월 오픈 일정으로 진행 - 키관리 운영 방안 : 영상접근시 ch 수량 키값 또는 접근 ip 등을 제안하는 구조로 개발 진행 요청 | V49: 2025-109
B50: =IF(ISERROR(VLOOKUP(J50,'==='!B:E,4,FALSE)),"",VLOOKUP(J50,'==='!B:E,4,FALSE)) -> 1월 3주 | C50: 2026-022 | D50: 기타서비스 | E50: SH서울주택공사 | F50: SH서울주택공사 | G50: SH서울주택공사 차세대 시스템 구축 | H50: 양승구 | I50: 3 제안중 | J50: 46043 | K50: SH서울주택공사 차세대 시스템 구축을 위한 업무 R&R 협의 - AX플랫폼의 기능과 SI 구축의 영역에 대한 구분 : RFP 자료를 세분화하여 정리 -> 차주 월요일까지 제공 예정 - LGCNS AX플랫폼의 교육시 당사의 개발자도 같이 교육 할 수 있도록 지원 요청 : 수용가능 - 포탈은 KL큐브 솔루션 제안하고 각각의 업무 요건에 따라 상호 협의 - NDS 주사업로 참여 예정
B51: =IF(ISERROR(VLOOKUP(J51,'==='!B:E,4,FALSE)),"",VLOOKUP(J51,'==='!B:E,4,FALSE)) -> 1월 3주 | C51: 2026-023 | D51: 수어 | E51: BNK부산은행 | F51: BNK부산은행 | G51: BNK부산은행 차세대 시스템 | H51: 양승구 | I51: 3 제안중 | J51: 46043 | K51: BNK부산은행에 당사 술루션 제안 - 2026.2.3 14:00 부산 및 경남 IT기획 담당자에게 당사 솔루션 발표 - ATM, 홈페이지, 모바일뱅킹, 콜센터에 접목 할 수 있는 솔루션 제안 - 1차 조안 자료 완료
B52: =IF(ISERROR(VLOOKUP(J52,'==='!B:E,4,FALSE)),"",VLOOKUP(J52,'==='!B:E,4,FALSE)) -> 2월 1주 | C52: 2026-023 | D52: 수어 | E52: BNK부산은행 | F52: BNK부산은행 | G52: BNK부산은행 차세대 시스템 | H52: 양승구 | I52: 3 제안중 | J52: 46056 | K52: BNK부산은행에 당사 술루션 제안 설명회 완료 (2.3일 14:00 ~ 15:30) - 부산은행 본점 9층 대회실에서 부산은행 , 경남은행 관계자 참석 (25명 정도 ), 솔루션 및 영상 설명 - 수어에 대한 이해와 도입의 필요성데 대한 공감대 형성 - 차세대 추진시(26.7~8월 제안 RFP 발송, 연말 시작 예쩡으로 , ATM, 홈페이지, 모바일뱅킹, 콜센터에 접목 할 수 있도록 검토 요청(부행장님)
B53: =IF(ISERROR(VLOOKUP(J53,'==='!B:E,4,FALSE)),"",VLOOKUP(J53,'==='!B:E,4,FALSE)) -> 1월 3주 | C53: 2026-023 | D53: 기타서비스 | E53: 알서포트 | F53: 알서포트 | G53: 알서포트 MOU 체결 | H53: 양승구 | I53: 3 제안중 | J53: 46044 | K53: 알서포트와 1.22일 MOU 체결 - 당사 부사장님 과 알서포트의 부사장님 MOU 체결 완료, 당사와의 지속적인 업무 제휴 - 일본 사업에 당사의 AI솔루션 추가로 제안하는 방안으로 협력, 차주 알서포트 사장님께 AI수어 솔루션 설명 요청
B54: =IF(ISERROR(VLOOKUP(J54,'==='!B:E,4,FALSE)),"",VLOOKUP(J54,'==='!B:E,4,FALSE)) -> 1월 4주 | C54: 2026-021 | D54: AICC | E54: LG D&O | F54: LG D&O | G54: AICC 시스템 구축 | H54: 양승구 | I54: 1 영업중 | J54: 46050 | K54: AICC 시스템 구축을 위한 제안 미팅 완료 - LG에서 관리하는 모든 리조트 및 연수원에 AICC 시스템 도입 - AI 상담 봇을 최우선 으로 도입하고 도입 장소는 연수원 우선 제안 - 기능 요건 확인하엿으며, 2.6일까지 구성도 및 예산 견적서의 자료 제출 (4 ~5억 정도 예산으로 반영 예정)
B55: =IF(ISERROR(VLOOKUP(J55,'==='!B:E,4,FALSE)),"",VLOOKUP(J55,'==='!B:E,4,FALSE)) -> 1월 3주 | C55: 2026-021 | D55: AICC | E55: LG D&O | F55: LG D&O | G55: AICC 시스템 구축 | H55: 양승구 | I55: 1 영업중 | J55: 46042 | K55: AICC 시스템 구축을 위한 사전 미팅 요청 - LG에서 운영하고 있는 콘도 및 관련 기관에 대하여 콜봇을 중심으로 한 I/out AICC 시스템 구축 - 기능 요건 확인, 1.28일 미팅 마곡에서 미팅 진행 예정
B56: =IF(ISERROR(VLOOKUP(J56,'==='!B:E,4,FALSE)),"",VLOOKUP(J56,'==='!B:E,4,FALSE)) -> 1월 3주 | C56: 2026-020 | D56: 수어 | E56: 대구빙상장 | F56: 대구빙상장 | G56: 배리어프리 키오스크 AI수어아바타 도입 | H56: 임철현 | I56: 2 견적제출 | J56: 46043 | K56: 정용주팀장 통화 L 내부프로세스 진행 중, 3월 초 진행사항관련 재협의 하기로 함 | L56: 43000000 | M56: 4월 | V56: 2025-115
B57: =IF(ISERROR(VLOOKUP(J57,'==='!B:E,4,FALSE)),"",VLOOKUP(J57,'==='!B:E,4,FALSE)) -> 1월 4주 | C57: 2026-021 | D57: 수어 | E57: KBS | F57: KBS | G57: 디지털뉴스(날씨분야) 수어아바타 영상 제작 공급건 | H57: 임철현 | I57: 1 영업중 | J57: 46049 | K57: KBS 보도시사본부 디지털뉴스국 김성호부장 미팅 w양승구, 안혜신, 임철현 L '25년 미팅시 언급된 디지털뉴스 기사 일기예보에 대한 실시간 수어아바타 수어영상 시연 L 요청사항: 1안) 1일 100개 디지털뉴스 기사를 수어아바타 수어영상 생성시 견적 2안) 1일 10개(KBS1-7개, KBS2-2개)기준 일기예보 실시간 수어아바타 수어영상 제작 견적 당사 공공기관 납품실적 내부보고관련 경영진 설득관련 기획안 자료 요청 L 내부상황: 경영진 보고시 금액에 민감(연간금액 1억 이상)하고, 6월 지선으로 인하여 세부적인 사항에 대한 협의는 지선이후 추진하고자 함 | V57: 2025-110
B58: =IF(ISERROR(VLOOKUP(J58,'==='!B:E,4,FALSE)),"",VLOOKUP(J58,'==='!B:E,4,FALSE)) -> 2월 1주 | C58: 2026-021 | D58: AICC | E58: LG D&O | F58: LG D&O | G58: AICC 시스템 구축 | H58: 양승구 | I58: 1 영업중 | J58: 46057 | K58: AICC 시스템 구축을 제안을 위한 협럭사 - 넥서스 및 스펙트라 미팅 완료 - 고객사 요건에 대한 설명 완료, 구성도 및 제안의 기능 자료 요청 - 고객사에게 자료의 제출은 금주 2.6일 진행 예정
B59: =IF(ISERROR(VLOOKUP(J59,'==='!B:E,4,FALSE)),"",VLOOKUP(J59,'==='!B:E,4,FALSE)) -> 1월 4주 | C59: 2026-022 | D59: 수어 | E59: 장애인고용공단 | F59: 장애인고용공단 | G59: 박람회 행사에 따른 AI 수어 시스템 구축 | H59: 양승구 | I59: 2 견적제출 | J59: 46048 | K59: 장애인고용공단에서 진행하는 박람회에 공담 및 각 협력업체 소개에 수어 안내 시스템을 도입 하고자 함 - QR코드를 이용한 공단 및 협력사의 소개 할 수 있는 AI 활용 디지털 도슨트 도입의 일환으로 시범 사업 진행 후 27년부터 정규 사업으로 확대 예정 - 구독형 서비스 이용에 따른 비용의 최적화 와 관리의 효율성 향상 방안 제안 - 제안자료 및 견적 금액 제시 (내부 검토 후 차주 협의 예정) | L59: 39000000 | M59: 3월
B60: =IF(ISERROR(VLOOKUP(J60,'==='!B:E,4,FALSE)),"",VLOOKUP(J60,'==='!B:E,4,FALSE)) -> 2월 1주 | C60: 2026-022 | D60: 수어 | E60: 장애인고용공단 | F60: 장애인고용공단 | G60: 박람회 행사에 따른 AI 수어 시스템 구축 | H60: 양승구 | I60: 2 견적제출 | J60: 46055 | K60: 본 솔루션 도입 구축을 위한 비용 부족 - 요청하는 방안으로 제시 (5.28 ~ 29일 양일간 사용하는 조건 제시 - 최종 견적서 발송, 본 박람회 진행시 우리회사 홍보 가능*(부수는 무상 임대 - 2일간 사용 가능) - 행사 마지막날 장관님 방문으로 솔루션 소개 가능 함. 준비하여 설명 예정 | L60: 39000000 | M60: 3월
B61: =IF(ISERROR(VLOOKUP(J61,'==='!B:E,4,FALSE)),"",VLOOKUP(J61,'==='!B:E,4,FALSE)) -> 1월 4주 | C61: 2026-023 | D61: 수어 | E61: 아이티센 | F61: 아이티센 | G61: LS 증건 홈페이지 개편에 따른 AI수어 추가 제안 | H61: 양승구 | I61: 3 제안중 | J61: 46051 | K61: 이직 인사 및 당사의 수어 솔루션 설명 - 당사의 수어솔루션에 대하여 적극적인 제안 하겟음 - LS증권 홈페이지 개편 프로젝트의 주사업자인 KICC에 소개 하겠음, 연락후 제안 협의 하겠음 - 4월 RFP 발송 예정, 예산 15억 중, 디지털 약자에 대한 포용적인 금융 서비스 제공의 이롼으로 당사의 AI 수어 서비스 추가 제안 - 당사에서 전략적으로 제안 하겠음 (차주 사전 미팅 진행, 웹에이전시 업체도 소개 요청 : 같이 검토하여 미팅 예정)
B62: =IF(ISERROR(VLOOKUP(J62,'==='!B:E,4,FALSE)),"",VLOOKUP(J62,'==='!B:E,4,FALSE)) -> 2월 2주 | C62: 2026-023 | D62: 수어 | E62: LS증권 | F62: KCC정보통신 | G62: LS 증건 홈페이지 개편에 따른 AI수어 추가 제안 | H62: 양승구 | I62: 3 제안중 | J62: 46062 | K62: KCC 정보통신 : 2.9일 14:00 미팅 예정 - 당사의 수어솔루션 및 WEB 에이전시 업채와 미팅으로 진행 예정 - LS증권 홈페이지에 당사의 솔루션 제공, 홈페이지 개편에 따란 WEB 기획, 디자인, 개발에 당사도 일부 참여
B63: =IF(ISERROR(VLOOKUP(J63,'==='!B:E,4,FALSE)),"",VLOOKUP(J63,'==='!B:E,4,FALSE)) -> 1월 4주 | C63: 2026-024 | D63: 수어 | E63: 카카오뱅크 | F63: 카카오뱅크 | G63: 카카오뱅크 AI수어상담 3D 아바타 및 영상제작 | H63: 양승구 | I63: 8 계약완료 | J63: 46051 | K63: 카카오뱅크 검수를 위한 일정 협의 - 내부 프로젝트 이슈 및 당사의 프로젝트 지연등의 이슈가 없게 26.2.28일까지 모두 완료로 협의 - 진행 일정 : 2.23일 영상자료 모두 납품, 2.26일 검수, 2.27일 계산서 발생 일정으로 합의 - 3.1 ~ 3.15일 까지는 비공식적인 지원 - 고도화 사업 올해말 협의, 실시간 대화에 따른 사업의 진행 협의는 2분기 이후에 진행 - 무상 100문장에 대한 사항은 3월 이후에 진행
B64: =IF(ISERROR(VLOOKUP(J64,'==='!B:E,4,FALSE)),"",VLOOKUP(J64,'==='!B:E,4,FALSE)) -> 1월 4주 | C64: 2026-025 | D64: 수어 | E64: 서울장애인가족지원센터 | F64: 서울장애인가족지원센터 | G64: 청각장애인을 위한 프로그램 제안 | H64: 양승구 | I64: 3 제안중 | J64: 46051 | K64: 당사에서 서울 이남에 있는 장애인 가족센터에 창각장애인을 위한 서비스 제안 - 센터별 테블릿 2대에 문해력 증진을 위한 수어 강좌 20강과 디지탈 치료를 위한 수어명상 5편 제공을 위한 수요기관의 조사 요청 - 한강 이남의 센터 11곳 : 2대씩 지원 - 1.30일까지 수요 기관의 조사 자료 제공 하겠음
B65: =IF(ISERROR(VLOOKUP(J65,'==='!B:E,4,FALSE)),"",VLOOKUP(J65,'==='!B:E,4,FALSE)) -> 2월 1주 | C65: 2026-025 | D65: 수어 | E65: 서울장애인가족지원센터 | F65: 서울장애인가족지원센터 | G65: 청각장애인을 위한 프로그램 제안 | H65: 양승구 | I65: 3 제안중 | J65: 46055 | K65: 장애인가족센터 및 강동 어울임복지재단 방문 완료, 당사의 지원사항에 대한 설명 및 지원 일정 공유 - 장애인가족센터 : 요청한 11곳 보다는 관리가 가능한 부분으ㅗ 조정 요청 (문해력 20강, 명상 : 5장 지원) - 강동어울림복지관 : 당사의 취지 설명, 적극적인 지원 과 협력 예정, 추가적인 테블릿 요청시 협의 하겟음, 앞으로 많은 협력 요청
B66: =IF(ISERROR(VLOOKUP(J66,'==='!B:E,4,FALSE)),"",VLOOKUP(J66,'==='!B:E,4,FALSE)) -> 2월 1주 | C66: 2026-025 | D66: 수어 | E66: 코레일 | F66: 코레일 | G66: KTX 열차내 수어안내 시스템 구축 | H66: 양승구 | I66: 3 제안중 | J66: 46052 | K66: KTX 열차내 수어안내 시스템 구축에 따른 자료 제출 - 견적서 400문자으 1000문장 기준으로 SL-CMS포함하여 견적서 전송 완료 - 업무의 진행 일정에 따라 바르게 진행도 할 수도 있음, 설전후해서 연락 드리겠음.
B67: =IF(ISERROR(VLOOKUP(J67,'==='!B:E,4,FALSE)),"",VLOOKUP(J67,'==='!B:E,4,FALSE)) -> 2월 2주 | C67: 2026-026 | D67: 수어 | E67: 국립국어원 | F67: 국립국어원 | G67: 2026년 한국어-한국수어 병렬 말뭉치 구축 | H67: 임철현 | I67: 3 제안중 | J67: 46062 | K67: 사전규격공고(26.02.06-02.11) - 사업금액: 1,513,000,000원(VAT포함) - 과업기간: '26년 11월 30일까지(약270일) - 선정방식: 협상에 의한 계약 - 참가조건: 소프트웨어사업자(데이터베이스제작 및 검색서비스사업/업종코드 1470) 직접생산증명서(8111200201 데이터처리서비스) ==> 당사 자격 갱신 중(현재: 26.02.22종료) 중소기업확인서 소지한 업체 | N67: 3월 말 예상 | R67: =1513000000/1.1 -> 1.3754545e+09 | U67: 주관사
B68: =IF(ISERROR(VLOOKUP(J68,'==='!B:E,4,FALSE)),"",VLOOKUP(J68,'==='!B:E,4,FALSE)) | C68: 2026-027 | D68: - | H68: - | I68: -
B69: =IF(ISERROR(VLOOKUP(J69,'==='!B:E,4,FALSE)),"",VLOOKUP(J69,'==='!B:E,4,FALSE)) | C69: 2026-028 | D69: - | H69: - | I69: -
B70: =IF(ISERROR(VLOOKUP(J70,'==='!B:E,4,FALSE)),"",VLOOKUP(J70,'==='!B:E,4,FALSE)) | C70: 2026-029 | D70: - | H70: - | I70: -
B71: =IF(ISERROR(VLOOKUP(J71,'==='!B:E,4,FALSE)),"",VLOOKUP(J71,'==='!B:E,4,FALSE)) | C71: 2026-030 | D71: - | H71: - | I71: -
B72: =IF(ISERROR(VLOOKUP(J72,'==='!B:E,4,FALSE)),"",VLOOKUP(J72,'==='!B:E,4,FALSE)) | C72: 2026-031 | D72: - | H72: - | I72: -
B73: =IF(ISERROR(VLOOKUP(J73,'==='!B:E,4,FALSE)),"",VLOOKUP(J73,'==='!B:E,4,FALSE)) | C73: 2026-032 | D73: - | H73: - | I73: -
B74: =IF(ISERROR(VLOOKUP(J74,'==='!B:E,4,FALSE)),"",VLOOKUP(J74,'==='!B:E,4,FALSE)) | C74: 2026-033 | D74: - | H74: - | I74: -
B75: =IF(ISERROR(VLOOKUP(J75,'==='!B:E,4,FALSE)),"",VLOOKUP(J75,'==='!B:E,4,FALSE)) | C75: 2026-034 | D75: - | H75: - | I75: -
B76: =IF(ISERROR(VLOOKUP(J76,'==='!B:E,4,FALSE)),"",VLOOKUP(J76,'==='!B:E,4,FALSE)) | C76: 2026-035 | D76: - | H76: - | I76: -
B77: =IF(ISERROR(VLOOKUP(J77,'==='!B:E,4,FALSE)),"",VLOOKUP(J77,'==='!B:E,4,FALSE)) | C77: 2026-036 | D77: - | H77: - | I77: -
B78: =IF(ISERROR(VLOOKUP(J78,'==='!B:E,4,FALSE)),"",VLOOKUP(J78,'==='!B:E,4,FALSE)) | C78: 2026-037 | D78: - | H78: - | I78: -
B79: =IF(ISERROR(VLOOKUP(J79,'==='!B:E,4,FALSE)),"",VLOOKUP(J79,'==='!B:E,4,FALSE)) | C79: 2026-038 | D79: - | H79: - | I79: -
... B241: =IF(ISERROR(VLOOKUP(J241,'==='!B:E,4,FALSE)),"",VLOOKUP(J241,'==='!B:E,4,FALSE)) | C241: 2026-200 | D241: - | H241: - | I241: -
B242: =IF(ISERROR(VLOOKUP(J242,'==='!B:E,4,FALSE)),"",VLOOKUP(J242,'==='!B:E,4,FALSE))

Sheet Sheet2

Sheet ===
C2: 월 | D2: 주차
B3: 45992 | C3: =MONTH(B3) -> 12 | D3: =WEEKNUM(B3,15) -> 49
B4: 45993 | C4: =MONTH(B4) -> 12 | D4: =WEEKNUM(B4,15) -> 49
B5: 45994 | C5: =MONTH(B5) -> 12 | D5: =WEEKNUM(B5,15) -> 49 | E5: 12월 1주
B6: 45995 | C6: =MONTH(B6) -> 12 | D6: =WEEKNUM(B6,15) -> 49 | E6: 12월 2주
B7: 45996 | C7: =MONTH(B7) -> 12 | D7: =WEEKNUM(B7,15) -> 50 | E7: 12월 2주
B8: 45997 | C8: =MONTH(B8) -> 12 | D8: =WEEKNUM(B8,15) -> 50 | E8: =E7 -> 12월 2주
B9: 45998 | C9: =MONTH(B9) -> 12 | D9: =WEEKNUM(B9,15) -> 50 | E9: =E8 -> 12월 2주
B10: 45999 | C10: =MONTH(B10) -> 12 | D10: =WEEKNUM(B10,15) -> 50 | E10: =E9 -> 12월 2주
B11: 46000 | C11: =MONTH(B11) -> 12 | D11: =WEEKNUM(B11,15) -> 50 | E11: =E10 -> 12월 2주
B12: 46001 | C12: =MONTH(B12) -> 12 | D12: =WEEKNUM(B12,15) -> 50 | E12: =E11 -> 12월 2주
B13: 46002 | C13: =MONTH(B13) -> 12 | D13: =WEEKNUM(B13,15) -> 50 | E13: =E12 -> 12월 2주
B14: 46003 | C14: =MONTH(B14) -> 12 | D14: =WEEKNUM(B14,15) -> 51 | E14: 12월 3주
B15: 46004 | C15: =MONTH(B15) -> 12 | D15: =WEEKNUM(B15,15) -> 51 | E15: =E14 -> 12월 3주
B16: 46005 | C16: =MONTH(B16) -> 12 | D16: =WEEKNUM(B16,15) -> 51 | E16: =E15 -> 12월 3주
B17: 46006 | C17: =MONTH(B17) -> 12 | D17: =WEEKNUM(B17,15) -> 51 | E17: =E16 -> 12월 3주
B18: 46007 | C18: =MONTH(B18) -> 12 | D18: =WEEKNUM(B18,15) -> 51 | E18: =E17 -> 12월 3주
B19: 46008 | C19: =MONTH(B19) -> 12 | D19: =WEEKNUM(B19,15) -> 51 | E19: =E18 -> 12월 3주
B20: 46009 | C20: =MONTH(B20) -> 12 | D20: =WEEKNUM(B20,15) -> 51 | E20: =E19 -> 12월 3주
B21: 46010 | C21: =MONTH(B21) -> 12 | D21: =WEEKNUM(B21,15) -> 52 | E21: 12월 4주
B22: 46011 | C22: =MONTH(B22) -> 12 | D22: =WEEKNUM(B22,15) -> 52 | E22: =E21 -> 12월 4주
B23: 46012 | C23: =MONTH(B23) -> 12 | D23: =WEEKNUM(B23,15) -> 52 | E23: =E22 -> 12월 4주
B24: 46013 | C24: =MONTH(B24) -> 12 | D24: =WEEKNUM(B24,15) -> 52 | E24: =E23 -> 12월 4주
B25: 46014 | C25: =MONTH(B25) -> 12 | D25: =WEEKNUM(B25,15) -> 52 | E25: =E24 -> 12월 4주
B26: 46015 | C26: =MONTH(B26) -> 12 | D26: =WEEKNUM(B26,15) -> 52 | E26: =E25 -> 12월 4주
B27: 46016 | C27: =MONTH(B27) -> 12 | D27: =WEEKNUM(B27,15) -> 52 | E27: =E26 -> 12월 4주
B28: 46017 | C28: =MONTH(B28) -> 12 | D28: =WEEKNUM(B28,15) -> 53 | E28: 12월 5주
B29: 46018 | C29: =MONTH(B29) -> 12 | D29: =WEEKNUM(B29,15) -> 53 | E29: =E28 -> 12월 5주
B30: 46019 | C30: =MONTH(B30) -> 12 | D30: =WEEKNUM(B30,15) -> 53 | E30: =E29 -> 12월 5주
B31: 46020 | C31: =MONTH(B31) -> 12 | D31: =WEEKNUM(B31,15) -> 53 | E31: =E30 -> 12월 5주
B32: 46021 | C32: =MONTH(B32) -> 12 | D32: =WEEKNUM(B32,15) -> 53 | E32: =E31 -> 12월 5주
B33: 46022 | C33: =MONTH(B33) -> 12 | D33: =WEEKNUM(B33,15) -> 53 | E33: =E32 -> 12월 5주
B34: 46023 | C34: =MONTH(B34) -> 1 | D34: =WEEKNUM(B34,15) -> 1 | E34: =E33 -> 12월 5주
B35: 46024 | C35: =MONTH(B35) -> 1 | D35: =WEEKNUM(B35,15) -> 2 | E35: 1월 1주
B36: 46025 | C36: =MONTH(B36) -> 1 | D36: =WEEKNUM(B36,15) -> 2 | E36: =E35 -> 1월 1주
B37: 46026 | C37: =MONTH(B37) -> 1 | D37: =WEEKNUM(B37,15) -> 2 | E37: =E36 -> 1월 1주
B38: 46027 | C38: =MONTH(B38) -> 1 | D38: =WEEKNUM(B38,15) -> 2 | E38: =E37 -> 1월 1주
B39: 46028 | C39: =MONTH(B39) -> 1 | D39: =WEEKNUM(B39,15) -> 2 | E39: =E38 -> 1월 1주
B40: 46029 | C40: =MONTH(B40) -> 1 | D40: =WEEKNUM(B40,15) -> 2 | E40: =E39 -> 1월 1주
B41: 46030 | C41: =MONTH(B41) -> 1 | D41: =WEEKNUM(B41,15) -> 2 | E41: =E40 -> 1월 1주
B42: 46031 | C42: =MONTH(B42) -> 1 | D42: =WEEKNUM(B42,15) -> 3 | E42: 1월 2주
B43: 46032 | C43: =MONTH(B43) -> 1 | D43: =WEEKNUM(B43,15) -> 3 | E43: =E42 -> 1월 2주
B44: 46033 | C44: =MONTH(B44) -> 1 | D44: =WEEKNUM(B44,15) -> 3 | E44: =E43 -> 1월 2주
B45: 46034 | C45: =MONTH(B45) -> 1 | D45: =WEEKNUM(B45,15) -> 3 | E45: =E44 -> 1월 2주
B46: 46035 | C46: =MONTH(B46) -> 1 | D46: =WEEKNUM(B46,15) -> 3 | E46: =E45 -> 1월 2주
B47: 46036 | C47: =MONTH(B47) -> 1 | D47: =WEEKNUM(B47,15) -> 3 | E47: =E46 -> 1월 2주
B48: 46037 | C48: =MONTH(B48) -> 1 | D48: =WEEKNUM(B48,15) -> 3 | E48: =E47 -> 1월 2주
B49: 46038 | C49: =MONTH(B49) -> 1 | D49: =WEEKNUM(B49,15) -> 4 | E49: 1월 3주
B50: 46039 | C50: =MONTH(B50) -> 1 | D50: =WEEKNUM(B50,15) -> 4 | E50: =E49 -> 1월 3주
B51: 46040 | C51: =MONTH(B51) -> 1 | D51: =WEEKNUM(B51,15) -> 4 | E51: =E50 -> 1월 3주
B52: 46041 | C52: =MONTH(B52) -> 1 | D52: =WEEKNUM(B52,15) -> 4 | E52: =E51 -> 1월 3주
B53: 46042 | C53: =MONTH(B53) -> 1 | D53: =WEEKNUM(B53,15) -> 4 | E53: =E52 -> 1월 3주
B54: 46043 | C54: =MONTH(B54) -> 1 | D54: =WEEKNUM(B54,15) -> 4 | E54: =E53 -> 1월 3주
B55: 46044 | C55: =MONTH(B55) -> 1 | D55: =WEEKNUM(B55,15) -> 4 | E55: =E54 -> 1월 3주
B56: 46045 | C56: =MONTH(B56) -> 1 | D56: =WEEKNUM(B56,15) -> 5 | E56: 1월 4주
B57: 46046 | C57: =MONTH(B57) -> 1 | D57: =WEEKNUM(B57,15) -> 5 | E57: =E56 -> 1월 4주
B58: 46047 | C58: =MONTH(B58) -> 1 | D58: =WEEKNUM(B58,15) -> 5 | E58: =E57 -> 1월 4주
B59: 46048 | C59: =MONTH(B59) -> 1 | D59: =WEEKNUM(B59,15) -> 5 | E59: =E58 -> 1월 4주
B60: 46049 | C60: =MONTH(B60) -> 1 | D60: =WEEKNUM(B60,15) -> 5 | E60: =E59 -> 1월 4주
B61: 46050 | C61: =MONTH(B61) -> 1 | D61: =WEEKNUM(B61,15) -> 5 | E61: =E60 -> 1월 4주
B62: 46051 | C62: =MONTH(B62) -> 1 | D62: =WEEKNUM(B62,15) -> 5 | E62: =E61 -> 1월 4주
B63: 46052 | C63: =MONTH(B63) -> 1 | D63: =WEEKNUM(B63,15) -> 6 | E63: 2월 1주
B64: 46053 | C64: =MONTH(B64) -> 1 | D64: =WEEKNUM(B64,15) -> 6 | E64: =E63 -> 2월 1주
B65: 46054 | C65: =MONTH(B65) -> 2 | D65: =WEEKNUM(B65,15) -> 6 | E65: =E64 -> 2월 1주
B66: 46055 | C66: =MONTH(B66) -> 2 | D66: =WEEKNUM(B66,15) -> 6 | E66: =E65 -> 2월 1주
B67: 46056 | C67: =MONTH(B67) -> 2 | D67: =WEEKNUM(B67,15) -> 6 | E67: =E66 -> 2월 1주
B68: 46057 | C68: =MONTH(B68) -> 2 | D68: =WEEKNUM(B68,15) -> 6 | E68: =E67 -> 2월 1주
B69: 46058 | C69: =MONTH(B69) -> 2 | D69: =WEEKNUM(B69,15) -> 6 | E69: =E68 -> 2월 1주
B70: 46059 | C70: =MONTH(B70) -> 2 | D70: =WEEKNUM(B70,15) -> 7 | E70: 2월 2주
B71: 46060 | C71: =MONTH(B71) -> 2 | D71: =WEEKNUM(B71,15) -> 7 | E71: =E70 -> 2월 2주
B72: 46061 | C72: =MONTH(B72) -> 2 | D72: =WEEKNUM(B72,15) -> 7 | E72: =E71 -> 2월 2주
B73: 46062 | C73: =MONTH(B73) -> 2 | D73: =WEEKNUM(B73,15) -> 7 | E73: =E72 -> 2월 2주
B74: 46063 | C74: =MONTH(B74) -> 2 | D74: =WEEKNUM(B74,15) -> 7 | E74: =E73 -> 2월 2주
B75: 46064 | C75: =MONTH(B75) -> 2 | D75: =WEEKNUM(B75,15) -> 7 | E75: =E74 -> 2월 2주
B76: 46065 | C76: =MONTH(B76) -> 2 | D76: =WEEKNUM(B76,15) -> 7 | E76: =E75 -> 2월 2주
B77: 46066 | C77: =MONTH(B77) -> 2 | D77: =WEEKNUM(B77,15) -> 8 | E77: 2월 3주
B78: 46067 | C78: =MONTH(B78) -> 2 | D78: =WEEKNUM(B78,15) -> 8 | E78: =E77 -> 2월 3주
B79: 46068 | C79: =MONTH(B79) -> 2 | D79: =WEEKNUM(B79,15) -> 8 | E79: =E78 -> 2월 3주
B80: 46069 | C80: =MONTH(B80) -> 2 | D80: =WEEKNUM(B80,15) -> 8 | E80: =E79 -> 2월 3주
B81: 46070 | C81: =MONTH(B81) -> 2 | D81: =WEEKNUM(B81,15) -> 8 | E81: =E80 -> 2월 3주
B82: 46071 | C82: =MONTH(B82) -> 2 | D82: =WEEKNUM(B82,15) -> 8 | E82: =E81 -> 2월 3주
B83: 46072 | C83: =MONTH(B83) -> 2 | D83: =WEEKNUM(B83,15) -> 8 | E83: =E82 -> 2월 3주
B84: 46073 | C84: =MONTH(B84) -> 2 | D84: =WEEKNUM(B84,15) -> 9 | E84: 2월 4주
B85: 46074 | C85: =MONTH(B85) -> 2 | D85: =WEEKNUM(B85,15) -> 9 | E85: =E84 -> 2월 4주
B86: 46075 | C86: =MONTH(B86) -> 2 | D86: =WEEKNUM(B86,15) -> 9 | E86: =E85 -> 2월 4주
B87: 46076 | C87: =MONTH(B87) -> 2 | D87: =WEEKNUM(B87,15) -> 9 | E87: =E86 -> 2월 4주
B88: 46077 | C88: =MONTH(B88) -> 2 | D88: =WEEKNUM(B88,15) -> 9 | E88: =E87 -> 2월 4주
B89: 46078 | C89: =MONTH(B89) -> 2 | D89: =WEEKNUM(B89,15) -> 9 | E89: =E88 -> 2월 4주
B90: 46079 | C90: =MONTH(B90) -> 2 | D90: =WEEKNUM(B90,15) -> 9 | E90: =E89 -> 2월 4주
B91: 46080 | C91: =MONTH(B91) -> 2 | D91: =WEEKNUM(B91,15) -> 10 | E91: 3월 1주
B92: 46081 | C92: =MONTH(B92) -> 2 | D92: =WEEKNUM(B92,15) -> 10 | E92: =E91 -> 3월 1주
B93: 46082 | C93: =MONTH(B93) -> 3 | D93: =WEEKNUM(B93,15) -> 10 | E93: =E92 -> 3월 1주
B94: 46083 | C94: =MONTH(B94) -> 3 | D94: =WEEKNUM(B94,15) -> 10 | E94: =E93 -> 3월 1주
B95: 46084 | C95: =MONTH(B95) -> 3 | D95: =WEEKNUM(B95,15) -> 10 | E95: =E94 -> 3월 1주
B96: 46085 | C96: =MONTH(B96) -> 3 | D96: =WEEKNUM(B96,15) -> 10 | E96: =E95 -> 3월 1주
B97: 46086 | C97: =MONTH(B97) -> 3 | D97: =WEEKNUM(B97,15) -> 10 | E97: =E96 -> 3월 1주
B98: 46087 | C98: =MONTH(B98) -> 3 | D98: =WEEKNUM(B98,15) -> 11 | E98: 3월 2주
B99: 46088 | C99: =MONTH(B99) -> 3 | D99: =WEEKNUM(B99,15) -> 11 | E99: =E98 -> 3월 2주
B100: 46089 | C100: =MONTH(B100) -> 3 | D100: =WEEKNUM(B100,15) -> 11 | E100: =E99 -> 3월 2주
B101: 46090 | C101: =MONTH(B101) -> 3 | D101: =WEEKNUM(B101,15) -> 11 | E101: =E100 -> 3월 2주
...

Sheet 25년 매출운영 현황
B2: ■ 2025년도 영업진행 및 계약 현황
I3: ↓ 이 부분만 수기로 작성하시기 바랍니다. ↓ | S3: ※ 금액: 단위 천원. VAT별도
B4: 파이프라인 ID | C4: 분야 | D4: 고객사 | E4: 발주처 | F4: 사업명 | G4: 담당 | H4: 진행단계 | I4: 계약일자 | J4: 프로젝트 기간 | L4: 계약 | N4: 매출 금액 | R4: 견적 제공 금액 | S4: 비고
J5: 시작 | K5: 종료 | L5: 수주금액 | M5: 계약금액 | N5: 45931 | O5: 45962 | P5: 45992 | Q5: 합계(10월~12월)
B6: ='2025년 주요추진사업(NEW)'!B4 -> 2025-001 | C6: ='2025년 주요추진사업(NEW)'!C4 -> AICC | D6: ='2025년 주요추진사업(NEW)'!D4 -> KB국민은행 | E6: ='2025년 주요추진사업(NEW)'!E4 -> SK쉴더스 | F6: ='2025년 주요추진사업(NEW)'!F4 -> KB국민은행 SynK 활용 AICC 통합관리포탈 구축 | G6: ='2025년 주요추진사업(NEW)'!G4 -> 함영민 | H6: ='2025년 주요추진사업(NEW)'!H4 -> 2 견적제출 | Q6: =SUM(N6:P6) -> 0 | R6: =VLOOKUP(B6, '2025년 주요추진사업(NEW)'!B:O, 14, FALSE) -> 2637000
B7: ='2025년 주요추진사업(NEW)'!B5 -> 2025-002 | C7: ='2025년 주요추진사업(NEW)'!C5 -> AICC | D7: ='2025년 주요추진사업(NEW)'!D5 -> 한국도로교통공단 | E7: ='2025년 주요추진사업(NEW)'!E5 -> 모비젠 | F7: ='2025년 주요추진사업(NEW)'!F5 -> 한국도로교통공단 STT API 개발 | G7: ='2025년 주요추진사업(NEW)'!G5 -> 함영민 | H7: ='2025년 주요추진사업(NEW)'!H5 -> 5 DROP | Q7: =SUM(N7:P7) -> 0 | R7: =VLOOKUP(B7, '2025년 주요추진사업(NEW)'!B:O, 14, FALSE) -> 0
B8: ='2025년 주요추진사업(NEW)'!B6 -> 2025-003 | C8: ='2025년 주요추진사업(NEW)'!C6 -> AICC | D8: ='2025년 주요추진사업(NEW)'!D6 -> 현대캐피탈 | E8: ='2025년 주요추진사업(NEW)'!E6 -> KT | F8: ='2025년 주요추진사업(NEW)'!F6 -> 현대캐피탈 LLM 기반 인바운드 AI음성봇 구축 | G8: ='2025년 주요추진사업(NEW)'!G6 -> 함영민 | H8: ='2025년 주요추진사업(NEW)'!H6 -> 5 DROP | Q8: =SUM(N8:P8) -> 0 | R8: =VLOOKUP(B8, '2025년 주요추진사업(NEW)'!B:O, 14, FALSE) -> 0
B9: ='2025년 주요추진사업(NEW)'!B7 -> 2025-004 | C9: ='2025년 주요추진사업(NEW)'!C7 -> AICC | D9: ='2025년 주요추진사업(NEW)'!D7 -> 평택시청 | E9: ='2025년 주요추진사업(NEW)'!E7 -> KT평택지사 | F9: ='2025년 주요추진사업(NEW)'!F7 -> 평택시청 AI 기반 민원분석시스템 구축 | G9: ='2025년 주요추진사업(NEW)'!G7 -> 함영민 | H9: ='2025년 주요추진사업(NEW)'!H7 -> 1 영업중 | Q9: =SUM(N9:P9) -> 0 | R9: =VLOOKUP(B9, '2025년 주요추진사업(NEW)'!B:O, 14, FALSE) -> 0
B10: ='2025년 주요추진사업(NEW)'!B8 -> 2025-005 | C10: ='2025년 주요추진사업(NEW)'!C8 -> AICC | D10: ='2025년 주요추진사업(NEW)'!D8 -> KT | E10: ='2025년 주요추진사업(NEW)'!E8 -> - | F10: ='2025년 주요추진사업(NEW)'!F8 -> KT EasyCMS(봇프레임웍) 운영유지보수 지명 입찰 | G10: ='2025년 주요추진사업(NEW)'!G8 -> 함영민 | H10: ='2025년 주요추진사업(NEW)'!H8 -> 3 제안중 | Q10: =SUM(N10:P10) -> 0 | R10: =VLOOKUP(B10, '2025년 주요추진사업(NEW)'!B:O, 14, FALSE) -> 0
B11: ='2025년 주요추진사업(NEW)'!B9 -> 2025-006 | C11: ='2025년 주요추진사업(NEW)'!C9 -> AICC | D11: ='2025년 주요추진사업(NEW)'!D9 -> KDB생명 | E11: ='2025년 주요추진사업(NEW)'!E9 -> 코난테크놀로지 | F11: ='2025년 주요추진사업(NEW)'!F9 -> KDB생명 콜센터 실시간 STT 구축 | G11: ='2025년 주요추진사업(NEW)'!G9 -> 함영민 | H11: ='2025년 주요추진사업(NEW)'!H9 -> 2 견적제출 | Q11: =SUM(N11:P11) -> 0 | R11: =VLOOKUP(B11, '2025년 주요추진사업(NEW)'!B:O, 14, FALSE) -> 0
B12: ='2025년 주요추진사업(NEW)'!B10 -> 2025-007 | C12: ='2025년 주요추진사업(NEW)'!C10 -> AICC | D12: ='2025년 주요추진사업(NEW)'!D10 -> 중앙전파관리소 | E12: ='2025년 주요추진사업(NEW)'!E10 -> 코난테크놀로지 | F12: ='2025년 주요추진사업(NEW)'!F10 -> 중앙전파관리소 방송 프로그램 심의 분석 구축 사업(STT 부문 참여) | G12: ='2025년 주요추진사업(NEW)'!G10 -> 함영민 | H12: ='2025년 주요추진사업(NEW)'!H10 -> 3 제안중 | Q12: =SUM(N12:P12) -> 0 | R12: =VLOOKUP(B12, '2025년 주요추진사업(NEW)'!B:O, 14, FALSE) -> 0
B13: ='2025년 주요추진사업(NEW)'!B11 -> 2025-008 | C13: ='2025년 주요추진사업(NEW)'!C11 -> AICC | D13: ='2025년 주요추진사업(NEW)'!D11 -> 국민건강보험공단 | E13: ='2025년 주요추진사업(NEW)'!E11 -> 엔디에스 | F13: ='2025년 주요추진사업(NEW)'!F11 -> 국민건강보험공단 정신건강 복지서비스 정보시스템 구축 사업 | G13: ='2025년 주요추진사업(NEW)'!G11 -> 박현후 | H13: ='2025년 주요추진사업(NEW)'!H11 -> 2 견적제출 | Q13: =SUM(N13:P13) -> 0 | R13: =VLOOKUP(B13, '2025년 주요추진사업(NEW)'!B:O, 14, FALSE) -> 0
B14: ='2025년 주요추진사업(NEW)'!B12 -> 2025-009 | C14: ='2025년 주요추진사업(NEW)'!C12 -> AICC | D14: ='2025년 주요추진사업(NEW)'!D12 -> 현대백화점 | E14: ='2025년 주요추진사업(NEW)'!E12 -> 부뜰정보시스템 | F14: ='2025년 주요추진사업(NEW)'!F12 -> 현대백화점 상담시스템 통합 및 고도화 | G14: ='2025년 주요추진사업(NEW)'!G12 -> 박현후 | H14: ='2025년 주요추진사업(NEW)'!H12 -> 2 견적제출 | Q14: =SUM(N14:P14) -> 0 | R14: =VLOOKUP(B14, '2025년 주요추진사업(NEW)'!B:O, 14, FALSE) -> 0
B15: ='2025년 주요추진사업(NEW)'!B13 -> 2025-010 | C15: ='2025년 주요추진사업(NEW)'!C13 -> AICC | D15: ='2025년 주요추진사업(NEW)'!D13 -> 한국무역보험공사 | E15: ='2025년 주요추진사업(NEW)'!E13 -> 유플러스아이티 | F15: ='2025년 주요추진사업(NEW)'!F13 -> 한국무역보험공사 RPA 적용 챗봇 구축 | G15: ='2025년 주요추진사업(NEW)'!G13 -> 박현후 | H15: ='2025년 주요추진사업(NEW)'!H13 -> 2 견적제출 | Q15: =SUM(N15:P15) -> 0 | R15: =VLOOKUP(B15, '2025년 주요추진사업(NEW)'!B:O, 14, FALSE) -> 0
B16: ='2025년 주요추진사업(NEW)'!B14 -> 2025-011 | C16: ='2025년 주요추진사업(NEW)'!C14 -> AICC | D16: ='2025년 주요추진사업(NEW)'!D14 -> 다날 | E16: ='2025년 주요추진사업(NEW)'!E14 -> 다날 | F16: ='2025년 주요추진사업(NEW)'!F14 -> 다날 챗봇 서비스 구축 | G16: ='2025년 주요추진사업(NEW)'!G14 -> 박현후 | H16: ='2025년 주요추진사업(NEW)'!H14 -> 1 영업중 | Q16: =SUM(N16:P16) -> 0 | R16: =VLOOKUP(B16, '2025년 주요추진사업(NEW)'!B:O, 14, FALSE) -> 0
B17: ='2025년 주요추진사업(NEW)'!B15 -> 2025-012 | C17: ='2025년 주요추진사업(NEW)'!C15 -> AICC | D17: ='2025년 주요추진사업(NEW)'!D15 -> 120다산콜센터 | E17: ='2025년 주요추진사업(NEW)'!E15 -> 부뜰정보시스템 | F17: ='2025년 주요추진사업(NEW)'!F15 -> 120다산콜재단 AICC 3단계, 통합 인공지능 상담 시스템 | G17: ='2025년 주요추진사업(NEW)'!G15 -> 박현후 | H17: ='2025년 주요추진사업(NEW)'!H15 -> 2 견적제출 | Q17: =SUM(N17:P17) -> 0 | R17: =VLOOKUP(B17, '2025년 주요추진사업(NEW)'!B:O, 14, FALSE) -> 0
... B19: ='2025년 주요추진사업(NEW)'!B17 -> 2025-014 | C19: ='2025년 주요추진사업(NEW)'!C17 -> AICC | D19: ='2025년 주요추진사업(NEW)'!D17 -> AXA손해보험 | E19: ='2025년 주요추진사업(NEW)'!E17 -> 부뜰정보시스템 | F19: ='2025년 주요추진사업(NEW)'!F17 -> AXA손해보험 KMS 검색엔진 구축 | G19: ='2025년 주요추진사업(NEW)'!G17 -> 박현후 | H19: ='2025년 주요추진사업(NEW)'!H17 -> 2 견적제출 | Q19: =SUM(N19:P19) -> 0 | R19: =VLOOKUP(B19, '2025년 주요추진사업(NEW)'!B:O, 14, FALSE) -> 0
B20: ='2025년 주요추진사업(NEW)'!B18 -> 2025-015 | C20: ='2025년 주요추진사업(NEW)'!C18 -> AICC | D20: ='2025년 주요추진사업(NEW)'!D18 -> 한국도로교통공단 | E20: ='2025년 주요추진사업(NEW)'!E18 -> 트루본 | F20: ='2025년 주요추진사업(NEW)'!F18 -> 한국도로교통공단 STT 유지보수 | G20: ='2025년 주요추진사업(NEW)'!G18 -> 오민규 | H20: ='2025년 주요추진사업(NEW)'!H18 -> 9 유지보수 | I20: 2025.05.14 | J20: 2025.03.06 | K20: 2026.12.31 | L20: 16392.832 | M20: 16392.832 | N20: 751.619 | O20: 751.619 | P20: 751.619 | Q20: =SUM(N20:P20) -> 2254.857 | R20: =VLOOKUP(B20, '2025년 주요추진사업(NEW)'!B:O, 14, FALSE) -> 16302
B21: ='2025년 주요추진사업(NEW)'!B19 -> 2025-016 | C21: ='2025년 주요추진사업(NEW)'!C19 -> 수어 | D21: ='2025년 주요추진사업(NEW)'!D19 -> 한국관광공사 | E21: ='2025년 주요추진사업(NEW)'!E19 -> 한국관광공사 | F21: ='2025년 주요추진사업(NEW)'!F19 -> 한국관광공사 열린관광지포탈 및 오디(ODII)외 수어서비스제안 | G21: ='2025년 주요추진사업(NEW)'!G19 -> 양승구 | H21: ='2025년 주요추진사업(NEW)'!H19 -> 2 견적제출 | Q21: =SUM(N21:P21) -> 0 | R21: =VLOOKUP(B21, '2025년 주요추진사업(NEW)'!B:O, 14, FALSE) -> 0
B22: ='2025년 주요추진사업(NEW)'!B20 -> 2025-017 | C22: ='2025년 주요추진사업(NEW)'!C20 -> 수어 | D22: ='2025년 주요추진사업(NEW)'!D20 -> 식품안전정보원 | E22: ='2025년 주요추진사업(NEW)'!E20 -> 식품안전정보원 | F22: ='2025년 주요추진사업(NEW)'!F20 -> 식품안전정보원 '25년 식품 스마트 푸드QR 지원사업 | G22: ='2025년 주요추진사업(NEW)'!G20 -> 임철현 | H22: ='2025년 주요추진사업(NEW)'!H20 -> 8 계약완료 | I22: 2025.06.05 | J22: 2025.06.05 | K22: 2025.11.30 | L22: 16200 | M22: 16200 | Q22: =SUM(N22:P22) -> 0 | R22: =VLOOKUP(B22, '2025년 주요추진사업(NEW)'!B:O, 14, FALSE) -> 0
B23: ='2025년 주요추진사업(NEW)'!B21 -> 2025-018 | C23: ='2025년 주요추진사업(NEW)'!C21 -> 수어 | D23: ='2025년 주요추진사업(NEW)'!D21 -> 남원시 | E23: ='2025년 주요추진사업(NEW)'!E21 -> 전북테크노파크 | F23: ='2025년 주요추진사업(NEW)'!F21 -> 남원시 어울림도서관 체험관 DID형 수어체험시스템구축 | G23: ='2025년 주요추진사업(NEW)'!G21 -> 심재홍 | H23: ='2025년 주요추진사업(NEW)'!H21 -> 1 영업중 | Q23: =SUM(N23:P23) -> 0 | R23: =VLOOKUP(B23, '2025년 주요추진사업(NEW)'!B:O, 14, FALSE) -> 0
B24: ='2025년 주요추진사업(NEW)'!B22 -> 2025-019 | C24: ='2025년 주요추진사업(NEW)'!C22 -> 수어 | D24: ='2025년 주요추진사업(NEW)'!D22 -> 라스테크(주) | E24: ='2025년 주요추진사업(NEW)'!E22 -> 라스테크(주) | F24: ='2025년 주요추진사업(NEW)'!F22 -> 라스테크(주) 생산 키오스크 및 로봇 답재용 수어서비스 제안 | G24: ='2025년 주요추진사업(NEW)'!G22 -> 심재홍 | H24: ='2025년 주요추진사업(NEW)'!H22 -> 2 견적제출 | Q24: =SUM(N24:P24) -> 0 | R24: =VLOOKUP(B24, '2025년 주요추진사업(NEW)'!B:O, 14, FALSE) -> 0
B25: ='2025년 주요추진사업(NEW)'!B23 -> 2025-020 | C25: ='2025년 주요추진사업(NEW)'!C23 -> 수어 | D25: ='2025년 주요추진사업(NEW)'!D23 -> 아마노코리아 | E25: ='2025년 주요추진사업(NEW)'!E23 -> 엘토브 | F25: ='2025년 주요추진사업(NEW)'!F23 -> 아마노코리아 무인주차시스템 수어서비스 제안 | G25: ='2025년 주요추진사업(NEW)'!G23 -> 심재홍 | H25: ='2025년 주요추진사업(NEW)'!H23 -> 1 영업중 | Q25: =SUM(N25:P25) -> 0 | R25: =VLOOKUP(B25, '2025년 주요추진사업(NEW)'!B:O, 14, FALSE) -> 0
B26: ='2025년 주요추진사업(NEW)'!B24 -> 2025-021 | C26: ='2025년 주요추진사업(NEW)'!C24 -> 수어 | D26: ='2025년 주요추진사업(NEW)'!D24 -> 국립과천과학관 | E26: ='2025년 주요추진사업(NEW)'!E24 -> 윤커뮤니케이션즈 | F26: ='2025년 주요추진사업(NEW)'!F24 -> 국립과천과학관 포탈시스템 재구축 및 클라우드 전환 입찰 | G26: ='2025년 주요추진사업(NEW)'!G24 -> 심재홍 | H26: ='2025년 주요추진사업(NEW)'!H24 -> 6 실주 | Q26: =SUM(N26:P26) -> 0 | R26: =VLOOKUP(B26, '2025년 주요추진사업(NEW)'!B:O, 14, FALSE) -> 0
B27: ='2025년 주요추진사업(NEW)'!B25 -> 2025-022 | C27: ='2025년 주요추진사업(NEW)'!C25 -> 수어 | D27: ='2025년 주요추진사업(NEW)'!D25 -> 조선호텔&리조트 | E27: ='2025년 주요추진사업(NEW)'!E25 -> 엘토브 | F27: ='2025년 주요추진사업(NEW)'!F25 -> 신세계 스타필드 기존 및 신규 안내 키오스크 배리어프리 키오스크 교체계획 | G27: ='2025년 주요추진사업(NEW)'!G25 -> 임철현 | H27: ='2025년 주요추진사업(NEW)'!H25 -> 5 DROP | Q27: =SUM(N27:P27) -> 0 | R27: =VLOOKUP(B27, '2025년 주요추진사업(NEW)'!B:O, 14, FALSE) -> 0
B28: ='2025년 주요추진사업(NEW)'!B26 -> 2025-023 | C28: ='2025년 주요추진사업(NEW)'!C26 -> 수어 | D28: ='2025년 주요추진사업(NEW)'!D26 -> 국민연금공단 | E28: ='2025년 주요추진사업(NEW)'!E26 -> 국민연금공단 | F28: ='2025년 주요추진사업(NEW)'!F26 -> 연금보험공단 AI휴먼 활용 대국민 뉴스외 수어서비스적용 검토 | G28: ='2025년 주요추진사업(NEW)'!G26 -> 양승구 | H28: ='2025년 주요추진사업(NEW)'!H26 -> 1 영업중 | Q28: =SUM(N28:P28) -> 0 | R28: =VLOOKUP(B28, '2025년 주요추진사업(NEW)'!B:O, 14, FALSE) -> 0
B29: ='2025년 주요추진사업(NEW)'!B27 -> 2025-024 | C29: ='2025년 주요추진사업(NEW)'!C27 -> 수어 | D29: ='2025년 주요추진사업(NEW)'!D27 -> 소다미술관 | E29: ='2025년 주요추진사업(NEW)'!E27 -> 소다미술관 | F29: ='2025년 주요추진사업(NEW)'!F27 -> 소다미술관 전시정보 수어서비스 사업제안 | G29: ='2025년 주요추진사업(NEW)'!G27 -> 오민규 | H29: ='2025년 주요추진사업(NEW)'!H27 -> 1 영업중 | Q29: =SUM(N29:P29) -> 0 | R29: =VLOOKUP(B29, '2025년 주요추진사업(NEW)'!B:O, 14, FALSE) -> 0
B30: ='2025년 주요추진사업(NEW)'!B28 -> 2025-025 | C30: ='2025년 주요추진사업(NEW)'!C28 -> 수어 | D30: ='2025년 주요추진사업(NEW)'!D28 -> AIA생명보험 | E30: ='2025년 주요추진사업(NEW)'!E28 -> 아이엔지피플(LG CNS) | F30: ='2025년 주요추진사업(NEW)'!F28 -> AIA생명보험 포털시스템 구축(수어서비스 추가제안) | G30: ='2025년 주요추진사업(NEW)'!G28 -> 양승구 | H30: ='2025년 주요추진사업(NEW)'!H28 -> 1 영업중 | Q30: =SUM(N30:P30) -> 0 | R30: =VLOOKUP(B30, '2025년 주요추진사업(NEW)'!B:O, 14, FALSE) -> 0
B31: ='2025년 주요추진사업(NEW)'!B29 -> 2025-026 | C31: ='2025년 주요추진사업(NEW)'!C29 -> 수어 | D31: ='2025년 주요추진사업(NEW)'!D29 -> KB증권 | E31: ='2025년 주요추진사업(NEW)'!E29 -> KB증권 | F31: ='2025년 주요추진사업(NEW)'!F29 -> KB증권 웹, 모바일서비스內 생성형 AI기반 수어서비스적용 검토 | G31: ='2025년 주요추진사업(NEW)'!G29 -> 양승구 | H31: ='2025년 주요추진사업(NEW)'!H29 -> 1 영업중 | Q31: =SUM(N31:P31) -> 0 | R31: =VLOOKUP(B31, '2025년 주요추진사업(NEW)'!B:O, 14, FALSE) -> 0
B32: ='2025년 주요추진사업(NEW)'!B30 -> 2025-027 | C32: ='2025년 주요추진사업(NEW)'!C30 -> 수어 | D32: ='2025년 주요추진사업(NEW)'!D30 -> 제주도 교육청 | E32: ='2025년 주요추진사업(NEW)'!E30 -> KT클라우드 | F32: ='2025년 주요추진사업(NEW)'!F30 -> 제주도교육청 320여개 초,중등 대상 홈페이지 및 키오스크 수어서비스 제안 | G32: ='2025년 주요추진사업(NEW)'!G30 -> 오민규 | H32: ='2025년 주요추진사업(NEW)'!H30 -> 1 영업중 | Q32: =SUM(N32:P32) -> 0 | R32: =VLOOKUP(B32, '2025년 주요추진사업(NEW)'!B:O, 14, FALSE) -> 0
B33: ='2025년 주요추진사업(NEW)'!B31 -> 2025-028 | C33: ='2025년 주요추진사업(NEW)'!C31 -> 수어 | D33: ='2025년 주요추진사업(NEW)'!D31 -> 한국철도공사(코레일) | E33: ='2025년 주요추진사업(NEW)'!E31 -> 케이알솔루션 | F33: ='2025년 주요추진사업(NEW)'!F31 -> 한국철도공사(코레일) 신형자동발매기內 수어서비스적용 | G33: ='2025년 주요추진사업(NEW)'!G31 -> 오민규 | H33: ='2025년 주요추진사업(NEW)'!H31 -> 8 계약완료 | I33: 2025.07.18 | J33: 2025.07.18 | K33: 2025.08.29 | L33: 7200 | M33: 7200 | N33: 7200 | Q33: =SUM(N33:P33) -> 7200 | R33: =VLOOKUP(B33, '2025년 주요추진사업(NEW)'!B:O, 14, FALSE) -> 0
B34: ='2025년 주요추진사업(NEW)'!B32 -> 2025-029 | C34: ='2025년 주요추진사업(NEW)'!C32 -> 수어 | D34: ='2025년 주요추진사업(NEW)'!D32 -> LG그룹 | E34: ='2025년 주요추진사업(NEW)'!E32 -> LG슈퍼스타트팀 | F34: ='2025년 주요추진사업(NEW)'!F32 -> LG그룹 계열사대상 수어서비스 적용 제안 진행중 | G34: ='2025년 주요추진사업(NEW)'!G32 -> 오민규 | H34: ='2025년 주요추진사업(NEW)'!H32 -> 1 영업중 | Q34: =SUM(N34:P34) -> 0 | R34: =VLOOKUP(B34, '2025년 주요추진사업(NEW)'!B:O, 14, FALSE) -> 0
B35: ='2025년 주요추진사업(NEW)'!B33 -> 2025-030 | C35: ='2025년 주요추진사업(NEW)'!C33 -> 수어 | D35: ='2025년 주요추진사업(NEW)'!D33 -> GS칼텍스 | E35: ='2025년 주요추진사업(NEW)'!E33 -> 지에스아이티엠(GSITM) | F35: ='2025년 주요추진사업(NEW)'!F33 -> GS칼텍스 주유소 운영 SW 혁신 프로젝트 수어서비스 | G35: ='2025년 주요추진사업(NEW)'!G33 -> 오민규 | H35: ='2025년 주요추진사업(NEW)'!H33 -> 8 계약완료 | I35: 2025.05.16 | J35: 2025.05.16 | K35: 2025.05.31 | L35: 1020 | M35: 1020 | Q35: =SUM(N35:P35) -> 0 | R35: =VLOOKUP(B35, '2025년 주요추진사업(NEW)'!B:O, 14, FALSE) -> 0
B36: ='2025년 주요추진사업(NEW)'!B34 -> 2025-031 | C36: ='2025년 주요추진사업(NEW)'!C34 -> 수어 | D36: ='2025년 주요추진사업(NEW)'!D34 -> 전국지자체 | E36: ='2025년 주요추진사업(NEW)'!E34 -> 전국지자체 | F36: ='2025년 주요추진사업(NEW)'!F34 -> - 전국 지자체 문화축제 수어서비스 적용 제안사업 | G36: ='2025년 주요추진사업(NEW)'!G34 -> 양승구 | H36: ='2025년 주요추진사업(NEW)'!H34 -> 1 영업중 | Q36: =SUM(N36:P36) -> 0 | R36: =VLOOKUP(B36, '2025년 주요추진사업(NEW)'!B:O, 14, FALSE) -> 0
B37: ='2025년 주요추진사업(NEW)'!B35 -> 2025-032 | C37: ='2025년 주요추진사업(NEW)'!C35 -> 수어 | D37: ='2025년 주요추진사업(NEW)'!D35 -> (주)채움씨앤아이 | E37: ='2025년 주요추진사업(NEW)'!E35 -> (주)채움씨앤아이 | F37: ='2025년 주요추진사업(NEW)'!F35 -> - (주)채움씨앤아이 도서관용 로봇 수어서비스 제안 | G37: ='2025년 주요추진사업(NEW)'!G35 -> 심재홍 | H37: ='2025년 주요추진사업(NEW)'!H35 -> 1 영업중 | Q37: =SUM(N37:P37) -> 0 | R37: =VLOOKUP(B37, '2025년 주요추진사업(NEW)'!B:O, 14, FALSE) -> 0
B38: ='2025년 주요추진사업(NEW)'!B36 -> 2025-033 | C38: ='2025년 주요추진사업(NEW)'!C36 -> 수어 | D38: ='2025년 주요추진사업(NEW)'!D36 -> KB국민은행 | E38: ='2025년 주요추진사업(NEW)'!E36 -> LG CNS | F38: ='2025년 주요추진사업(NEW)'!F36 -> KB국민은행 수어번역서비스 | G38: ='2025년 주요추진사업(NEW)'!G36 -> 함영민 | H38: ='2025년 주요추진사업(NEW)'!H36 -> 2 견적제출 | Q38: =SUM(N38:P38) -> 0 | R38: =VLOOKUP(B38, '2025년 주요추진사업(NEW)'!B:O, 14, FALSE) -> 0
B39: ='2025년 주요추진사업(NEW)'!B37 -> 2025-034 | C39: ='2025년 주요추진사업(NEW)'!C37 -> 수어 | D39: ='2025년 주요추진사업(NEW)'!D37 -> 부천도시공사 | E39: ='2025년 주요추진사업(NEW)'!E37 -> 부천도시공사 | F39: ='2025년 주요추진사업(NEW)'!F37 -> 부천도시공사 수어번역서비스 제안 | G39: ='2025년 주요추진사업(NEW)'!G37 -> 함영민 | H39: ='2025년 주요추진사업(NEW)'!H37 -> 1 영업중 | Q39: =SUM(N39:P39) -> 0 | R39: =VLOOKUP(B39, '2025년 주요추진사업(NEW)'!B:O, 14, FALSE) -> 0
B40: ='2025년 주요추진사업(NEW)'!B38 -> 2025-035 | C40: ='2025년 주요추진사업(NEW)'!C38 -> 수어 | D40: ='2025년 주요추진사업(NEW)'!D38 -> 남양주도시공사 | E40: ='2025년 주요추진사업(NEW)'!E38 -> 남양주도시공사 | F40: ='2025년 주요추진사업(NEW)'!F38 -> 남양주도시공사 수어번역서비스 제안 | G40: ='2025년 주요추진사업(NEW)'!G38 -> 함영민 | H40: ='2025년 주요추진사업(NEW)'!H38 -> 1 영업중 | Q40: =SUM(N40:P40) -> 0 | R40: =VLOOKUP(B40, '2025년 주요추진사업(NEW)'!B:O, 14, FALSE) -> 0
B41: ='2025년 주요추진사업(NEW)'!B39 -> 2025-036 | C41: ='2025년 주요추진사업(NEW)'!C39 -> 수어 | D41: ='2025년 주요추진사업(NEW)'!D39 -> 현대백화점 | E41: ='2025년 주요추진사업(NEW)'!E39 -> 에이치엘엠 | F41: ='2025년 주요추진사업(NEW)'!F39 -> 현대백화점 수어번역서비스 키오스크 적용 | G41: ='2025년 주요추진사업(NEW)'!G39 -> 함영민 | H41: ='2025년 주요추진사업(NEW)'!H39 -> 3 제안중 | Q41: =SUM(N41:P41) -> 0 | R41: =VLOOKUP(B41, '2025년 주요추진사업(NEW)'!B:O, 14, FALSE) -> 0
B42: ='2025년 주요추진사업(NEW)'!B40 -> 2025-037 | C42: ='2025년 주요추진사업(NEW)'!C40 -> 수어 | D42: ='2025년 주요추진사업(NEW)'!D40 -> 카카오뱅크 | E42: ='2025년 주요추진사업(NEW)'!E40 -> 본사영업 | F42: ='2025년 주요추진사업(NEW)'!F40 -> 카카오뱅크 AI수어상담 3D 아바타 및 영상제작 | G42: ='2025년 주요추진사업(NEW)'!G40 -> 양승구 | H42: ='2025년 주요추진사업(NEW)'!H40 -> 8 계약완료 | I42: 2025.09.08 | J42: 2025.09.08 | K42: 2026.02.28 | L42: 44100 | M42: 44100 | N42: - | O42: - | P42: 44100 | Q42: =SUM(N42:P42) -> 44100 | R42: =VLOOKUP(B42, '2025년 주요추진사업(NEW)'!B:O, 14, FALSE) -> 0
B43: ='2025년 주요추진사업(NEW)'!B41 -> 2025-038 | C43: ='2025년 주요추진사업(NEW)'!C41 -> 수어 | D43: ='2025년 주요추진사업(NEW)'!D41 -> 웅진씽크빅 | E43: ='2025년 주요추진사업(NEW)'!E41 -> 웅진씽크빅 | F43: ='2025년 주요추진사업(NEW)'!F41 -> 웅진씽크빅 디지털교과서 수어번역서비스 제안 | G43: ='2025년 주요추진사업(NEW)'!G41 -> 함영민 | H43: ='2025년 주요추진사업(NEW)'!H41 -> 1 영업중 | Q43: =SUM(N43:P43) -> 0 | R43: =VLOOKUP(B43, '2025년 주요추진사업(NEW)'!B:O, 14, FALSE) -> 0
B44: ='2025년 주요추진사업(NEW)'!B42 -> 2025-039 | C44: ='2025년 주요추진사업(NEW)'!C42 -> 수어 | D44: ='2025년 주요추진사업(NEW)'!D42 -> KB저축은행 | E44: ='2025년 주요추진사업(NEW)'!E42 -> LG CNS | F44: ='2025년 주요추진사업(NEW)'!F42 -> KB저축은행 수어번역서비스 적용 | G44: ='2025년 주요추진사업(NEW)'!G42 -> 함영민 | H44: ='2025년 주요추진사업(NEW)'!H42 -> 1 영업중 | Q44: =SUM(N44:P44) -> 0 | R44: =VLOOKUP(B44, '2025년 주요추진사업(NEW)'!B:O, 14, FALSE) -> 0
B45: ='2025년 주요추진사업(NEW)'!B43 -> 2025-040 | C45: ='2025년 주요추진사업(NEW)'!C43 -> 수어 | D45: ='2025년 주요추진사업(NEW)'!D43 -> KB국민카드 | E45: ='2025년 주요추진사업(NEW)'!E43 -> LG CNS | F45: ='2025년 주요추진사업(NEW)'!F43 -> KB국민카드 수어번역서비스 | G45: ='2025년 주요추진사업(NEW)'!G43 -> 함영민 | H45: ='2025년 주요추진사업(NEW)'!H43 -> 1 영업중 | Q45: =SUM(N45:P45) -> 0 | R45: =VLOOKUP(B45, '2025년 주요추진사업(NEW)'!B:O, 14, FALSE) -> 0
B46: ='2025년 주요추진사업(NEW)'!B44 -> 2025-041 | C46: ='2025년 주요추진사업(NEW)'!C44 -> 수어 | D46: ='2025년 주요추진사업(NEW)'!D44 -> BGF네트웍스 | E46: ='2025년 주요추진사업(NEW)'!E44 -> BGF네트웍스 | F46: ='2025년 주요추진사업(NEW)'!F44 -> CU 편의점 모바일앱 수어번역서비스 | G46: ='2025년 주요추진사업(NEW)'!G44 -> 함영민 | H46: ='2025년 주요추진사업(NEW)'!H44 -> 1 영업중 | Q46: =SUM(N46:P46) -> 0 | R46: =VLOOKUP(B46, '2025년 주요추진사업(NEW)'!B:O, 14, FALSE) -> 0
B47: ='2025년 주요추진사업(NEW)'!B45 -> 2025-042 | C47: ='2025년 주요추진사업(NEW)'!C45 -> 수어 | D47: ='2025년 주요추진사업(NEW)'!D45 -> 연구개발특구진흥재단 | E47: ='2025년 주요추진사업(NEW)'!E45 -> 연구개발특구진흥재단 | F47: ='2025년 주요추진사업(NEW)'!F45 -> 연구개발특구진흥재단 수어번역서비스 | G47: ='2025년 주요추진사업(NEW)'!G45 -> 함영민 | H47: ='2025년 주요추진사업(NEW)'!H45 -> 1 영업중 | Q47: =SUM(N47:P47) -> 0 | R47: =VLOOKUP(B47, '2025년 주요추진사업(NEW)'!B:O, 14, FALSE) -> 0
B48: ='2025년 주요추진사업(NEW)'!B46 -> 2025-043 | C48: ='2025년 주요추진사업(NEW)'!C46 -> 수어 | D48: ='2025년 주요추진사업(NEW)'!D46 -> 식품안전정보원 | E48: ='2025년 주요추진사업(NEW)'!E46 -> 식품안전정보원 | F48: ='2025년 주요추진사업(NEW)'!F46 -> 식품안전정보원 홈페이지 기본 안내 설명 수어 자막 서비스 | G48: ='2025년 주요추진사업(NEW)'!G46 -> 함영민 | H48: ='2025년 주요추진사업(NEW)'!H46 -> 2 견적제출 | Q48: =SUM(N48:P48) -> 0 | R48: =VLOOKUP(B48, '2025년 주요추진사업(NEW)'!B:O, 14, FALSE) -> 0
B49: ='2025년 주요추진사업(NEW)'!B47 -> 2025-044 | C49: ='2025년 주요추진사업(NEW)'!C47 -> 수어 | D49: ='2025년 주요추진사업(NEW)'!D47 -> S&I코퍼레이션 | E49: ='2025년 주요추진사업(NEW)'!E47 -> S&I코퍼레이션 | F49: ='2025년 주요추진사업(NEW)'!F47 -> 건물관리 분야 수어번역서비스 보급 확산 | G49: ='2025년 주요추진사업(NEW)'!G47 -> 임철현 | H49: ='2025년 주요추진사업(NEW)'!H47 -> 1 영업중 | Q49: =SUM(N49:P49) -> 0 | R49: =VLOOKUP(B49, '2025년 주요추진사업(NEW)'!B:O, 14, FALSE) -> 0
B50: ='2025년 주요추진사업(NEW)'!B48 -> 2025-045 | C50: ='2025년 주요추진사업(NEW)'!C48 -> 수어 | D50: ='2025년 주요추진사업(NEW)'!D48 -> 서울의료원 | E50: ='2025년 주요추진사업(NEW)'!E48 -> 서울시 원무팀 | F50: ='2025년 주요추진사업(NEW)'!F48 -> 2025년 테스트베드 서울 실증 지원사업(서울의료원) | G50: ='2025년 주요추진사업(NEW)'!G48 -> 임철현 | H50: ='2025년 주요추진사업(NEW)'!H48 -> 7 수주완료 | I50: 26년 초 계약 예정 | L50: =200000/1.1 -> 181818.18 | M50: =200000/1.1 -> 181818.18 | Q50: =SUM(N50:P50) -> 0 | R50: =VLOOKUP(B50, '2025년 주요추진사업(NEW)'!B:O, 14, FALSE) -> 0
B51: ='2025년 주요추진사업(NEW)'!B49 -> 2025-046 | C51: ='2025년 주요추진사업(NEW)'!C49 -> 수어 | D51: ='2025년 주요추진사업(NEW)'!D49 -> 롯데백화점 | E51: ='2025년 주요추진사업(NEW)'!E49 -> 엘토브 | F51: ='2025년 주요추진사업(NEW)'!F49 -> 롯데백화점 기존 매장안내 키오스크 수어서비스 업그레이드 사업 | G51: ='2025년 주요추진사업(NEW)'!G49 -> 오민규 | H51: ='2025년 주요추진사업(NEW)'!H49 -> 2 견적제출 | Q51: =SUM(N51:P51) -> 0 | R51: =VLOOKUP(B51, '2025년 주요추진사업(NEW)'!B:O, 14, FALSE) -> 0
B52: ='2025년 주요추진사업(NEW)'!B50 -> 2025-047 | C52: ='2025년 주요추진사업(NEW)'!C50 -> 수어 | D52: ='2025년 주요추진사업(NEW)'!D50 -> NH농협은행 | E52: ='2025년 주요추진사업(NEW)'!E50 -> SK쉴더스 | F52: ='2025년 주요추진사업(NEW)'!F50 -> NH농협은행 창구혁신 운영을 위한 수어서비스 | G52: ='2025년 주요추진사업(NEW)'!G50 -> 양승구 | H52: ='2025년 주요추진사업(NEW)'!H50 -> 8 계약완료 | I52: 2025.06.19 | J52: 2025.06.19 | K52: 2025.07.15 | L52: 18050 | M52: 18050 | Q52: =SUM(N52:P52) -> 0 | R52: =VLOOKUP(B52, '2025년 주요추진사업(NEW)'!B:O, 14, FALSE) -> 0
B53: ='2025년 주요추진사업(NEW)'!B51 -> 2025-048 | C53: ='2025년 주요추진사업(NEW)'!C51 -> 수어 | D53: ='2025년 주요추진사업(NEW)'!D51 -> IBK기업은행 | E53: ='2025년 주요추진사업(NEW)'!E51 -> LG CNS&에이텍에이피 | F53: ='2025년 주요추진사업(NEW)'!F51 -> IBK기업은행 화상상담시스템 구축 및 디지털데스크 도입 사업 | G53: ='2025년 주요추진사업(NEW)'!G51 -> 양승구 | H53: ='2025년 주요추진사업(NEW)'!H51 -> 8 계약완료 | I53: 2024.12.04 | J53: 2024.12.04 | K53: 2025.06.17 | L53: 8800 | M53: 8800 | Q53: =SUM(N53:P53) -> 0 | R53: =VLOOKUP(B53, '2025년 주요추진사업(NEW)'!B:O, 14, FALSE) -> 0
B54: ='2025년 주요추진사업(NEW)'!B52 -> 2025-049 | C54: ='2025년 주요추진사업(NEW)'!C52 -> 수어 | D54: ='2025년 주요추진사업(NEW)'!D52 -> 서울시 | E54: ='2025년 주요추진사업(NEW)'!E52 -> 서울시 | F54: ='2025년 주요추진사업(NEW)'!F52 -> 서울시청 장애인편의증진팀 협업사업 발굴 영업진행 | G54: ='2025년 주요추진사업(NEW)'!G52 -> 양승구 | H54: ='2025년 주요추진사업(NEW)'!H52 -> 3 제안중 | Q54: =SUM(N54:P54) -> 0 | R54: =VLOOKUP(B54, '2025년 주요추진사업(NEW)'!B:O, 14, FALSE) -> 0
B55: ='2025년 주요추진사업(NEW)'!B53 -> 2025-050 | C55: ='2025년 주요추진사업(NEW)'!C53 -> 수어 | D55: ='2025년 주요추진사업(NEW)'!D53 -> 국립국악원 | E55: ='2025년 주요추진사업(NEW)'!E53 -> 국립국악원 | F55: ='2025년 주요추진사업(NEW)'!F53 -> 국립국악원 국악 아카이브 포털 및 공연 영상자료 수어서비스 적용 제안 | G55: ='2025년 주요추진사업(NEW)'!G53 -> 오민규 | H55: ='2025년 주요추진사업(NEW)'!H53 -> 3 제안중 | Q55: =SUM(N55:P55) -> 0 | R55: =VLOOKUP(B55, '2025년 주요추진사업(NEW)'!B:O, 14, FALSE) -> 0
B56: ='2025년 주요추진사업(NEW)'!B54 -> 2025-051 | C56: ='2025년 주요추진사업(NEW)'!C54 -> 수어 | D56: ='2025년 주요추진사업(NEW)'!D54 -> 토스뱅크 | E56: ='2025년 주요추진사업(NEW)'!E54 -> (주)브리지텍 | F56: ='2025년 주요추진사업(NEW)'!F54 -> (주)브리지텍_토스뱅크 콜 인프라 재구축 사업중 수어서비스 추가제안 | G56: ='2025년 주요추진사업(NEW)'!G54 -> 오민규 | H56: ='2025년 주요추진사업(NEW)'!H54 -> 3 제안중 | Q56: =SUM(N56:P56) -> 0 | R56: =VLOOKUP(B56, '2025년 주요추진사업(NEW)'!B:O, 14, FALSE) -> 60000
B57: ='2025년 주요추진사업(NEW)'!B55 -> 2025-052 | C57: ='2025년 주요추진사업(NEW)'!C55 -> 수어 | D57: ='2025년 주요추진사업(NEW)'!D55 -> 우리은행 | E57: ='2025년 주요추진사업(NEW)'!E55 -> LGCNS | F57: ='2025년 주요추진사업(NEW)'!F55 -> 우리은행 3개지점 AI브랜치 시범사업 구축사업 | G57: ='2025년 주요추진사업(NEW)'!G55 -> 오민규 | H57: ='2025년 주요추진사업(NEW)'!H55 -> 1 영업중 | Q57: =SUM(N57:P57) -> 0 | R57: =VLOOKUP(B57, '2025년 주요추진사업(NEW)'!B:O, 14, FALSE) -> 0
B58: ='2025년 주요추진사업(NEW)'!B56 -> 2025-053 | C58: ='2025년 주요추진사업(NEW)'!C56 -> 수어 | D58: ='2025년 주요추진사업(NEW)'!D56 -> SRT | E58: ='2025년 주요추진사업(NEW)'!E56 -> 에이텍모빌리티/지엔시스 | F58: ='2025년 주요추진사업(NEW)'!F56 -> SRT 4개역사 배리어프리 발권기內 수어아바타 적용사업 | G58: ='2025년 주요추진사업(NEW)'!G56 -> 심재홍 | H58: ='2025년 주요추진사업(NEW)'!H56 -> 6 실주 | Q58: =SUM(N58:P58) -> 0 | R58: =VLOOKUP(B58, '2025년 주요추진사업(NEW)'!B:O, 14, FALSE) -> 0
B59: ='2025년 주요추진사업(NEW)'!B57 -> 2025-054 | C59: ='2025년 주요추진사업(NEW)'!C57 -> 수어 | D59: ='2025년 주요추진사업(NEW)'!D57 -> 삼성전자 | E59: ='2025년 주요추진사업(NEW)'!E57 -> 엘토브 | F59: ='2025년 주요추진사업(NEW)'!F57 -> 삼성전자 서비스센터 배리어프리 대기자 발권 키오스크 도입사업 | G59: ='2025년 주요추진사업(NEW)'!G57 -> 오민규 | H59: ='2025년 주요추진사업(NEW)'!H57 -> 2 견적제출 | Q59: =SUM(N59:P59) -> 0 | R59: =VLOOKUP(B59, '2025년 주요추진사업(NEW)'!B:O, 14, FALSE) -> 0
B60: ='2025년 주요추진사업(NEW)'!B58 -> 2025-055 | C60: ='2025년 주요추진사업(NEW)'!C58 -> 수어 | D60: ='2025년 주요추진사업(NEW)'!D58 -> 미래에셋생명 | E60: ='2025년 주요추진사업(NEW)'!E58 -> 부뜰정보시스템 | F60: ='2025년 주요추진사업(NEW)'!F58 -> 미래에셋생명 차세대시스템 구축 추가 솔루션(AI수어) 도입사업 | G60: ='2025년 주요추진사업(NEW)'!G58 -> 오민규 | H60: ='2025년 주요추진사업(NEW)'!H58 -> 2 견적제출 | Q60: =SUM(N60:P60) -> 0 | R60: =VLOOKUP(B60, '2025년 주요추진사업(NEW)'!B:O, 14, FALSE) -> 163000
B61: ='2025년 주요추진사업(NEW)'!B59 -> 2025-056 | C61: ='2025년 주요추진사업(NEW)'!C59 -> 수어 | D61: ='2025년 주요추진사업(NEW)'!D59 -> (주)서원 | E61: ='2025년 주요추진사업(NEW)'!E59 -> (주)서원 | F61: ='2025년 주요추진사업(NEW)'!F59 -> (주)서원 고속도록 휴게소 배리어프리 무인발권기 도입사업 | G61: ='2025년 주요추진사업(NEW)'!G59 -> 오민규 | H61: ='2025년 주요추진사업(NEW)'!H59 -> 1 영업중 | Q61: =SUM(N61:P61) -> 0 | R61: =VLOOKUP(B61, '2025년 주요추진사업(NEW)'!B:O, 14, FALSE) -> 0
B62: ='2025년 주요추진사업(NEW)'!B60 -> 2025-057 | C62: ='2025년 주요추진사업(NEW)'!C60 -> 수어 | D62: ='2025년 주요추진사업(NEW)'!D60 -> 공공? | E62: ='2025년 주요추진사업(NEW)'!E60 -> 더라이즈 | F62: ='2025년 주요추진사업(NEW)'!F60 -> 더라이즈 영상제작사 전시장 영상 수어아바타적용 사업 | G62: ='2025년 주요추진사업(NEW)'!G60 -> 심재홍 | H62: ='2025년 주요추진사업(NEW)'!H60 -> 2 견적제출 | Q62: =SUM(N62:P62) -> 0 | R62: =VLOOKUP(B62, '2025년 주요추진사업(NEW)'!B:O, 14, FALSE) -> 0
B63: ='2025년 주요추진사업(NEW)'!B61 -> 2025-058 | C63: ='2025년 주요추진사업(NEW)'!C61 -> 수어 | D63: ='2025년 주요추진사업(NEW)'!D61 -> 이대목동병원 | E63: ='2025년 주요추진사업(NEW)'!E61 -> 이대목동병원 | F63: ='2025년 주요추진사업(NEW)'!F61 -> 이대목동병원 장애인 의료기관 이용편의 지원사업 선정/ 수어서비스 도입 검토중 | G63: ='2025년 주요추진사업(NEW)'!G61 -> 임철현 | H63: ='2025년 주요추진사업(NEW)'!H61 -> 3 제안중 | Q63: =SUM(N63:P63) -> 0 | R63: =VLOOKUP(B63, '2025년 주요추진사업(NEW)'!B:O, 14, FALSE) -> 0
B64: ='2025년 주요추진사업(NEW)'!B62 -> 2025-059 | C64: ='2025년 주요추진사업(NEW)'!C62 -> 수어 | D64: ='2025년 주요추진사업(NEW)'!D62 -> 동부병원 | E64: ='2025년 주요추진사업(NEW)'!E62 -> 동부병원 | F64: ='2025년 주요추진사업(NEW)'!F62 -> 서울시 동부병원 장애인 의료기관 이용편의 지원사업 3자화상통화외 입점 영업진행 | G64: ='2025년 주요추진사업(NEW)'!G62 -> 임철현 | H64: ='2025년 주요추진사업(NEW)'!H62 -> 3 제안중 | Q64: =SUM(N64:P64) -> 0 | R64: =VLOOKUP(B64, '2025년 주요추진사업(NEW)'!B:O, 14, FALSE) -> 0
B65: ='2025년 주요추진사업(NEW)'!B63 -> 2025-060 | C65: ='2025년 주요추진사업(NEW)'!C63 -> 수어 | D65: ='2025년 주요추진사업(NEW)'!D63 -> 경기도의료원/분당서울대병원/원광대학교병원 | E65: ='2025년 주요추진사업(NEW)'!E63 -> 경기도의료원/분당서울대병원/원광대학교병원 | F65: ='2025년 주요추진사업(NEW)'!F63 -> 장애인 의료기관 이용편의 지원사업 4개병원 3자통화/QR 제안 | G65: ='2025년 주요추진사업(NEW)'!G63 -> 임철현 | H65: ='2025년 주요추진사업(NEW)'!H63 -> 1 영업중 | Q65: =SUM(N65:P65) -> 0 | R65: =VLOOKUP(B65, '2025년 주요추진사업(NEW)'!B:O, 14, FALSE) -> 0
... B67: ='2025년 주요추진사업(NEW)'!B65 -> 2025-062 | C67: ='2025년 주요추진사업(NEW)'!C65 -> AICC | D67: ='2025년 주요추진사업(NEW)'!D65 -> 경찰청 | E67: ='2025년 주요추진사업(NEW)'!E65 -> 펜타시스템 | F67: ='2025년 주요추진사업(NEW)'!F65 -> 경찰청 전기통신금융사기 통합분석대응시스템 고도화 사업 | G67: ='2025년 주요추진사업(NEW)'!G65 -> 오민규 | H67: ='2025년 주요추진사업(NEW)'!H65 -> 5 DROP | Q67: =SUM(N67:P67) -> 0 | R67: =VLOOKUP(B67, '2025년 주요추진사업(NEW)'!B:O, 14, FALSE) -> 0
B68: ='2025년 주요추진사업(NEW)'!B66 -> 2025-063 | C68: ='2025년 주요추진사업(NEW)'!C66 -> AICC | D68: ='2025년 주요추진사업(NEW)'!D66 -> 한국증권금융 | E68: ='2025년 주요추진사업(NEW)'!E66 -> 부뜰정보시스템 | F68: ='2025년 주요추진사업(NEW)'!F66 -> 한국증권금융 콜센터시스템 재구축 사업內 KMS 구축 | G68: ='2025년 주요추진사업(NEW)'!G66 -> 오민규 | H68: ='2025년 주요추진사업(NEW)'!H66 -> 8 계약완료 | I68: 2025.06.30 | J68: 2025.07.01 | K68: 2026.02.02 | L68: 53000 | M68: 53000 | Q68: =SUM(N68:P68) -> 0 | R68: =VLOOKUP(B68, '2025년 주요추진사업(NEW)'!B:O, 14, FALSE) -> 0
B69: ='2025년 주요추진사업(NEW)'!B67 -> 2025-064 | C69: ='2025년 주요추진사업(NEW)'!C67 -> 수어 | D69: ='2025년 주요추진사업(NEW)'!D67 -> 국립국어원 | E69: ='2025년 주요추진사업(NEW)'!E67 -> 국립국어원 | F69: ='2025년 주요추진사업(NEW)'!F67 -> 국립국어원 수어문자 사업기획 | G69: ='2025년 주요추진사업(NEW)'!G67 -> 오민규 | H69: ='2025년 주요추진사업(NEW)'!H67 -> 2 견적제출 | Q69: =SUM(N69:P69) -> 0 | R69: =VLOOKUP(B69, '2025년 주요추진사업(NEW)'!B:O, 14, FALSE) -> 749931.07
B70: ='2025년 주요추진사업(NEW)'!B68 -> 2025-065 | C70: ='2025년 주요추진사업(NEW)'!C68 -> AICC | D70: ='2025년 주요추진사업(NEW)'!D68 -> 경찰청 | E70: ='2025년 주요추진사업(NEW)'!E68 -> 펜타시스템 | F70: ='2025년 주요추진사업(NEW)'!F68 -> 경찰청 경찰견문관리시스템 고도화 사업(STT) | G70: ='2025년 주요추진사업(NEW)'!G68 -> 오민규 | H70: ='2025년 주요추진사업(NEW)'!H68 -> 7 수주완료 | I70: 26년 초 계약 예정 | L70: 130000 | Q70: =SUM(N70:P70) -> 0 | R70: =VLOOKUP(B70, '2025년 주요추진사업(NEW)'!B:O, 14, FALSE) -> 130000 | S70: 26년 초 계약 예정
B71: ='2025년 주요추진사업(NEW)'!B69 -> 2025-066 | C71: ='2025년 주요추진사업(NEW)'!C69 -> 수어 | D71: ='2025년 주요추진사업(NEW)'!D69 -> 국립호남권생물자원관 | E71: ='2025년 주요추진사업(NEW)'!E69 -> 국립호남권생물자원관 | F71: ='2025년 주요추진사업(NEW)'!F69 -> 국립호남권생물자원관 개인정보 처리방침 수어 안내 | G71: ='2025년 주요추진사업(NEW)'!G69 -> 오민규 | H71: ='2025년 주요추진사업(NEW)'!H69 -> 8 계약완료 | I71: 2025.09.09 | J71: 2025.09.09 | K71: 2025.10.08 | L71: 2500 | M71: 2500 | N71: 2500 | Q71: =SUM(N71:P71) -> 2500 | R71: =VLOOKUP(B71, '2025년 주요추진사업(NEW)'!B:O, 14, FALSE) -> 2500
B72: ='2025년 주요추진사업(NEW)'!B70 -> 2025-067 | C72: ='2025년 주요추진사업(NEW)'!C70 -> AICC | D72: ='2025년 주요추진사업(NEW)'!D70 -> 교보라이프플래닛생명보험 | E72: ='2025년 주요추진사업(NEW)'!E70 -> 부뜰정보시스템 | F72: ='2025년 주요추진사업(NEW)'!F70 -> 교보라이프플래닛생명보험 검색엔진 유지보수 | G72: ='2025년 주요추진사업(NEW)'!G70 -> 오민규 | H72: ='2025년 주요추진사업(NEW)'!H70 -> 9 유지보수 | I72: 2025.08.13 | J72: 2025.01.01 | K72: 2026.06.30 | L72: 900 | M72: 900 | Q72: =SUM(N72:P72) -> 0 | R72: =VLOOKUP(B72, '2025년 주요추진사업(NEW)'!B:O, 14, FALSE) -> 900 | S72: 25년 무상. 26년 6개월(15만원/월)
B73: ='2025년 주요추진사업(NEW)'!B71 -> 2025-068 | C73: ='2025년 주요추진사업(NEW)'!C71 -> AICC | D73: ='2025년 주요추진사업(NEW)'!D71 -> 유비케어 | E73: ='2025년 주요추진사업(NEW)'!E71 -> 복스유니버스 | F73: ='2025년 주요추진사업(NEW)'!F71 -> 유비케어 KMS 지식 데이터 구축 | G73: ='2025년 주요추진사업(NEW)'!G71 -> 오민규 | H73: ='2025년 주요추진사업(NEW)'!H71 -> 5 DROP | Q73: =SUM(N73:P73) -> 0 | R73: =VLOOKUP(B73, '2025년 주요추진사업(NEW)'!B:O, 14, FALSE) -> 33000
B74: ='2025년 주요추진사업(NEW)'!B72 -> 2025-069 | C74: ='2025년 주요추진사업(NEW)'!C72 -> 수어 | D74: ='2025년 주요추진사업(NEW)'!D72 -> 가톨릭대학교 성빈센트병원 | E74: ='2025년 주요추진사업(NEW)'!E72 -> 가톨릭대학교 성빈센트병원 | F74: ='2025년 주요추진사업(NEW)'!F72 -> 수원 가톨릭대학교 성빈센트병원 "수어안내키오스크 구축" | G74: ='2025년 주요추진사업(NEW)'!G72 -> 임철현 | H74: ='2025년 주요추진사업(NEW)'!H72 -> 8 계약완료 | I74: 2025.08.11 | J74: 2025.08.11 | K74: 2025.09.25 | L74: 14545.455 | M74: 14545.455 | Q74: =SUM(N74:P74) -> 0 | R74: =VLOOKUP(B74, '2025년 주요추진사업(NEW)'!B:O, 14, FALSE) -> 0
B75: ='2025년 주요추진사업(NEW)'!B73 -> 2025-070 | C75: ='2025년 주요추진사업(NEW)'!C73 -> 수어 | D75: ='2025년 주요추진사업(NEW)'!D73 -> 남양주시수어통역센터 | E75: ='2025년 주요추진사업(NEW)'!E73 -> 남양주시수어통역센터 | F75: ='2025년 주요추진사업(NEW)'!F73 -> 남양주시수어통역센터 핸드사인톡톡-모바일서비스 제안 | G75: ='2025년 주요추진사업(NEW)'!G73 -> 양승구 | H75: ='2025년 주요추진사업(NEW)'!H73 -> 1 영업중 | Q75: =SUM(N75:P75) -> 0 | R75: =VLOOKUP(B75, '2025년 주요추진사업(NEW)'!B:O, 14, FALSE) -> 0
B76: ='2025년 주요추진사업(NEW)'!B74 -> 2025-071 | C76: ='2025년 주요추진사업(NEW)'!C74 -> 수어 | D76: ='2025년 주요추진사업(NEW)'!D74 -> 브로드씨엔에스 고객사 중 병원 | E76: ='2025년 주요추진사업(NEW)'!E74 -> 브로드씨엔에스 | F76: ='2025년 주요추진사업(NEW)'!F74 -> 브로드씨엔에스 병원 내 수어서비스 제안 | G76: ='2025년 주요추진사업(NEW)'!G74 -> 임철현 | H76: ='2025년 주요추진사업(NEW)'!H74 -> 1 영업중 | Q76: =SUM(N76:P76) -> 0 | R76: =VLOOKUP(B76, '2025년 주요추진사업(NEW)'!B:O, 14, FALSE) -> 0
B77: ='2025년 주요추진사업(NEW)'!B75 -> 2025-072 | C77: ='2025년 주요추진사업(NEW)'!C75 -> 수어 | D77: ='2025년 주요추진사업(NEW)'!D75 -> 파주나비나라박물관 | E77: ='2025년 주요추진사업(NEW)'!E75 -> 파주나비나라박물관 | F77: ='2025년 주요추진사업(NEW)'!F75 -> 파주나비나라박물관 홍보영상 내 수어영상 제작 | G77: ='2025년 주요추진사업(NEW)'!G75 -> 오민규 | H77: ='2025년 주요추진사업(NEW)'!H75 -> 5 DROP | Q77: =SUM(N77:P77) -> 0 | R77: =VLOOKUP(B77, '2025년 주요추진사업(NEW)'!B:O, 14, FALSE) -> 4950
B78: ='2025년 주요추진사업(NEW)'!B76 -> 2025-073 | C78: ='2025년 주요추진사업(NEW)'!C76 -> AICC | D78: ='2025년 주요추진사업(NEW)'!D76 -> DOWHAT | E78: ='2025년 주요추진사업(NEW)'!E76 -> DOWHAT | F78: ='2025년 주요추진사업(NEW)'!F76 -> DOWHAT AI 음성봇 제안 | G78: ='2025년 주요추진사업(NEW)'!G76 -> 오민규 | H78: ='2025년 주요추진사업(NEW)'!H76 -> 1 영업중 | Q78: =SUM(N78:P78) -> 0 | R78: =VLOOKUP(B78, '2025년 주요추진사업(NEW)'!B:O, 14, FALSE) -> 0
B79: ='2025년 주요추진사업(NEW)'!B77 -> 2025-074 | C79: ='2025년 주요추진사업(NEW)'!C77 -> 수어 | D79: ='2025년 주요추진사업(NEW)'!D77 -> 남양주시 | E79: ='2025년 주요추진사업(NEW)'!E77 -> 경기도 남양주시 | F79: ='2025년 주요추진사업(NEW)'!F77 -> 남양주시 스마트관광지도 수어 안내 | G79: ='2025년 주요추진사업(NEW)'!G77 -> 양승구 | H79: ='2025년 주요추진사업(NEW)'!H77 -> 8 계약완료 | I79: 2025.10.30 | J79: 2025.10.30 | K79: 2026.11.29 | L79: 4596 | M79: 4596 | O79: 3996 | P79: 600 | Q79: =SUM(N79:P79) -> 4596 | R79: =VLOOKUP(B79, '2025년 주요추진사업(NEW)'!B:O, 14, FALSE) -> 3996 | S79: 1차 3,996 + 2차 600 = 4,596
B80: ='2025년 주요추진사업(NEW)'!B78 -> 2025-075 | C80: ='2025년 주요추진사업(NEW)'!C78 -> 수어 | D80: ='2025년 주요추진사업(NEW)'!D78 -> 원주시 시설관리공단 | E80: ='2025년 주요추진사업(NEW)'!E78 -> 원주시 시설관리공단 | F80: ='2025년 주요추진사업(NEW)'!F78 -> 원주시 시설관리공단 키오스크 수어 안내 | G80: ='2025년 주요추진사업(NEW)'!G78 -> 오민규 | H80: ='2025년 주요추진사업(NEW)'!H78 -> 2 견적제출 | Q80: =SUM(N80:P80) -> 0 | R80: =VLOOKUP(B80, '2025년 주요추진사업(NEW)'!B:O, 14, FALSE) -> 56500
B81: ='2025년 주요추진사업(NEW)'!B79 -> 2025-076 | C81: ='2025년 주요추진사업(NEW)'!C79 -> 수어 | D81: ='2025년 주요추진사업(NEW)'!D79 -> 경기도장애인복지종합지원센터 | E81: ='2025년 주요추진사업(NEW)'!E79 -> 경기도장애인복지종합지원센터 | F81: ='2025년 주요추진사업(NEW)'!F79 -> 경기복지재단 장애인 생활환경 개선사업 수어 영상 | G81: ='2025년 주요추진사업(NEW)'!G79 -> 양승구 | H81: ='2025년 주요추진사업(NEW)'!H79 -> 8 계약완료 | I81: 2025.10.02 | J81: 2025.10.02 | K81: 2025.11.30 | L81: 450 | M81: 450 | N81: 450 | Q81: =SUM(N81:P81) -> 450 | R81: =VLOOKUP(B81, '2025년 주요추진사업(NEW)'!B:O, 14, FALSE) -> 450
B82: ='2025년 주요추진사업(NEW)'!B80 -> 2025-077 | C82: ='2025년 주요추진사업(NEW)'!C80 -> 수어 | D82: ='2025년 주요추진사업(NEW)'!D80 -> 부산대병원 | E82: ='2025년 주요추진사업(NEW)'!E80 -> 아이티아이즈 | F82: ='2025년 주요추진사업(NEW)'!F80 -> 아이티아이즈 헬스케어본부 배리어프리 키오스크 제안 | G82: ='2025년 주요추진사업(NEW)'!G80 -> 임철현 | H82: ='2025년 주요추진사업(NEW)'!H80 -> 1 영업중 | Q82: =SUM(N82:P82) -> 0 | R82: =VLOOKUP(B82, '2025년 주요추진사업(NEW)'!B:O, 14, FALSE) -> 0
B83: ='2025년 주요추진사업(NEW)'!B81 -> 2025-078 | C83: ='2025년 주요추진사업(NEW)'!C81 -> 수어 | D83: ='2025년 주요추진사업(NEW)'!D81 -> 기상청 | E83: ='2025년 주요추진사업(NEW)'!E81 -> (주)러닝플레닛 | F83: ='2025년 주요추진사업(NEW)'!F81 -> (주)러닝플레닛 기상청 - 기후변화 과학 용어집의 AI수어번역서비스 제안 | G83: ='2025년 주요추진사업(NEW)'!G81 -> 양승구 | H83: ='2025년 주요추진사업(NEW)'!H81 -> 2 견적제출 | Q83: =SUM(N83:P83) -> 0 | R83: =VLOOKUP(B83, '2025년 주요추진사업(NEW)'!B:O, 14, FALSE) -> 65000
B84: ='2025년 주요추진사업(NEW)'!B82 -> 2025-079 | C84: ='2025년 주요추진사업(NEW)'!C82 -> 수어 | D84: ='2025년 주요추진사업(NEW)'!D82 -> 부천도시공사 | E84: ='2025년 주요추진사업(NEW)'!E82 -> 부천도시공사 디지털정보팀 (소사스포츠센터) | F84: ='2025년 주요추진사업(NEW)'!F82 -> 부천도시공사 AI 수어아바타 핸드사인톡톡(구축형) | G84: ='2025년 주요추진사업(NEW)'!G82 -> 임철현 | H84: ='2025년 주요추진사업(NEW)'!H82 -> 2 견적제출 | Q84: =SUM(N84:P84) -> 0 | R84: =VLOOKUP(B84, '2025년 주요추진사업(NEW)'!B:O, 14, FALSE) -> 2950 | S84: 25년 잔여 예산
B85: ='2025년 주요추진사업(NEW)'!B83 -> 2025-080 | C85: ='2025년 주요추진사업(NEW)'!C83 -> 수어 | D85: ='2025년 주요추진사업(NEW)'!D83 -> 천안시 | E85: ='2025년 주요추진사업(NEW)'!E83 -> 아이비테크 주식회사 | F85: ='2025년 주요추진사업(NEW)'!F83 -> 천안시 홈페이지 수어안내 | G85: ='2025년 주요추진사업(NEW)'!G83 -> 오민규 | H85: ='2025년 주요추진사업(NEW)'!H83 -> 2 견적제출 | Q85: =SUM(N85:P85) -> 0 | R85: =VLOOKUP(B85, '2025년 주요추진사업(NEW)'!B:O, 14, FALSE) -> 82512
B86: ='2025년 주요추진사업(NEW)'!B84 -> 2025-081 | C86: ='2025년 주요추진사업(NEW)'!C84 -> AICC | D86: ='2025년 주요추진사업(NEW)'!D84 -> ABL생명 | E86: ='2025년 주요추진사업(NEW)'!E84 -> 유니디아 | F86: ='2025년 주요추진사업(NEW)'!F84 -> ABL 생명 통합 유지보수 | G86: ='2025년 주요추진사업(NEW)'!G84 -> 오민규 | H86: ='2025년 주요추진사업(NEW)'!H84 -> 9 유지보수 | I86: 2025.10.11 | J86: 2025.10.12 | K86: 2028.10.11 | L86: 27998.384 | M86: 27998.384 | O86: 836 | P86: 836 | Q86: =SUM(N86:P86) -> 1672 | R86: =VLOOKUP(B86, '2025년 주요추진사업(NEW)'!B:O, 14, FALSE) -> 27998.384
B87: ='2025년 주요추진사업(NEW)'!B85 -> 2025-082 | C87: ='2025년 주요추진사업(NEW)'!C85 -> AICC | D87: ='2025년 주요추진사업(NEW)'!D85 -> 미래에셋생명 | E87: ='2025년 주요추진사업(NEW)'!E85 -> 부뜰정보시스템 | F87: ='2025년 주요추진사업(NEW)'!F85 -> 미래에셋생명 차세대시스템 구축 프로젝트 | G87: ='2025년 주요추진사업(NEW)'!G85 -> 오민규 | H87: ='2025년 주요추진사업(NEW)'!H85 -> 8 계약완료 | I87: 2025.07.03 | J87: 2025.04.21 | K87: 2027.04.30 | L87: =495000+487640 -> 982640 | M87: =495000+487640 -> 982640 | Q87: =SUM(N87:P87) -> 0 | R87: =VLOOKUP(B87, '2025년 주요추진사업(NEW)'!B:O, 14, FALSE) -> 982640 | S87: 용역, 제품 합산
B88: ='2025년 주요추진사업(NEW)'!B86 -> 2025-083 | C88: ='2025년 주요추진사업(NEW)'!C86 -> 수어 | D88: ='2025년 주요추진사업(NEW)'!D86 -> 카카오뱅크 | E88: ='2025년 주요추진사업(NEW)'!E86 -> 카카오뱅크 | F88: ='2025년 주요추진사업(NEW)'!F86 -> 카카오뱅크 AI수어상담 3D 아바타 리 디자인 구축 | G88: ='2025년 주요추진사업(NEW)'!G86 -> 양승구 | H88: ='2025년 주요추진사업(NEW)'!H86 -> 8 계약완료 | I88: 2025.01.15 | J88: 2025.09.08 | K88: 2026.02.28 | L88: 50500 | M88: 50500 | N88: 50500 | Q88: =SUM(N88:P88) -> 50500 | R88: =VLOOKUP(B88, '2025년 주요추진사업(NEW)'!B:O, 14, FALSE) -> 50500 | S88: 25년 10월 15일 계약 완료
B89: ='2025년 주요추진사업(NEW)'!B87 -> 2025-084 | C89: ='2025년 주요추진사업(NEW)'!C87 -> 수어 | D89: ='2025년 주요추진사업(NEW)'!D87 -> KB국민은행 | E89: ='2025년 주요추진사업(NEW)'!E87 -> KB국민은행 | F89: ='2025년 주요추진사업(NEW)'!F87 -> KB국민은행 무인화상 디지털데스크 및 모바일 화상상담(기존시스템) 수어서비스 적용 구축 | G89: ='2025년 주요추진사업(NEW)'!G87 -> 양승구 | H89: ='2025년 주요추진사업(NEW)'!H87 -> 3 제안중 | Q89: =SUM(N89:P89) -> 0 | R89: =VLOOKUP(B89, '2025년 주요추진사업(NEW)'!B:O, 14, FALSE) -> 811930 | S89: 26년도 예산
B90: ='2025년 주요추진사업(NEW)'!B88 -> 2025-085 | C90: ='2025년 주요추진사업(NEW)'!C88 -> AICC | D90: ='2025년 주요추진사업(NEW)'!D88 -> 하나카드 | E90: ='2025년 주요추진사업(NEW)'!E88 -> 지뉴소프트 | F90: ='2025년 주요추진사업(NEW)'!F88 -> 하나카드 AICC 통합운영관리플랫폼 유지보수 | G90: ='2025년 주요추진사업(NEW)'!G88 -> 오민규 | H90: ='2025년 주요추진사업(NEW)'!H88 -> 9 유지보수 | I90: 2025.01.01 | J90: 2025.01.01 | K90: 2025.12.31 | L90: 9000 | M90: 9000 | N90: 750 | O90: 750 | P90: 750 | Q90: =SUM(N90:P90) -> 2250 | R90: =VLOOKUP(B90, '2025년 주요추진사업(NEW)'!B:O, 14, FALSE) -> 9000
B91: ='2025년 주요추진사업(NEW)'!B89 -> 2025-086 | C91: ='2025년 주요추진사업(NEW)'!C89 -> AICC | D91: ='2025년 주요추진사업(NEW)'!D89 -> 부천시 | E91: ='2025년 주요추진사업(NEW)'!E89 -> 부천시 | F91: ='2025년 주요추진사업(NEW)'!F89 -> 부천시 민원과 AI챗봇 서비스 구축 | G91: ='2025년 주요추진사업(NEW)'!G89 -> 임철현 | H91: ='2025년 주요추진사업(NEW)'!H89 -> 5 DROP | Q91: =SUM(N91:P91) -> 0 | R91: =VLOOKUP(B91, '2025년 주요추진사업(NEW)'!B:O, 14, FALSE) -> 80000
B92: ='2025년 주요추진사업(NEW)'!B90 -> 2025-087 | C92: ='2025년 주요추진사업(NEW)'!C90 -> 수어 | D92: ='2025년 주요추진사업(NEW)'!D90 -> 한국가스안전공사 | E92: ='2025년 주요추진사업(NEW)'!E90 -> 한국가스안전공사 | F92: ='2025년 주요추진사업(NEW)'!F90 -> 한국가스안전공사 전시 해설 수어통역 서비스 제안 | G92: ='2025년 주요추진사업(NEW)'!G90 -> 양승구 | H92: ='2025년 주요추진사업(NEW)'!H90 -> 2 견적제출 | Q92: =SUM(N92:P92) -> 0 | R92: =VLOOKUP(B92, '2025년 주요추진사업(NEW)'!B:O, 14, FALSE) -> 37280
B93: ='2025년 주요추진사업(NEW)'!B91 -> 2025-088 | C93: ='2025년 주요추진사업(NEW)'!C91 -> 수어 | D93: ='2025년 주요추진사업(NEW)'!D91 -> 평창군시설관리 공단 | E93: ='2025년 주요추진사업(NEW)'!E91 -> 평창군시설관리 공단 | F93: ='2025년 주요추진사업(NEW)'!F91 -> 광천선굴테마파크 관광 해설 영상 수어 안내시스템 구축 | G93: ='2025년 주요추진사업(NEW)'!G91 -> 양승구 | H93: ='2025년 주요추진사업(NEW)'!H91 -> 5 DROP | Q93: =SUM(N93:P93) -> 0 | R93: =VLOOKUP(B93, '2025년 주요추진사업(NEW)'!B:O, 14, FALSE) -> 11800
B94: ='2025년 주요추진사업(NEW)'!B92 -> 2025-089 | C94: ='2025년 주요추진사업(NEW)'!C92 -> 수어 | D94: ='2025년 주요추진사업(NEW)'!D92 -> 서울주택도시개발공사 | E94: ='2025년 주요추진사업(NEW)'!E92 -> 서울주택도시개발공사 | F94: ='2025년 주요추진사업(NEW)'!F92 -> 서울주택도시개발공사 차세대 구축시 당사 AI 수어 제안 | G94: ='2025년 주요추진사업(NEW)'!G92 -> 양승구 | H94: ='2025년 주요추진사업(NEW)'!H92 -> 2 견적제출 | Q94: =SUM(N94:P94) -> 0 | R94: =VLOOKUP(B94, '2025년 주요추진사업(NEW)'!B:O, 14, FALSE) -> 214210
B95: ='2025년 주요추진사업(NEW)'!B93 -> 2025-090 | C95: ='2025년 주요추진사업(NEW)'!C93 -> 수어 | D95: ='2025년 주요추진사업(NEW)'!D93 -> 문화체육관광부 국립국어원 | E95: ='2025년 주요추진사업(NEW)'!E93 -> 국립국어원 | F95: ='2025년 주요추진사업(NEW)'!F93 -> 2026년 한국수어-한국어 사전 자료 집필 | G95: ='2025년 주요추진사업(NEW)'!G93 -> 임철현 | H95: ='2025년 주요추진사업(NEW)'!H93 -> 3 제안중 | Q95: =SUM(N95:P95) -> 0 | R95: =VLOOKUP(B95, '2025년 주요추진사업(NEW)'!B:O, 14, FALSE) -> 0
B96: ='2025년 주요추진사업(NEW)'!B94 -> 2025-091 | C96: ='2025년 주요추진사업(NEW)'!C94 -> 수어 | D96: ='2025년 주요추진사업(NEW)'!D94 -> 한국잡월드 | E96: ='2025년 주요추진사업(NEW)'!E94 -> 한국잡월드 | F96: ='2025년 주요추진사업(NEW)'!F94 -> 26년 배리어프리 키오스크 관련 수어서비스 도입 | G96: ='2025년 주요추진사업(NEW)'!G94 -> 임철현 | H96: ='2025년 주요추진사업(NEW)'!H94 -> 1 영업중 | Q96: =SUM(N96:P96) -> 0 | R96: =VLOOKUP(B96, '2025년 주요추진사업(NEW)'!B:O, 14, FALSE) -> 0
B97: ='2025년 주요추진사업(NEW)'!B95 -> 2025-092 | C97: ='2025년 주요추진사업(NEW)'!C95 -> AICC | D97: ='2025년 주요추진사업(NEW)'!D95 -> 예금보험공사 | E97: ='2025년 주요추진사업(NEW)'!E95 -> 에쎈텍네트웍스 | F97: ='2025년 주요추진사업(NEW)'!F95 -> 디지털 뉴딜 IT 구축 | G97: ='2025년 주요추진사업(NEW)'!G95 -> 오민규 | H97: ='2025년 주요추진사업(NEW)'!H95 -> - | Q97: =SUM(N97:P97) -> 0 | R97: =VLOOKUP(B97, '2025년 주요추진사업(NEW)'!B:O, 14, FALSE) -> 0
B98: ='2025년 주요추진사업(NEW)'!B96 -> 2025-093 | C98: ='2025년 주요추진사업(NEW)'!C96 -> 수어 | D98: ='2025년 주요추진사업(NEW)'!D96 -> 한국지능정보사회진흥원(NIA) | E98: ='2025년 주요추진사업(NEW)'!E96 -> 한국지능정보사회진흥원(NIA) | F98: ='2025년 주요추진사업(NEW)'!F96 -> 촬영 된 영상에 실시간 수어 영상 제작 | G98: ='2025년 주요추진사업(NEW)'!G96 -> 양승구 | H98: ='2025년 주요추진사업(NEW)'!H96 -> 2 견적제출 | Q98: =SUM(N98:P98) -> 0 | R98: =VLOOKUP(B98, '2025년 주요추진사업(NEW)'!B:O, 14, FALSE) -> 29360
B99: ='2025년 주요추진사업(NEW)'!B97 -> 2025-094 | C99: ='2025년 주요추진사업(NEW)'!C97 -> 수어 | D99: ='2025년 주요추진사업(NEW)'!D97 -> SK텔레콤 | E99: ='2025년 주요추진사업(NEW)'!E97 -> 한솔인티큐브/브리지텍 | F99: ='2025년 주요추진사업(NEW)'!F97 -> SKT/B 차세대 Call Infra 구축(수어서비스 추가 제안) | G99: ='2025년 주요추진사업(NEW)'!G97 -> 오민규 | H99: ='2025년 주요추진사업(NEW)'!H97 -> 2 견적제출 | Q99: =SUM(N99:P99) -> 0 | R99: =VLOOKUP(B99, '2025년 주요추진사업(NEW)'!B:O, 14, FALSE) -> 0
B100: ='2025년 주요추진사업(NEW)'!B98 -> 2025-095 | C100: ='2025년 주요추진사업(NEW)'!C98 -> 수어 | D100: ='2025년 주요추진사업(NEW)'!D98 -> 한국의료기기안전정보원 | E100: ='2025년 주요추진사업(NEW)'!E98 -> 한국의료기기안전정보원 | F100: ='2025년 주요추진사업(NEW)'!F98 -> 의정원 시청각장애인용 의료기기 안전정보 콘텐츠 제작 | G100: ='2025년 주요추진사업(NEW)'!G98 -> 임철현 | H100: ='2025년 주요추진사업(NEW)'!H98 -> 8 계약완료 | I100: 2025.07.25 | J100: 2025.07.25 | K100: 2025.10.31 | L100: 37568.182 | M100: 37568.182 | N100: 37568.182 | Q100: =SUM(N100:P100) -> 37568.182 | R100: =VLOOKUP(B100, '2025년 주요추진사업(NEW)'!B:O, 14, FALSE) -> 0
B101: ='2025년 주요추진사업(NEW)'!B99 -> 2025-096 | C101: ='2025년 주요추진사업(NEW)'!C99 -> 수어 | D101: ='2025년 주요추진사업(NEW)'!D99 -> 문화체육관광부 | E101: ='2025년 주요추진사업(NEW)'!E99 -> 문화체육관광부 | F101: ='2025년 주요추진사업(NEW)'!F99 -> 2026년 대한민국정부 디지털콘텐츠 수어통역 영상 제작 | G101: ='2025년 주요추진사업(NEW)'!G99 -> 임철현 | H101: ='2025년 주요추진사업(NEW)'!H99 -> 6 실주 | Q101: =SUM(N101:P101) -> 0 | R101: =VLOOKUP(B101, '2025년 주요추진사업(NEW)'!B:O, 14, FALSE) -> 0
B102: ='2025년 주요추진사업(NEW)'!B100 -> 2025-097 | C102: ='2025년 주요추진사업(NEW)'!C100 -> 수어 | D102: ='2025년 주요추진사업(NEW)'!D100 -> BC카드 | E102: ='2025년 주요추진사업(NEW)'!E100 -> 매입운영본부 상담팀 | F102: ='2025년 주요추진사업(NEW)'!F100 -> BC카드 AI 수어 제안 | G102: ='2025년 주요추진사업(NEW)'!G100 -> 양승구 | H102: ='2025년 주요추진사업(NEW)'!H100 -> 1 영업중 | Q102: =SUM(N102:P102) -> 0 | R102: =VLOOKUP(B102, '2025년 주요추진사업(NEW)'!B:O, 14, FALSE) -> 0
B103: ='2025년 주요추진사업(NEW)'!B101 -> 2025-098 | C103: ='2025년 주요추진사업(NEW)'!C101 -> AICC | D103: ='2025년 주요추진사업(NEW)'!D101 -> 롯데홈쇼핑 | E103: ='2025년 주요추진사업(NEW)'!E101 -> 부뜰정보시스템 | F103: ='2025년 주요추진사업(NEW)'!F101 -> 롯데홈쇼핑 KMS 검색엔진 유지보수 | G103: ='2025년 주요추진사업(NEW)'!G101 -> 오민규 | H103: ='2025년 주요추진사업(NEW)'!H101 -> 9 유지보수 | I103: 2025.04.01 | J103: 2025.04.01 | K103: 2026.12.31 | L103: 5250 | M103: 5250 | P103: 2250 | Q103: =SUM(N103:P103) -> 2250 | R103: 5250 | S103: 2025.12.22 발주서 수령
...

Sheet 2025년 주요추진사업(NEW)
A1: ㅑ | B1: 2025년도 DX사업본부 주요사업 추진 내역
N2: ↓ 내용이 길면 잘라서 오른쪽 셀(진행사항 및 영업전략(1))로 옮겨 주세요!!! | O2: 단위. 천원 vat제외
B3: 파이프라인 ID | C3: 분야 | D3: 고객사 | E3: 발주처 | F3: 사업명 | G3: 담당자 | H3: 진행단계 | I3: 발주시기 | J3: 계약시기 | K3: 매출 | L3: 사업구도 ex) 마도 : OOO | M3: 변동여부 | N3: - | O3: 견적가(vat제외) | P3: 비고 | Q3: 진행상황 및 영업전략(1) | R3: 진행상황 및 영업전략(2) | S3: 진행상황 및 영업전략(3) | T3: 진행상황 및 영업전략(4)
B4: 2025-001 | C4: AICC | D4: KB국민은행 | E4: SK쉴더스 | F4: KB국민은행 SynK 활용 AICC 통합관리포탈 구축 | G4: 함영민 | H4: 2 견적제출 | J4: 6월 | K4: - 발주금액 : 20억 | M4: N | N4: - 요구사항 : AICC 관련 포인트 별 엔진 및 이기종 솔루션의 통합사용자 관리 필요 - 예상적용범위 : 챗봇, 음성봇(콜봇), 상담어시스트 연동 - 예산편성용 견적서 제출(인터페이스 규격서, SynK 도입배경 및 기대효과 포함 소개자료 포함) · 개발공수 및 인터페이스 규격서 : 플랫폼사업본부 지원 · SynK 기대효과 포함 소개자료 : 미래전략팀 지원 · 견적내역 : Synk 라이선스(2억) + 개발(24.37억/191MM) = 26.37억 - 제품규격서, 매뉴얼 등 SynK의 정식 제품에 대한 필요서류 미리 구비 필요 - 24년 12월에 금융지주에서 실무진과 SynK 당위성 논의 후 사실 상 예산기안 통과 - 4~5월 입찰 공고 후 6월에 프로젝트 착수 계획 중 · 2-3월 중 RFP 작업 관여 및 지원 제안 예정 - 통합관리포탈 20억 예산 편성 대비 4월 중 예산 하향 조정 협의 예정 - 통합관리포탈 구축 관련 인력 준비 필요 | O4: 2637000 | P4: * 앞단에서 영업 중인 디씨온 이재문 이사(KB출신으로 인프라 유지보수 업체) 케이엘큐브 명함 발행 요청 * 계약라인업 : KB국민은행 < SK쉴더스 < 케이엘큐브
B5: 2025-002 | C5: AICC | D5: 한국도로교통공단 | E5: 모비젠 | F5: 한국도로교통공단 STT API 개발 | G5: 함영민 | H5: 5 DROP | J5: 6월 | K5: - 발주금액 : 0.4억 | L5: - 주관사 : 모비젠 - 하도급 : 케이엘큐브 | M5: N | N5: - 요구사항 : STT API 개발 검토 및 다수 동영상 동시다발적 업로드 기능 필요 · 타 시스템에서 직접 호출 가능한 서비스 구성(호출방식은 추후 협의) · 다중사용자 및 다중파일 처리 구축(Queue, 멀티스레딩 등) · 처리현황 · 서버 활용 모니터링, 변환 이력 관리 - 방송 쪽에서 STT 사용해 보고 실 적용 업무 대상 기획 · 1분 정도 동영상 10개 정도 STT 적용 테스트 진행 완료 - 기존에 카카오 STT 도입해서 교통제보 대상 야간 상황실 담당자 부재에 대한 상담 대응용으로 사용해 왔으나 카카오에서 STT EOS를 한 상황이라 공단 내부적으로 대안 고민해 옴 - 3차 사업용 STT API 개발 견적서 발송(4.5M/M) (25.07.03 기준) - 모비젠 오진욱책임: 과업 범위 일부 조정되면서 STT 활용 연동 API 개발 부문은 제외하는 것으로 최종 협의됨 | P5: * 6월초 계약, 12월 종료 혹은 1월 종료(변동 가능성 있음)
B6: 2025-003 | C6: AICC | D6: 현대캐피탈 | E6: KT | F6: 현대캐피탈 LLM 기반 인바운드 AI음성봇 구축 | G6: 함영민 | H6: 5 DROP | J6: 4월 | K6: - 추정예산 : 20억 이하 - 발주금액 : 5억 | L6: - 주관사 : KT - 하도급1 : 케이엘큐브 - 하도급2 : 코난테크놀로지 | M6: N | N6: - 3월~4월 인바운드 LLM 기반 AI음성봇 구축 계획 중(AI개발팀 담당자 미팅) · 동시접속 50채널, 약190개 시나리오 AI음성봇 구축 계획 · KT STT, TTS, 챗봇/콜봇과 코난테크놀로지 LLM 활용 구축 제안 · 고객 발화에 대한 의도 분류 및 파악을 위해 LLM 필요 · 예상경쟁사 : 한솔인티큐브(현 아웃바운드 AI음성봇 구축사), 마인드웨어웍스(현 챗봇 구축사), 솔트룩스 등 (예산이 20억 혹은 그 이하 정도 예상되어 대기업 참여 원하지 않으나 예산에 맞출 수 있다면 대기업도 참여 가능) - 주관사 : KT / 당사 : STT,TTS,AMP,지식구축 / 코난 : LLM - RFP 수령 자격 검증을 위한 1차 가견적 중(KT에서 가견적은 25억 정도로 제출 예정) · 당사 : 7.65억->6.295억 / 코난 : 11.46억 -> 9.25억 -> 7.56억 · 최종 입찰 제안 시 예상 금액 구도(개인적인 추정치) - 당사 : 5.5억 / 코난 : 6억 / KT : 6.5억 (합계 18억으로 투찰하는 시나리오) - (25.03.13) · 예산 20억 이하가 될 것으로 추정(15억 내외 추정) ㄴ 예산 문제로 주관사인 KT 내부적으로 참여 가능 여부 관건 ㄴ 예상 보다 적은 예산이라 당사의 역할이 축소될 가능성 있음 · 3월에 입찰 완료 후 4월 중순 착수 / 9월 오픈 / 10월 검수 · STT의 경우 기존 리턴제로 활용하는 것으로 변경 · 금주 혹은 차주 중 현대캐피탈 실무진에서 판단한 RFP 대상 후보업체 기안을 올린 후 구매팀에서 차주 내 RFP 발송 예정 ㄴ RFP 수령 후 KT 사업 참여 내부 승인여부에 따라 해당 사업 입찰 여부 결정 ㄴ 입찰 참여 결정 시 AI음성봇 부문 KT와 R&R 및 금액 재조정 예상 - (25.03.20) · 입찰공고 및 KT RFP 수령 · KT 내부적으로 당사의 C-HUB, STT 구축 수행 경험의 부재 이슈를 제기하며 당사의 역할을 축소시키려 함 ㄴ C-HUB는 제외한다고 하더라도 AMP+STT+TTS는 한 업체에서 구축을 해야 하므로 당사에서 수행하는 것을 거듭 강조하는 중 (사전에 미리미리 KT에 함께 언급해 두어야 하는 부분 관련 대표님 도움 필요 예상) - KT로 부터 RFP수령(3/20)에 따른 STT+TTS+AMP(1안), TTS(2안) 입찰용 견적 요청 받음 · STT+TTS+AMP(1안) 견적 금액 : 498,500,000원 (47M/M) · TTS(2안) 견적 금액 : 81,750,000원 (8M/M) (2025.03.26 기준) - KT 내부 사업심의 결과 "사업원가 및 LLM과의 첫 연동 리스크 등의 사유로 사업 DROP 결정" | P6: * 구축 현황 - 아웃바운드콜봇 : 한솔인티큐브 구축 - AI챗봇 : 마인드웨어웍스 구축 * 사업 일정 요약 - 계약기간(예상) : 2025.04.15 ~ 2025.11.28 - RFP발송 : 3/20(목) - 제안서 접수/마감 : 4/1(화) 18:00 - 제안발표회 : 4/2(수) - 우선협상대상자 업체 선정 : 4/2(수) 이후
B7: 2025-004 | C7: AICC | D7: 평택시청 | E7: KT평택지사 | F7: 평택시청 AI 기반 민원분석시스템 구축 | G7: 함영민 | H7: 1 영업중 | J7: 2026년 | K7: - 발주금액 : 10억 | M7: N | N7: - 요구사항(예상) : 콜센터 없고 3000회선 배치 STT/TA 민원분석시스템 구축 - 진행계획 · 2월 중 KT평택지사 담당자의 고객 컨택 후 장주석 부장과 업무 상담 지원 · 상반기 중 RFP 작업 지원 · 예산계획 : 20억 기안 후 10억 정도 수주하는 시나리오 제안(지자체 예산 편성 수준 및 예산 기안 중 삭감과 입찰투찰율 고려) ㄴ 올해 예산 기안 후 2026년 프로젝트 진행 · 제품 : STT(KT), AMP(KT), TA(코난테크놀로지) - 평택시에서 벤치마킹을 희망하나 코난 TA고객사들에서 민감한 민원 정보의 대외 공유 어려움으로 벤치마킹 불가 확인 · 한국도로교통공단 TA 완료보고서 기반 당사 수행PM 주관 회의 확인 협조 요청 및 TA PoC도 제안 협조 요청 - 분석하기 좋은 민원데이터 선정하여 PoC 제안 중 | P7: KT평택지사 권순철 차장 담당
B8: 2025-005 | C8: AICC | D8: KT | E8: - | F8: KT EasyCMS(봇프레임웍) 운영유지보수 지명 입찰 | G8: 함영민 | H8: 3 제안중 | J8: 잠정적 보류로 인해 지속 확인 중 | K8: - 발주금액 : 12억~13억/년 | M8: N | N8: - 작년 진행 예정이었다가 잠정적보류가 되었으므로 재진행 관련 지속적인 컨택 및 모니터링
B9: 2025-006 | C9: AICC | D9: KDB생명 | E9: 코난테크놀로지 | F9: KDB생명 콜센터 실시간 STT 구축 | G9: 함영민 | H9: 2 견적제출 | J9: 잠정적 보류 | K9: - 발주금액 : | M9: N | N9: - 콜센터 30석 대상 실시간 STT 시범사업 계획 중(총 좌석수 : 약 200석) · KT STT로 제안 중이고 실시간 30석에 해당하는 예산용 견적서 제출 - 고객사에 기존 실시간 STT 수집/분배 시스템이 존재하므로 별도 추가 견적 불필요 - 실무자는 필요성을 느끼고 있으나 조직 전반적으로 콜배석 수가 적으므로 추진 여부에 대해 고민 중 · 콜센터 규모가 작으므로 별도 정보화 기안을 하지 않고 내부적으로 AICC 필요성 합일치 시 즉시 추진 가능 ㄴ 코난에서는 가능성은 있다고 보며 지속 영업 예정
B10: 2025-007 | C10: AICC | D10: 중앙전파관리소 | E10: 코난테크놀로지 | F10: 중앙전파관리소 방송 프로그램 심의 분석 구축 사업(STT 부문 참여) | G10: 함영민 | H10: 3 제안중 | J10: 2026년 | K10: - 발주금액 : 3억 | M10: N | N10: - 코난테크놀로지에서 사업 및 예산 계획 제안 중 - 국내 방송 프로그램 약 300채널 대상 배치 STT 후 TA 사업 계획 제안 중(2026년 사업 진행 예정) - 예산용 견적 제출(STT 부문) ㄴ 1차견적(방송 300ch 대상 적용) : 5.65억(11M/M + 전사300h) ㄴ 2차견적(방송 100ch 대상 적용 조정) : 4.75억(예산용이라 구두상으로만 금액 조정 안내) - 중앙전파관리소에서 코난테크놀로지로 방문하여 사업계획 관련 업무 상담 · 26년 예산확보를 위한 사업 범위와 구축 방향성 등 정보수집 및 자문 단계 | P10: * 차후 H/W서버 권장 사양 및 수량 등 구성 재확인
B11: 2025-008 | C11: AICC | D11: 국민건강보험공단 | E11: 엔디에스 | F11: 국민건강보험공단 정신건강 복지서비스 정보시스템 구축 사업 | G11: 박현후 | H11: 2 견적제출 | J11: 2월 | M11: N | N11: - 제안서 제출(엔디에스) · 상담 Assistant(요구사항) 및 양방향 챗봇 수어 서비스(추가제안)
B12: 2025-009 | C12: AICC | D12: 현대백화점 | E12: 부뜰정보시스템 | F12: 현대백화점 상담시스템 통합 및 고도화 | G12: 박현후 | H12: 2 견적제출 | J12: 2월 | K12: - 예산금액 : 60억 | M12: N | N12: - 제안 구성형태 · 주관사(LGCNS), 협력사(부뜰정보시스템) - 제안 참여범위 · Synk, TA, Assist - 진행단계 · 주관사에서 1차 견적 취합 후 제안 진행 여부 결정 예정 · 1차 견적 제출(17억원) - 진행계획 · 제품 : Synk, TA/Assist(코난테크놀로지)
B13: 2025-010 | C13: AICC | D13: 한국무역보험공사 | E13: 유플러스아이티 | F13: 한국무역보험공사 RPA 적용 챗봇 구축 | G13: 박현후 | H13: 2 견적제출 | J13: 상반기 | K13: - 발주금액 : 1.5억 | M13: N | N13: - 유플러스아이티에서 IT 시스템 통합유지관리 운영중(장기계속), 유지보수 비용으로 챗봇 도입 예정(2025년) - 삼성 RPA 챗봇이 적용되어있지만, 고객 불만족(UI 등) - 진행단계 · 견적서 제출(1.59억)
B14: 2025-011 | C14: AICC | D14: 다날 | E14: 다날 | F14: 다날 챗봇 서비스 구축 | G14: 박현후 | H14: 1 영업중 | J14: 미정 | K14: - 제안금액 : 월 0.04억 | M14: N | N14: - 24년 8월 제품 시연 및 제안 작업 진행 - 클라우드(SaaS)형태로 제안 · 케이티(온프라미스) 제품 구매 후 IDC 내에서 월 사용 형태로 운영 제안 · 월 운영비 0.04억(초기구축비 0.7억 별도) - 진행단계 · 사업부서 내부 검토 진행중
B15: 2025-012 | C15: AICC | D15: 120다산콜센터 | E15: 부뜰정보시스템 | F15: 120다산콜재단 AICC 3단계, 통합 인공지능 상담 시스템 | G15: 박현후 | H15: 2 견적제출 | J15: 상반기 | M15: N | N15: - 예산용 견적 제출(AI 콜봇, Synk) · 제출시기(24년 6월), 견적금액(16.8억) - 기존 운영 팀장 퇴사로 인하여 신규 담당자 컨택 진행예정(부뜰정보시스템)
B16: 2025-013 | C16: AICC | D16: 흥국화재 | E16: 부뜰정보시스템 | F16: 흥국화재 AI 음성봇 구축 | G16: 박현후 | H16: 1 영업중 | J16: 미정 | M16: N | N16: - 사업기획단계 - 적용대상 : 해피콜 서비스(30채널) - 진행계획 · 제품 : STT(KT), 봇(KT), TTS(KT), 운영관리(Synk) ※ 기존 음성인식 엔진 : 마음AI
B17: 2025-014 | C17: AICC | D17: AXA손해보험 | E17: 부뜰정보시스템 | F17: AXA손해보험 KMS 검색엔진 구축 | G17: 박현후 | H17: 2 견적제출 | K17: - 발주금액 : 0.2억 | M17: N | N17: - KMS 검색엔진 번들 라이선스(단중화) - 견적서 발송(0.2억)
B18: 2025-015 | C18: AICC | D18: 한국도로교통공단 | E18: 트루본 | F18: 한국도로교통공단 STT 유지보수 | G18: 오민규 | H18: 9 유지보수 | J18: 4월 | K18: 16392832 | L18: - 주관사 : 트루본 | M18: N | N18: (2025.03.14 기준) - STT 1차 사업에 대한 유지보수 견적 제출(견적금액 : 16,302,000원/22개월 - 도입가 대비 12%) - 트루본에서 공단 측과 통합유지보수 금액 협상 중 · 3월말 협상 완료 목표 / 4월초순 계약 진행 목표(당사를 포함하여 업체들 모두 금액 협의 조정 가능성 있음) · 예상 대로 당사에 견적 금액 하향 조정 요청(조정금액 : 9,900,000원/22개월 - 도입가 대비 약6% 정도됨) - 계약서 기준. 총 금액 16,392,832원 월 금액 751,619원 . 1차년도 계약기간: 2025.03.06~2025.12.31 7,373,404원 . 2차년도 : 2026.01.01~2026.12.31. 9,019,428원 | O18: 16302
B19: 2025-016 | C19: 수어 | D19: 한국관광공사 | E19: 한국관광공사 | F19: 한국관광공사 열린관광지포탈 및 오디(ODII)외 수어서비스제안 | G19: 양승구 | H19: 2 견적제출 | J19: 미정 | K19: - 사업금액 : 4900만원 | L19: - 본사영업 | M19: N | N19: - 한국관광공사에서 서비스중인 관광포탈(열린관광지,오디(ODII)외) 수어적용관련 제안 - 관광포탈의 여러 서비스에 대한 분석이 필요하며, 수어서비스 적용에 대한 논리적 제안필요 - 전국 열린관광지 20개소(2023년기준: 충남,대전,경남,경기,경남,전북,전남)대상 견적요청 - 사이트 분석후 견적제출 예정 (2025.03.13 기준) - 열린관광포털 수어서비스 적용범위(안) 및 시범서비스 견적서 발송완료(3/13) ※ 수신자 : 한국관광공사 관광복지안전센터 문지영파트장, 전성민전문위원, 유영재대리 - 3/17(월) 관광복지안전센터 부서 회의시 안건으로 채택하여 논의후 별도 연락주기로 함. (2025.04.15 기준) ※ 관광공사 내부 연이은 행사로 기 제출한 열린관광포탈 수어적용 견적서 및 기초 기획안 검토를 못하고 있는 상태 ※ 금주중 행사가 마무리될 예정이라고 하며, 차주(21일주) 검토를 진행하겠다고 함. ※ 본 건과 관련하여 방문하여 브리핑 진행하겠다는 요청에 자료검토후 필요하면 방문요청 하겠다는 의견상태 (2025.05.29 기준) ※ 관광공사 내부 업무과다로 열린관광포털 수어서비스 적용범위(안) 및 시범서비스 견적서 현재까지 미검토 ※ 금주 관광복지안전센터 문지영파트장 출장으로 차주 재검토 예정 (2025.06.06 기준) ※ 관광공사 내부 업무과다로 열린관광포털 수어서비스 적용범위(안) 및 시범서비스 견적서 현재까지 미검토 ※ 관광복지안전센터 문지영파트장 출장으로 차주 재검토(변동사항 없음) L 해당부서 수어서비스 적용에 대한 소극적 대응상태로 중기적 대응이 필요 할 것으로 판단됨 ※ 2025.11.27 담당자 변경 심재홍 → 양승구
B20: 2025-017 | C20: 수어 | D20: 식품안전정보원 | E20: 식품안전정보원 | F20: 식품안전정보원 '25년 식품 스마트 푸드QR 지원사업 | G20: 임철현 | H20: 8 계약완료 | J20: 5월~6월 | K20: - 사업금액 : 3000만원 | L20: - 본사영업 | M20: N | N20: (2025.05.08 기준) ※ 입찰참여사 미공개 상태에서 3개사 참여(예상 : 케이엘큐브+이큐포올 컨소시엄, 멀틱스, 에스엘제스처(?) ※ 제안서 평가 진행중 ※ 대면평가 진행 : 5/14(수) 10시25분(발표 15분, 질의 10분), 참석인원 : 발표자 외 3인 [포스트타워 10층(대기실), 12층(발표장)] L 당초 현업부서에서 서면평가로 진행하는것을 계약부서에서 대면평가로 변경상태(식품안전정보원 문성 팀장 확인) (2025.05.15 기준) ※ 케이엘큐브 컨소시엄 낙찰 * 케이엘큐브 (기술평가 : 90 가격: 9.2593 총점 : 99.2593) * 멀틱스 (기술: 87 가격: 9.7519 총점 : 96.7519) * 더씨앗 (기술: 0 가격: 10 총점 : 10) = 평가부적격 (2025.05.22 기준) - 5/27(화) 10시 계약진행을 위한 형식적 기술협상 진행(티타임 형태로 진행)_with.대표님 ※ 식품업체 참여상태 및 식품수량 확인 (2025.05.25 기준) - 5/27(화) 10시 기술협상 진행 완료_with.유영복상무 ※ 식품업체 참여도 저조상태 / 계약 종료시점까지 계약물량 150개 식품 미달시 종료후에도 진행(계산서발행은 종료시점 선발행진행) - 5/28(수) 기술협상결과 통보서 식품안전정보원 회신완료 / 계약 대기중 (2025.06.05 기준) - 6/5(월) 기술협상 진행 완료에 따른 식품안전정보원 '25년 식품 푸드QR 지원사업 조달계약 완료 L 차주 사업진행에 따른 식품안전정보원과의 협의 진행 예정(착수보고 일정, 식품업체 방문 및 식품업체 선정등) (2025.06.12 기준) - 사업진행에 따른 SL사업본부 식품안전정보원 사업진행 논의(하윤호이사) L 1차 50개 식품 품목에 대한 이큐포올과 업무배분 체크필요 L 6월 중 식품안전정보원에서 삼성전자 미팅시 케이엘큐브 참석시 사전체크 ※ '24년 컨텍하였던 삼성전자 가전사업부(김진형담당) 사전 연락하여 식품안전정보원 사업과 가전 이모지사업 재추진 제안(예정) (2025.06.19 기준) - 선급금 70% 신청진행중 (2025.06.27 기준) - 선급금 80% 신청완료(경영지원실+사업지원팀) - 사업진행시 SL사업본부에서는 이큐포올 담당자와의 직접적 업무조율 필요 (2025.09.17 기준) - 2차 : 수어서비스 이큐포올 2차 리스트 발송 완료(수어데이터 연구팀 하윤호이사) L 이큐포올(60%) / 케이엘큐브(40%) - 현재까지 식품업체 신청 40% L 사업종료 : 11월 말(단, 수어컨텐츠식품업체 미달시 종료후 계속진행) (2025.10.20 기준) - 업무담당자 변경(심재홍 -> 임철현)에 따른 임현수선임연구원 인사 및 '26년 예산 문의 L '26년 예산규모 확인(약3천만원 예상), 입찰방식 협상에 의한 계약이 아닌 수의계약에 대한 방안 마련 요청 접수 L 현재 컨소 구성으로 '26년 참여에 대해 문의, 컨소 부분에 대해선 아직 검토된 바 없음 언급 (2025.11.13 기준) - 임현수 선임연구원 통화, 4차 스크립트 제공 일정 재협의 14일까지 준비 및 제공해주기로 함. L 과업기간이 '25.11.30까지이나, 스크립트 제공 지연에 따라 검수는 진행하되 최종 납품은 연장하기로 재확인 함 (2025.11.18 기준) - 11월30일 과업종료에 따른 검수서류 준비 및 차주 검사검수신청 예정 L 스크립트 제공 지연에 따라 최종 납품은 12월까지 연장 (25.12.02 기준) - 완료보고에 따른 공문 접수, 컨소사 지분에 따라 세금계산서 발행 예상되고 실무업무는 관련과에서 각사로 연락 주기로 함, - '26년 예산확인 금년과 동일 금액 확보, 금년 작업 규모와 동일시 수행에 애로사항 있음 언급, 관련 자료 준비 후 방문 하기로 함 L 수행팀에서 금년 사업 수행시 애로사항과 '26년 사업시 이를 해결할 수 있는 방안 제시 요청 (25.12.10) - '26년 예산관련 식약처 식품안전정책국장 지시로 과업내역 변경 예상됨 L 기존 식품표시정보 아바타 수어 영상 제작 -> 기보유 식품표시정보 수어 영상 실시간 모바일 서비스 활용 (예산 1억내외) L 세부 사항은 차주 미팅을 통해 수집 예정 (25.12.15) (식품안전정보원 통합식품정보화실 문성실장, 임현수 선임연구원 미팅) - '26년 예산 확보(3,000만원)하였으나, 식약처 식품안전정책국장 지시로 식품표시정보 수어영상 모바일앱 구축건으로 전용 예상됨 L 식약처 기보유 식품표시정보 456개에 대한 모바일 문자인식(OCR) 및 수어영상 표출 서비스 구축 추진 중 L '26년 1월 경 발주 및 2~3개월 개발, '26년 6월이내 상용서비스 계획 하고 있음 | Q20: - 현재 입찰준비중 - 2/28일 식품안전정보원에서 식품업체대상 푸드 QR 설명회 진행 - 식품수량: 300개 / 예산 : 3000만원 / 입찰시점 : 5월~6월 예상 - 3/6(목) 입찰 예가산정을 위한 단가 견적서(식품당 20만원) 및 입찰참가자격 참고용 내용 발송완료 (2025.03.14 기준) - 3/18(화) 1시 식품안전정보원에서 푸드QR 수어제작사 대상 설명회 및 간담회 진행 ※ 간담회 참여사 : 케이엘큐브, 멀틱스, 이큐포올 3사 ※ 주요내용 : 푸드QR 입찰관련 사항 공지 및 식품당 수어제작 단가 협의 예상됨 (2025.03.18 기준) - 3/18(화) 1시 식품안전정보원에서 푸드QR 수어제작사 대상 설명회 및 간담회 참석 ※ 간담회 참석자 : 식품안전정보원(문성팀장,임현수연구원외 3명), 케이엘큐브, 멀틱스, 이큐포올 3사 ※ 주요내용 : * 참가자격은 이큐포올도 사업참여 토록 관련 법령 적용예정 * 컨소시엄구성 허용 / 상황에 따라 제안발표는 없이 서면평가로만 평가 * 당초 300개 식품 → 150개 식품으로 하향조정(당사, 멀틱스 식품당 20만원 예가용 견적제출) (2025.03.25 기준) - 3/25(화) 식품 표시정보 아바타 수어영상 제작 용역사업(조달 발주계획 상태) ※ 사업일정 : 3월말~4월 사전규격 공개 및 조달입찰 / 5월 계약진행 ※ 사전규격(예상) : 평가 9:1(당초8:2), 공동수급 허용, 사업기간 11월까지, 내부평가, 제안서분량 30~50페이지 이내(당초100페이지), 식품수량 150개 ※ 단독응찰 or 경쟁사 컨소시엄 결정필요 ※ 결정사항에 따라 이큐포올 대표 미팅예정 (2025.04.04 기준) - 4/7(목)까지 사전규격 공개상태 ※ 사전규격은 전 주 보고내용 대로 공고 (2025.04.10 기준) - 4/10 입찰공고 개시 ※ 입찰마감 : 4/25(금) ※ 제안구도 확정필요 → 단독응찰 or 협회,강남대 컨소시엄 or 경쟁사 컨소시엄 (2025.04.16 기준) - 입찰 참가자격 이슈로 인해 재공고 ※ 입찰마감 : 05/02(금) → 제안 및 공동수급 완료시점은 04/30(수)이전 완료목표 ※ 제안구도 : 케이엘큐브(60%)+이큐포올(40%) 공동수급 합의 완료 ㅁ 실 수행시 : 수어컨텐츠 제작은 각사 75개식품으로 5:5로 작업진행 ※ 투찰금액 : 99% 투찰예정 (2025.04.24 기준) ※ 본제안서 작성 중, 4.25(금) 초안 완성 목표로 작업 중 ※ 4.29(화)리뷰 예정_with.이큐포올_김준경이사 ※ 발표자료 작성 및 제안서 제출(~4.30)
B21: 2025-018 | C21: 수어 | D21: 남원시 | E21: 전북테크노파크 | F21: 남원시 어울림도서관 체험관 DID형 수어체험시스템구축 | G21: 심재홍 | H21: 1 영업중 | J21: 5월 | K21: - 사업금액 : 500만원 ※ 구독형 /월 50만원/12월까지 ※ 이후 연장계약 | L21: - 본사영업 | M21: N | N21: 2/19(수) 기준 - 전북테크노파크에서 남원시 어울림도서관(신축)에 AI휴먼(이스트소프트) 체험관을 설치하였으나, SaaS사용료 과다로 당사 수어체험서비스 교체예정 - 적용시점은 금년 3월부터 적용하고자하며, 서비스기간은 3월~12월까지 10개월 계약 진행예정('26년 계약여부는 별도 협의예정) (2025.03.14 기준) - 수어체험서비스 컨텐츠 세부사항 및 설치환경등에 관한 연구소, 서비스개발팀 관련내용 지원필요 ※연구소 및 서비스개발팀 수어체험서비스 진행여부 판단 필요 - 진행여부에 따라 전북테크노파크 피드백 예정 (2025.03.25 기준) - 전북TP 임대환수석과 수어체험시스템 납품일정 협의완료 * 당사 수어체험시스템 5월 납품전까지 이스트소프트 AI휴먼 계속운영 ※ 당사 4월 테스트후 5월납품 약속함 / 시스템 납품전 수어시연 영상자료 또는 데모요청(수어체험시스템 소개자료포함) ※ 당사 요청에 의한 전북TP 담당자 남원 어울림도서관 기 납품 DID H/W스팩 확인차 도서관방문3/28(금) / 스팩확인후 회신예정 (2025.04.04 기준) - 전북TP 임대환수석 인사발령으로 담당자 김성일연구원으로 변경 ※ 변경 담당자 도서관 수어체험 진행여부 검토중 ※ 본 건과 관련하여 SL사업본부 하윤호이사와 전북TP 김성일연구원 대면미팅 예정 (2025.04.04 기준) -남원시 어울림도서관 DID 디바이스정보 요청중이나 고객측 소극적 대응중 ※ 임대환수석께 요청시 김성일연구원에 요청주라고 하며, 김성일연구원은 기다려달라는 얘기만 반복상태(2주째 ) ※ 전북TP측 지속적 딜레이시 남원시 어울림도서관 직접 방문이 필요할 것으로 판단됨. (2025.04.18 기준) ※ 4/17(금) 어울림도서관 적용 수어체험 적용 기획안 김성일연구원 전달 및 검토요청 완료 (2025.04.24일 기준) ※ 어울림도서관 (주)이스트소프트 AI휴먼 서비스 중지상태(예산문제) ※ 금일 김성일연구원께서 전북TP 선행사업으로 기존 어울림도서관에 들어갈 예산 여력이 없다고 함. 우선 선행사업 예산 확인후 5월중 별도 연락 드리겠다고 함.
B22: 2025-019 | C22: 수어 | D22: 라스테크(주) | E22: 라스테크(주) | F22: 라스테크(주) 생산 키오스크 및 로봇 답재용 수어서비스 제안 | G22: 심재홍 | H22: 2 견적제출 | J22: 미정 | K22: - 사업금액 : 600만원 | L22: - 본사영업 | M22: N | N22: - 키오스크 및 로봇 생산업체인 라스테크에서 생산 제품 수어서비스 적용 검토중 - 구독형 서비스는 지양하고 온프라미스 1회성 견적요청 - 3/6(목) 온프레미스 클라이언트 라이선스용 으로 견적전달 완료 - 라스테크 내부검토후 연락주기로 함. (2025.03.12 기준) - 3/20(목) 2시 수어서비스 적용관련 라스테크 방문 / 담당자 대면미팅 진행 / - 수어서비스 적용시 제품 원가상승 고민중
B23: 2025-020 | C23: 수어 | D23: 아마노코리아 | E23: 엘토브 | F23: 아마노코리아 무인주차시스템 수어서비스 제안 | G23: 심재홍 | H23: 1 영업중 | K23: - 사업금액 : | L23: - 엘토브 | M23: N | N23: - 2/13(목) 현재 엘토브와 아마노코리아 양사가 초기미팅중
B24: 2025-021 | C24: 수어 | D24: 국립과천과학관 | E24: 윤커뮤니케이션즈 | F24: 국립과천과학관 포탈시스템 재구축 및 클라우드 전환 입찰 | G24: 심재홍 | H24: 6 실주 | J24: 3월말 | K24: - 사업금액 : 수주후 논의 | L24: - 윤커뮤니케이션즈 | M24: N | N24: - 국립과천과학관 포탈시스템 재구축 및 클라우드 전환 입찰공고 공고중 - 사업예산 : 15.2억 / 공고:2/3(월) / 제안마감 : 3/7(금) - 국립과천과학관 포탈시스템은 2008년 구축 후, 2015년에 개편하여 운영 중으로 비호환 기술 동시 사용에 의한 유지보수 난이도 증가로 재구축상황 - 현재 국립과천과학관의 "과학수어"와 국립어린이과학관의 "전시물수어해설"에 대해 수어통역사를 활용한 과학관련 수어컨텐츠 제공중 - 과학전시관의 컨셉에 맞추어 과학관련 수어서비스를 AI기반 수어 아바타를 적용한 컨텐츠를 추가제안 제안하는것으로 제안사측과 협의중 - 제안사는 당사 협력사인 (주)윤커뮤니케이션즈에서 제안 준비중 - (주)윤커뮤니케이션 제안팀 내부 검토후 추가제안 여부 확정예정. (2025.03.11 기준) - 3/7(금) 수어서비스 추가제안을 포함한 제안서 제출완료 / 제안발표 대기중 - 경쟁사 : 윤컴포함 9개사 제안서제출 / 결과나오면 별도 연락주기로 함.(하혜정상무) ※ 조달 입찰결과 모니터링중 (2025.03.20 기준) - 입찰결과 : 9개 참여사중 윤커뮤니케이션즈 4위로 / 실주
B25: 2025-022 | C25: 수어 | D25: 조선호텔&리조트 | E25: 엘토브 | F25: 신세계 스타필드 기존 및 신규 안내 키오스크 배리어프리 키오스크 교체계획 | G25: 임철현 | H25: 5 DROP | J25: 7월~8월중 | K25: - 사업금액 : 수주후 논의 | L25: - 엘토브 | M25: N | N25: 구,신세계 E&C - 엘토브 협업 - - 기존 신세계 스타필드에서 운영중인 안내 키오스크등 장차법대비 배리어프리 키오스크 교체 필요성 보고자료 작성중 - 기존 안내 키오스크는 당사 협력사인 엘토브 장비가 포함 되어있어 엘토브와의 협력으로 당사 수어서비스 적용목표 - 2/5(금) 장차법관련자료 및 수어를 포함한 엘토브 배리어프리 관련자료 신세계 스타필드 담당자 전달완료 - 계획단계로 적용시점은 시일이 걸릴것으로 예상 - 엘토브측 당사에서 신세계 E&C에 자료발송 전에 조선호텔측과 배리어프리 안내키오스크 상담진행 했던것으로 확인됨 - 신세계 스타필드 영업사항은 (주)엘토브와 협업으로 영업진행하며, 신규 도입하는 배리어프리 키오스크에 당사 수어탑재 진행 - 사업시점 : 7월~8월예상 / 사업규모 30~200대 예상 (2025.10.20) - 업무담당자 변경(심재홍 ->임철현), 엘토브 성원배상무 차주(29일) 인사 예정 (2025.10.29 기준) - 신세계 스타필드건 수주 및 수행 중, 고객사와의 협의 및 예산으로 인하여 수어 대신 문자 적용으로 진행 됨 확인
B26: 2025-023 | C26: 수어 | D26: 국민연금공단 | E26: 국민연금공단 | F26: 연금보험공단 AI휴먼 활용 대국민 뉴스외 수어서비스적용 검토 | G26: 양승구 | H26: 1 영업중 | J26: 상반기 | K26: - 사업금액 : | L26: - 본사영업 | M26: N | N26: (2025.05.08 기준) ※ 입찰참여사 미공개 상태에서 3개사 참여(예상 : 케이엘큐브+이큐포올 컨소시엄, 멀틱스, 에스엘제스처(?) ※ 제안서 평가 진행중 ※ 대면평가 진행 : 5/14(수) 10시25분(발표 15분, 질의 10분), 참석인원 : 발표자 외 3인 [포스트타워 10층(대기실), 12층(발표장)] L 당초 현업부서에서 서면평가로 진행하는것을 계약부서에서 대면평가로 변경상태(식품안전정보원 문성 팀장 확인) (2025.05.15 기준) ※ 케이엘큐브 컨소시엄 낙찰 * 케이엘큐브 (기술평가 : 90 가격: 9.2593 총점 : 99.2593) * 멀틱스 (기술: 87 가격: 9.7519 총점 : 96.7519) * 더씨앗 (기술: 0 가격: 10 총점 : 10) = 평가부적격 (2025.05.22 기준) - 5/27(화) 10시 계약진행을 위한 형식적 기술협상 진행(티타임 형태로 진행)_with.대표님 ※ 식품업체 참여상태 및 식품수량 확인 (2025.05.25 기준) - 5/27(화) 10시 기술협상 진행 완료_with.유영복상무 ※ 식품업체 참여도 저조상태 / 계약 종료시점까지 계약물량 150개 식품 미달시 종료후에도 진행(계산서발행은 종료시점 선발행진행) - 5/28(수) 기술협상결과 통보서 식품안전정보원 회신완료 / 계약 대기중 (2025.06.05 기준) - 6/5(월) 기술협상 진행 완료에 따른 식품안전정보원 '25년 식품 푸드QR 지원사업 조달계약 완료 L 차주 사업진행에 따른 식품안전정보원과의 협의 진행 예정(착수보고 일정, 식품업체 방문 및 식품업체 선정등) (2025.06.12 기준) - 사업진행에 따른 SL사업본부 식품안전정보원 사업진행 논의(하윤호이사) L 1차 50개 식품 품목에 대한 이큐포올과 업무배분 체크필요 L 6월 중 식품안전정보원에서 삼성전자 미팅시 케이엘큐브 참석시 사전체크 ※ '24년 컨텍하였던 삼성전자 가전사업부(김진형담당) 사전 연락하여 식품안전정보원 사업과 가전 이모지사업 재추진 제안(예정) (2025.06.19 기준) - 선급금 70% 신청진행중 (2025.06.27 기준) - 선급금 80% 신청완료(경영지원실+사업지원팀) - 사업진행시 SL사업본부에서는 이큐포올 담당자와의 직접적 업무조율 필요 (2025.09.17 기준) - 2차 : 수어서비스 이큐포올 2차 리스트 발송 완료(수어데이터 연구팀 하윤호이사) L 이큐포올(60%) / 케이엘큐브(40%) - 현재까지 식품업체 신청 40% L 사업종료 : 11월 말(단, 수어컨텐츠식품업체 미달시 종료후 계속진행) (2025.10.20 기준) - 업무담당자 변경(심재홍 -> 임철현)에 따른 임현수선임연구원 인사 및 '26년 예산 문의 L '26년 예산규모 확인(약3천만원 예상), 입찰방식 협상에 의한 계약이 아닌 수의계약에 대한 방안 마련 요청 접수 L 현재 컨소 구성으로 '26년 참여에 대해 문의, 컨소 부분에 대해선 아직 검토된 바 없음 언급 (2025.11.13 기준) - 임현수 선임연구원 통화, 4차 스크립트 제공 일정 재협의 14일까지 준비 및 제공해주기로 함. L 과업기간이 '25.11.30까지이나, 스크립트 제공 지연에 따라 검수는 진행하되 최종 납품은 연장하기로 재확인 함 (2025.11.18 기준) - 11월30일 과업종료에 따른 검수서류 준비 및 차주 검사검수신청 예정 L 스크립트 제공 지연에 따라 최종 납품은 12월까지 연장 (25.12.02 기준) - 완료보고에 따른 공문 접수, 컨소사 지분에 따라 세금계산서 발행 예상되고 실무업무는 관련과에서 각사로 연락 주기로 함, - '26년 예산확인 금년과 동일 금액 확보, 금년 작업 규모와 동일시 수행에 애로사항 있음 언급, 관련 자료 준비 후 방문 하기로 함 L 수행팀에서 금년 사업 수행시 애로사항과 '26년 사업시 이를 해결할 수 있는 방안 제시 요청
B27: 2025-024 | C27: 수어 | D27: 소다미술관 | E27: 소다미술관 | F27: 소다미술관 전시정보 수어서비스 사업제안 | G27: 오민규 | H27: 1 영업중 | J27: 상반기 | K27: - 사업금액 : | L27: - 본사영업 | M27: N | N27: - 1/22(수) 회사 홈페이지 인바운드 접수건(이용방법 및 견적서 요청) - 1/23(목) 서비스 이용방법 및 견적서 요청사항 발송완료. - 소다미술관 전시물대상 수어서비스를 하고자 내부 논의중이라고 하며, 좀더 확인후 궁금한 사항 다시 연락주겠다고 함. - 2/12(수) 이수연매니져 대면미팅진행. 현재 소다미술관 겨울 시즌은 휴관중이며, 전시진행시 농인 참관객을 위한 작품설명을 수어서비스를 해보고자 전시관 내부직원 아이디어 차원에서 의견이 나와서 알아보던중 국어문을 수어로 번역한다는 뉴스기사를 보고 문의. ※ 현재는 아이디어 의견차원이고 수시로 변경되는 전시물에 대해 수어아바타를 제작하는것에 비용적 부담이 있는 상태임. ※ 내부적으로 수어서비스 구축은 잠정 보류하기로 함. ※ 2025.11.27 담당자 변경 심재홍 → 오민규
B28: 2025-025 | C28: 수어 | D28: AIA생명보험 | E28: 아이엔지피플(LG CNS) | F28: AIA생명보험 포털시스템 구축(수어서비스 추가제안) | G28: 양승구 | H28: 1 영업중 | J28: 하반기 | K28: - 사업금액 : 3000만원 | L28: - 교보DTS - 아이엔지피플(수행사) | M28: N | N28: - 교보DTS마더사로 사업진행중이며, 아이앤지피플은 협력사로 제안 - AIA생명보험 포탈內 “청구서류안내, 청구방법안내, 지급절차안내” 3개항목에 대한 수어서비스 적용 검토중 - 기본문장수 200개기준으로 LGCNS에 견적진행중에 있으며, 적용여부는 교보DTS에서 결정 예정 - 24/11/1 금융서비스 개선 필요성 명분자료 아이앤지피플 발송완료 - 24/12/13 수어서비스 일부 적용 확정(분석/설계후 수어적용 시나리오 확정) - 사업기간 : 25/01/2~26/2/28까지(13개월) 프로젝트 - 수어적용시점은 25년 하반기부터 적용 예상 (2025.09.17 기준) - AIA생명 포탈사업 (주)아이엔지피플 분석,설계, 개발 진행.. L (주)아이앤지피를 계약시 고객 수어서비스 필요없음 강조 L (주)아이앤지피플 유은희대표.. 분석,설계, 개발 진행시 고객께 수어서비스 적용강조(10월) ※ 적용 여부는 10월초 or 10월중순 확인후 보고 예정 ※ 2025.11.27 담당자 변경 심재홍 → 양승구
B29: 2025-026 | C29: 수어 | D29: KB증권 | E29: KB증권 | F29: KB증권 웹, 모바일서비스內 생성형 AI기반 수어서비스적용 검토 | G29: 양승구 | H29: 1 영업중 | J29: 하반기 | K29: - 사업금액 : | L29: - 본사영업 | M29: N | N29: - KB이노베이션허브를 통해 KB증권 신기술팀(이진우차장) 컨텍 상태임. - 현재 수어서비스에 대한 양방향 서비스를 원하고 있으나 현실적 상황 세부 설명완료(연구소 방기덕소장) - 금융영역에 있어 단계적으로 수어인식 및 시나리오기반 챗봇서비스에 대한 당사 기술 소개자료 발송완료 - 2/7(목) 연구과제 "청각장앤 비식별화 플랫폼 개발 제안"과 관련하여 연구과제 실증 및 협력기관 참여 독려를 하였으나, 내부보고 절차의 절대적인 시간이 부족하여 불가상태라 함.(내부보고 절차 진행상황을 봤을때 최소 1개월전 사전협의 요청) ※ KB이노베이션 허브 측에서는 관계사에 본 사업에 대한 협력기관 참여 독려는 내부 프로세스상 어려움이 있다고 함.(불가) - 수어분야 생성형AI 기술협의는 장기적 시간 필요한 상태 / 현재 기술기반에서는 기술미팅 무의미 상태라는 의견 ※ 2025.11.27 담당자 변경 심재홍 → 양승구
B30: 2025-027 | C30: 수어 | D30: 제주도 교육청 | E30: KT클라우드 | F30: 제주도교육청 320여개 초,중등 대상 홈페이지 및 키오스크 수어서비스 제안 | G30: 오민규 | H30: 1 영업중 | J30: 하반기 | K30: - 사업금액 : | L30: - KT클라우드 - 에즈원시스템즈(지역영업) | M30: N | N30: - KT클라우드 제주 총판인 ㈜에즈원시스템즈에서 DaaS 사업등으로 제주도청 및 교육청 영업중 - 클라우드기반 유치원,특수학교를 제외한 199개교 홈페이지외 수어서비스 적용 제안 - 제주교육청산하 전체학교 대상으로 진행하는 상황이라 예산과 시간이 좀더 필요하다는 의견상태 - 제주도청 및 교육청 미팅은 어려운 상황이며, KT-C에서 에즈원시스템과 별도의 미팅을 잡을 예정 - ㈜에즈원시스템즈측 ’25년 2차 추경 예산작업을 위한 기관 초기 영업진행중 - 1/15(수) KT클라우드 담당자에게 제언자료 전달 → 대표님 ※ 관련미팅 대기상태 ※ 2025.11.27 담당자 변경 심재홍 → 오민규
B31: 2025-028 | C31: 수어 | D31: 한국철도공사(코레일) | E31: 케이알솔루션 | F31: 한국철도공사(코레일) 신형자동발매기內 수어서비스적용 | G31: 오민규 | H31: 8 계약완료 | J31: 상반기 | K31: - 사업금액 : 9,000,000원(vat제외) | L31: - 씨아이테크 - 지앤시스(개발사) | M31: N | N31: (2025.08.01 기준) - KTX 발권기 적용 샘플 2종 수어아바타 (주)지앤시스 발송완료 L 요구 해상도 356×260 해상도 문제로 712×520 해상도 역 제안 진행중 ※ 샘플제작 : KTX 전용 유니폼 및 명찰 적용 2종 ※ 지앤시스 샘플아바타 발권기 테스트 진행 및 코레일측 검토후 확정 예정 (2025.08.08기준) - KTX 발권기 적용 샘플 2종 수어아바타 선정 지연상태 L 요구 해상도 356×260 에서 712×520 해상도로 테스트 완료 ※ 기존 해상도 356×260에서 역 제안 해상도 "712×520 확정"으로 문장 제작진행 ※ 본 사업 개발사인 (주)지앤시스에서 SRT사업 제안 준비로 KTX개발사업 신경을 못쓰는 상태 (2025.09.04 기준) - KTX 발권기 수어아바타 최종본 발송에 따른 수어아바타 적용중 L 서울역, 광명역 프로토타입 발권기 9월말~10월초순 납품예정 ※ 금년 프로토아입 발권기 시범서비스이후 '26년 전국 KTX역사 적용예정 ※ KTX객차내 수어 안내방송 적용관련 코레일 영업진행중(지앤시스) (2025.09.17 기준) - KTX 발권기 수어아바타 최종본 발송에 따른 수어아바타 적용 L 추석전 세금계산서 발행 및 영업사 수수료 지급 예정 ※ '26년 KTX객차내 수어 안내방송 적용관련 코레일 영업진행중(지앤시스) (2025.10.16 기준) - 세금계산서 발행(10/16) 및 변경수주품의작성 완료(지앤시스 9,000,000원 → 케이알솔루션 7,200,000원) (11.24 기준) - 12월 말까지 개발 완료 일정으로 진행중(지앤시스 최호영 대표 통화完) ※ 2025.11.27 담당자 변경 심재홍 → 오민규 (12.17 기준) - KTX 발권 키오스크 수어 탑재 확인(12/17 광주송정역. 12월 설치됨 확인) - 지앤시스 확인: 프로젝트 기간 12월말까지로 정산도 안되었음 ※ 주요역사 확인 예정: 서울역, 용산, 광명, 행신 → 1월 중 기사 송출 예상, 지속모니터링 예정 (12.24 기준) - 주요역사 발권 키오스크 수어 탑재 확인(서울, 용산, 행신) → 뉴스 기사 송출 여부 지속 모니터링중 | Q31: - 수주사인 ㈜씨아이테크 => 실 구축사 ㈜지앤시스 - 실 구축 개발사인 ㈜지앤시스 최호영대표 수어적용관련 미팅완료 - KTX 발권기 키오스크 UI/UX 복잡성으로 인해 수어적용 범위 미확정 상태. - ’25년 1월중 수어적용 문장 스크립트 수급예정 / 7~8월까지 개발 및 장비 프로토타입 완료계획 ※ 서울역 시범운영후 전 역사 확대예정/ 전체 310대 ※ 개발사측 추가제안으로 인해 당사를 포함한 멀틱스와 이큐포올 견적확인후 결정예정 - 1월중 수어적용 문장 스크립트 수급 예정이였으나 발권기 프로세스 복잡성으로 미완료 상태. 코레일측과 논의등을 감안했을시 완료시점을 3월경으로 보고 있다고 함. (2025.03.12 기준) - 3/20(목) 수어적용관련 미팅진행 예정 ※ 수어제작 업체선정 및 KTX 발권기 적용문장 스크립트 준비상황 확인차 (2025.04.16 기준) - 개발사인 (주)지앤시스측, KTX발권기 키오스크 UI/UX 복잡성으로 현재까지 설계중 - 5월말 경이나 수어적용 범위가 나올것으로 예상상태 - 수어적용범위 확정시 당사외 이큐포올 및 멀틱스 견적요청 진행예정 (2025.05.15 기준) - 5/15(목) (주)지앤시스 최호용대표 미팅_with.대표님 ※ 전국 KTX역사대상 310대 배리어프리 발권기 수어적용 ※ KTX 발권기 UI/UX 설계 완료에 따른 수어아바타 제작사 대상 견적요청 진행중 L 추가 제안건으로 금액적 이슈가 관건 (2025.05.23 기준) - 당사 잠정적 확정(코레일측에 의견만 남은 상태) ※ 향후 진행사항 및 확인사항에 대한 답신 완료 L 아바타의상 변경, SL-CMS 필수 도입여부, 향후 추가문장 도입비용등 ※ 계약 및 발주 진행시 지앤시스 → 티랜드 → 케이엘큐브로 진행요청 L 참고 : 티랜드 이경렬대표(씨아이테크출신)측에서 KTX 발권기사업 개발사인 지앤시스 당사소개 (2025.05.29 기준) - 5/30(금) 본사업 개발사인 (주)지앤시스에서 코레일측에 당사 및 이큐포올 사항 보고 완료 / 당사 선정완료 ※ 향후 당사 수어아바타와 개발사간 발권기內 수어적용과 관련한 협의진행 예정 | R31: (2025.06.27 기준) - 본사업 개발사인 (주)지앤시스에서 코레일측과 향후 지원등 협의 완료 L 기존 50문장이외 추가 지원되는 범위는? → 계약 문장수의 10% 범위內 L 기존 문장 수정의 경우 유/무상여부? → Warranty기간(1년) 이내에서는 계약문장수의 20%범위 내에서는 무상처리 Warranty기간(1년) 이후에는 년간 변경 예상 문장수를 반영한 유지보수 계약 L 향후 코레일측과 유지보수 및 추가 적용사항은 개발사인 지앤시스와 진행 → 수용 - KTX 배리어프리 발권기 프로토타입 시범적용은 서울역을 시작으로 전국확대(310대) 예정 L 지앤시스 발주전 코레일 역무원 표준 유니폼 샘플사진 요청. 사전 샘플디자인 작업 필요(코레일 검토용) (2025.07.17 기준) - 7/16 본 사업 (주)지앤시스 발주진행 완료 L 코레일 화면 : 64문장(TTS기준) / 실 어절단위 문장 : 477어절-32문장 L 표준디자인 : 1) KTX 전용유니폼 이미지 수급(컬러 넘버 없음_최대한 비슷한 색상으로 샘플 2종 요청) 2) 유니폼 사각 영문명찰(샘플용 KORAIL_표준CI 및 KTX_표준디자인) L납품일정 : 8월29일까지 / 계획된 납품일정보다 빠를수록 Prototype장비가 서울역 시범적용이 빨라질 수 있음 (2025.07.22 기준) - KTX 발권 키오스크 테스트용 수어콘텐츠 (주)지앤시스 발송완료 L 요구해상도 712×520 사이즈로 기존 제작 수어콘텐츠 적용시 화질문제(문개짐현상) 확인 L 당사 제안해상도 712×520 사이즈로 개발사에 역 제안중 ※ 1차 BF 발권 키오스크 완료후 2차 사업으로 열차 객차내 안내방송 수어서비스 적용 제안예정(지앤시스 → 코레일) ※ SRT열차 객차내 안내방송 수어서비스 이큐포올 수어아바타 적용 서비스중(지앤시스 → SRT)
B32: 2025-029 | C32: 수어 | D32: LG그룹 | E32: LG슈퍼스타트팀 | F32: LG그룹 계열사대상 수어서비스 적용 제안 진행중 | G32: 오민규 | H32: 1 영업중 | J32: 하반기 | K32: - 사업금액 : | L32: - LG그룹 계열사 | M32: N | N32: - 1/7(화) LG슈퍼스타트팀 LG그룹 계열사 수어서비스 적용 콜라보레이션 미팅 진행 - LG그룹 계열사중 우선순위 계열사를 순차적으로 PoC형태로 사업적용 제안 예정 - 1순위 : LG전자 가전사업부 및 로봇사업 / 2순위 : LG전자 VS -> HUD(Head Up Display) / 3순위 : LG전자 KIOSK사업 / 4순위 : LG생활건강 - 서비스방식은 QR코드를 활용한 수어서비스 및 수어 응용서비스 발굴 - 1/10(금)우선순위관련 자료 LG슈퍼스타트팀 제출완료(기획팀 고윤창부장) - 1/20(월) 현재 LG그룹 계열사 미팅일정은 설명절 이후 순차적으로 진행될 것으로 예상. - 2월 현재 LG슈퍼스타트팀 이진아책임께 계열사 미팅관련 전화와 문자를 드리고 있으나 연락두절 상태 - 2/12(수) LG전자 A2X센터에서 자체적으로 AI기반 수어개발중. 금년 5월에 출시될 TV에 수어적용 출시 예정 ※ 2/18(화) LG 전체 계열사 내부미팅 자리가 있는 상태이며, LG슈퍼스타트측에서 LG생활건강, HUD관련 계열사 상담 및 현황확인 예정 ※ 3월말~4월초 아고라 발표자리에서 당사 수어서비스 어필해 보자고 함. (2025.03.18) - LG 유플러스 측에 "핸드사인톡톡"서비스 도입 검토 요청 - LG 유플러스 측 수어서비스보다 AICC솔루션 활용에 대한 논의 요청상태. ※ LG유플러스와 AICC솔루션관련 기술개발 및 사업적 협업 논의를 비롯한 투자검토 이력이 있는지 확인요청중 - 차주중 회신예정 (2025.04.17 기준) - LG유플러스와 AICC솔루션관련 협업 논의 및 당사 투자검토 이력에 대해 LG슈퍼스타트 이진아책임께 회신완료 - LG유플러스측에 당사와의 협업 논의 자리 만든후 다시 회신주기로 함. ※ LG그룹 계열사 협업 프로그램 확인 요청중 ※ 2025.11.27 담당자 변경 심재홍 → 오민규
B33: 2025-030 | C33: 수어 | D33: GS칼텍스 | E33: 지에스아이티엠(GSITM) | F33: GS칼텍스 주유소 운영 SW 혁신 프로젝트 수어서비스 | G33: 오민규 | H33: 8 계약완료 | J33: 3월결정 | K33: - 사업금액 : 1,020,000원(vat별도) | L33: - GS ITM ※ 계약시 GS칼텍스와 직접계약 | M33: N | N33: (2025.10.16 기준) - GS칼텍스 주유기 키오스크(TEST) 수어영상 확인(10/14) L 기존 주유기 키오스크 옆에 추가 설치 의도로 제작됨 (상단 광고 영역에서 수어 안내(정전기패드-일반주유-유종-결제수단-주유금액-포인트적립-카드결제) L 운영방안, 오픈 일정 등은 미정 상태 (11.06 기준) - GS칼텍스 주유기 키오스크(수어) 배포 일정 확인 . 내부 운영방안, 오픈 일정 미정 지속 → 연내 현장 설치 어려울 것으로 예상함 (11.18 기준) - GS칼텍스 주유기 키오스크(수어) 배포 일정 확인 . 내부 운영방안, 오픈 일정 미정 지속 → 연내 현장 설치 어려울 것으로 예상함 ※ 2025.11.27 담당자 변경 심재홍 → 오민규 | Q33: - GS칼텍스 주유소 운영 SW개발 사업을 GS ITM에서 개발사업 진행중 - 개발사업분야 : 셀프ODT, 주유기 KIOSK, 세차키오스크(15”화면상의 음성에 맞추어 수어영상 표출) - 현재는 검토 단계이며, 계약진행시 당사와 GS칼텍스간 직접계약하여 GS ITS와 사업진행 - 사업진행계획 : 5월까지 개발완료 / 7월까지 테스트 / 8월 허브주유소 1~2곳 오픈(안정화) / 9월 사업종료 - 1/8(수) 1차 견적 발송 : 1안) Server License / 2안 Kiosk Client License (1,2안 모두 SL-CMS포함 제안) - GS ITM담당자 의견 : On-premis방식으로 주유기 수어서비스 예정이므로 CMS제외한 컨텐츠만 제공요청 - 1/14(화) SL-CMS제외 200문장기준 견적서 발송완료 / GS ITM측 수어서비외 추가 아이템 금액 산출후 GS칼텍스측에 품목 및 금액 발송예정 ※ GS칼텍스측 결정시 5월전까지 ASAP으로 구축해야 되는 상황임. - 2/7(금) 현재 GS ITM에서 추가 아이템을 취합하여 GS칼텍스에 전달한 상태이며, 임원결재 대기 상태 - 결정은 빠르면 2월 늦어도 3월중으로 추가사업 결정을 할것으로 예상한다고 함.(추가계약건은 GS ITM 계약대상이 아니라 GS칼텍스 결정상황 무관심) (2025.03.13 기준) - 내부검토결과 수어적용 비용이 너무 과다하여 수어서비스 최소화로 하여 일부만(몇개만?) 적용하는것으로 결론 - 수어서비스 최소화 적용은 현재 화면디자인 설계중이라 확정된건 없다고 하며, 화면설계 진행하면서 확정되면 연락주겠다고 함 (2025.04.09기준) - GS칼텍스 사업금액 문제로 최소 문장(10문장) 수어서비스 적용 잠정확정 및 견적발송 - 견적 및 계약관련사항은 운영 SW혁신 프로젝트 PM결재를 득한후 GS칼텍스 계약팀으로 전달후 계약 진행예정 - 허브주유소대상 시범서비스이후 확대시 SL-CMS도입 및 수어문장 확대 계획중 (2025.04.18기준) - 최소 문장(10문장) 수어서비스 적용에 대한 GS ITM SW혁신 프로젝트 PM결재 완료상태이며, GS칼텍스 내부 결재 진행중 - GS ITM 담당자 의견은 4월중 계약 5월 제작진행 예상한다는 입장(GS칼텍스측 변수 없을시) [진행중] 4월 24일 기준 ※ GS ITM ----> GS칼텍스 계약부서 전달 완료. ※ 차주중 계약관련 연락대기 상태 (2025.05.07 기준) ※ GSITM 협력사 등록완료 ※ 5/9(금) 현재 GSITM 계약부서에서 내부 결재지연 상태이므로 현업부서와 선행하여 사업진행 요청 (2025.05.14 기준) - 차주 계약진행 예정 ※ 1차 샘플아바타 제공상태에서 아바타 옷색상 변경 샘플 요청중 L 요청사항 : * 현재 아바타 크기 유지 / 투명 부문 최소화하도록 전체이미지 조정 요청 (즉, 배경 포함된 사이즈를 캐럭터의 동선에 맞게 제작, 투명 배정 부분을 최소화 요청) * 전체 프레임 :동작이 있기까지 초기 대기 영역 삭제 요청 (사유는 파일 사이즈를 최소화하여 메모리 사용 효율성을 높이고자 합니다.) | R33: (2025.05.23 기준) - 5/23 계약진행 완료 ※ 계약기간 5/16 ~ 5/31까지 L 계약은 위의 날짜로 진행하고 사업진행은 6/6까지 납품 및 계산서발행(GSITM 계약부서와 합의 완료) L SL사업본부 업무 포화로 6/6 이후 납품지연 가능성으로 GSITM측에 연기요청 진행 예정 (2025.05.30 기준) - GS칼텍스 적용아바타 디자인 협의 및 마무리 단계 진행 ※ 차주중 적용아바타 픽스후 제작진행 예정 (2025.06.27 기준) - GS칼텍스 수어아바타 납품완료에 따른 청구진행중 L GSITM 현업부서와 계약부서간 협의중 / 차주 계산서 발행예정 (2025.07.23 기준) - GS칼텍스 수어아바타 납품완료에 따른 향후 진행사항 L 개발사인 GSITM에서 금년 9월까지 개발완료를 목표로 진행중 L 프로토타입적용 허브주유소 5곳은 아직 미선정 상태 L 허브주유소 테스트 및 안정화이후 전국 GS칼텍스 직영주유소에 배포 계획을 가지고 있음 L 견적내역중 1차 계약에 사항에 포함된 내용 : ※ "향후 추가 주유기 키오스크당 공급되는 수어아바타 컨텐츠 저작권에 대해 주유기 키오스크당 클라이언트 라이선스 추가 금액이 발생합니다." ※ 주유기 KIOSK Client License / 소비자가 50만원 제시 상태 (2025.08.29 기준) - GS칼텍스 검수 확인서 등록, 세금계산서 처리 완료 (2025.09.17 기준) - GS칼텍스 수어아바타 납품완료에 따른 향후 진행사항 확인차 방문 L 9/29(월) 오후 2시 / 추석전 인사 및 향후 계획관련 (주)GSITM 담당자 미팅 ※ '26년 GS칼텍스 향후 사업 방향 확인차_With.오민규부장
B34: 2025-031 | C34: 수어 | D34: 전국지자체 | E34: 전국지자체 | F34: - 전국 지자체 문화축제 수어서비스 적용 제안사업 | G34: 양승구 | H34: 1 영업중 | J34: 2025년 | L34: - 본사영업 | M34: N | N34: [2024년] - 문화축제 수어서비스 방향은 홈페이지, 앱, 안내표지판, 브로셔 등 QR적용 수어서비스 적용제안 - 하반기 전국 668개 행사기관 컨텍은 전문 텔레마케팅 대행사를 통해 1차 진행 요청중 ※ 먼져 진행중인 아웃바운드 콜과 휴가시즌으로 인래 당사 진행은 8월 넷째주 진행예정 * 2차 고객수집은 상반기 지역축제 완료 기관대상 ‘25년 행사준비를 위한 텔레마케팅 진행 및 고객수집 * 남양주시 경기정원박람회 홍보물 스마트 수어QR서비스 제안 차 남양주시 공원녹지관리사업소 방문 / 예산문제로 도입불가 [2025년] - '25년 상,하반기 지역축제대상 TM진행 예정 ※ 2/12(수) 미래전략팀 박현후과장 지원으로 '25년 지역축제 전체 리스트 조사중 ※ '25년 상,하반기 전체 리스트 확보후 전체 지역축제 대상 TM전문업체 "김&김콜센터"를 통해 아웃바운드 진행예정(2월 셋째주중) (2025.03.12 기준) - 지역축제 TM 내부결재 완료따른 사업추진 - 3/17(월) 콜센터 발주진행 및 콜 진행 스케쥴 협의 예정(사업지원팀+미래전략팀) - 아웃바운드 콜은 상반기, 하반기 전체 지역축제 대상으로 진행 - 수어서비스 적용에 긍정적 기관대상 영업추진 ※ 표준 수어서비스 가격책정 필요 (2025.03.25 기준) - 1차 고객처대상 아웃바운드 콜 진행(3/19~24일) / 고객 호응도 중,상 대상 eDM 및 본사 콜 진행 예정 ※ DX팀 영업인력 부족으로 유관부서 아웃바운드 콜진행 지원필요 - 2차 고객처대상 아웃바운드 콜 진행중(3/25~ing) (2025.04.08 기준) - SK쉴더스 지역 협력사를 통한 영업 추진 ※ 1차 아웃바운드 고객대상 SK쉴더스 협력사에서 2차 eDM발송 및 지역별 방문영업 진행 ※ SK쉴더스 협력사 가능지역이외 타 지역은 본사에서 진행 [진행중] 4월 23일 기준 ※ SK쉴더스에서 지역 협력사 자료 배포완료 ※ 케이엘큐브 소개자료기반 커스텀으로 자료작성후 고객께 배포. ※ 2025.11.27 담당자 변경 심재홍 → 양승구
B35: 2025-032 | C35: 수어 | D35: (주)채움씨앤아이 | E35: (주)채움씨앤아이 | F35: - (주)채움씨앤아이 도서관용 로봇 수어서비스 제안 | G35: 심재홍 | H35: 1 영업중 | J35: 2분기 | K35: - 사업금액 : | L35: - 채움씨앤아이 | M35: N | N35: - 로봇 생산업체인 ㈜채움씨앤아이 도서관 최적화된 수어서비스 적용 검토중 - 로봇에 수어인식 기능을 적용 검토중에 있으나 변수사항(학습데이터)에 대한 문제로 단방향으로 제안 - 1/16(목) 100문장 기준 견적서 발송완료(SL-CMS제외) - 1/20(월) 로봇 수어 적용과 관련하여 김승철상무 미팅진행 ※ 수어적용으로 인해 로봇 판매에 대한 원가상승 부담 / PoC적용후 판매 수량별 로봇 Client License형 금액정책 역제안중 - 2/11(화) 도서관 안내로봇에 수어아바타 적용에 대한 양사간 미팅진행 ※ 세종시립도서관 기 도입 도서관 로봇에 프로토타입으로 수어서비스 적용 논의 ※ 프로토타입 적용후 타 도서관 밴치마킹 거첨사이트 활용 ※ 25년 신축도서관, 리모델링도서관 도서관 로봇적용 고객처대상 영업진행 계획 - 2/12(수) 세종시립도서관 과장님 (주)채움씨앤아이 내방에 따른 청각애인인에 대한 브리핑 및 도서관로봇 수어아바타적용 논의 진행 ※ 도서관 로봇에 수어적용 테스트를 위한 샘플 수어아바타 (주)채움씨앤아이 개발팀 발송완료 ※ 로봇 개발사 개발팀에서 로봇 UI/UX상 수어아바타 적용에 따른 문제점이 없는지 기술검토후 의견 제시할 예정
B36: 2025-033 | C36: 수어 | D36: KB국민은행 | E36: LG CNS | F36: KB국민은행 수어번역서비스 | G36: 함영민 | H36: 2 견적제출 | J36: 2분기 | K36: - 발주금액 : 0.4억 | M36: N | N36: - 장차법 대응 및 ESG경영 실천을 위해 수어번역서비스 도입 검토 예정 - 챗봇 시범 적용용 수어번역서비스 예산용 견적 및 인프라 구성안 제출 - 구축형, 구독형(금액 구조만 구독형으로 제안) 견적 제출 - 24년 12월에 금융지주에서 실무진과 SynK 당위성 논의 후 사실 상 예산기안 통과 - 4~5월 입찰 공고 후 6월에 프로젝트 착수 계획 중 · 2-3월 중 RFP 작업 관여 및 지원 제안 예정 | P36: * 계약라인업 : KB국민은행 < SK쉴더스 < LG CNS
B37: 2025-034 | C37: 수어 | D37: 부천도시공사 | E37: 부천도시공사 | F37: 부천도시공사 수어번역서비스 제안 | G37: 함영민 | H37: 1 영업중 | J37: 2026년 | K37: - 발주금액 : 0.15억 | M37: N | N37: - ESG경영지표 충족의 일환으로 수어번역서비스 적용 검토(웹, 키오스크 대상) - 스포츠센터 4군데 정도 있고 1군데 시범 적용 후 차차 확산 예정 · 소사국민체육센터 로비 키오스크 PoC 중
B38: 2025-035 | C38: 수어 | D38: 남양주도시공사 | E38: 남양주도시공사 | F38: 남양주도시공사 수어번역서비스 제안 | G38: 함영민 | H38: 1 영업중 | J38: 2026년 | K38: - 발주금액 : 0.15억 | M38: N | N38: - 25년3월에 키오스크 CMS의 WEB 전환 진행이라 그 이후 수어번역서비스 검토 · 작년 경영평가 점수 다소 부족하여 수어번역서비스를 활용하면 개선에 도움될 것으로 공감 · 키오스크 수량 : 29대 (체육센터)
B39: 2025-036 | C39: 수어 | D39: 현대백화점 | E39: 에이치엘엠 | F39: 현대백화점 수어번역서비스 키오스크 적용 | G39: 함영민 | H39: 3 제안중 | J39: 2025년 | M39: N | N39: - 키오스크의 컨텐츠들은 대부분 도식화가 잘 갖추어져 있어서 수어 안내가 실용적이지 못할 것으로 예상 - 판교, 다산, 부산, 송도 지점들에 있는 미술관 제안 중 (2025.03.25 기준) - 4/3(수) 10시 현대백화점內 미술관(판교,다산,부산,송도)대상 수어서비스 제안 대면 미팅진행 ※ (주)스위트케이 한정현이사 동행
B40: 2025-037 | C40: 수어 | D40: 카카오뱅크 | E40: 본사영업 | F40: 카카오뱅크 AI수어상담 3D 아바타 및 영상제작 | G40: 양승구 | H40: 8 계약완료 | J40: 12월 혹은 2026년초 | M40: N | N40: (2025.09.24기준) - 카카오뱅크 수어영상에 실사형 리디자인 추가 협의 미팅 완료 : 9.24일(수) 10:00 ~11:30 판교 카뱅 사무실 L 기술적인 업무 협의 완료(레퍼런스 이미지 당사에서 작성 협의 완료), 구매팀 : 개발 기간 및 제안시의 단가로 조정 요청 L 구축 이후 문구의 수정 보안의 비용 여부 - 협의하여 조정 하겠음 L 구매팀 : 실사형 아바타 타 사업에 제한기간의 설정필요(딥페이크 독점사용 기간 : 1분기 또는 6개월 요청으로 예상), 타 업권은 제외 요청함 L 수정 견적서 발송(9.24일), 협의 완료시 : 10.17일 이전 예약 체결 예정 (2025.09.30기준) - 카카오뱅크 수어영상에 실사형 리디자인 추가 협의 및 계약금액 확정 L 1차 계약 : 44,100,000, 2차 계약 : 50,500,000 = 합계 94,600,000 예정 L 추가 범위 : 수어영상의 리디자인 작업 범위를 기존 사업수행 계획서 추가하여 10.1일까지 제출 요 (추석 전 품의 예정) L 추석 이후에 계약을 바로 진행 될 수 있도록 햠조 요청함 (2025.10.14기준) - 카카오뱅크 수어영상에 실사형 리디자인 계약서 상호 확인 완료 - 금주 계약 체결 예정 L 계약서는 1차의 추가 계약으로 진행(금액은 합산 금액 : 94,600,000 수정 계약) L 계약이행보증보험 증권 발행(총액 금액으로) (2025.10.23기준) - 카카오뱅크 수어영상에 실사형 리디자인 모델에 대한 레퍼런스 이미지 테스트본 공유 (가산 수어통역센터 10:00 ~!4:00) L 당사 농인분들과 인터뷰 진행 - 개선 요구 사항 접수(수어영상 이미지 표출, 위치조정, 영상에 대한 선택, 배경색, 보이스피싱 등의 의견 제시) L 레퍼런스 이미지에 대하여 고객사 만족, 이미지 모델 2 ~ 3개 선택 후 수어영상으로 제작 테스트 진행 | P40: 함영민 | Q40: * 수어번역서비스 설명회 및 업무 상담(2/19, with 대표님) - 모션인식을 통한 수어 양방향 소통 뱅킹서비스 계획 중 · 교보생명 사례 활용 농인 대상 카카오뱅킹 app에 핵심키워드 클릭 유도하여 질의 처리 후 수어 답변 제안 (질의 처리를 위한 핵심키워드 시나리오 기획 고민 예정) · 상세 상담의 경우 손말이음센터 혹은 전국 수어통역센터 연결 처리 대안 제시(개인정보인증 정책에 따름) · 제안 내용 검토 및 고민 후 올해말 혹은 내년초 사업 추진 예정 (2025.04.03 기준) - 카카오뱅크 Web/ App 수어서비스 진행에 따른 견적진행 완료 ※ 구축 방법에 따른 비용 (각각) * Web / App 2개 채널 이용 시 비용, App 1개 채널 이용 시 비용 * On-Premise 구축형과 SaaS 구독형 비용 - 예상 소요일정 : 4~5개월 - 4/4(금) 데모사이트 요청에 따라 KB저축은행 데모사이트 발송 (2025.04.11 기준) - 4/7(월) 카카오뱅크 담당자 3차 대면미팅 진행 - On-Premise구축형 견적 사항에 대해서는 이해되었으나, 클라우드 구독형에 대한 견적은 의문상태 ※ 당사 클라우드 구독형 가격정책 재정립 필요 [진행중] 4월 24일 기준 ※ 당사 표준 수어아바타 이슈 ※ 카카오뱅크 타 금융기관과의 차별화 이슈 ※ 카카오뱅크 Needs.. 독자적인 캐릭터 만들고자 하며, 금액은 2차 문제라고 함. ※ 차주중 고객 Needs사항에 대해 회신예정_SL사업본부와 소통완료 상태 (2025.05.07 기준) ※ 카카오뱅크 전용 신규 수어아바타 모델제작 견적 및 클라우드 구독형 재정립 견적서 발송완료 ※ 5/8(목) 카카오뱅크 유관부서 내부논의후 이슈사항 또는 확인사항 필요시 대면미팅요청 또는 서면질의 예정 L 신규 수어아바타 모델제작에 따른 기간 문제로 당사 표준 수어아바타 제작후 카카오뱅크에서 영상을 자체적으로 변경또는 커스텀요청을 해도 되는지 등.. 에 대한 서면질의 예정 (2025.05.16 기준) ※ 5/12(월) 카카오뱅크 현업담당자 미팅_with.안혜신팀장 L 아젠다 : On-Premise 구축시 SL-CMS 필요성 여부 및 SL-CMS와 FAQ 통합 재구축 논의 ※ 5/15(수) SL-CMS와 FAQ 통합 재구축 견적서 제출 L 견적분야 : FAQ & CMS 통합시스템 분야 / 카카오뱅크 전용 수어아바타 신규제작 분야 / 수어아바타 구성 및 검수외 분야 L 카카오뱅크 유관부서와 논의후 별도 연락 예정 ※ 경쟁사 : 이큐포올, 멀틱스 (2025.05.23 기준) - FAQ 및 CMS 통합 재구축관련 카카오뱅크 내부 논의 진행중 ※ 사업진행은 빠르면 6월말진행. 늦어도 7월초에는 진행할 것으로 예상(카카오뱅크 강영욱매니저 의견) ※ 현재 통합으로 갈지, 별도로 진행할지에 대해서는 카카오뱅크 유관부서에서 논의후 결과 도출 예정 ※ 요구사항 정의서 작성시 그간 얘기나왔던 전용 수어아바타 모델개발등 적용 예정 ※ 당사에서 과업지시서 작성 지원을 얘기하였으나, 카카오뱅크 내부에서 별도 작성후 궁금한 사항이 있으면 연라 주겠다 함. (2025.05.30 기준) - FAQ 및 CMS 통합 재구축관련 카카오뱅크 내부 논의 진행중(변동사항 없음) ※ 사업진행은 빠르면 6월말진행. 늦어도 7월초에는 진행할 것으로 예상(카카오뱅크 강영욱매니저 의견) ※ 당사에서 과업지시서 작성 지원을 얘기하였으나, 카카오뱅크 내부에서 별도 작성후 궁금한 사항이 있으면 연라 주겠다 함. | R40: (2025.06.04 기준) - FAQ 및 CMS 통합 재구축관련 카카오뱅크 내부 논의 결과 통합구축에서 분리입찰 잠정결론 ※ 분리과업 : 1) Web UI개발(카카오뱅크 내부 개발부서에서 진행) 2) FAQ Admin 개발(카카오뱅크 개발부서 내부논의후 별도 입찰 고민중 예정) 3) 카카오뱅크 전용 신규아바타 모델 적용+수어생성(입찰진행 예정) ※ 6월중 입찰예정 / 과업지시서는 카카오뱅크 내부에서 작성후 검증차원으로 사전 배포 예정 (2025.06.13 기준) - FAQ 및 CMS 통합 재구축관련 카카오뱅크 내부 논의 결과 통합구축에서 분리입찰 잠정결론 ※ 분리과업 : 1) Web UI개발(카카오뱅크 내부 개발부서에서 진행) 2) FAQ Admin 개발(카카오뱅크 개발부서 내부논의후 별도 입찰 고민중 예정) 3) 카카오뱅크 전용 신규아바타 모델 적용+수어생성(입찰진행 예정) ※ 차주 입찰공고 예정 : 카카오뱅크 홈페이지 입찰사이트 게시 L 사업범위 : 2) FAQ Admin개발과 3) 신규아바타+수어생성 2가지로 분리하여 입찰공고 L 공고기간 : 2~3주 예상 L 입찰예가 : 비공개 ※ 당사외 예상 참여사 확인불가상태(비공개)이며, 과업지시서 사전공개는 차주 월요일에 재확인예정(카카오뱅크 신진상팀장) ※ 당사 통합 견적가 : 4.18억(vat포함) (2025.06.19 기준) - 본 사업 및 타 시스템 예산편성 취합중으로 입찰공고 지연상태 ※ 공고 일정은 차차주(7월초) 예상(카카오뱅크 신진상팀장) L 입찰공고전 입찰 참여사에 과업지시서 공개 예정 (2025.06.26 기준) - 카카오뱅크 변경 현업 담당자 인사 및 구매팀 논의 완료 ※ 7월 cms개발 공고이후 8월 아바타(신규모델+문장생성) 공고 예정 L 아직까지 통합으로갈지 분리해서갈지 현업부서와 구매팀 협의 안됨. L 차주 사업방향 결정후 구매팀에서 연락주기로 함. L 통합으로 갈시 단일건으로 7월 공고로 완료 (2025.07.04 기준) - 카카오뱅크 AI수어상담 시스템 구축 사업 입찰공고 게시 ※ 세부일정(카뱅 내부사정에 의해 변경될 수 있음) 입찰공고 : 7/4(금) 제안서 접수 마감: 7/24(목) 16시까지 제안설명회 : 7/28(월) 예정 (카뱅 판교오피스) 우선협상대상자 선정 : 7/28(월) 예정 계약진행 : 8월內 (2025.07.10 기준) - 카카오뱅크 AI수어상담 시스템 구축 사업 입찰공고 게시 L 입찰공고 : 7/4(금) / 접수마감: 7/24(목) 16시까지 / 제안발표 : 7/28(월) 예정 / 업체선정 : 7/28(월) 예정 / 계약진행 : 8월內 L 이슈사항 : 제안요청서상의 투입인력 상주 원칙사항은 계약후 인력투입관련 현업부서와 논의 과정에서 상주/비상주 사항에 대해 논의가 될 수 있다고 함(카뱅 CS플랫폼기획팀 신진상팀장 의견) | S40: (2025.07.14 기준) - 카카오뱅크 AI수어상담 시스템 구축 사업 입찰공고 게시 L 입찰공고 : 7/4(금) / 접수마감: 7/24(목) 16시까지 / 제안발표 : 7/28(월) 예정 / 업체선정 : 7/28(월) 예정 / 계약진행 : 8월內 L 진행사항 : 아젠다 배포 및 장표별 담당부서 지정배포(유영복상무님) (2025.07.25 기준) - 카카오뱅크 AI수어상담 시스템 구축 사업 제안서 및 가격제안서 제출완료 L 제안 참여사 현황 : 비공개 ※ 이큐포올 : 1차 개발사업 불참(2차 카뱅표준 수어아바타 제작사업 준비중)_김준경 연구소장 확인 ※ 멀틱스 : 1차 개발사업 참여에 대해 명확하지 않음(2차 카뱅표준 수어아바타 제작사업 준비중)_백종민 영업팀장 확인 L 제안설명회 확정 : ※ 일 정 : '25.07.29(화) 10:30 ~ 11:20 (발표 30분 / Q&A 20분) ※ 장 소 : 발표 10분전 까지 "카카오뱅크 판교오피스 15층" 대기후 → 발표장소 13층으로 이동 ※ 평가위원 : 5명 ※ 참석인원 : 정상욱부장(PM), 안혜신팀장(PL), 김종화대표, 심재홍이사(총4명) (2025.07.30 기준) - 1차사업 : AI수어상담 시스템 구축 사업 제안 / 미선정 L 제안 참여사 현황 : 4개사 중 당사 2위 ※ 카카오뱅크 CS플렛폼기획팀 신진상팀장 확인 L 미선정 사유 : 솔루션 패키지 커스터마이징 제안 매우만족. 금액제안은 경쟁 3개사 대비 당사가 매우(?) 높아서 미선정 사유가 됨. ※ 카카오뱅크 CS플렛폼기획팀 연경은 매니저 확인_평가위원 참여 - 2차사업 "카카오뱅크 표준 수어아바타 제작 및 FAQ 수어번역 아바타 제작사업" L 차주 입찰공고 게시 예정 / 공고시 공유예정 L 경쟁사 이큐포올 및 멀틱스 제안참여 확실 ※ 이큐포올(김준경이사 확인), 멀틱스(백종민팀장 확인) (2025.08.04 기준) - 2차사업 : AI수어 상담 3D 아바타 및 영상제작 사업 ■ 주요 추진 일정 1. 입찰참가마감일: 2025년 8월 20일 16시까지 2. 제안서 및 입찰서 제출 마감: 2025년 8월 20일 16시까지 (입찰참가마감일과동일) 3. 제안서 평가일: 2025년 8월 21일 (예정) 4. 우선협상대상자 지정: 2025년 8월 21일 (예정) 5. 기술협상 및 가격협상: 협상대상자 지정 통보일 익일 6. 계약 체결: 2025년 9월 중 ■ 카카오뱅크 전용 수어아바타 샘플 영상 제공(5페이지 3.1 제안 방법 개요 참조) ※ 3.1.2 사업 수행 능력 평가를 위하여 아바타 샘플 영상을 필수로 제공해야 함 ★ 제안한 3D 아바타를 사용한 5초 내외의 영상 1 Copy 이상 필수 제출 ■ 8/5(화) 당사 확인 요청사항(CS플랫폼 기획팀 신진상팀장) ☞ 아바타 3D모션데이터 제공해줄수 있는지? ※ 사유 : 아바타 3D모션데이터 요청사항은 향후 카카오뱅크에서 자체내 아바타 리터치(비쥬얼적인 부분) 작업을 위해 문의하는 사항임. ※ 현재 위의 질문에 대해 "당사에서 수어아바타 영상을 제공하면서 3D모션데이터까지 제공해준 사례는 없는 상태"라고 하였으나, ※ 제안발표 평가시 위의 질문이 나올 것으로 예상됨(답변준비 필요) | T40: (2025.08.14 기준) - 2차사업 : AI수어 상담 3D 아바타 및 영상제작 사업 ■ 주요 추진 일정 1. 입찰참가마감일: 2025년 8월 20일 16시까지 2. 제안서 및 입찰서 제출 마감: 2025년 8월 20일 16시까지 (입찰참가 마감일과 동일) 3. 제안서 평가일: 2025년 8월 21일 (예정) 4. 우선협상대상자 지정: 2025년 8월 21일 (예정) 5. 기술협상 및 가격협상: 협상대상자 지정 통보일 익일 6. 계약 체결: 2025년 9월 중 L 제안서 작성 중. 취합(~8/14), 08/18(월) 리뷰 예정 L 카카오뱅크 전용 수어아바타 샘플 영상 제공 방안 검토중 (2025.08.21 기준) - 2차사업 : AI수어 상담 3D 아바타 및 영상제작 사업 ※ 8/21(목) 제안서 평가진행 (경쟁사 : 이큐포올, 멀틱스) ※ 8/21(목) 케이엘큐브 우선협상대상자 선정 ※ 8/22(금) 기술협상진행_하윤호이사외 (2025.08.28 기준) - 8/28(목) 사업수행계획서 제출완료(카카오뱅크 구매팀) ※ 사업수행계획서는 구매팀에서 현업부서인 CS플랫폼기획팀에 전달완료(구매팀 김재현 매니저 확인) ※ 현업부서에서 사업수행계획서상의 문제점이 없으면 차주중 바로 계약진행 예정 ※ 카카오뱅크 영업담당자 변경 심재홍 → 양승구이사 / 고객처 인수인계중 (2025.08.28기준) - 카카오뱅크에서 계약서 초안 발송으로 계약서 검토 진행 L 1차 경영기획팀에서 계약서 검토 후 카카오에 전송 예정 L 주요변경 사항 요청 사항 : " 손해배상의 한도를 계약금액의 총액으로 명기 요청" --> 카카오내부에서 확인 후 답변 받아서 수정 예정 L 계약서 수정 완료 및 상호 검토 완료 후에, 가능한 9.1 ~ 2일 중으로 계약체결 예정 (2025.09.04기준) - 카카오뱅크 내부에서 계약서 등기 발송 예정(09.05 예정) L 내부 결재 지연으로 25.09.05일 계약서 카카오뱅크 직인 후 등기 발송 예정 L 계약서 등기 접수 후(09/09 예정) - 케이엘큐브 직인 후에 계약이행보증보험증권, 인감증명서와 같이 등기 발송 요청 (2025.09.10기준) - 카카오뱅크 계약 체결 완료 (09.08자) L 계약서 등기 접수 후(09/09 완료) - 케이엘큐브 직인 후에 계약이행보증보험증권, 인감증명서와 같이 등기 발송 완료(9.10) L 대금지급 : 프로젝트 검수 후 100% 지급 (검수 후 7일 이내 계산서 발행) (2025.09.11기준) - 카카오뱅크 수어영상에 실사형 리디자인 요청에 따른 협의(9.11일 카뱅 여의도 14:00 진행) L 기존 영상을 실사 기반의 리디자인 진행으로 협의 - 기술지원 및 문서공유 : 카뱅, 개발 : 공동 진행 L 협의 사항 : 1. 당사 GPU 서버 사용으로 공동 개발, 2. 당사의 수어통역사 및 청각장애인과의 간담회 및 테스트 시 의견 청취 L 계약은 추가 신규 계약으로 진행 - (1차 견적: 87백만원 , 2차 수정 요청 견적 : 72백만원 수정 제시 --> 비상주 조건) L 시스템의 실사형 기반의 리디자인 오픈은 기존 프로젝트와 동일하게 OPEN(25.12월) (2025.09.18기준) - 카카오뱅크 수어영상에 실사형 리디자인 추가 협의(9.24일(수) 카뱅 여의도 14:00 진행) L 기술적인 업무 협의 완료 하였고, 구매팀과 AI기술 이전, 라이선스, 비용에 대한 협의 L 카뱅 : CS플랫폼 기획팀, 구매팀, 당사 : 영업, 수어데이타 연구팀, 수행팀 참석 예정
B41: 2025-038 | C41: 수어 | D41: 웅진씽크빅 | E41: 웅진씽크빅 | F41: 웅진씽크빅 디지털교과서 수어번역서비스 제안 | G41: 함영민 | H41: 1 영업중 | J41: ? | M41: N | N41: - 수학 샘플데이터 수신(해설지, 해설 영상 및 스크립트) · 수학 교육에 대해 현실적으로 수어번역서비스 적합 유무 검토 필요 -> 적합 시 수학 학습데이터 준비 방안 및 구축 시간과 비용 등 제안 준비
B42: 2025-039 | C42: 수어 | D42: KB저축은행 | E42: LG CNS | F42: KB저축은행 수어번역서비스 적용 | G42: 함영민 | H42: 1 영업중 | J42: ? | M42: N | N42: - KB저축은행용 수어번역서비스 데모 시연 · 우선순위 타프로젝트들의 수행으로 수어번역서비스는 중장기적으로 시간을 두고 도입 검토 예정 (단독 사업으로 검토는 어려우며 타 프로젝트에 포함시켜 검토 예정)
B43: 2025-040 | C43: 수어 | D43: KB국민카드 | E43: LG CNS | F43: KB국민카드 수어번역서비스 | G43: 함영민 | H43: 1 영업중 | J43: ? | M43: N | N43: - 수어번역서비스 기본 소개 및 데모 시연 · 정보보호부 부장을 컨택하였고 유관 부서인 소비자보호부로 전달하여 지속 영업활동 예정(LG CNS)
B44: 2025-041 | C44: 수어 | D44: BGF네트웍스 | E44: BGF네트웍스 | F44: CU 편의점 모바일앱 수어번역서비스 | G44: 함영민 | H44: 1 영업중 | J44: ? | M44: N | N44: - 편의점 CU앱에 장차법 대응 수어번역서비스 제품 소개 및 관련 법령 안내 - 모바일 상품권 등 타 프로젝트 우선순위로 장차법 대응 잠정적보류(지속적인 모니터링으로 사업기회 확인)
B45: 2025-042 | C45: 수어 | D45: 연구개발특구진흥재단 | E45: 연구개발특구진흥재단 | F45: 연구개발특구진흥재단 수어번역서비스 | G45: 함영민 | H45: 1 영업중 | J45: 2025년 | K45: - 발주금액 : 0.1억 | M45: N | N45: - 홈페이지 기관 소개용 수어 3D 아바타 영상만 도입 검토 · 도입 검토 결과 차후 본사업으로 입찰 공고 예정(시스템 구축 방식 미정) - 추가 정보 수집 후 2025년 입찰 준비 예정(지속적인 모니터링으로 사업기회 확인)
B46: 2025-043 | C46: 수어 | D46: 식품안전정보원 | E46: 식품안전정보원 | F46: 식품안전정보원 홈페이지 기본 안내 설명 수어 자막 서비스 | G46: 함영민 | H46: 2 견적제출 | J46: ? | M46: N | N46: - 수어서비스 라이선스 구축형과 영상 도입 방식 견적 제출 - 정보 수집 단계이며 구체적인 사업계획은 없고 미팅도 불필요하다고 함(지속적인 모니터링으로 사업기회 확인)
B47: 2025-044 | C47: 수어 | D47: S&I코퍼레이션 | E47: S&I코퍼레이션 | F47: 건물관리 분야 수어번역서비스 보급 확산 | G47: 임철현 | H47: 1 영업중 | J47: ? | M47: N | N47: - 실무진은 협력 사업기회발굴에 긍정적인 느낌을 가지고 있으나 경영진은 법적 강제성이 취약한 부분으로 인한 보급 확산이 쉽지 않을 것으로 보고 있음 - 베리어프리 키오스크와 번들로 판매하려니 베리어프리 키오스크가 고가라 제안하기 어려운 느낌이 있음 - 중장기적 협력 사업기회발굴 예정 (2025.10.20) - 업무담당자 변경(심재홍 -> 임철현)에 따른 담당자 확인 및 방문일정 협의 예정
B48: 2025-045 | C48: 수어 | D48: 서울의료원 | E48: 서울시 원무팀 | F48: 2025년 테스트베드 서울 실증 지원사업(서울의료원) | G48: 임철현 | H48: 7 수주완료 | J48: =200000000/1.1 -> 1.8181818e+08 | M48: N | N48: (2025.07.08기준) - 7/10(목) 발표자료 PMS 등록 완료 - 7/15(화) 발표평가 13:00 ~ 13:35(발표 15분, 질의응답 20분) L 서울의료원 기획경영실 이미현팀장 섭외완료 및 발표평가 참석 (2025.09.02기준) - 2025년 테스트베드 서울 실증 지원사업_서울의료원 최종 선정 L 향후일정 : 협약 일정 및 제출 서류 작업 진행중(전략기획실 사업기획팀) L 서울의료원 기획경영실 이미현팀장 실증사업 최종선정관련 통보(완료) ※ 이미현팀장 요청사항 : 향후 일정계획 및 사업 진행관련 미팅 요청 ※ 당사와 서울경제진흥원간 협약 및 행정절차 완료이후 방문예정사항 이미현팀장께 전달 완료 (2025.09.17 기준) - 2025년 테스트베드 서울 실증 지원사업_서울의료원 최종 선정 L 9/19(금) 오전 10시 / 서울의료원 기획경영팀 + 원무과 팀장외 미팅(예정) ※ 향후 진행사항 브리핑 및 협약 날인 ※ 방문자 김종화대표님, 정상욱부장원 ※ 9/19(금) 미팅상황은 9/22(월) 주간보고시 공유예정 (2025.10.16 기준) - 10.14. SBA로 부터 협약관련 추가 보완 요청에 따라 고윤창팀장이 보완자료 준비 후 제출한 뒤 협약체결 진행예상됨 - 10.15. 키오스크관련 배리어프리 키오스크 전문업체(케어랩스)와 업무 미팅 진행 함, 차주까지 키오스크 견적 및 의료분야 협업BM 만들기로 함 - 10.16. 정상욱부장 경유 서울의료원과 차주 중 초도미팅 일정 협의 중, 초도 미팅 이후 협약체결 후 킥오프 진행 추진코자 함 (2025.10.25 기준) - 원무과 윤혜영팀장, 박주연차장, 박재라담당/ KL큐브 정상욱, 임철현, 백승준, 김해밝음 L 배리어프리키오스크, 발급기, QR관련 미팅 진행 및 설치 위치관련 현지실사 진행 L 배리어프리키오스크 설치 이후 유지보수 등을 위해 기존 공급사(헬스케넥트-포씨게이트) 장비와 동일 형식 장비 공급 선호 함 L 당사 솔루션 구독형관련 실증기관 종료('26.09.14)이후 3개월 무상지원에 대한 계획서 상 언급 있으며 이에 대해 재검토 요청 접수 L 발급기 관련해서는 양사간 내부 협의후 재미팅시 합의점 찾기로 함, QR설치위치에 대해선 운무팀 내부 재협의 후 얘기나누기로 함 (2025.11.03 기준) - 매출관련 경영지원실과 협의 / 전체 매출 중 자부담금 제외 한 금액(2억원, VAT포함)으로 산정 (2025.11.11 기준) - 업무미팅(윤혜영팀장, 박주연차장, 박재라담당, KL 정상욱, 임철현, 백승준) L 수행일정관련 업무협의, 실증관련 배리어프리키오스크1, 발급기3, QR관련 협의 --> 발급기관련 1대(2층 건강검진센터)에 대해 안내형 전환요청/ 예산문제로 변경어려움 설명, 발급기로 공급하나 안내형으로 제공가능한지 내부 검토 후 재협의 하기로 함 L 과제완료후 유지보수: 1. 키오스크는 제조사 유지보수 정책(3년 또는 1년) 준용, 키오스크 탑재 SW는 12개월 무상 유지보수 2. 모바일 핸드사인버스(SaaS) 입점은 '26년 10월 부터 월 50만원 비용 발생 안내, -> 관련 세부사항은 추후 재협의 하기로 함 (25.12.11) 배리어프리키오스크(안내형) 및 발급기용 키오스크 견적 수령 - 엘토브, 포씨게이트 L 금액비교 및 개발팀, 수행팀 협의 후 제품 선정 진행 필요 (25.12.18) 발급기용 키오스크 견적 요청 및 발급시스템 개발소스 제공받기 위한 '비밀유지서약서' 제공요청 L 발급기용 키오스크 대당 금액 2벡만원 이내 확인 진행 중 L 키오스크 전략적 협업관련 포씨에스 대표이사 미팅건 협의 중 (25.12.30) 과제관련 시스템 도입 및 과제이후 유지보수 예산배정관련 견적 제공 L 내부 보고 시급성으로 인하여 선 견적작업 진행 함. 기존 키오스크(안내형1, 발급기3)기준 월 70만원 이상 배정시 예산확보 어려움 L SaaS기반 구독형 핸드사인 톡톡 4ea(안내형 1, 발급기3) 제안 및 3년 약정 기준 추가 할인적용 월 84만원으로 제안 함 -> 내부 보고후 재협의 예정 L 발급기 키오스크관련 포시게이트와 금액 조율 진행, 기존 발급기 서울의료원 대당 7백만원 규모 제안으로 당사에 350만원이하 제공 불가 기술지원서비스관련 비용도 추가 네고 어렵다고 함, 타 키오스크 도입에 대해 검토 필요 및 기술지원서비스관련 자체 진행가능여부 판단 필요 (26.01.02) 과제관련 당사 핸드사인톡톡 조달청'혁신제품' 선정 및 유지보수 금액관련 협의, 의료원 내부 보고관련 사전 협의 및 관련 견적서(비교) 2부 제공 완료 (26.01.07) 과제관련 키오스크(배리어프리 안내형 1식, 발급기 3식)관련 내부 사전 품의 완료 - 배리어프리 안내형 1식 키오스크 -> 엘토브 43인치 스탠드형 BF인증 키오스크 선정 - 발급기 3식 키오스그 -> 포시케이트 21.5인치 발급기 3식 선정, 발급시스템 연동관련 금액 조정 협의 중 | Q48: [진행중]4/24(목)기준 ※ 제안서 시스템 상 제출 완료(04.17) ※ 6월 중 지원규모의 1.3배수 내외 발표평가 진행 예정 (2025.05.28기준) ※ 서울형 R&D 테스트배드 실증사업 1차 통과 / 1차 통과에 따른 최유나주무관께 공유 완료_대표님 ※ 발표평가 대비 실증기관 자격, 자격적합성, 연구중복성, 제재사항 조회, 실증기관의 수용 불수용 여부등 확인후 7월 초순 발표평가 진행 예정 (2025.06.05기준) ※ 서울형 R&D 테스트배드 실증사업관련 차주 서울시 복지실 장애인자립지원과 이계원팀장, 최유나주무관 대면미팅 진행 예정_with.대표님 L 6/10(화) or 6/12(목)중 서울시청 담당자 일정확인후 당사로 통보예정 (2025.06.12기준) - 기관 사업부서 변경 : L 복지실 장애인자립지원과 에서 "홍보기획관 민원실" L 서울시청 1층 관리주체 : 인포메이션(행정국 총무과), 민원실(홍보기획관 민원과) L 6.12(목) 홍보기획관 민원실 본 사업관련 논의진행중 ※ 기존 순번대기표 키오스크 사후관리사 "S/W (주)픽넘버" "H/W (주)포스뱅크" ※ 민원실 이슈사항 : 1층 구역별 관리주체가 달라 향후 장비 사후관리 문제 및 실증사업 1년이후 처리방안 고민중 L'26년 민원실 배리어프리 예산 반영중 / 중복사업에 대한 우려 고민중 (2025.06.18기준) - 당초 실증사업을 서울시청(인포메이션, 민원실)에서 서울의료원으로 변경 L 변경사유 : 서울시청 행정국 총무국 및 홍보기획관 민원과에서 "불수용"통보 (개인정보보호문제) L 6/18(수) 서울의료원 내부논의후 "수용"으로 서울시청 경제정책과 혁신기술팀 공문접수 완료 및 서울경제진흥원 통보 완료(23일(월) 시스템 확인예정) L 서울시청 경제정책과 혁신기술팀 김혜선주무관께서 발표장표에 실증기관 변경에 따른 사유를 명시하면 좋겠다고 함. L 본 사업 서울의료원 담당부서 변경(의료사회복지팀 → 기획팀+홍보팀) L 차주 서울의료원 기획팀외 관련부서 대상 사업진행 브리핑요청(일정확인중) (2025.06.27기준) - 최종 발표평가대상 선정완료 L 1. 접수번호 : TE250095로 최종 발표평가 대상으로 선정 2. 실증기관 : 서울특별시 서울의료원 기획경영팀 3. 발표자료 제출일 : 7월10일(목) 18시 마감(PMS 등록) 4. 평가시간 : 7월 15일(화) 13:00 ~ 13:35. 발표 15분, 질의응답 20분 ※ 실증기관 담당자 참석 시 실증 필요성 발언 가능 5. 발표장소 : 서울경제진흥원 본사(마포구 월드컵북로 400) - 7/1(화) am10시 서울의료원 기획경영팀외 미팅확정 L 당사 실증사업 컨셉발표 및 서울의료원 Needs파악차 방문 L 고객측 정확한 Needs파악을 위해 사업지원팀 김태형팀장or고윤창부장 동행예정 | R48: (2025.3.18 기준) - 서울시 내부 상부의 지시에 의한 장애인 편의증진을 위한 AI기술 정보 수집중 - [1차미팅] 서울시 복지실 장애인자립지원과 이계원팀장, 최유나주무관 대면미팅 진행 ※ 수어서비스 적용에 대한 제안중 농인,상담사,수어통역센터 3자통화 앱 개발 사업에 대한 관심을 보이며, 자료요청 및 발송(3/20) ※ 사업추진 방향 : 서울경제진흥원 "2025년도 서울형 R&D 지원사업"을 서울시 도움을 받아 노원구 보건소를 실증기관으로 지정 요청예정 ※ 차주 장애인자립지원과 2차 대면미팅 예정 → 미팅일정 픽스전 (2025.3.24 기준) - [2차미팅] 서울시 복지실 장애인자립지원과 이계원팀장, 최유나주무관 대면미팅 진행 ※ 1차 제출 자료에 대해 윗선 보고자료로 보완요청 * 1안) 보건소 무장애서비스 * 2안) 서울시청 민원실 대상 시각,청각장애인 위한 무장애서비스 ※ 보건소 대상으로 진행시 "서울시 복지시 장애인자립지원과"의 협업에 대한 업무 롤이 없는것에 대한 의견 (2025.04.02 기준) - [2차미팅] 서울시 복지실 장애인자립지원과 이계원팀장, 최유나주무관 대면미팅 진행 ※ 1차 제출 자료에 대해 복지실 과장 보고자료로 보완 제출 * 1안) 보건소 무장애서비스 * 2안) 서울시청 민원실 대상 시각,청각장애인 위한 무장애서비스 ※ 2025년도 서울형 R&D 지원사업 "2안" 확정 (2025.04.11기준) - 서울시청 열린민원실 및 안내데스크 실증계획서 1차리뷰(04/11) - 4/15(화) 실증계획서 설명차 서울시 복지실 장애인자립지원과 이계원팀장, 최유나주무관 대면미팅(예정) (2025.04.15기준) ※ 서울형 R&D 테스트배드 실증사업 자료(초안) 서울시청 복지정책실 이계원팀장, 최유나주무관 검토 완료 ※ 4/17(목) 테스트배드 실증 제안자료 SBA(서울경제진흥원)제출 완료
B49: 2025-046 | C49: 수어 | D49: 롯데백화점 | E49: 엘토브 | F49: 롯데백화점 기존 매장안내 키오스크 수어서비스 업그레이드 사업 | G49: 오민규 | H49: 2 견적제출 | K49: 사업금액 : 0.44억 | M49: N | N49: (2025.3.24 기준) - 롯데백화점 기존 매장 키오스크 83대 대상 수어서비스 적용 업그레이드 예산 작업중 - 적용범위 : 400문장 기준 / 키오스크 대당 라이센스 20만원 적용 ※ 예산작업 중이라 수어서비스 적용여부는 예산배정이 확정되어야 알수있는 관계로 관망상태 ※ 2025.11.27 담당자 변경 심재홍 → 오민규
B50: 2025-047 | C50: 수어 | D50: NH농협은행 | E50: SK쉴더스 | F50: NH농협은행 창구혁신 운영을 위한 수어서비스 | G50: 양승구 | H50: 8 계약완료 | J50: 미정 | K50: - 사업금액 : 18,050,000원(vat제외) | M50: N | N50: (2025.06.05 기준) - NH농협은행 내부 결재 진행중 L 구매예산 확정된 상태이며, 차주중 계약진행 예정 L 수어아바타 제작을 위한 스크립트 30문장은 작성된 상태이며, 계약진행시 당사 배포예정 (2025.06.12 기준) - 차주 계약진행 예정 L 견적금액중 구매부서 내고 5% 감안 예정 L 전략기획실 요청사항 : 수어컨텐츠 제작금액 보다 수어플레이어 제작 금액이 70%비중을 감안하여 수어플레이어 퀄리티 상향필요(인스톨버젼) (2025.06.16 기준) - 견적금액 내고 없이 원금액 발주서 접수 완료 L NH농협은행은 수의계약시 별도의 계약없이 발주서로 대처함. (2025.06.24기준) - 고객 발주에 따른 내부 사업진행에 따른 협의진행 L 로컬 수어플레이어 제작에 따른 직접개발 or 외주제작 or 개발분야 취소 = 결정필요 (2025.07.08기준) - NH농협은행 각 지점별 청각장애인을 위한 수어콘텐츠 활용 홍보진행중 L 7/15(화)까지 수어콘텐츠 및 수어플레이어 납품 要請 (2025.07.15기준) - 수어콘텐츠 및 수어플레이어 최종 납품완료 L 납품사항에 대한 고객이슈 없음 L 향후 비슷한 상황의 고객처 이슈대비 수어플레이어 업그레이드 필요해 보임 ※ 특히, 플레이어기능(고대비,배속,투명/반투명 추가 및 문장별 하드코딩 사항 등 (2025.09.30기준) - 수어문장 추가 요청 (기존 : 17, 추가 : 13 = 총 30개 운영 예쩡) L 추석 이후에 제공 될 수 있도록 협의 예정(10.1일) L 플레이어도 13개 추가된 플레이어 제공(고대비,배속,투명/반투명 추가 및 문장별 하드코딩 사항 등) -> 버젼관리 필요 ※ 2025.11.27 담당자 변경 심재홍 → 양승구 | Q50: (2025.04.16 기준) - SK쉴더스 프리세일즈 영업라인을 통해 NH농협은행 프로세스혁신부 김용환부장 및 심필남팀장(창구혁신운영팀) 초도미팅 진행 ※ 타 금융권 수어적용 사례 및 금융권 수어적용 필요성에 대한 어필 ※ 4/17(목) 담당 부장 및 팀장께 "청각장애인을 위한 NH농협은행 수어서비스 제언서" 및 "청각장애인의 은행 서비스 개선을 위한 FGI결과 보고서" 제출완료 ※ 4/18(금) 금융권 창구에서 테블릿을 이용한 수어서비스 레퍼런스 문의 및 IBK기업은행 실시간 화상상담 완료시점등 문의에 대한 대응진행 [심필남팀장 문의] ※ [내부미팅] 4/22(화) 10시반 SK쉴더스 정철진수석 및 이재문상무 NH농협은행 영업사항 논의차 당사 방문예정 (2025.04.24 기준) ※ SK쉴더스 정철진수석 및 이재문상무 NH농협은행 영업사항 논의(완료) ※ 우리은행 명분자료 추가 요청중(고윤창부장 대응중) (2025.05.08 기준) ※ 전국 16개지점 대상 수어 시범서비스 진행예정 ※ 본 사업 담당부서인 "프로세스혁신부 창구혁신운영팀"과 NH농협은행 전산센터와의 업무협조 불가상태 ※ 시범서비스는 16개 각 지점별 창구담당자 PC에서 로컬로 수어컨텐츠 포팅후 필요시 영상송출하는 방식으로 서비스 제공 예정 ※ 5/8(목) 구축형 및 구독형 견적서 발송완료 / NH농협은행 내부 검토후 별도연락 예정 L 견적서상 지점별 수어컨텐츠 저작권 라이선스 책정에 대해 재검토 요청상태 L 지점별 수어컨텐츠 저작권 라인선스 책정시 전국 1000여개 지점에 적용해야 하는 부담으로 사업 못할수 있다는 입장 (2025.05.14 기준) ※ 5/14(수) 수의계약범위 내 견적요청 L 기본 30문장 범위 ※ 5/16(금) 기본 30문장 및 수어아바타 플레이어 개발분야 적용 견적제출 L 내부 결재의 복잡성으로 늦어도 6월말까지는 계약 및 발주진행 예정 (2025.05.29 기준) - 5/27(화) NH농협은행 내부 결재 진행중 ※ 늦어도 6월말까지는 계약 및 발주진행 예정사항은 지난주와 변동사항 없음
B51: 2025-048 | C51: 수어 | D51: IBK기업은행 | E51: LG CNS&에이텍에이피 | F51: IBK기업은행 화상상담시스템 구축 및 디지털데스크 도입 사업 | G51: 양승구 | H51: 8 계약완료 | J51: 45667 | K51: - 발주금액 : 0.088억 | M51: N | N51: - 견적서 발송(0.088억) - 1/10 발주 - 전체 계약기간 : 2024. 12. 04 ~ 2025. 06. 17 - 2/27 번역 대상 문장 1차본 수령 - 3/17까지 50문장 1차본 완료 예정(3월말까지 연장해 둔 상태) · 3월말 연구소 심다은 과장에게 완료본 수령하여 에이텍에이피 김지호 책임에게 전달(이메일 발송 시 LG CNS 류진걸 책임 항상 참조) - 아바타 케릭터 : 여성(자켓&Y셔츠 - 검정색&회색) / 아바타 사이즈 : 교보생명과 동일 / - 4/29 시범오픈(4월초 정도까지 제작 및 테스트 완료) - 5/13 대고객 오픈 - 6월 중순 안정화 완료 및 종료 - 6월말 : 대금결제 예정(세금계산서 발행일 확인 - 매출계산서 역발행 여부 확인) (2025.05.14 기준) ※ 5/14(수) 수어제작 2차 54건 요청중 L 6/2(월) 대고객 오픈으로 2차 54건에 대한 빠른 제작요청중 L에이텍 담당자측에는 6/2(월)까지 노력은 하겠으나 6/13(금)까지 가능예상 통보 L 짧은 제작기간으로 수어제작과 동시에 순차적으로 발송하는 방식으로 진행 통보 (2025.05.30 기준) - 6/2(월) IBK기업은행 대고객 오픈 진행(시흥점, 과천점, 김포점) L 화상상담 오픈 진행시 기 제출 1차 수어아바타로 진행 / 2차분 수어아바타는 안정화 기간동안 적용 예정 ※ 2차 수어제작분 순차적OR일괄적 배포시점 명확화하여 에이텍에 일정공유 필요 (2025.06.04 기준) - 전체 100문장중 2차분 54문장 최종본 에이텍 발송완료 - IBK기업은행(과천점) 고객 오픈 행사 완료에 따른 레퍼런스 사이트 방문예정 L 에이텍측에서 디지털 데스크 오픈에 따른 기사송출 예정 (2025.06.13 기준) - 사업완료에 따른 치주 LGCNS 청구절차 진행 예정 L 절차 : 케이엘큐브 -> LGCNS -> 에이텍 -> LGCNS -> 케이엘큐브(계산서발행) L LGCNS 류진걸팀장 공유 완료 (2025.06.19 기준) - 사업완료에 따른 주주 LGCNS 청구절차 진행 예정이였으나 LGCNS에서 에이텍에 사업완료 미확인상태 L 계산서 발행과 관련하여 차주 LGCNS 류진걸팀장 별도 연락주기로 함. (2025.06.27 기준) - 사업완료에 따른 차주 LGCNS 청구절차 진행 L 차주 검수확인서 확인후 계산서 발행예정 ※ 2025.11.27 담당자 변경 심재홍 → 양승구
B52: 2025-049 | C52: 수어 | D52: 서울시 | E52: 서울시 | F52: 서울시청 장애인편의증진팀 협업사업 발굴 영업진행 | G52: 양승구 | H52: 3 제안중 | M52: N | N52: (2025.07.29기준) - 서울시청 장애인편의증진팀 향후 실증사업 논의 미팅 L 일시 : 8/4(월) 15시~ L 미팅목적 : 2025년 테스트베드 서울 실증 지원사업 서울의료원과의 진행사항 공유 및 향후 서울시청 장애인편의증진팀과의 실증사업 진행 논의 L 참석자 : 장애인편의증진팀 이계원팀장 / 최유나주무관 후임 주무관 참석 (2025.08.04기준) - 8/4(월) 서울시청 장애인편의증진팀 향후 실증사업 논의 미팅 완료 L 참석자 : 장애인편의증진팀 이계원팀장 / 박진수주무관(최유나주무관 후임) L 논의사항 : 서울시청 장애인편의증진팀과의 협업사업 계획안 2가지 버젼으로 차주 제출예정 ※ '26년 본 예산 진행은 어려운 상태. '26년 추경사업으로 검토 예정 (2025.08.14기준) - 8/4(월) 서울시청 장애인편의증진팀 향후 실증사업 논의 미팅 완료 L 참석자 : 장애인편의증진팀 이계원팀장 / 박진수주무관(최유나주무관 후임) L 논의사항 : 서울시청 장애인편의증진팀과의 협업사업 계획안 2가지 버젼으로 제출완료 L 청각장애인을 위한 수어통역서비스 시범구축 계획(안) 제출 1안: 의료원 1곳 시범구축. 2안: SaaS기반의 클라우드 서비스 26개 기관 단계별 구축 L 8/18(월) 10시 장애인편의증진팀 미팅 예정_with.대표님 (2025.08.18기준) - 서울시청 장애인편의증진팀 2차 미팅 완료 L 참석자 : 장애인편의증진팀 이계원팀장 / 박진수주무관 L 논의사항 : 3자 화상통화 서비스 제안 및 서울시청 홈페이지 수어서비스 적용 논의 ※ 3자 화상통화 서비스는 현재 꼭 필요한 서비스가 아니라는 의견 ※ 시범적으로 홈페이지 카테고리별 수어적용후 향후 확대 (2025.08.28기준) - 서울시 대표 홈페이지 수어서비스 적용 시범사업을 위한 1차 자료제출 완료 L 1차 대표 홈페이지 103개 카테고리별 대표메뉴 및 서브메뉴까지 수어아바타 적용 L 2차 모바일 페이지 진행 L 3차 전체 페이지 확대 제안예정 ※ 반응형 웹으로 제작된 것으로 판단되며, 홈페이지 적용시 홈페이지 구축사와 수어서비스 적용에 대한 기술적 논의가 필요 함. ※ 서울시청 담당주무관 및 팀장 검토후 차주 대면미팅(필요시)요청 예정 (2025.09.04기준) - 서울시 대표 홈페이지 수어서비스 적용 시범사업을 위한 1차 자료제출 완료 L 1차 대표 홈페이지 103개 카테고리별 대표메뉴 및 서브메뉴까지 수어아바타 적용 ※ 서울시청 담당주무관 및 팀장 검토진행중이며, 예산문제 및 수어적용관련 유관부서와의 협의등 절차가 많이 남은 상태고, 추후 대면미팅 필요시 요청하겠다 함. (2025.09.17 기준) - 서울시 대표 홈페이지 수어서비스 적용 시범사업을 위한 2차 자료제출 완료 L 9/17(수) 1차 견적에대해 서울시 대표홈페이지 카테고리 변경으로 인해 2차 문장 견적요청 ※ 요청사항에 대한 견적서 발송 완료 및 추석전 영업대표 변경에 따른 방문예정 ※ 방문자 심재홍이사, 오민규부장 ※ 10월 초순경 서울시 홈페이지 PoC 적용 가능성 80%(예산배정 실패지 '26년 진행) 단, 2차 견적서는 "수의계약" 범위내 발송 ※ 2025.11.27 담당자 변경 심재홍 → 양승구
B53: 2025-050 | C53: 수어 | D53: 국립국악원 | E53: 국립국악원 | F53: 국립국악원 국악 아카이브 포털 및 공연 영상자료 수어서비스 적용 제안 | G53: 오민규 | H53: 3 제안중 | M53: N | N53: (2025.05.28 기준) - [인바운드] 국립국악원 국악 아카이브 포털(홈페이지 포함) 및 공연 영상자료 수어서비스 적용 대응 ※ 수어서비스에 대한 순차적 적용 제안 L 1차(초기) : 국악 아카이브 포털 및 홈페이지(기본 100문장 진행) 및 7개 공연 영상(5분 분량) 영상당 10문장 = 70문장 L 2차(확대) : SL-CMS도입 OR 클라우드 서비스 적용 ※ 위의 제안의 기반으로 국립국악원 내부 검토중 ※ 2025.11.27 담당자 변경 심재홍 → 오민규
B54: 2025-051 | C54: 수어 | D54: 토스뱅크 | E54: (주)브리지텍 | F54: (주)브리지텍_토스뱅크 콜 인프라 재구축 사업중 수어서비스 추가제안 | G54: 오민규 | H54: 3 제안중 | M54: N | N54: (2025.06.05 기준) - 제안사 : 브리지텍 - 고객사 : 토스뱅크 - 사업명 : "토스뱅크 콜 인프라 재구축"중 수어서비스 추가제안 건 - 사업범위 : 서버, 네트워크, 전화기, PBX, CTI, IVR, 녹취, 상담APP, 웹팩스, 통합운영관리 통합관제, STT, TA, 보이는ARS, 말로하는 ARS, AI콜봇(NLU), 연동/연계 - 추가제안 : 수어아바타 서비스(디바이스_미확정) ※ 사업확정시 브리지텍에서 토스뱅크와 논의예정 ※ 견적범위 : 핸드사인톡톡(SL-CMS), 수어 200문장(문장범위는 상황에 따라 가감) - 추가제안금액 : 5천~7천만원 - [케이엘큐브] 추가제안 제출기한 : 6월10일(화)까지 / DX사업본부 사업지원팀 제안작업 진행중 - [브리지텍] 본 제안서제출기한 : 6월17일(화)까지 - [브리지텍] 제안발표 : 6월19(목) (2025.06.10 기준) - 6.10(화) 추가 제안서 작성완료(사업지원팀) 및 가격제안(DX팀) 브리지텍 제출완료 L 추가제안 금액 : 6천만원(vat별도) L 예정 : [브리지텍] 본 제안서제출기한 : 6월17일(화)까지 L 예정 : [브리지텍] 제안발표 : 6월19(목) (2025.06.19 기준) - 6.10(화) 추가 제안서 작성완료(사업지원팀) 및 가격제안(DX팀) 브리지텍 제출완료 L 추가제안 금액 : 6천만원(vat별도) L [브리지텍] 본 제안서제출기한 : 6월17일(화) 완료 L [브리지텍] 제안발표 : 6월19(목) 완료 ※ 브리지텍 경쟁사 :(주)이씨에스, (주)한솔인티큐브 (2025.06.27 기준) - 업체선정 대기중 L 제안 참여사 : (주)브리지텍, (주)이씨에스, (주)한솔인티큐브 경쟁 ※ 현재 분위기는 당사와의 협력중인 (주)브리지텍 선정가능성 높음 ※ 단, 브리지텍 사업자선정시 기술협상에서 추가제안의 수어아바타 적용여부 지켜봐야 됨. (2025.07.10 기준) - 우선협상 진행중 : 7/8~ ※ 수어 포함 여부 미확정 (2025.07.18 기준) : 전주 동일 (2025.07.22 기준) - 콜센터 시스템 노후교체 PJT 브리지텍 우선협상 대상자로 선정후 금액협상중 2위 업체 금액으로 납품요구 L 기능에서 우위. 가격에서는 5억 가량 높음 ※ 브리지텍, 한솔인티큐브, ECS텔레콤 3개사 경쟁입찰이 되면서 2위 업체 금액으로 납품 요구(5억 ↓) ※ 납품 솔루션 LIST 정리하면서 추가제안 수어서비스와 일부 솔루션도 제외됨 ※ 수어서비스 사항은 브리지텍에서 본 사업 진행하면서 당사와 협업으로 별도 예산 반영을 위한 공동영업 진행예정 | O54: 60000
B55: 2025-052 | C55: 수어 | D55: 우리은행 | E55: LGCNS | F55: 우리은행 3개지점 AI브랜치 시범사업 구축사업 | G55: 오민규 | H55: 1 영업중 | M55: N | N55: (2025.06.27 기준) - 우리은행 3개지점 AI브랜치 시범사업 진행중(구축사: LGCNS) L AI브랜치? : 2024년 LGCNS에서 신한은행을 대상으로 AI휴먼 무인은행 구축이후 금융권 확산 사업중 L 당사 롤 : AI휴먼 서비스중 서비스 카테고리별 단방향 수어콘텐츠 적용으로 기획중 L 구축시점 : 현재 LGCNS에서 우리은행 AI브랜치사업에 대해 구축중이며, 금년안에 대고객 서비스 개시 목표로 진행중 ※ 협력사인 LGCNS 총판에서 리셀러 하향조정에 따른 리셀러계약서 발송 및 리셀러 가격정책확정후 LGCNS 발송 필요 (2025.07.15 기준) - 우리은행 3개지점 AI브랜치 시범사업 진행중(구축사: LGCNS) L 금년 11월말까지 완료목표로 사업을 진행중이며, 수어적용에 대한 사항은 LGCNS에서 영업진행중(류진걸책임) ※ AI브랜치 사업과 관련하여 현재 NH농협은행과도 논의 중 (2025.09.17 기준) - 우리은행 3개지점 AI브랜치 시범사업 진행중(구축사: LGCNS) L당초 우리은행 소공동지점 AI브런치에 AI기반 수어아바타 시범사업 제안을 하였으나, 예산문제로 제외됨(류진걸책임) ※ 참고 : LG CNS에서 추진하는 사업의 담당자는 본차 차원으로 우리은행 담당자 미팅을 하였으나, 공통적인 사항은 예산문제(팩트) ※ 단, '26년 금융권 수어서비스 적용관련해서 재차 예산반영 진행중에 있음.(예 : 교보생명, IBK기업은행, NH농협은행, 카카오뱅크 등..) ※ 금융권 무인화 정책으로인해 향후 수어서비스 적용은 디폴트로 인식 과정임(패러다임 정책) ※ 2025.11.27 담당자 변경 심재홍 → 양승구
B56: 2025-053 | C56: 수어 | D56: SRT | E56: 에이텍모빌리티/지엔시스 | F56: SRT 4개역사 배리어프리 발권기內 수어아바타 적용사업 | G56: 심재홍 | H56: 6 실주 | M56: N | N56: (2025.07.01 기준) - SRT 4개역사 배리어프리 발권기內 수어아바타 구축사업(제안사: 에이텍모빌리티) L 입찰 대기상태 (입찰 예상참여사 : 에이텍모빌리티, 엘토브외 6개사) / 수어아바타 제작비용 협의 중(영업사: 아이앤지피플) L '25년12월까지 사업 완료목표 (2025.07.10 기준) L SRT 4개역사 배리어프리 발권기內 수어아바타 구축사업(제안사: 에이텍모빌리티) L 7/16(수) 진행상항 확인차 김대환선임 미팅예정_with.오민규부장 ※ 사업참여 예정이였던 엘토브는 사업참여 포기 고민중(사업기간 문제 / 25년12월말까지 사업종료_BF인증 부담외) (2025.07.17 기준) L SRT 4개역사 배리어프리 발권기內 수어아바타 구축사업(제안사: 에이텍모빌리티) L 7/16(수) 진행상항 확인차 김대환선임 미팅완료_with.오민규부장 ※ 차주 사전규격 공고예정 L 당사 견적 진행상황 : (주)에이텍모빌리티, (주)엘토브, (주)지앤시스_예정(現 KTX BF발권기 개발사이며, 당사 수어서비스 적용중) ※ (주)지앤시스의 경우 SRT 기존 발권기 납품사이며, 기존 발권기,차량안내 수어서비스는 이큐포올 수어아바타 적용 사례있음 ※ (주)지앤시스의 측에서 이번 BF발권기 사업의 경우 이큐포올에서 당사로 지정하여 진행하고자 함(Win back) ★ (주)에이텍 모빌리티에서 현재 제주도 BIS시스템 수주예정 L 쉘터의 경우 LED로 되어있어 수어적용 불가 / 버스內 LCD 디스플레이를 활용하여 수어서비스 적용제안 고민중 ※ 차주 에이텍 모빌리티와의 협업관련 오창송 부사장님 미팅관련 방문(?)일정 문의(김대환선임) (2025.08.01 기준) L SRT 4개역사 배리어프리 발권기內 수어아바타 구축사업(제안사: 에이텍모빌리티외 2개사) L 일찰공고 지연상태 빠르면 8/1(금) 늦으면 차주 공고예정이나 명확하지는 않다고 함.(ITS사업부 김대환선임 확인) ※ 제안작업시 DX사업본부 사업지원팀 제안작업 지원 예정(에이텍 모빌리티, 지앤시스, 엘토브 3사) (2025.08.07 기준) L SRT 4개역사 배리어프리 발권기內 수어아바타 구축사업(제안사: 에이텍모빌리티외 2개사) L 입찰공고 게시 : 8/1(금) / 입찰마감 8/12(화) ※ 입찰 참여사 에이텍 모빌리티 및 지앤시스 당사 제안장표 제출완료 ※ 차주중 제안발표후 바로 우선협상자 선정 (2025.08.14 기준) L SRT 4개역사 배리어프리 발권기內 수어아바타 구축사업(제안사: 에이텍모빌리티외 2개사) L 입찰공고 게시 : 8/1(금) / 입찰마감 8/12(화) ※ 입찰 참여사 에이텍 모빌리티 및 지앤시스 당사 제안장표 제출완료 ※ 차주 중 제안발표 후 바로 우선협상자 선정예정 (2025.08.20기준) L SRT 4개역사 배리어프리 발권기內 수어아바타 구축사업(제안사: 에이텍모빌리티외 2개사) L 입찰공고 게시 : 8/1(금) / 입찰마감 8/12(화) ※ 에이텍 모빌리티 제안포기(제안서 기한내 제출못함) ※ 엘토브 제안포기(실적문제) ※ 지앤시스 제안서 제출완료. 제안설명회 대기중(선정가능성 높음) ※ 차주 중 제안발표 후 바로 우선협상자 선정예정 (2025.08.27기준) L SRT 4개역사 배리어프리 발권기內 수어아바타 구축사업(제안사: 에이텍모빌리티외 2개사) L 입찰결과 : (주)닷 → 우선협상대상자 선정 ※ (주)닷은 작년 (주)엘리비젼_KIOSK제조사, (주)마음AI, (주)멀틱스 MOU상태 ※ 에이텍 모빌리티 제안포기(제안서 기한내 제출못함), 엘토브 제안포기(실적문제), 지앤시스(정상 입찰) ※ 본 사업 설계를 (주)지앤시스에서 설계를 했는데 엉뚱한 업체에서 우선협상대상자가되어 좀 지켜봐야 되는 상황이라 함.
B57: 2025-054 | C57: 수어 | D57: 삼성전자 | E57: 엘토브 | F57: 삼성전자 서비스센터 배리어프리 대기자 발권 키오스크 도입사업 | G57: 오민규 | H57: 2 견적제출 | M57: N | N57: (2025.07.08 기준) - 삼성전자 서비스센터 배리어프리 대기자 발권 키오스크 도입사업 (제안사: 엘토브) L 입찰공고 : 당초 7/7(월)예정에서 공고 지연중 / 신규 도입 수량 460대 (2025.07.16 기준) - 삼성전자 서비스센터 배리어프리 대기자 발권 키오스크 460대 도입사업 (제안사: 엘토브) L 엘토브 제안작업에 필요한 업무지원중(DX사업본부 사업지원팀) (2025.07.31 기준) - 삼성전자 서비스센터 배리어프리 대기자 발권 키오스크 460대 도입사업 (제안사: 엘토브) L 공고대기 상태 / 삼성전자 MRO업체를 통해 사업진행 예정 L 기존 서비스센터 대기자 발권 키오스크 납품사 2곳중 본 사업은 (주)아이티센 마더사로 (주)엘토브 협력으로 제안 대기중 ※ 삼성전자 서비스센터 기존 발권키오스크 수어아바타 멀틱스 아바타 적용상태 (2025.08.06 기준) - 삼성전자 서비스센터 배리어프리 대기자 발권 키오스크 460대 도입사업 (제안사: 엘토브) L 공고대기 상태 / 8월중 공고예정 / 당사 견적 발권키오스크 수량베이스 라이선스 제출완료(엘토브 담당 : 홍영복차장) L 엘토브측 삼성전자 MRO업체(코리아이플랫폼) 및 "아이티센클로잇" 2개사 투트랙 제안중 ※ 입찰공고 게시이후 당사 제안분 제안작업 예정 (2025.08.14 기준) - 삼성전자 서비스센터 배리어프리 대기자 발권 키오스크 460대 도입사업 (제안사: 엘토브) L 공고대기 상태 / 8월중 공고예정 / 당사 견적 발권키오스크 수량베이스 라이선스 제출완료 (엘토브 담당 : 홍영복차장) L 엘토브측 삼성전자 MRO업체 및 아이티센 클로잇 2개사 투트랙 제안중 ※ 입찰공고 게시이후 당사 제안분 제안작업 예정 (2025.09.10 기준) - 삼성전자 서비스센터 배리어프리 대기자 발권 키오스크 460대 도입사업 (제안사: 엘토브) L 입찰공고 지연중 / 당사 견적 발권키오스크 수량베이스 라이선스 제출완료 ※ 당초 올해 SW개발과 BF키오스크 전체 발주 예정이였으나 '25년 SW개발 '26년 하드웨어납품으로 사업 변경됨 (2025.09.17 기준) - 삼성전자 서비스센터 배리어프리 대기자 발권 키오스크 460대 도입사업 (제안사: 엘토브) L 입찰공고 지연중이나, (주)엘토브와의 협업관계는 확정(당사 견적 발권키오스크 수량베이스 라이선스 제출완료) ※ 당초 올해 SW개발과 BF키오스크 전체 발주 예정이였으나 '25년 SW개발 '26년 하드웨어납품으로 사업 변경됨 ※ 진행사항은 9월말 or 10월초순 사업진행 확인 예정(중기('26년) 사업) ※ 9월말 or 10월 초순_(주)엘토브 진행사항 확인후 유관부서 공유예정 ※ 2025.11.27 담당자 변경 심재홍 → 오민규
B58: 2025-055 | C58: 수어 | D58: 미래에셋생명 | E58: 부뜰정보시스템 | F58: 미래에셋생명 차세대시스템 구축 추가 솔루션(AI수어) 도입사업 | G58: 오민규 | H58: 2 견적제출 | M58: N | N58: (2025.07.02 기준) - 7/2(화) 미래에셋생명 차세대시스템 구축 추가솔루션 구축에 따른 Needs파악 고객미팅 진행 - 부뜰정보시스템 미래에셋생명 차세대시스템 구축 추가솔루션 구축 기술 검토회의 진행예정 L 회의안건 : AI수어 및 번역솔루션 도입에 따른 I/F 협의 요청 건 L 회의일시 : 25.07.07 (월) 14시 L 회의장소 : 부뜰정보시스템 본사 9층 회의실 L 회의내용 : 1) AI수어 솔루션 도입에 따른 화상시스템, MISO 시스템 I/F 등 협의 2) 번역솔루션 도입에 따른 MISO 및 STT 시스템 I/F등 협의 2025.07.10 기준) - 7/10(목) 부뜰정보시스템 최종 견적제출 완료 L 견적가 1.79억(vat포함) L 업무내역 : (1) SL-CMS 단일화(솔루션베이스) / (2)수어생성 150문장 / (3)SL-CMS 커스터마이징 및 I/F 개발 (4) 구독형 3자 통화_월정액 (2025.10.21 기준) - 보류중(부뜰 주지웅부장, 진행사항 확인차 연락) | O58: 163000
B59: 2025-056 | C59: 수어 | D59: (주)서원 | E59: (주)서원 | F59: (주)서원 고속도록 휴게소 배리어프리 무인발권기 도입사업 | G59: 오민규 | H59: 1 영업중 | M59: N | N59: (2025.07.03 기준) [홈페이지_인바운드] - (주)서원_고속도로 휴게소 수어아바타를 적용한 배리어프리 주문 무인발권 키오스크 도입 L (주)서원에서 관리하고 있는 10여개 휴게소중 1곳을 지정하여 사회적약자를 위한 식음료 결재시스템 도입 검토중 L 결재시스템은 (주)드림하이테크 VAN사 키오스크 이용중 L 수어아바타가 적용된 배리어프리 키오스크 요청하였으나 기존 (주)드림하이테크 메뉴 키오스크에 수어적용 제안중 L 내부검토 별도 연락주기로 함. ※ 담당자: (주)서원 임재현팀장 010-2109-1271 js1444@naver.com ※ 2025.11.27 담당자 변경 심재홍 → 오민규
B60: 2025-057 | C60: 수어 | D60: 공공? | E60: 더라이즈 | F60: 더라이즈 영상제작사 전시장 영상 수어아바타적용 사업 | G60: 심재홍 | H60: 2 견적제출 | M60: N | N60: (2025.07.04 기준) [홈페이지_인바운드] - 공공기관 대상 영상제작중 AI로 생성한 수어아바타 적용 검토중(공공기관에서 요청??) L 견적서 발송 및 문체부 전시정보 참고영상 발송완료 L 더라이즈 대표 영업중인 공공기관에 참고영상 검토후 적용여부 판단예정 (2025.07.08 기준) [홈페이지_인바운드] - 공공기관 대상 영상제작중 AI로 생성한 수어아바타 적용 검토중 L 당사에서 견적서 및 문체부 전시정보 참고영상 발송자료는 더라이즈 영업 기관에 전달완료 L 영업 기관에서 확인후 적용 확정시 당사와 직접 계약할지 더라이즈를 통해서 계약할지는 기관에서 에서 별도 판단 ※ 영업 기관에 대해서는 현재 Open을 못하는 상황이라고 함.
B61: 2025-058 | C61: 수어 | D61: 이대목동병원 | E61: 이대목동병원 | F61: 이대목동병원 장애인 의료기관 이용편의 지원사업 선정/ 수어서비스 도입 검토중 | G61: 임철현 | H61: 3 제안중 | M61: N | N61: (2025.07.09 기준) [홈페이지_인바운드] - 이대목동병원 장애인 의료기관 이용편의 지원사업 선정 / 수어서비스 도입 "잠정확정" L 8월말~9월초 3자 통화 앱 입점(구독형) 및 QR병원 구역 안내 QR병원 안내 계약예정 ※ B/F 키오스크형 수어봇 도입은 지원사업예산이 아닌 병원자체 예산으로 추진예정('26년초) L 8월중 이대목동병원 센터장외 직원들 대상 설명회 진행 내부 검토중 / 3자통화 및 QR데모 사전준비 필요 ※ 이대목동병원외 5개 지원사업 선정병원 담당자는 박준홍 연구원이 서울시청에 확인후 별도로 알려주기로 함. (2025.07.18 기준) [홈페이지_인바운드] - 이대목동병원 장애인 의료기관 이용편의 지원사업 선정 / 수어서비스 도입 L 7/18(금) 3자 화상 통화 앱 입점 및 QR 안내 가격정책 확정안 수급 완료(전략기획실) L 차주 1차 서비스에 대한 견적서 발송 및 방문설명 예정 ※ 이대목동병원외 4개 지원사업 선정병원 담당자 확인은 박준홍 연구원이 내부 업무로 미확인 상태 / 차주 다시 확인해 보겠다고 함. (2025.07.23 기준) - 이대목동병원 장애인 의료기관 이용편의 지원사업 선정 / 수어서비스 도입 L 7/23(수) 3자 화상 통화 앱 입점 및 QR 안내 가격정책 설명차 방문완료 ※ 확인사항 : 고객처 구독형 입점방법(App에서 가입? / 가입신청서 페이퍼가입? / 청구 및 입급방법 / 고객처 기본정보입력 표준신청서 양식 필요 / 구독형 가입시 약정기간은?(1년,2년,3년) 장기 가입 고객처 Benefit은?? (2025.09.03 기준) - 이대목동병원 장애인 의료기관 이용편의 지원사업 선정 / 수어서비스 도입 L 9/3(수) 수어통역사 채용 및 물품구입비 예산배정 완료(사업비 4개월분) ※ 물품구입비 예산이 2천만원 배정으로 인해 올해는 PC등 물품구매로 인해 수어서비스 적용은 힘든상태고 내년예산으로 수어서비스 적용하고자 함. ※ 미팅은 2차 사업진행시 다시 하자고 함. (2025.09.17 기준) - 이대목동병원 장애인 의료기관 이용편의 지원사업 선정 / 수어서비스 도입 L 당초 올해 SW개발과 BF키오스크 전체 발주 예정이였으나 '25년 SW개발 '26년 하드웨어납품으로 사업 변경됨 ※ 영업대표 변경으로 차원으로 9월말 or 10월초 병원 센터장 및 담당자 미팅 예정_With.임철현부장 (2025.10.16 기준) - 이대목동병원 장애인 의료기관 이용편의 지원사업 선정 / 수어서비스 도입 L 배하석교수 미팅: 영업대표 변경(심재홍 -> 임철현), 수어서비스 도입건관련 진행사항문의, 수어통역사 채용 진행 어려움 확인, 3차 채용 공고 진행중 L 복지부 및 서울시에 상기 사항에 대해 어필 예정, 예산 배정시 수어통역사위주로 되어 있어 운영에 대한 이슈 제기 예정, '26년 예산 작업시 수어통역사외 대체방안(수서서비스등)언급 코자 함 | Q61: (2025.07.03 기준) [홈페이지_인바운드] - 이대목동병원 장애인 의료기관 이용편의 지원사업 선정/ 수어서비스 도입 검토 L 장애인 의료기관 이용편의 지원사업 수행기관에 5개병원 선정 ※ 선정병원 : 이대목동병원, 서울동부병원, 경기도의료원, 수원병원, 분당서울대병원 5개 L 예산 : 1차년도 (1개소당 9천만원[6개월]) 2차년도 (1개소당 1.8억[12개월]) 예산의 80%는 인건비(코디네이터,수어통역사) L 7/9(수) 16시30분 이대목동병원 배하석 교수 연구팀 미팅 확정 ※ 서울의료원 모델로 제안 예정(3자통화, QR서비스)
B62: 2025-059 | C62: 수어 | D62: 동부병원 | E62: 동부병원 | F62: 서울시 동부병원 장애인 의료기관 이용편의 지원사업 3자화상통화외 입점 영업진행 | G62: 임철현 | H62: 3 제안중 | M62: N | N62: (2025.07.30 기준) - 서울시 동부병원 장애인 의료기관 이용편의 지원사업 3자화상통화외 입점 영업진행 L 일시 : 8/5(화) 10시~ 담당부서 부서 미팅 진행 L 미팅목적 : 서울의료원 및 이대목동병원 3자화상통화 입점 사례 설명, 입점 독려 영업진행 L 참석자 : 동부병원 공공의료사업단 윤화영차장 / 기획팀 오승민팀장 (2025.08.05 기준) - 서울시 동부병원 장애인 의료기관 이용편의 지원사업 3자화상통화외 입점 제안 완료 L 참석자 : 동부병원 공공의료사업단 윤화영차장 / 기획팀 오승민팀장 ※ 3자화상통화 입점 및 QR 수어서비스에 대해 긍정적으로 검토 하기로 함. L 요청사항 : 3자화상통화 입점 및 QR 수어서비스 자료 및 서비스 로직에 대한 영상자료, 견적서 ※ 요청자료에 대한 재 정리후(영상자료) 차주 제출 및 방문 설명(미정) 예정 (2025.08.14 기준) - 서울시 동부병원 장애인 의료기관 이용편의 지원사업 3자화상통화외 입점 제안 완료 L 참석자 : 동부병원 공공의료사업단 윤화영차장 / 기획팀 오승민팀장 ※ 3자화상통화 입점 및 QR 수어서비스에 대해 긍정적으로 검토하기로 함. L 요청사항 : 3자화상통화 입점 및 QR 수어서비스 자료 및 서비스 로직에 대한 영상자료, 견적서 ※ 요청자료에 대한 재 정리 후(영상자료) 차주 제출 및 방문 설명(미정) 예정 (2025.09.03 기준) - 서울시 동부병원 장애인 의료기관 이용편의 지원사업 3자화상통화외 입점 제안 L 동부병원 공공의료사업단 윤화영차장 / 기획팀 오승민팀장 ※ 차주 미팅관련 9/8(월) 오후에 재통화 요청 / 출장일정등 확인후 알려주겠다함. ※ 미팅시 3자 수어통역 화상통화 및 QR안내 시연요청과 농인+수어통역센터 앱 가입현황등 준비 필요 (2025.09.17 기준) - 서울시 동부병원 장애인 의료기관 이용편의 지원사업 3자화상통화외 입점 제안 L 현재 수어통역사 채용완료 / 직원 채용후 교육 및 유관부서 교육으로 인해 당사 미팅은 9월말 or 10월초 미팅 했으면 한다는 고객측 의견상태 ※ 사업진행시 자투리 예산(저예산)으로 추진해야되는 상황인점 참고(시범사업 상황) ※ 기보고 드린.. 미팅시 미팅시 3자 수어통역 화상통화 및 QR안내 시연요청과 농인+수어통역센터 앱 가입현황등 준비 필요(중요) (2025.10.01) - 업무담당자 변경(심재홍->임철현)에 따른 방문, 오승민팀장인사, 윤화영차장 행사참여로 차기 재방문예정 - 오승민팀장: 병원 적자로 인하여 사소한 지출도 병원장이 직접 챙기고 있어 수어솔루션도입에 대한 부분은 검토 어려움, '의료편의 지원사업' 인건비만 지급되고 월급여 형식으로 지급되고 있음. 사업비 구성(복지부50% : 서울시50%)으로 의사결정이 느림
B63: 2025-060 | C63: 수어 | D63: 경기도의료원/분당서울대병원/원광대학교병원 | E63: 경기도의료원/분당서울대병원/원광대학교병원 | F63: 장애인 의료기관 이용편의 지원사업 4개병원 3자통화/QR 제안 | G63: 임철현 | H63: 1 영업중 | M63: N | N63: (2025.07.24 기준) - 장애인 의료기관 이용편의 지원사업 선정 4개병원 담당부서 및 담당자 확인완료 L 담당부서 및 담담자 : ※ 서울특별시 동부병원 : 기획팀 / 오승민 기획팀장(02-920-9387) → 서울의료원 기획경영팀 이미현팀장 소개 ※ 분당서울대병원(경기남부지역장애인보건의료센터) : 운영기획팀 / 김희성팀장(031-787-4851) ※ 경기도의료원 : 담당부서 확인중 ※ 원광대학교병원(전북지역장애인보건의료센터) : 운영기획팀 / 담당자 미지정(063-859-0053) L 현재 목동이대병원을 포함하여 4개병원 공통사항은 8~9월 예산 배정완료후 사업을 진행할 예정이며, 대부분 수어통역사 채용으로 사업을 지행하고자 함. 목동이대병원 사례를 들어 전체 예산중 자투리 예산을 활용하여 3자화상통화 앱 가입 독려예정 (2025.09.03 기준) ○ 경기도의료원 수원병원 - 031-888-0114 → 검진센터 장애검진 담당자 표은채님(gpmc7707@medical.or.kr) 연결 - 수어통역사 상주 → ‘의사소통 지원 체계’ 부분에서 3자화상, QR 서비스 제안드리고자 함. 회사소개서 e-mail 전달 完 ※ 참고사항: [수원병원][2025-42호]장애인 의료기관 편의지원 사업 작업치료사(비정규직) 신규채용 공고 - 인원 1명. 접수기간 08.29~09.08. 면접 9월 중순/말 예정 ○ 분당서울대병원 - 분당서울대병원 031-787-1113 기획담당 조수정 통화. 담당부서 확인 후 연락주기로 함. 연락처 남김 - 경기남부지역장애인보건의료센터 031-787-4851 김희성팀장(010-2067-9705, paekim27@grdhc.org) 통화(9/3). 인력 채용중 & 실제 사업 시작 전. 회사 소개서 전달 完 ○ 원광대학교병원(전북지역장애인보건의료센터) - 063-859-0055 사회복지사 오찬솔님(jbrhmc@wkuh.org). 담당자 외근중. 회사소개서 전달 完 (2025.10.23 기준) ○ 분당서울대병원 - 분당서울대병원 김희정팀장 -> 수어통역사 채용완료, 금년도 수어솔루션도입 어려움, 당사 소개자료 재발송 요청 접수 및 발송 ○ 원광대학교병원(전북지역장애인보건의료센터) - 사회복지사 오찬솔담당자 -> 수어통역사 채용완료, 추가 수어솔루션 도입이슈 있으면 전화 주기로 함
B64: 2025-061 | C64: 수어 | D64: 아르코대학로예술극장 | E64: 아르코대학로예술극장 | F64: 한국문화예술위원회 아르코대학로예술극장 극장 안내영상內 수어아바타적용 검토중 | G64: 심재홍 | H64: 2 견적제출 | M64: N | N64: (2025.07.03 기준) [홈페이지_인바운드] - 한국문화예술위원회 아르코대학로예술극장 극장 안내영상內 수어아바타적용 검토중 L 견적서 발송 및 문체부 전시정보 참고영상 발송완료 ※ 고객측과 연락이 안되어 게시판 질의사항에 대한 회신 상태 / 차주 재연락 또는 대면미팅 예정
B65: 2025-062 | C65: AICC | D65: 경찰청 | E65: 펜타시스템 | F65: 경찰청 전기통신금융사기 통합분석대응시스템 고도화 사업 | G65: 오민규 | H65: 5 DROP | M65: N | N65: (2025.07.10 기준) - 보이스피싱 녹음 파일을 텍스트로 변환하는 기능(펜타시스템) L KT STT : 제안 불가 - 현재 기능 개발중이며(완료 일정 미정), GPU 필요(RFP CPU x86) L 파워보이스 미회신 → 리드스피커코리아 검토 진행중 (2025.07.18 기준) L 리드스피커코리아 사업 미진행 ∵ 화자분리 정확성 Risk 有 L 펜타시스템쪽으로 금번 PJT 미진행 의견 송부 完
B66: 2025-063 | C66: AICC | D66: 한국증권금융 | E66: 부뜰정보시스템 | F66: 한국증권금융 콜센터시스템 재구축 사업內 KMS 구축 | G66: 오민규 | H66: 8 계약완료 | M66: N | N66: (2025.07.03 기준) - 금액: 53,000,000원 ※ 검색엔진(Konan Search 3식. 커스터마이징 1MM(중급. vat별도) - 납기일: 2025.07.01~2026.02.02(PJT 종료일) ※ 6/30 김홍태부장(부뜰) → 박현후과장 : 발주서 확인 및 회신 요청 7/1 박현후과장 → 김홍태부장 : 발주서 전달(참조: 이하형본부장, 김형일팀장) - 코난테크놀러지 발주서: 32,300,000원(Konan Search(4Core) 3식 , 인건비 2MM) - 코난테크놀러지 설치확인서 전달. 인감날인 完(2025.10.14)
B67: 2025-064 | C67: 수어 | D67: 국립국어원 | E67: 국립국어원 | F67: 국립국어원 수어문자 사업기획 | G67: 오민규 | H67: 2 견적제출 | M67: N | N67: (2025.07.18 기준) - 2종 FP 견적서 제출 完(수어문자 변환기(에디터) 개발, 수어 통합저작도구 개발) - 수어문자 변환기(에디터) 개발: 271,500,000원(VAT포함) - 수어 통합저작도구 개발) : 553,300,000원(VAT포함) | O67: =246842.606+503088.46 -> 749931.07
B68: 2025-065 | C68: AICC | D68: 경찰청 | E68: 펜타시스템 | F68: 경찰청 경찰견문관리시스템 고도화 사업(STT) | G68: 오민규 | H68: 7 수주완료 | K68: 130000 | L68: 삼성SDS-펜타시스템(?)-당사 | M68: N | N68: (2025.06.10 기준) - 요구사항: 모바일/PC 등으로 노음되는 음성을 TEXT로 변환. STT 200ch. 재학습, 정확도 검증 지원 - 견적회신: K-HIVE STT 200Ch. 배치처리, HW 단중화. 130,000천원(VAT제외) (2025.07.03 기준) - 당사 STT/SynK 솔루션 검토(안) 보고 - WhisperX 프레임워크 기반 STT, SynK 관리기능 Web 개발에 대한 인력 충원(개발 공수) 의사결정 필요(~7월말) (2025.07.22 기준) - 삼성SDS 문의 대응 L 이중화 구성시 채널 할당 : 서버 이중화시 200 + 200ch 필요. 동시처리 100ch으로 변경시 100 + 100ch로 구성 L 서버 구성시 S/W: Linux 셋팅. API 통신 고려(Web/WAS 불필요) L 외부 학습 가능 여부: 가능 ※ WhisperX 프레임워크 기반 STT, SynK 관리기능 Web 개발에 대한 인력 충원(개발 공수) 의사결정 필요(대표님) (2025.08.01 기준) - 유지보수 기간 재조정 요청: 삼성SDS. 개발 설치 2026.01(예정), 운영 설치 2027.01(예정) L 전체 PJT 검수완료 2027.10 → 2027.11~2028.10 무상유지보수 요청 → 전체 PJT 검수가 아닌, 견문관리시스템STT 검수 이후 1년 무상, 이후 유상 반영 요청 (11.27 기준) - 유지보수 요율, 기간 문의: 삼성SDS 오상인님 . 견문관리 PJT 기간(2차수): 2026년 6월~12월. 전체PJT 종료 ~2027년 10월 . 요율: 15%, 무상기간 2027년. 유상유지보수 2028년 1월~ | O68: 130000
B69: 2025-066 | C69: 수어 | D69: 국립호남권생물자원관 | E69: 국립호남권생물자원관 | F69: 국립호남권생물자원관 개인정보 처리방침 수어 안내 | G69: 오민규 | H69: 8 계약완료 | K69: 2500 | M69: N | N69: (2025.08.08 기준) [홈페이지_인바운드] - 국립호남권생물자원관 홈페이지 內 개인정보 처리방침 안내 수어아바타적용 검토중 L 견적서 발송 및 게시판 질의사항에 대한 회신 상태 / 차주 연락 예정 (2025.08.13 기준) - 담당자 통화: 검토후 연락주기로 함. → 주 단위 체크 예정 (2025.08.21 기준) - 잔여예산 추진건으로 할인 요청(300만원 정도) → 스크립트를 보내주셔야 정확한 견적 가능 안내 검토 후 스크립트 전달 주기로 함. (2025.08.29 기준) - "개인정보 처리방침 안내" 본영상 + 수어영상 제작 요청 L 본영상은 생물자원관에서 제작해야 함 안내 L 본영상 제작 후 연락 주기로 함 (2025.09.05 기준) - "개인정보 처리방침 안내" 수어영상 제작 및 편집 요청 L 본영상 제작 완료 연락. 수어영상 제작 및 편집 2주 내 완료 가능 여부 문의 L 견적 2,750,000원(VAT포함) 전달 (2025.09.12 기준) - "개인정보 목적외 이용 및 제3자제공 수어 영상 제작 및 편집" L 용역승낙서, 견적서, 과업내용서 등 전달 L 수어 영상 제작/편집 전달 : ~9/19 예정 (09.26 기준) - "개인정보 목적외 이용 및 제3자제공 수어 영상 제작 및 편집" L 수어 영상 크기 조절 최종 수정본 전달 L 최종 대금지급을 위한 서류 준비 중(검수확인서, 납품확인서, 계약(이행)보증지급각서 등) (10.01 기준) - 세금계산서 발행 完(09.30) - 최종 대급지급 서류 전달 完(납품확인서 外) (10.16 기준) - 세금계산서 재발행(기존 9/29 → 10/10. 10.13 完) | O69: 2500
B70: 2025-067 | C70: AICC | D70: 교보라이프플래닛생명보험 | E70: 부뜰정보시스템 | F70: 교보라이프플래닛생명보험 검색엔진 유지보수 | G70: 오민규 | H70: 9 유지보수 | K70: 900 | M70: N | N70: (2025.08.21 기준) ○ 본사업: 교보라이프 플래닛 디지털 마케팅 및 옴니채널 시스템 구축 사업 L 검색엔진: Konan Search(4Core) 1식, 솔루션 커스터마이징 0.5MM(중급) 19,000,000원(VAT제외) ○ 유지보수 계약 L 계약기간: 2025.7.1~2026.6.30(무상 2025.1.1~2025.12.31. 유상 2026.1.1~2026.6.30. 6개월) L 계약금액: 900,000원(vat제외). 2026.1월 ~ 6월 각 150,000원/월 청구. 분기점검 L 계약서 전달 : 2025.08.22 L 계약서 수령 : 2025.08.27(수) | O70: 900
B71: 2025-068 | C71: AICC | D71: 유비케어 | E71: 복스유니버스 | F71: 유비케어 KMS 지식 데이터 구축 | G71: 오민규 | H71: 5 DROP | M71: N | N71: (2025.08.21 기준) [복스유니버스 한정진상무(함영민부장 소개) 인바운드] - 유비케어 생성형 AI기반 상담어시스트 고도화 및 AI챗봇 자동화 구축사업 L STT 기반 유형별 학습데이터 수집, 정제, FAQ 생성, 검수 등의 인력 소싱 요청 L 제안수행팀-AICC파트 인력 서칭하여 인력 프로파일 전달 L 인력 단가 비용 이슈로 최종 미추진함 ※ 개선 포인트: 인력 소싱 요청시 예상 등급/MM 단가/근무지역 확인 必 | O71: 33000
B72: 2025-069 | C72: 수어 | D72: 가톨릭대학교 성빈센트병원 | E72: 가톨릭대학교 성빈센트병원 | F72: 수원 가톨릭대학교 성빈센트병원 "수어안내키오스크 구축" | G72: 임철현 | H72: 8 계약완료 | J72: 2025.08.13 | K72: 16,000,000원(vat포함) | M72: N | N72: (2025.08.14 기준) - 사업명 : 가톨릭대학교 성빈센트병원 수어안내키오스크 구축 - 계약내용: 수어통역사 영상 사용. 1대, 1,600만원 (부가세 포함, 납품 완료 후 익월 말 일괄 결제) L 사업기간: 25. 08. 11 ~ 25. 09. 25. L 조건 : 9월 23일까지 납품 및 현장테스트가 완료 必. 9/26일 병원행사에서 사용 ※ 키오스크 종류 : 49인치, 터치형, PC 내장형 사용 (고대 안암병원과 동일) L 계약일: 2025.08.13(수) (2025.09.17 기준) - 사업명 : 가톨릭대학교 성빈센트병원 수어안내키오스크 구축 L 9/18(목) 납품진행(고객사 방문자 : 정상욱부장, 김태민사원, 채승주사원) ※납품이후 이슈사항은 별도 보고 예정(보고자: 정상욱부장->이하형부무장)
B73: 2025-070 | C73: 수어 | D73: 남양주시수어통역센터 | E73: 남양주시수어통역센터 | F73: 남양주시수어통역센터 핸드사인톡톡-모바일서비스 제안 | G73: 양승구 | H73: 1 영업중 | M73: N | N73: (2025.08.28 신규 ) ○ 남양주시수어통역센터 핸드사인톡톡-모바일서비스 시연 L QR코드 생성과 3자통화서비스에 대한 주요 기능에 대한 설명 과 시연 L 설명 후 반응 : QR코드는 요즘 많이 사용함으로 적용이 가능하지만, 3자통화서비스는 사용의 어려움과 기존 사용 방법으로 본 제안은 불편함(예약 및 수어통역센터의 역할에 의문)이 있음으로 작용에 대하여서는 부정적 L 현재 남양주시와의 협력관계가 미온적으로 남양주수어통역센터를 통해서는 진행이 어려 울 수 있음. L 당사에서 남양주시의 관계자와 협의해서 진행 하겠으니, 많은 지원을 부탁요청 (2025.11.07 ) ○ 남양주시수어통역센터 핸드사인톡톡-모바일서비스 제공에 대한 지연 L 남양주도시공사의 전체 키오스크에 적용하는 것은 현싷적으로 어려움과 예산의 부족으로 25년에는 어려움이 있음 L 26년도 장비의 추가시 검토 진행 하겟음 - 지속적으로 지원 요청과 협의 드리겠음 (2025.11.28 ) ○ 남양주시수어통역센터 방문 L 남양주시 장애인복지센터 센타장님 미팅 - 당사 기업의 소개 및 차후 지원 사업 진행시 협의(당사 소개자료 전송) L 남양주시에 AI 수어의 지속적인 사업 진행 예정으로 협조 요청, 수 L 남양주 수어센터 당사의 핸드사인톡톡 앱에 입주하여 서비스 가능에 대한 협의 진행 (테블릿 - 3대 지원) (2025.12.08 ) ○ 남양주시수어통역센터 내부 지원 사항 확정 --> 대표님 보고 완료 L 남양주 수어센터 당사의 핸드사인톡톡 앱에 입주 결정 (개발팀과 협의 진행 -> 메일 전송) L 테블릿 - 2대 지원 확정 및 수어통역사 교육 등을 위한 일정은 차주 협의 (12/18일 예정) (2025.12.17 ) ○ 남양주시수어통역센터 내부 지원 사항 협의 --> 일정에 대한 조정으로 차주 진행 예정 L 테블릿 - 2대 지원 확정 및 수어통역사 교육 등을 위한 일정 협의차 방문(12.23일)
B74: 2025-071 | C74: 수어 | D74: 브로드씨엔에스 고객사 중 병원 | E74: 브로드씨엔에스 | F74: 브로드씨엔에스 병원 내 수어서비스 제안 | G74: 임철현 | H74: 1 영업중 | K74: - | M74: N | N74: (2025.08.29 기준 ) ○ 브로드씨엔에스 병원 고객사 대상 챗봇 內 수어서비스 PoC L 7문장 수어 제작(방문 감사 인사, 진료예약 1번, 주민등록번호 입력 등) 후 영상 전달 예정 (09.03 기준) - 영상 제작 완료. 브로드씨엔에스 전달 ※ 차주 구성 방안 미팅 예정 (09.12 기준) - 병원 제안서 작성 후 전달 예정 L 포함 내용: 수어 필요성, 홈페이지, Web, 챗/콜봇, 보이는ARS 내 수어 안내 화면 포함 ※ 2025.11.28 담당자 변경: 오민규 → 임철현
B75: 2025-072 | C75: 수어 | D75: 파주나비나라박물관 | E75: 파주나비나라박물관 | F75: 파주나비나라박물관 홍보영상 내 수어영상 제작 | G75: 오민규 | H75: 5 DROP | M75: N | N75: (2025.08.29 기준 ) ○ (홈페이지 IN) 파주나비나라박물관 홍보영상 2개 수어영상 제작 L 영상 1(100문장), 영상 2(49문장) 견적 전달. 검토 후 연락주기로 함 (2025.09.05 기준) - 홍보영상 2개 수어영상 제작 및 영상편집 건 L 예산 부족으로 진행 어려움(500만원 이하) L 홍보영상 1개 진행으로 제안(견적 4,950,000원. vat포함) (2025.09.12 기준) - 홍보영상 "벅스라이프" 수어 영상 제작 및 영상편집" L 견적 4,950,000원(vat포함) L 영상 조회수 낮은 상황. 잠정 보류 | O75: 4950
B76: 2025-073 | C76: AICC | D76: DOWHAT | E76: DOWHAT | F76: DOWHAT AI 음성봇 제안 | G76: 오민규 | H76: 1 영업중 | M76: N | N76: (2025.09.05 기준) - 호텔 단순, 정형화 문의 대응 AI 음성봇 제안 L 대표님 검토중 (09.26 기준) - AI음성봇 성능유지방안(인식율 95%, 답변 정확도 98%) 보완(대표님 전달)
B77: 2025-074 | C77: 수어 | D77: 남양주시 | E77: 경기도 남양주시 | F77: 남양주시 스마트관광지도 수어 안내 | G77: 양승구 | H77: 8 계약완료 | M77: N | N77: 기존 사업명 : 경기도 남양주시 수어 시스템 소개 및 26년도 사업 예산 작업 지원 (2025.10.13 기준) 1) 남양주시 : 스마트관광지도 서비스에 AI 기반의 수어 솔루션 도입을 위한 견적서 제출 L 문화관광과 박수림주무관 전화 연락 - 3개 장소에 대한 소개 문구 접수 (18문장 산출) --> 당사 최소 문장 단위(30문장)로 견적 제출 하고, 추후 문장 추가하여 37개로 제출 완료 - 내부 검토 후 의견 주지로 함. L 문화관광과 과장님과 통화 함 - 내부에서 진행 예정이며, 확정 되면 연락 주기로 함. (2025.10.23 기준) 1) 남양주시 : 스마트관광지도 서비스에 AI 기반의 수어 솔루션 도입을 위한" 과업내역서 요청"에 대한 처리 완료 L 차주 계약 진행 예상하고 있으며, 계약하면 11월 21일까지 납품하는 것으로 제안 (2025.10.29 기준) 1) 남양주시 : 스마트관광지도 서비스에 AI 기반의 수어 솔루션 도입" 진행 결정 완료 L 10월 30일 계약서 작성을 위한 방문, 계약 체결 예정(기존 금액과 동일) L 계약기간 : 계약 체결 후 - 25.11.21일까지 예정 --> 계약 종료 일 변경 (11.21일 --> 11.29일) (2025.11.10 기준) 1) 남양주시 : 현재 계약하여 주신 시나리오 수조롭게 진행 중이며, 차주에는 초안 제공 예정 L 금주 목요일 정도에 방문하여 진행 사항 공유 및 26년도 추가 사업에 대한 협의 (2025.11.13 기준) 1) 남양주시 : 영상 제작 11.21 완료 후 차주 월요일 제공 예정 L 남양주시 시의원님 미팅 예정 : 11.17일 열인관광의 시 조례에 당사의 수어가 기본으 될 수 있도록 시 조례의 수정 제안 예정 L 2026년도 시장님 신년인사에 당사의 수어를 제안하여 진행하기로 함 (무상 제안) - 2025년도 신년인사 영상 확인 사항 : 유트브 - 2.30초, 문구 - 18개 - 카뱅과 같이 실사형 아바타로 제작하여 진행하는 방안으로 진행 할 예정으로 일정상 불가시 표준아바타로 진행 (2025.11.26 기준) 1) 남양주시 : 영상 제작 11.21 제공 완료 2) 소개지역에 대한 수어영상을 각 저절로 표현한 것을 WEB Page에서 보이기 위해서 1개의 파일로 통합하여 제공 요청 L 23개파일을 5개 파일로 통합하여 제공 완료(11,27일) 3) 시장님의 새해 인사 문구확정 되면 수보 받기로 함 - 예상일 12월 2째주 (2025.12.02 기준) 1) 남양주시 : 남양주시 스마트관광지도 수어 시스템 오픈 완료, (추가 계약 : 수어영상에 자막편집 요청, 60만원 계약 금주 예정) 2) 시장님의 새해 인사 문구 확정 : 12.17일 예정 일주 인내에 작업 진행 요청(11/27일 이전 납품예정으로 진행) L 예산 금액 조정 요청 : 200만원 선에서 진행요청, 협의후 메일 드리겠음 (2025.12.09 기준) 1) 남양주시 : 남양주시 스마트관광지도 수어 시스템 오픈 후 일부 수정 요청으로 진행 완료 L 계약 : 25.12.11 , 계약 기간 : 12.11 ~ 12.31 일까지, 12월 30일 이내에 계싼서 발행 예정 2) 시장님의 새해 인사 문구 확정 : 12.17일 예정 일주 인내에 작업 진행 요청(11/27일 이전 납품예정으로 진행) L 예산 금액 조정 요청 : 200만원 선에서 진행요청, 협의후 메일 드리겠음 L 예산에 대한 금액의 조정을 진행 중임 (2025.12.15 기준) 1) 시장님의 새해 인사 문구 확정 : 12.17일 예정 일주 인내에 작업 진행 요청(11/27일 이전 납품예정으로 진행) L 예산 부족으로 26년 진행으로 협의 조정, 설 인사에 AI수어 도입 검토 협의 2) 남양주도시공사 사장님 미팅 : 25.12.19일 15시 L 당사 솔루션애 대한 제안 예정 (2025.12.23 기준) 1) 남양주도시공사 사장님 미팅 : 25.12.19일 15시 미팅 완료 L 당사 솔루션애 대한 제안 설명, 현재 시의 예산에 대한 지원의 부족으로 26년바로 진행은 불가 한 상황 L 솔루션의 도입에 대한 필요성 인식함, 추가에 진행에 대한 사항은 협의 하겠음. | O77: 3996 | Q77: (2025.09.08 기준) 1) 남양주시를 위한 AI 기반의 수어 시스템 소개 및 미팅 (9.5일) L 장애인복지과, 복지정책과 담당과장님께 - 남양주시 AI수어번역 시스템 구축 제안 자료 및 영상자료 제공 (9.9일 - 메일전송) L 장애인복지과 9.12일 미팅 예정 - 각 부서에서 사전 수요 조사 후 , 26년의 각 업무 적용 요청을 위한 예산에 반영 할 수 있는 방안 협의 2) 남양주도시공사 L 남양주도시공사 시설본부장님 소개 받음. L 차주 9.17일 오후 16:00에 AI수어 번역 시스템에 대한 소계 L 주요관리 운영시설 : 문화센터 7곳, 청소년 수련관 4곳, 교통환경 6곳(전철,주차장 등) L 중점제안 : QR코드와 점자를 기반으로한 의한 시설안내 및 가이드(SaaS 구독형 서비스 제안) (2025.09.18 기준) 1) 남양주시 : AI 기반의 수어 시스템 소개 및 미팅 (09.12일 오후 17:00) L 장애인복지과 미팅 - 각 부서에서 사전 수요 조사 후 , 26년의 각 업무 적용 요청을 위한 예산에 반영 할 수 있는 방안 협의 - 25년도 1차적으로 적용 할 수 있는 방안 : 남양주 "다산정약용문화제"에 QR코드 기반의 행사 안내서비스 제안 (09.19일 14:00 남양주시청에서 해당 사업 진행을 위한 협의 - 구축자료 및 예산 견적서 제공 예정) L 26년도 장애인의 날(6월 3일) 행사 진행시 AI 수어서비스 수행을 위한 예산 반영예정(서비스 및 예산 비용 확인) 2) 남양주도시공사 L 9.17일(목) 오후 16:00 : AI수어 번역 시스템에 대한 소계 완료, 수어 도입 및 설치에 대한 필요성 인식 --> 추후 모든 시설 및 서비스에 도입 L 26년도 추진 사업 : 26년도 키오스크 교체 사업시 수어를 도입 할 수 있는 방안 추진 하겠음 주요내용 : 문화센터 8곳, 8대 BF키오스크 도입 시 예산 범위 안에서 AI 수어 도입 검토 하겠음 차주 타 업무팀장과 IT와 협의하는 시간을 가지고 함. 금주 중 연락 하겠음 (2025.09.23 기준) 1) 남양주시 : AI 기반의 수어 시스템 소개 및 미팅 (09.24일 오후 15:00 ~ 16:00) L 문화관광과 박선영과장 미팅 예정 - 당사 솔루션에 대한 설명과 수어서비스 필요성에 대한 설명(AI수어의 확대에 따른 수어통역사의 역할의 중여성과 업무의 확대) - 26년도 예산에 반영 할 수 있는 방안 제시 - 25년 남은 예산으로 구축 할 수 있는 업무 선정요청(스마트관광안내지도에 AI수어서비스 제공방안 작성요청 -> 제안자료 전송완료) 2) 남양주도시공사 L 9.23일 : AI수어 번역 시스템을 26년도입하는 BF 키오스크에 모두 수용하는 것은 예산문제로 시범적으로 시행 예정 L 25.11월 중순 이후 BF 발주 진행시 당사와 협의 할 수 있도록 진행 하겠으며, 남양주체육관에 시범적으로 우선 진행 예정 L 시설본부장님께 진행 사항 보고 : 가능한 전체 8대 도입시 적용 할 수 있도록 진행 요청(확인 후 답변 예정) (2025.09.29 기준) 1) 남양주시 : AI 기반의 수어 시스템 신규 사업으로 추진 협의 중 L 문화관광과 박선영과장 미팅 - 당사 솔루션에 대하여 어떤 명분으로, 어느 사업 부분에 적용 할지에 대하여 고민 중임. - 추석 이후 에 추진으로 내부 검토 중임(추석이후 미팅 일정 협의하기로 함)
B78: 2025-075 | C78: 수어 | D78: 원주시 시설관리공단 | E78: 원주시 시설관리공단 | F78: 원주시 시설관리공단 키오스크 수어 안내 | G78: 오민규 | H78: 2 견적제출 | M78: N | N78: (2025.09.12 기준 ) ○ (대표번호 IN) 산업AI 엑스포 전시 보고 문의 - 시설관리공단 키오스크 15대 수어 안내 L CMS, Client, 50문장 : 62,150,000원(vat포함 견적전달) L 구축형 지양 지침으로 구독형 진행 검토(담당자 월 예산 200만원 책정 예정) L 당사 서비스 디지털서비스몰 이용 등록 후 재연락 예정 (12.09 기준) - 원주시에서 예산삭감. 추경예산(5월)에 반영 예정 ※ 큰 규모 위주로 편성. 신규/소규모 예산(200만원/월) 항목은 제외됨(서원준대리) - 체육시설과 관광시설 키오스크에 꼭 적용 예정(강한의지. 지속 comm. 예정) | O78: 56500
B79: 2025-076 | C79: 수어 | D79: 경기도장애인복지종합지원센터 | E79: 경기도장애인복지종합지원센터 | F79: 경기복지재단 장애인 생활환경 개선사업 수어 영상 | G79: 양승구 | H79: 8 계약완료 | M79: N | N79: (2025.09.17 기준 ) ○ 장애인 생활환경 개선사업 영상에 AI수어서비스 구축 L 재단에서 11월 경기도 도지사님과 관련 관계자를 모시고 장애인 생활환경 개선사업 사업 보고시 제작 영상에 AI 수어 시스템 추가 하고자 함 L 현재 예산 - 경기도 보조금으로 :50만원 책정 중인 상황으로 10월 중순까지 제작이 가능한지 문의 드림 L 주신 시나리오 분석시 70 ~ 80개의 문장 산출 됨으로, 내부 협의 후 진행 여부를 알려 드리겠음. (2025.09.22 기준 ) ○ 경기복지재단 미팅 완료 L 업무의 내용은 파악 하였고, 전략적인 금액으로 제안, 재단에서 10월 2일까지 촬영 완료 후 시나리오 문구 조정하여 당사에 제공 예정 L 사업 범위: 재단에서 영상제공시, 해당 영상에 당사의 아바타 영상을 편집하여 제공(문구는 30문장 이내) L 제공 견적서, 사업자등록증, 통장 사본 제출 완료, 추석전까지 계약완료 예정(계약서는 발주서로 대체함) (2025.09.30 기준 ) ○ 최종 시나리오 수보 받음 (수어영상 제작 진행 예정) L 경기복지재단의 내부 영상 촬영 지연으로, 당사 수어영상 먼저 작성 후 제공하여 주면, 수어영상을 경기복지재단의 영상에 추가하는 작업은 재단에 진행하기로 함 L 금주중으로 결재된 내부품의문서 제공 후, 계산서는 검수 이후에 진행 L 내부문서가 아니 발주서 요청으로 협의 예정(직인 불가시, 담당 및 팀장의 사인으로 대체 예정) (2025.10.16 기준 ) ○ 최종 시나리오 수보 받음 (수어영상 제작 진행 예정) L 당사에서 수어영상을 10.24일 이전에 제공하는 조건으로 수어영상 제작의 진행 사항체크 L 25.10.24일 이전 작성 완료 확인 (하윤호 이사님) (2025.10.23 기준 ) ○ 최종 시나리오 영상 작성완료로 고객사에 전송 완료(고객사 확인) L 기존 홍보 영상과 결합 후 최종본 공유하여 제공하기로 함(당사의 영업자료로 활용 가능) L 25.11 중순 경기도 도지사 보고 행사시 당사도 참석 할 수 있도록 요청 (2025.10.28 기준 ) ○ 최종 시나리오 영상 작성완료 및 전달 완료 (10.23) L 기존 홍보 영상에서 추가 되는 부분이 있어서 이에 대한 추가 요청(8개 맨트) _작성 후 전달 예정 L 11.7일까지 제출 가능 회신 (2025.11.12 기준 ) ○ 최종 시나리오 영상 전달 완료 후 복지재단의 최종 통합 영상에 대하여 수어문장이 잘 적용 되었는지 획인 요청 L 최종 통합 영상 확인 후 전달 예정이며, 최종 전달 완료, 계산서 발행 완료 (2025.11.17 기준 ) ○ 최종 시나리오 영상 전달, 계싼서 발행 완료 L 11.28일 도시지사님 참석하는 행사의 주요일정은 내부 결재 후 공유 예정 (2025.11.27 기준 ) ○ 경기도 예산 편성에 대한 회의로 도지사님 참석 불가로 행사 취소 됨 L 자체적인 행사로 조용히 진행 예정이며, 참여 인력은 최소화 함, L 당사의 수어 솔루션에 대한 부분은 각 부서에 적극적인 홍보 진행 하겠음 | O79: 450
B80: 2025-077 | C80: 수어 | D80: 부산대병원 | E80: 아이티아이즈 | F80: 아이티아이즈 헬스케어본부 배리어프리 키오스크 제안 | G80: 임철현 | H80: 1 영업중 | M80: N | N80: (2025.09.17 기준 ) - 아이티아이즈 헬스케어본부 협업 배리어프리 키오스크 제안 L 금주(~09.18) 부산대병원 및 부산시와 연구과제관련 업무미팅 예정 L 당사 소개자료 기반 배리어프리 키오스크 관련 의견 청취 예정, 이 후 당사 미팅 주선 예정 L 아이티아이즈 헬스케어본부와 협업을 통해 상급종합병원 47개 담당자 정보 확보예정 L 아이티아이즈 수행중인 ‘건강정보 고속도로’사업에 당사 솔루션 추가 제안 예정
B81: 2025-078 | C81: 수어 | D81: 기상청 | E81: (주)러닝플레닛 | F81: (주)러닝플레닛 기상청 - 기후변화 과학 용어집의 AI수어번역서비스 제안 | G81: 양승구 | H81: 2 견적제출 | M81: N | N81: (2025.09.23 기준 ) - (주)러닝플레닛에서 기상청에서 26년도 사업 진행을 위힌 "기후변화 과학 용어집"에 AI수어번역서비스 추가 제안 요청 L 과학용어집 : 400, 500개 문장에 대하여 청각장애인을 위한 AI수어번역 시스템을 구축 하고자 함 L 견적서 2개 제출, 당사 솔루션 소개 자료 및 동영상 제료 제공 L 금주 9.25일 기상청 방문 이후에 차주 미팅 예정 (2025.10.02 기준 ) - (주)러닝플레닛에서 기상청에서 26년도 사업 진행을 위힌 "기후변화 과학 용어집"에 AI수어번역서비스 추가 제안 자료 및 견적서 제공 완료 L 새부적인 사항은 추석 이후에 별도의 미팅을 잡아서 협의 하기로 조정 | O81: 65000
B82: 2025-079 | C82: 수어 | D82: 부천도시공사 | E82: 부천도시공사 디지털정보팀 (소사스포츠센터) | F82: 부천도시공사 AI 수어아바타 핸드사인톡톡(구축형) | G82: 임철현 | H82: 2 견적제출 | M82: N | N82: (2025.09.24 기준) - 부천도시공사 잔여예산 반영 기보유 키오스크(3ea)에 수어아바타 제안 L 키오스크별 : 5개 문장에 대하여 청각장애인을 위한 AI수어번역 시스템을 구축 하고자 함 L 소사스포츠센터에서 견적을 의뢰한 것이고, 소사스포츠센터 내부 품의 결과에 따라 도입결정시 당사로 연락주겠다고 함 (2025.10.01 기준) - 부천도시공사 잔여예산 반영 기보유 키오스크(3ea)에 수어아바타 제안 L 키오스크별 : 5개 문장에 대하여 청각장애인을 위한 AI수어번역 시스템을 구축 하고자 함 L 기존 디지털정보팀 김종수팀장 전배로 인하여 추진 담당자 확인 중 (2025.10.13 기준) - 디지털정보팀(김종수팀장)에서 수어아바타 도입관련 견적을 센터(?)로 전달했다고 하여 - 3개센터(복사골, 오정, 송내) 각 담당자에게 전화상 문의하였으나 관련 내용을 알고 있지 못함 (소사센터는 '26년 도입 고려중, 추후 배리어프리 키오스크 도입건 영업 필요, 오정센터는 예산 없음확인) | O82: 2950
B83: 2025-080 | C83: 수어 | D83: 천안시 | E83: 아이비테크 주식회사 | F83: 천안시 홈페이지 수어안내 | G83: 오민규 | H83: 2 견적제출 | M83: N | N83: (09.26 기준) - 천안시 홈페이지 "복지일반" 내용 수어 안내 L (대표번호 IN) (주)아이비테크 신현섭이사. AI 스마트 로봇 기업. 지차제 납품 실적 有. 천안시 수어 문의 대응 L 천안시 홈페이지 메인 - 1차 - 2차메뉴 - 내용. 단계별 수어 안내 제언중 (10.16 기준) - 천안시에 수어 안내 자료 전달함. 검토 의견 대기중(아이비테크 신협섭이사 확인. 10.15) (11.27 기준) - 천안시 검토 의견 대기중(신현섭이사 확인) - 차주 당사 방문 & 수어 시스템 소개 예정(일정 미정) | O83: 82512
B84: 2025-081 | C84: AICC | D84: ABL생명 | E84: 유니디아 | F84: ABL 생명 통합 유지보수 | G84: 오민규 | H84: 9 유지보수 | M84: N | N84: "(09.26 기준) - ABL 생명 유지보수 계약 진행중. 담당자 유니디아 이진우이사 L STT 2EA, 160Ch 2025.10.12~2028.10.11 / STT 10Ch 2026.06.01~2028.10.11 L 유지보수 총 금액 : 27,998,384원(vat제외) (10.01 기준) - 유지보수 계약 체결을 위한 라이런스 증서, 기술지원확약서 서류 전달 (11/06 기준) - ABL생명 유지보수 계약 체결(27,998,384원. 2025.10.12~2028.10.11) - DR 훈련 대비 시스템 구성(안) F/up 중 (11.13 기준) - DR 훈련 대비 가견적 전달 : 160ch, 연동개발 1.5MM = 51,500,000원 : 최종 구성안 확정시 재연락 주기로 함 - 재해 복구 시스템 운영시 솔루션 라이선스 재활용 가능함 공문 전달 | O84: 27998.384
B85: 2025-082 | C85: AICC | D85: 미래에셋생명 | E85: 부뜰정보시스템 | F85: 미래에셋생명 차세대시스템 구축 프로젝트 | G85: 오민규 | H85: 8 계약완료 | M85: N | N85: [본계약] - (용역) 미래에셋생명보험 차세대시스템 TA/AI-QA/컨텐츠등록 구축. 2025.04.21~2027.02.15. 495,000.000원 (계약일: 2025.07.03) - (제품) 미래에셋생명보험 차세대시스템 구축 사업. 최종검수예정일 2027.04.30. 487,640.000원 (계약일: 2025.07.03) (09.26 기준) - 매입처 계약 진행중 L 지란지교 소프트 (10.01 기준) - 매입처 계약 진행중: 지란지교 소프트, 코난테크놀러지 그외 매입처 확인중 (10.16 기준) - 매입처 계약 진행중: 코난테크놀러지(검색/제품/용역 3개 항목) (10.30 기준) - 매입처 계약: 코난 17MM → SynK 라이선스 계약 지란지교 발주처리 예정. 그외 1개사 요청오면 진행. 한군데 업체는 박현후과장 SW, 용역 계약 진행 (11.06 기준) - 코난테크놀러지 SynK 매출계약 협의중(153,000,000원) (11.13 기준) - 매입계약 : 코난테크놀로지, 지란지교, 시냅소프트 진행중 - 매출계약 : 코난테크놀로지 SynK 진행중 (11.20 기준) - 매입계약 : 코난테크놀로지, 지란지교, 시냅소프트 완료 - 매출계약 : 코난테크놀로지 SynK . 차주 대표님. 박현후과장 추가사항 확인 예정 (11.27 기준) - 매입계약 : 코난, 지란지교, 시냅소프트 계약서 및 발주서 전달 완료 (12.24 기준) - 코난테크놀로지 투입인력 잦은 교체 원인 및 재발 방지 방안 요청 공문 송부 完(~12/30) - 기술지원확약서 전달(TA, TAssist, 검색, 웹에디터, 문서뷰어) ※ CMS/AI분류엔진 등 추가 전달 필요 | O85: =495000+487640 -> 982640
